Workbook
Name In_Calc: Saisie!$F$13:$F$92
Name In_Cles: Saisie!$B$13:$B$92
Name In_Retenue: Saisie!$G$13:$G$92
Name In_Saisie: Saisie!$E$13:$E$92
Name P_Classes: P_General!$A$27:$E$36
Name P_ClsCodes: P_General!$A$27:$A$36
Name P_Date: P_General!$B$5
Name P_DomCodes: P_General!$A$16:$A$23
Name P_DomNoms: P_General!$B$16:$B$23
Name P_DomPoids: P_General!$C$16:$C$23
Name P_DPD1: P_General!$B$45
Name P_DPD2: P_General!$B$46
Name P_DPD3: P_General!$B$47
Name P_ExtraKey: P_General!$B$12
Name P_GO: P_General!$B$7
Name P_GWC: P_General!$B$8
Name P_PDa: P_General!$B$10
Name P_PDb: P_General!$B$11
Name P_PhaseCodes: P_General!$A$40:$A$42
Name P_PhaseHdr: P_General!$B$39:$I$39
Name P_PhaseTbl: P_General!$A$40:$I$42
Name P_Scale: P_General!$B$6
Name P_SegCodes: P_Ajustements!$A$5:$A$24
Name P_SegTbl: P_Ajustements!$A$5:$C$24
Name P_Version: P_General!$B$4
Name P_WATCH: P_General!$B$9
Name P_ZoneCodes: P_Ajustements!$E$5:$E$24
Name P_ZoneTbl: P_Ajustements!$E$5:$G$24
Name R_AuthCodes: P_Referentiels!$A$6:$A$29
Name R_AuthTbl: P_Referentiels!$A$6:$I$29
Name R_FinCodes: P_Referentiels!$A$34:$A$45
Name R_FinTbl: P_Referentiels!$A$34:$C$45
Name Res_Adj: Resultat!$C$11
Name Res_Alertes: Resultat!$C$26
Name Res_ClasseInt: Resultat!$C$8
Name Res_Comite: Resultat!$E$27
Name Res_Decision: Resultat!$C$7
Name Res_DomCodes: Resultat!$A$32:$A$39
Name Res_DomScores: Resultat!$C$32:$C$39
Name Res_EcoScore: Resultat!$C$15
Name Res_GuarScore: Resultat!$C$16
Name Res_Incomplet: Resultat!$E$23
Name Res_Malus: Resultat!$C$12
Name Res_Manquantes: Resultat!$C$24
Name Res_PD: Resultat!$C$9
Name Res_ScoreEco: Resultat!$C$10
Name Res_ScoreFinal: Resultat!$C$6

Sheet LisezMoi
B1: Outil de scoring — Promotion immobilière
B2: ="Modèle PI_PROMOTION "&P_Version&" — publié le "&P_Date -> 0
B4: À quoi sert ce classeur | C4: Calculer le score, la décision et la classe interne d'un dossier de promotion immobilière selon le modèle PI_PROMOTION v4.0.0, hors de l'application : simulation, comité, agence, dépannage. Il reproduit le moteur de production (vérifié sur 20 cas de référence).
B5: Principe | C5: Le MOTEUR est en formules Excel (onglet Resultat) : chaque note est traçable cellule par cellule et les barèmes se modifient sans code. Le VBA (fichiers .bas fournis) AUTOMATISE : scoring de portefeuille, stress test, validation du modèle, autotests, journal, export PDF.
B6: 1. Renseigner un dossier | C6: Onglet Saisie : segment, zone, classe réglementaire BAM, puis les données (cellules jaunes). Les données dérivées (autorisations, ventes sécurisées, mainlevée, division des risques) peuvent être calculées dans l'onglet Calculateurs ; une valeur saisie prime.
B7: 2. Lire le résultat | C7: Onglet Resultat : score final, décision, classe interne, malus, alertes, détail par critère et par domaine. Une donnée décisionnelle absente donne « DOSSIER_INCOMPLET » — jamais un meilleur score.
B8: 3. Automatiser (VBA) | C8: Alt+F11 → Fichier → Importer un fichier → sélectionner les 5 fichiers .bas du dossier « vba ». Puis exécuter InstallerBoutons (une seule fois) et enregistrer le classeur au format .xlsm.
B9: 4. Vérifier | C9: Exécuter ExecuterAutotests : compare les résultats du classeur à 20 cas de référence issus du moteur de production. Exécuter ValiderModele après toute modification des paramètres.
B10: Invariants de décision | C10: Donnée manquante ≠ amélioration (note plancher ; alerte « non exclue » si sa donnée numérique manque) · Défaut avéré → NO_GO · Classe non renseignée → dossier incomplet · Aucun malus pour la division des risques (retour en comité).
B11: Ce que le classeur ne fait pas | C11: Classification BAM complète (déclencheurs qualitatifs 1/W, restructuration, effet de groupe) : la classe est saisie ; seule une suggestion fondée sur le retard est affichée. Trésorerie mensuelle, LGD, IFRS 9, workflow d'approbation, historisation multi-utilisateurs : dans l'application.
B12: Limites d'usage | C12: Classeur individuel : pas de contrôle d'accès ni de piste d'audit opposable. La PD affichée est INDICATIVE et non calibrée : ne pas l'utiliser pour des pertes attendues ou du capital. Les grilles par phase et l'effet des coefficients territoriaux sont des challengers, pas la décision.
B13: Paramétrage | C13: Onglets P_* (bleus) : critères, barèmes, alertes, ajustements, référentiels, seuils. Modifier = ValiderModele + nouvelle version (macro SnapshotModele) + information du propriétaire du modèle. La version de référence reste celle de l'application.
B14: Compatibilité | C14: Excel 2010 ou plus récent (Windows), Excel pour Mac pour les formules. Les macros n'utilisent pas de bibliothèque externe. Aucun contenu actif n'est intégré au fichier .xlsx fourni.
B16: Onglets
B17: Saisie | C17: Données du dossier
B18: Resultat | C18: Moteur de calcul et restitution
B19: Calculateurs | C19: Autorisations, ventes sécurisées, mainlevée, division des risques
B20: Portefeuille | C20: Scoring de masse (macro)
B21: Stress | C21: Chocs sur le dossier courant (macro)
B22: Tests | C22: 20 cas de référence (macro)
B23: Historique | C23: Journal des calculs
B24: P_* | C24: Paramètres du modèle (bleus)

Sheet Saisie
A1: Saisie du dossier
A2: Cellules jaunes = à renseigner. Une donnée absente n'améliore JAMAIS le résultat (note plancher, ou « dossier incomplet » si la donnée est décisionnelle).
A4: Référence dossier
A5: Nom du projet
A6: Segment
A7: Zone
A8: Classe réglementaire BAM | E8: =IFERROR(IF(NOT(ISNUMBER(INDEX(In_Retenue,MATCH("dpd_days",In_Cles,0)))),"",IF(INDEX(In_Retenue,MATCH("dpd_days",In_Cles,0))>=P_DPD3,"COMPROMIS",IF(INDEX(In_Retenue,MATCH("dpd_days",In_Cles,0))>=P_DPD2,"DOUTEUX",IF(INDEX(In_Retenue,MATCH("dpd_days",In_Cles,0))>=P_DPD1,"PRE_DOUTEUX","SAIN")))),"") -> 0 | F8: =IF(OR(C8="",E8=""),"",IF(MATCH(C8,P_ClsCodes,0)<MATCH(E8,P_ClsCodes,0),"⚠ Classe moins sévère que le retard constaté","Cohérent avec le retard")) -> 0 | G8: ← classe suggérée par le seul retard de paiement (les déclencheurs qualitatifs 1/W — art. 5, 12.6, 12.7, restructuration — restent à apprécier)
A9: Phase du projet (challenger)
A10: Version du modèle | C10: =P_Version&" — "&P_Date -> 0
A12: Section | B12: Clé technique | C12: Donnée | D12: Type | E12: Valeur saisie | F12: Valeur calculée | G12: Valeur retenue | H12: Aide
A13: D1 — Sponsor & Gouvernance | B13: promoter_completed_projects | C13: Projets similaires livrés (5 ans) | D13: NUM | G13: =IF(E13<>"",IF(D13="BOOL",IF(E13="Oui",TRUE,IF(E13="Non",FALSE,"")),E13),IF(F13="","",IF(D13="BOOL",IF(F13="Oui",TRUE,IF(F13="Non",FALSE,"")),F13))) -> 0 | H13: nombre (ratio/%)
A14: D1 — Sponsor & Gouvernance | B14: promoter_gearing | C14: Gearing promoteur (dettes nettes / FP) | D14: NUM | G14: =IF(E14<>"",IF(D14="BOOL",IF(E14="Oui",TRUE,IF(E14="Non",FALSE,"")),E14),IF(F14="","",IF(D14="BOOL",IF(F14="Oui",TRUE,IF(F14="Non",FALSE,"")),F14))) -> 0 | H14: nombre (ratio/%)
A15: D1 — Sponsor & Gouvernance | B15: governance_quality | C15: Gouvernance & structure juridique | D15: QUAL | G15: =IF(E15<>"",IF(D15="BOOL",IF(E15="Oui",TRUE,IF(E15="Non",FALSE,"")),E15),IF(F15="","",IF(D15="BOOL",IF(F15="Oui",TRUE,IF(F15="Non",FALSE,"")),F15))) -> 0 | H15: valeurs : opaque | partielle | claire
A16: D1 — Sponsor & Gouvernance | B16: mono_project_concentration | C16: Concentration mono-projet (CA projet / CA total) | D16: NUM | G16: =IF(E16<>"",IF(D16="BOOL",IF(E16="Oui",TRUE,IF(E16="Non",FALSE,"")),E16),IF(F16="","",IF(D16="BOOL",IF(F16="Oui",TRUE,IF(F16="Non",FALSE,"")),F16))) -> 0 | H16: nombre (ratio/%)
A17: D1 — Sponsor & Gouvernance | B17: promoter_type | C17: Typologie promoteur | D17: QUAL | G17: =IF(E17<>"",IF(D17="BOOL",IF(E17="Oui",TRUE,IF(E17="Non",FALSE,"")),E17),IF(F17="","",IF(D17="BOOL",IF(F17="Oui",TRUE,IF(F17="Non",FALSE,"")),F17))) -> 0 | H17: valeurs : opportuniste | regional | structure
A18: D1 — Sponsor & Gouvernance | B18: equity_injected_ratio | C18: Apport effectif (injecté / prévu) | D18: NUM | G18: =IF(E18<>"",IF(D18="BOOL",IF(E18="Oui",TRUE,IF(E18="Non",FALSE,"")),E18),IF(F18="","",IF(D18="BOOL",IF(F18="Oui",TRUE,IF(F18="Non",FALSE,"")),F18))) -> 0 | H18: nombre (ratio/%)
A19: D2 — Qualité intrinsèque du projet | B19: land_permits_status | C19: Foncier & autorisations | D19: QUAL | G19: =IF(E19<>"",IF(D19="BOOL",IF(E19="Oui",TRUE,IF(E19="Non",FALSE,"")),E19),IF(F19="","",IF(D19="BOOL",IF(F19="Oui",TRUE,IF(F19="Non",FALSE,"")),F19))) -> 0 | H19: valeurs : absentes | partielles | definitives
A20: D2 — Qualité intrinsèque du projet | B20: market_positioning | C20: Marché & positionnement | D20: QUAL | G20: =IF(E20<>"",IF(D20="BOOL",IF(E20="Oui",TRUE,IF(E20="Non",FALSE,"")),E20),IF(F20="","",IF(D20="BOOL",IF(F20="Oui",TRUE,IF(F20="Non",FALSE,"")),F20))) -> 0 | H20: valeurs : sur_positionne | moyen | aligne
A21: D2 — Qualité intrinsèque du projet | B21: technical_complexity | C21: Complexité technique | D21: QUAL | G21: =IF(E21<>"",IF(D21="BOOL",IF(E21="Oui",TRUE,IF(E21="Non",FALSE,"")),E21),IF(F21="","",IF(D21="BOOL",IF(F21="Oui",TRUE,IF(F21="Non",FALSE,"")),F21))) -> 0 | H21: valeurs : elevee | moyenne | standard
A22: D2 — Qualité intrinsèque du projet | B22: progress_vs_plan | C22: Avancement vs planning | D22: NUM | G22: =IF(E22<>"",IF(D22="BOOL",IF(E22="Oui",TRUE,IF(E22="Non",FALSE,"")),E22),IF(F22="","",IF(D22="BOOL",IF(F22="Oui",TRUE,IF(F22="Non",FALSE,"")),F22))) -> 0 | H22: nombre (ratio/%)
A23: D2 — Qualité intrinsèque du projet | B23: sav_litigation | C23: Litiges clients / SAV | D23: QUAL | G23: =IF(E23<>"",IF(D23="BOOL",IF(E23="Oui",TRUE,IF(E23="Non",FALSE,"")),E23),IF(F23="","",IF(D23="BOOL",IF(F23="Oui",TRUE,IF(F23="Non",FALSE,"")),F23))) -> 0 | H23: valeurs : eleve | moyen | faible
A24: D2 — Qualité intrinsèque du projet | B24: macro_sensitivity | C24: Sensibilité macro / subvention | D24: QUAL | G24: =IF(E24<>"",IF(D24="BOOL",IF(E24="Oui",TRUE,IF(E24="Non",FALSE,"")),E24),IF(F24="","",IF(D24="BOOL",IF(F24="Oui",TRUE,IF(F24="Non",FALSE,"")),F24))) -> 0 | H24: valeurs : elevee | moyenne | faible
A25: D2 — Qualité intrinsèque du projet | B25: land_cost_ratio | C25: Coût foncier / CA | D25: NUM | G25: =IF(E25<>"",IF(D25="BOOL",IF(E25="Oui",TRUE,IF(E25="Non",FALSE,"")),E25),IF(F25="","",IF(D25="BOOL",IF(F25="Oui",TRUE,IF(F25="Non",FALSE,"")),F25))) -> 0 | H25: nombre (ratio/%)
A26: D2 — Qualité intrinsèque du projet | B26: authorization_completeness_pct | C26: Chaîne d'autorisations (complétude) | D26: NUM | F26: =IF(Calculateurs!C35,Calculateurs!C33,"") -> 0 | G26: =IF(E26<>"",IF(D26="BOOL",IF(E26="Oui",TRUE,IF(E26="Non",FALSE,"")),E26),IF(F26="","",IF(D26="BOOL",IF(F26="Oui",TRUE,IF(F26="Non",FALSE,"")),F26))) -> 0 | H26: nombre (%) — calculé par l'onglet Calculateurs ; la saisie prime
A27: D3 — Commercial & Cash-flow | B27: pre_sale_rate | C27: Préventes sécurisées (encaissées / CA) | D27: NUM | G27: =IF(E27<>"",IF(D27="BOOL",IF(E27="Oui",TRUE,IF(E27="Non",FALSE,"")),E27),IF(F27="","",IF(D27="BOOL",IF(F27="Oui",TRUE,IF(F27="Non",FALSE,"")),F27))) -> 0 | H27: nombre (ratio/%)
A28: D3 — Commercial & Cash-flow | B28: sales_vs_plan | C28: Ventes vs planning | D28: NUM | G28: =IF(E28<>"",IF(D28="BOOL",IF(E28="Oui",TRUE,IF(E28="Non",FALSE,"")),E28),IF(F28="","",IF(D28="BOOL",IF(F28="Oui",TRUE,IF(F28="Non",FALSE,"")),F28))) -> 0 | H28: nombre (ratio/%)
A29: D3 — Commercial & Cash-flow | B29: dso_days | C29: DSO (jours) | D29: NUM | G29: =IF(E29<>"",IF(D29="BOOL",IF(E29="Oui",TRUE,IF(E29="Non",FALSE,"")),E29),IF(F29="","",IF(D29="BOOL",IF(F29="Oui",TRUE,IF(F29="Non",FALSE,"")),F29))) -> 0 | H29: nombre (ratio/%)
A30: D3 — Commercial & Cash-flow | B30: cash_coverage | C30: Cash coverage (cash / échéances) | D30: NUM | G30: =IF(E30<>"",IF(D30="BOOL",IF(E30="Oui",TRUE,IF(E30="Non",FALSE,"")),E30),IF(F30="","",IF(D30="BOOL",IF(F30="Oui",TRUE,IF(F30="Non",FALSE,"")),F30))) -> 0 | H30: nombre (ratio/%)
A31: D3 — Commercial & Cash-flow | B31: funding_gap_pct | C31: Impasse brute | D31: NUM | G31: =IF(E31<>"",IF(D31="BOOL",IF(E31="Oui",TRUE,IF(E31="Non",FALSE,"")),E31),IF(F31="","",IF(D31="BOOL",IF(F31="Oui",TRUE,IF(F31="Non",FALSE,"")),F31))) -> 0 | H31: nombre (ratio/%)
A32: D3 — Commercial & Cash-flow | B32: stock_rotation_months | C32: Rotation stock (mois) | D32: NUM | G32: =IF(E32<>"",IF(D32="BOOL",IF(E32="Oui",TRUE,IF(E32="Non",FALSE,"")),E32),IF(F32="","",IF(D32="BOOL",IF(F32="Oui",TRUE,IF(F32="Non",FALSE,"")),F32))) -> 0 | H32: nombre (ratio/%)
A33: D3 — Commercial & Cash-flow | B33: stressed_margin_pct | C33: Marge brute stressée (prix -10%) | D33: NUM | G33: =IF(E33<>"",IF(D33="BOOL",IF(E33="Oui",TRUE,IF(E33="Non",FALSE,"")),E33),IF(F33="","",IF(D33="BOOL",IF(F33="Oui",TRUE,IF(F33="Non",FALSE,"")),F33))) -> 0 | H33: nombre (ratio/%)
A34: D3 — Commercial & Cash-flow | B34: secured_sales_rate | C34: Ventes sécurisées (financement acquéreur) | D34: NUM | F34: =Calculateurs!C85 -> 0 | G34: =IF(E34<>"",IF(D34="BOOL",IF(E34="Oui",TRUE,IF(E34="Non",FALSE,"")),E34),IF(F34="","",IF(D34="BOOL",IF(F34="Oui",TRUE,IF(F34="Non",FALSE,"")),F34))) -> 0 | H34: nombre (%) — calculé par l'onglet Calculateurs ; la saisie prime
A35: D4 — Structuration financière & LGD | B35: gross_margin_pct | C35: Marge brute (CA - coûts directs)/CA | D35: NUM | G35: =IF(E35<>"",IF(D35="BOOL",IF(E35="Oui",TRUE,IF(E35="Non",FALSE,"")),E35),IF(F35="","",IF(D35="BOOL",IF(F35="Oui",TRUE,IF(F35="Non",FALSE,"")),F35))) -> 0 | H35: nombre (ratio/%)
A36: D4 — Structuration financière & LGD | B36: ltc | C36: LTC (dette / coût total) | D36: NUM | G36: =IF(E36<>"",IF(D36="BOOL",IF(E36="Oui",TRUE,IF(E36="Non",FALSE,"")),E36),IF(F36="","",IF(D36="BOOL",IF(F36="Oui",TRUE,IF(F36="Non",FALSE,"")),F36))) -> 0 | H36: nombre (ratio/%)
A37: D4 — Structuration financière & LGD | B37: ltv_stressed | C37: LTV stressée (dette / valeur×0,90) | D37: NUM | G37: =IF(E37<>"",IF(D37="BOOL",IF(E37="Oui",TRUE,IF(E37="Non",FALSE,"")),E37),IF(F37="","",IF(D37="BOOL",IF(F37="Oui",TRUE,IF(F37="Non",FALSE,"")),F37))) -> 0 | H37: nombre (ratio/%)
A38: D4 — Structuration financière & LGD | B38: guarantee_coverage | C38: Couverture garanties réalisable | D38: NUM | G38: =IF(E38<>"",IF(D38="BOOL",IF(E38="Oui",TRUE,IF(E38="Non",FALSE,"")),E38),IF(F38="","",IF(D38="BOOL",IF(F38="Oui",TRUE,IF(F38="Non",FALSE,"")),F38))) -> 0 | H38: nombre (ratio/%)
A39: D4 — Structuration financière & LGD | B39: first_rank | C39: Rang bancaire 1er rang | D39: QUAL | G39: =IF(E39<>"",IF(D39="BOOL",IF(E39="Oui",TRUE,IF(E39="Non",FALSE,"")),E39),IF(F39="","",IF(D39="BOOL",IF(F39="Oui",TRUE,IF(F39="Non",FALSE,"")),F39))) -> 0 | H39: valeurs : non | oui
A40: D4 — Structuration financière & LGD | B40: interest_coverage | C40: Interest coverage (EBITDA / charges fin.) | D40: NUM | G40: =IF(E40<>"",IF(D40="BOOL",IF(E40="Oui",TRUE,IF(E40="Non",FALSE,"")),E40),IF(F40="","",IF(D40="BOOL",IF(F40="Oui",TRUE,IF(F40="Non",FALSE,"")),F40))) -> 0 | H40: nombre (ratio/%)
A41: D4 — Structuration financière & LGD | B41: release_quotity_gap_pts | C41: Quotité de désengagement vs équilibre | D41: NUM | F41: =Calculateurs!C94 -> 0 | G41: =IF(E41<>"",IF(D41="BOOL",IF(E41="Oui",TRUE,IF(E41="Non",FALSE,"")),E41),IF(F41="","",IF(D41="BOOL",IF(F41="Oui",TRUE,IF(F41="Non",FALSE,"")),F41))) -> 0 | H41: nombre (pts) — calculé par l'onglet Calculateurs ; la saisie prime
A42: Alertes D5 | B42: dpd_days | C42: Retard de paiement (jours) | D42: NUM | G42: =IF(E42<>"",IF(D42="BOOL",IF(E42="Oui",TRUE,IF(E42="Non",FALSE,"")),E42),IF(F42="","",IF(D42="BOOL",IF(F42="Oui",TRUE,IF(F42="Non",FALSE,"")),F42))) -> 0 | H42: nombre — donnée décisionnelle
A43: Alertes D5 | B43: construction_delay_months | C43: Retard chantier (mois) | D43: NUM | G43: =IF(E43<>"",IF(D43="BOOL",IF(E43="Oui",TRUE,IF(E43="Non",FALSE,"")),E43),IF(F43="","",IF(D43="BOOL",IF(F43="Oui",TRUE,IF(F43="Non",FALSE,"")),F43))) -> 0 | H43: nombre
A44: Alertes D5 | B44: project_stopped_months | C44: Arrêt du projet (mois) | D44: NUM | G44: =IF(E44<>"",IF(D44="BOOL",IF(E44="Oui",TRUE,IF(E44="Non",FALSE,"")),E44),IF(F44="","",IF(D44="BOOL",IF(F44="Oui",TRUE,IF(F44="Non",FALSE,"")),F44))) -> 0 | H44: nombre
A45: Alertes D5 | B45: restructured | C45: Créance restructurée | D45: QUAL | G45: =IF(E45<>"",IF(D45="BOOL",IF(E45="Oui",TRUE,IF(E45="Non",FALSE,"")),E45),IF(F45="","",IF(D45="BOOL",IF(F45="Oui",TRUE,IF(F45="Non",FALSE,"")),F45))) -> 0 | H45: valeurs : yes | no
A46: Alertes D5 | B46: legal_exposure | C46: Exposition juridique | D46: QUAL | G46: =IF(E46<>"",IF(D46="BOOL",IF(E46="Oui",TRUE,IF(E46="Non",FALSE,"")),E46),IF(F46="","",IF(D46="BOOL",IF(F46="Oui",TRUE,IF(F46="Non",FALSE,"")),F46))) -> 0 | H46: valeurs : clear | watch | litigation
A47: Alertes D5 | B47: equity_negative | C47: Fonds propres négatifs | D47: BOOL | G47: =IF(E47<>"",IF(D47="BOOL",IF(E47="Oui",TRUE,IF(E47="Non",FALSE,"")),E47),IF(F47="","",IF(D47="BOOL",IF(F47="Oui",TRUE,IF(F47="Non",FALSE,"")),F47))) -> 0 | H47: Oui / Non
A48: Alertes D5 | B48: funding_gap_persistent | C48: Impasse de trésorerie persistante | D48: BOOL | G48: =IF(E48<>"",IF(D48="BOOL",IF(E48="Oui",TRUE,IF(E48="Non",FALSE,"")),E48),IF(F48="","",IF(D48="BOOL",IF(F48="Oui",TRUE,IF(F48="Non",FALSE,"")),F48))) -> 0 | H48: Oui / Non
A49: Alertes D5 | B49: works_authorization_blocked | C49: Autorisation de travaux bloquante | D49: BOOL | F49: =IF(Calculateurs!C35,IF(Calculateurs!C34,"Oui","Non"),"") -> 0 | G49: =IF(E49<>"",IF(D49="BOOL",IF(E49="Oui",TRUE,IF(E49="Non",FALSE,"")),E49),IF(F49="","",IF(D49="BOOL",IF(F49="Oui",TRUE,IF(F49="Non",FALSE,"")),F49))) -> 0 | H49: Oui / Non — calculé par l'onglet Calculateurs ; la saisie prime
A50: Alertes D5 | B50: buyers_financing_at_risk | C50: Financement des acquéreurs à risque | D50: BOOL | F50: =IF(Calculateurs!C86="","",IF(Calculateurs!C86,"Oui","Non")) -> 0 | G50: =IF(E50<>"",IF(D50="BOOL",IF(E50="Oui",TRUE,IF(E50="Non",FALSE,"")),E50),IF(F50="","",IF(D50="BOOL",IF(F50="Oui",TRUE,IF(F50="Non",FALSE,"")),F50))) -> 0 | H50: Oui / Non — calculé par l'onglet Calculateurs ; la saisie prime
A51: Alertes D5 | B51: release_underpriced | C51: Mainlevée sous-tarifée | D51: BOOL | F51: =IF(Calculateurs!C95="","",IF(Calculateurs!C95,"Oui","Non")) -> 0 | G51: =IF(E51<>"",IF(D51="BOOL",IF(E51="Oui",TRUE,IF(E51="Non",FALSE,"")),E51),IF(F51="","",IF(D51="BOOL",IF(F51="Oui",TRUE,IF(F51="Non",FALSE,"")),F51))) -> 0 | H51: Oui / Non — calculé par l'onglet Calculateurs ; la saisie prime
A52: Alertes D5 | B52: division_limit_breach | C52: Limite de division des risques dépassée | D52: BOOL | F52: =IF(Calculateurs!C120="","",IF(Calculateurs!C120,"Oui","Non")) -> 0 | G52: =IF(E52<>"",IF(D52="BOOL",IF(E52="Oui",TRUE,IF(E52="Non",FALSE,"")),E52),IF(F52="","",IF(D52="BOOL",IF(F52="Oui",TRUE,IF(F52="Non",FALSE,"")),F52))) -> 0 | H52: Oui / Non — calculé par l'onglet Calculateurs ; la saisie prime
G53: =IF(E53<>"",E53,IF(F53="","",F53)) -> 0
G54: =IF(E54<>"",E54,IF(F54="","",F54)) -> 0
G55: =IF(E55<>"",E55,IF(F55="","",F55)) -> 0
G56: =IF(E56<>"",E56,IF(F56="","",F56)) -> 0
G57: =IF(E57<>"",E57,IF(F57="","",F57)) -> 0
G58: =IF(E58<>"",E58,IF(F58="","",F58)) -> 0
G59: =IF(E59<>"",E59,IF(F59="","",F59)) -> 0
G60: =IF(E60<>"",E60,IF(F60="","",F60)) -> 0
G61: =IF(E61<>"",E61,IF(F61="","",F61)) -> 0
G62: =IF(E62<>"",E62,IF(F62="","",F62)) -> 0
G63: =IF(E63<>"",E63,IF(F63="","",F63)) -> 0
G64: =IF(E64<>"",E64,IF(F64="","",F64)) -> 0
... G92: =IF(E92<>"",E92,IF(F92="","",F92)) -> 0

Sheet Resultat
A1: Résultat du scoring
A2: ="Modèle "&P_Version&" — "&Saisie!C4&" "&Saisie!C5 -> 0
E5: (interne) | F5: Challengers (indicatifs — score officiel inchangé)
A6: Score final (0–100) | C6: =IF(E28,0,ROUND(MIN(100,MAX(0,C13*C14)),2)) -> 0 | F6: Phase du projet | H6: =IF(Saisie!C9="","(non renseignée)",Saisie!C9) -> 0
A7: Décision | C7: =IF(E28,"NO_GO",IF(E21,"NO_GO",IF(E22,"NO_GO",IF(E23,"DOSSIER_INCOMPLET",IF(E20,"NO_GO",IF(C6>=P_GO,"GO",IF(C6>=P_GWC,"GO_WITH_CONDITIONS",IF(C6>=P_WATCH,"WATCH_LIST","NO_GO")))))))) -> 0 | F7: Score éco. avec pondération de phase | H7: =IF(Saisie!C9="","",IF(SUM(F32:F39)=0,"",ROUND(SUM(G32:G39)/SUM(F32:F39),2))) -> 0
A8: Classe interne | C8: =IF(E28,"Souffrance",IF(E21,"Souffrance",IF(E22,"Défaut avéré",IF(E23,"Dossier incomplet",IF(C6>=P_GO,"Sain",IF(C6>=P_GWC,"Surveillance",IF(C6>=P_WATCH,"Sensible probable","Sensible"))))))) -> 0 | F8: Écart vs score éco. officiel | H8: =IF(H7="","",ROUND(H7-C10,2)) -> 0
A9: PD proxy (indicative, non calibrée) | C9: =ROUND(1/(1+EXP(-(P_PDa-P_PDb*C6))),4) -> 0 | F9: Score ajusté sans coefficients territoriaux | H9: =ROUND(MIN(100,MAX(0,C10)),2) -> 0
A10: Score économique S_éco (avant ajustement) | C10: =IF(SUM(D32:D39)=0,0,ROUND(SUM(E32:E39)/SUM(D32:D39),2)) -> 0 | F10: Effet des coefficients segment / zone | H10: =ROUND(C11-H9,2) -> 0
A11: Score ajusté S_adj = S_éco×(1+α+β) | C11: =ROUND(MIN(100,MAX(0,C10*(1+C17+C18))),2) -> 0
A12: Malus cumulés D5 (points) | C12: =SUM(J108:J137) -> 0
A13: Score après pénalités | C13: =ROUND(MIN(100,MAX(0,C11-C12)),2) -> 0
A14: Coefficient réglementaire BAM | C14: =IF(Saisie!C8="",1,IFERROR(VLOOKUP(Saisie!C8,P_Classes,5,FALSE),1)) -> 0
A15: Note économique (capacité de remboursement) | C15: =IFERROR(ROUND(SUMPRODUCT($Q$44:$Q$103*($N$44:$N$103<>"GUARANTEE")*$F$44:$F$103)/SUMPRODUCT($Q$44:$Q$103*($N$44:$N$103<>"GUARANTEE"))/P_Scale*100,2),C10) -> 0
A16: Note de sûretés (perte en cas de défaut) | C16: =IFERROR(ROUND(SUMPRODUCT($Q$44:$Q$103*($N$44:$N$103="GUARANTEE")*$F$44:$F$103)/SUMPRODUCT($Q$44:$Q$103*($N$44:$N$103="GUARANTEE"))/P_Scale*100,2),"n/a") -> 0
A17: α segment | C17: =IF(Saisie!C6="",0,IFERROR(VLOOKUP(Saisie!C6,P_SegTbl,3,FALSE),0)) -> 0
A18: β zone | C18: =IF(Saisie!C7="",0,IFERROR(VLOOKUP(Saisie!C7,P_ZoneTbl,3,FALSE),0)) -> 0
A19: Segment / zone hors référentiel | C19: =IF(E19,"Oui — à signaler","Non") -> 0 | E19: =OR(AND(Saisie!C6<>"",ISNA(MATCH(Saisie!C6,P_SegCodes,0))),AND(Saisie!C7<>"",ISNA(MATCH(Saisie!C7,P_ZoneCodes,0)))) -> 0
A20: Critère éliminatoire (gate) franchi | C20: =IF(E20,"Oui","Non") -> 0 | E20: =OR(I44:I103) -> 0
A21: Alerte bloquante (souffrance automatique) | C21: =IF(E21,"Oui","Non") -> 0 | E21: =SUMPRODUCT((C108:C137="BLOCKING")*(H108:H137=TRUE))>0 -> 0
A22: Défaut avéré (classe réglementaire) | C22: =IF(E22,"Oui","Non") -> 0 | E22: =OR(IFERROR(VLOOKUP(Saisie!C8,P_Classes,3,FALSE)="Oui",FALSE),Saisie!C8="CTX") -> 0
A23: Dossier incomplet (donnée décisionnelle absente) | C23: =IF(E23,"Oui","Non") -> 0 | E23: =OR(Saisie!C8="",J43,SUMPRODUCT((J44:J103=TRUE)*1)>0,SUMPRODUCT((L108:L137=TRUE)*1)>0) -> 0
A24: Données décisionnelles manquantes | C24: =IF(C6=C6,SUBSTITUTE(M137,",",", "),"") -> 0
A25: Critères éliminatoires franchis | C25: =S103 -> 0
A26: Alertes déclenchées / non exclues | C26: =N137 -> 0
A27: Retour en comité requis | C27: =IF(E27,"Oui","Non") -> 0 | E27: =OR(K108:K137) -> 0
A28: Classe bloquante (contentieux) | C28: =IF(E28,"Oui","Non") -> 0 | E28: =OR(IFERROR(VLOOKUP(Saisie!C8,P_Classes,4,FALSE)="Oui",FALSE),Saisie!C8="CTX") -> 0
A30: Scores par domaine
A31: Code | B31: Domaine | C31: Score /100 | D31: Poids | E31: Contribution | F31: Poids phase | G31: Contribution phase
A32: =IF(P_General!A16="","",P_General!A16) -> 0 | B32: =IF($A32="","",P_General!B16) -> 0 | C32: =IF($A32="",0,IF(SUMIF($B$44:$B$103,$A32,$G$44:$G$103)>0,ROUND(SUMIF($B$44:$B$103,$A32,$H$44:$H$103)/SUMIF($B$44:$B$103,$A32,$G$44:$G$103)/P_Scale*100,2),0)) -> 0 | D32: =IF($A32="",0,P_General!C16) -> 0 | E32: =IF($A32="",0,ROUND(C32*D32,2)) -> 0 | F32: =IF($A32="",0,IFERROR(INDEX(P_PhaseTbl,MATCH(Saisie!$C$9,P_PhaseCodes,0),MATCH($A32,P_PhaseHdr,0)+1),0)) -> 0 | G32: =ROUND(C32*F32,2) -> 0
A33: =IF(P_General!A17="","",P_General!A17) -> 0 | B33: =IF($A33="","",P_General!B17) -> 0 | C33: =IF($A33="",0,IF(SUMIF($B$44:$B$103,$A33,$G$44:$G$103)>0,ROUND(SUMIF($B$44:$B$103,$A33,$H$44:$H$103)/SUMIF($B$44:$B$103,$A33,$G$44:$G$103)/P_Scale*100,2),0)) -> 0 | D33: =IF($A33="",0,P_General!C17) -> 0 | E33: =IF($A33="",0,ROUND(C33*D33,2)) -> 0 | F33: =IF($A33="",0,IFERROR(INDEX(P_PhaseTbl,MATCH(Saisie!$C$9,P_PhaseCodes,0),MATCH($A33,P_PhaseHdr,0)+1),0)) -> 0 | G33: =ROUND(C33*F33,2) -> 0
A34: =IF(P_General!A18="","",P_General!A18) -> 0 | B34: =IF($A34="","",P_General!B18) -> 0 | C34: =IF($A34="",0,IF(SUMIF($B$44:$B$103,$A34,$G$44:$G$103)>0,ROUND(SUMIF($B$44:$B$103,$A34,$H$44:$H$103)/SUMIF($B$44:$B$103,$A34,$G$44:$G$103)/P_Scale*100,2),0)) -> 0 | D34: =IF($A34="",0,P_General!C18) -> 0 | E34: =IF($A34="",0,ROUND(C34*D34,2)) -> 0 | F34: =IF($A34="",0,IFERROR(INDEX(P_PhaseTbl,MATCH(Saisie!$C$9,P_PhaseCodes,0),MATCH($A34,P_PhaseHdr,0)+1),0)) -> 0 | G34: =ROUND(C34*F34,2) -> 0
A35: =IF(P_General!A19="","",P_General!A19) -> 0 | B35: =IF($A35="","",P_General!B19) -> 0 | C35: =IF($A35="",0,IF(SUMIF($B$44:$B$103,$A35,$G$44:$G$103)>0,ROUND(SUMIF($B$44:$B$103,$A35,$H$44:$H$103)/SUMIF($B$44:$B$103,$A35,$G$44:$G$103)/P_Scale*100,2),0)) -> 0 | D35: =IF($A35="",0,P_General!C19) -> 0 | E35: =IF($A35="",0,ROUND(C35*D35,2)) -> 0 | F35: =IF($A35="",0,IFERROR(INDEX(P_PhaseTbl,MATCH(Saisie!$C$9,P_PhaseCodes,0),MATCH($A35,P_PhaseHdr,0)+1),0)) -> 0 | G35: =ROUND(C35*F35,2) -> 0
A36: =IF(P_General!A20="","",P_General!A20) -> 0 | B36: =IF($A36="","",P_General!B20) -> 0 | C36: =IF($A36="",0,IF(SUMIF($B$44:$B$103,$A36,$G$44:$G$103)>0,ROUND(SUMIF($B$44:$B$103,$A36,$H$44:$H$103)/SUMIF($B$44:$B$103,$A36,$G$44:$G$103)/P_Scale*100,2),0)) -> 0 | D36: =IF($A36="",0,P_General!C20) -> 0 | E36: =IF($A36="",0,ROUND(C36*D36,2)) -> 0 | F36: =IF($A36="",0,IFERROR(INDEX(P_PhaseTbl,MATCH(Saisie!$C$9,P_PhaseCodes,0),MATCH($A36,P_PhaseHdr,0)+1),0)) -> 0 | G36: =ROUND(C36*F36,2) -> 0
A37: =IF(P_General!A21="","",P_General!A21) -> 0 | B37: =IF($A37="","",P_General!B21) -> 0 | C37: =IF($A37="",0,IF(SUMIF($B$44:$B$103,$A37,$G$44:$G$103)>0,ROUND(SUMIF($B$44:$B$103,$A37,$H$44:$H$103)/SUMIF($B$44:$B$103,$A37,$G$44:$G$103)/P_Scale*100,2),0)) -> 0 | D37: =IF($A37="",0,P_General!C21) -> 0 | E37: =IF($A37="",0,ROUND(C37*D37,2)) -> 0 | F37: =IF($A37="",0,IFERROR(INDEX(P_PhaseTbl,MATCH(Saisie!$C$9,P_PhaseCodes,0),MATCH($A37,P_PhaseHdr,0)+1),0)) -> 0 | G37: =ROUND(C37*F37,2) -> 0
A38: =IF(P_General!A22="","",P_General!A22) -> 0 | B38: =IF($A38="","",P_General!B22) -> 0 | C38: =IF($A38="",0,IF(SUMIF($B$44:$B$103,$A38,$G$44:$G$103)>0,ROUND(SUMIF($B$44:$B$103,$A38,$H$44:$H$103)/SUMIF($B$44:$B$103,$A38,$G$44:$G$103)/P_Scale*100,2),0)) -> 0 | D38: =IF($A38="",0,P_General!C22) -> 0 | E38: =IF($A38="",0,ROUND(C38*D38,2)) -> 0 | F38: =IF($A38="",0,IFERROR(INDEX(P_PhaseTbl,MATCH(Saisie!$C$9,P_PhaseCodes,0),MATCH($A38,P_PhaseHdr,0)+1),0)) -> 0 | G38: =ROUND(C38*F38,2) -> 0
A39: =IF(P_General!A23="","",P_General!A23) -> 0 | B39: =IF($A39="","",P_General!B23) -> 0 | C39: =IF($A39="",0,IF(SUMIF($B$44:$B$103,$A39,$G$44:$G$103)>0,ROUND(SUMIF($B$44:$B$103,$A39,$H$44:$H$103)/SUMIF($B$44:$B$103,$A39,$G$44:$G$103)/P_Scale*100,2),0)) -> 0 | D39: =IF($A39="",0,P_General!C23) -> 0 | E39: =IF($A39="",0,ROUND(C39*D39,2)) -> 0 | F39: =IF($A39="",0,IFERROR(INDEX(P_PhaseTbl,MATCH(Saisie!$C$9,P_PhaseCodes,0),MATCH($A39,P_PhaseHdr,0)+1),0)) -> 0 | G39: =ROUND(C39*F39,2) -> 0
A41: Détail par critère (explicabilité)
A42: Code | B42: Domaine | C42: Critère | D42: Clé | E42: Valeur | F42: Note /10 | G42: Poids | H42: Pondéré | I42: Gate franchi | J42: Donnée critique manquante | K42: Note plancher | L42: Nb correspondances | M42: Note brute | N42: Famille | O42: Type | P42: Poids domaine | Q42: Poids effectif | R42: Cumul manquantes | S42: Cumul gates
A43: (clé additionnelle) | D43: =P_ExtraKey -> 0 | E43: =IF(D43="","",IFERROR(INDEX(In_Retenue,MATCH(D43,In_Cles,0)),"")) -> 0 | J43: =AND(D43<>"",E43="") -> 0 | R43: =IF(J43,D43,"") -> 0 | S43: ="" -> 0
A44: =IF(P_Criteres!A5="","",P_Criteres!A5) -> 0 | B44: =IF($A44="","",P_Criteres!B5) -> 0 | C44: =IF($A44="","",P_Criteres!C5) -> 0 | D44: =IF($A44="","",P_Criteres!F5) -> 0 | E44: =IF($A44="","",IFERROR(INDEX(In_Retenue,MATCH($D44,In_Cles,0)),"")) -> 0 | F44: =IF($A44="",0,ROUND(MIN(P_Scale,MAX(0,IF($L44=0,$K44,$M44))),2)) -> 0 | G44: =IF($A44="",0,P_Criteres!E5) -> 0 | H44: =ROUND(F44*G44,2) -> 0 | I44: =IF($A44="",FALSE,AND(P_Criteres!G5="Oui",ISNUMBER(P_Criteres!H5),F44<=N(P_Criteres!H5))) -> 0 | J44: =IF($A44="",FALSE,AND(OR(P_Criteres!G5="Oui",P_Criteres!K5="Oui"),$E44="")) -> 0 | K44: {=IF($A44="",0,MIN(IF(P_Baremes!$A$5:$A$400=$A44,P_Baremes!$H$5:$H$400)))} -> 0 | L44: =IF($A44="",0,IF($O44="NUM",IF(ISNUMBER($E44),SUMPRODUCT((P_Baremes!$A$5:$A$400=$A44)*(P_Baremes!$B$5:$B$400="PLAGE")*(((P_Baremes!$D$5:$D$400="")+($E44>=P_Baremes!$D$5:$D$400))>0)*(((P_Baremes!$E$5:$E$400="")+($E44<P_Baremes!$E$5:$E$400))>0)),0),SUMPRODUCT((P_Baremes!$A$5:$A$400=$A44)*(P_Baremes!$B$5:$B$400="MODALITE")*(P_Baremes!$C$5:$C$400=$E44)))) -> 0 | M44: =IF($A44="",0,IF($L44=0,0,IF($O44="NUM",SUMPRODUCT((P_Baremes!$A$5:$A$400=$A44)*(P_Baremes!$B$5:$B$400="PLAGE")*(((P_Baremes!$D$5:$D$400="")+($E44>=P_Baremes!$D$5:$D$400))>0)*(((P_Baremes!$E$5:$E$400="")+($E44<P_Baremes!$E$5:$E$400))>0)*P_Baremes!$H$5:$H$400),SUMPRODUCT((P_Baremes!$A$5:$A$400=$A44)*(P_Baremes!$B$5:$B$400="MODALITE")*(P_Baremes!$C$5:$C$400=$E44)*P_Baremes!$H$5:$H$400)))) -> 0 | N44: =IF($A44="","",P_Criteres!J5) -> 0 | O44: =IF($A44="","",P_Criteres!D5) -> 0 | P44: =IF($A44="",0,IFERROR(INDEX(P_DomPoids,MATCH($B44,P_DomCodes,0)),0)) -> 0 | Q44: =P44*G44 -> 0 | R44: =IF(J44,IF(ISNUMBER(SEARCH(","&D44&",",","&R43&",")),R43,R43&IF(R43="","",",")&D44),R43) -> 0 | S44: =IF(I44,S43&IF(S43="","",", ")&A44,S43) -> 0
A45: =IF(P_Criteres!A6="","",P_Criteres!A6) -> 0 | B45: =IF($A45="","",P_Criteres!B6) -> 0 | C45: =IF($A45="","",P_Criteres!C6) -> 0 | D45: =IF($A45="","",P_Criteres!F6) -> 0 | E45: =IF($A45="","",IFERROR(INDEX(In_Retenue,MATCH($D45,In_Cles,0)),"")) -> 0 | F45: =IF($A45="",0,ROUND(MIN(P_Scale,MAX(0,IF($L45=0,$K45,$M45))),2)) -> 0 | G45: =IF($A45="",0,P_Criteres!E6) -> 0 | H45: =ROUND(F45*G45,2) -> 0 | I45: =IF($A45="",FALSE,AND(P_Criteres!G6="Oui",ISNUMBER(P_Criteres!H6),F45<=N(P_Criteres!H6))) -> 0 | J45: =IF($A45="",FALSE,AND(OR(P_Criteres!G6="Oui",P_Criteres!K6="Oui"),$E45="")) -> 0 | K45: {=IF($A45="",0,MIN(IF(P_Baremes!$A$5:$A$400=$A45,P_Baremes!$H$5:$H$400)))} -> 0 | L45: =IF($A45="",0,IF($O45="NUM",IF(ISNUMBER($E45),SUMPRODUCT((P_Baremes!$A$5:$A$400=$A45)*(P_Baremes!$B$5:$B$400="PLAGE")*(((P_Baremes!$D$5:$D$400="")+($E45>=P_Baremes!$D$5:$D$400))>0)*(((P_Baremes!$E$5:$E$400="")+($E45<P_Baremes!$E$5:$E$400))>0)),0),SUMPRODUCT((P_Baremes!$A$5:$A$400=$A45)*(P_Baremes!$B$5:$B$400="MODALITE")*(P_Baremes!$C$5:$C$400=$E45)))) -> 0 | M45: =IF($A45="",0,IF($L45=0,0,IF($O45="NUM",SUMPRODUCT((P_Baremes!$A$5:$A$400=$A45)*(P_Baremes!$B$5:$B$400="PLAGE")*(((P_Baremes!$D$5:$D$400="")+($E45>=P_Baremes!$D$5:$D$400))>0)*(((P_Baremes!$E$5:$E$400="")+($E45<P_Baremes!$E$5:$E$400))>0)*P_Baremes!$H$5:$H$400),SUMPRODUCT((P_Baremes!$A$5:$A$400=$A45)*(P_Baremes!$B$5:$B$400="MODALITE")*(P_Baremes!$C$5:$C$400=$E45)*P_Baremes!$H$5:$H$400)))) -> 0 | N45: =IF($A45="","",P_Criteres!J6) -> 0 | O45: =IF($A45="","",P_Criteres!D6) -> 0 | P45: =IF($A45="",0,IFERROR(INDEX(P_DomPoids,MATCH($B45,P_DomCodes,0)),0)) -> 0 | Q45: =P45*G45 -> 0 | R45: =IF(J45,IF(ISNUMBER(SEARCH(","&D45&",",","&R44&",")),R44,R44&IF(R44="","",",")&D45),R44) -> 0 | S45: =IF(I45,S44&IF(S44="","",", ")&A45,S44) -> 0
A46: =IF(P_Criteres!A7="","",P_Criteres!A7) -> 0 | B46: =IF($A46="","",P_Criteres!B7) -> 0 | C46: =IF($A46="","",P_Criteres!C7) -> 0 | D46: =IF($A46="","",P_Criteres!F7) -> 0 | E46: =IF($A46="","",IFERROR(INDEX(In_Retenue,MATCH($D46,In_Cles,0)),"")) -> 0 | F46: =IF($A46="",0,ROUND(MIN(P_Scale,MAX(0,IF($L46=0,$K46,$M46))),2)) -> 0 | G46: =IF($A46="",0,P_Criteres!E7) -> 0 | H46: =ROUND(F46*G46,2) -> 0 | I46: =IF($A46="",FALSE,AND(P_Criteres!G7="Oui",ISNUMBER(P_Criteres!H7),F46<=N(P_Criteres!H7))) -> 0 | J46: =IF($A46="",FALSE,AND(OR(P_Criteres!G7="Oui",P_Criteres!K7="Oui"),$E46="")) -> 0 | K46: {=IF($A46="",0,MIN(IF(P_Baremes!$A$5:$A$400=$A46,P_Baremes!$H$5:$H$400)))} -> 0 | L46: =IF($A46="",0,IF($O46="NUM",IF(ISNUMBER($E46),SUMPRODUCT((P_Baremes!$A$5:$A$400=$A46)*(P_Baremes!$B$5:$B$400="PLAGE")*(((P_Baremes!$D$5:$D$400="")+($E46>=P_Baremes!$D$5:$D$400))>0)*(((P_Baremes!$E$5:$E$400="")+($E46<P_Baremes!$E$5:$E$400))>0)),0),SUMPRODUCT((P_Baremes!$A$5:$A$400=$A46)*(P_Baremes!$B$5:$B$400="MODALITE")*(P_Baremes!$C$5:$C$400=$E46)))) -> 0 | M46: =IF($A46="",0,IF($L46=0,0,IF($O46="NUM",SUMPRODUCT((P_Baremes!$A$5:$A$400=$A46)*(P_Baremes!$B$5:$B$400="PLAGE")*(((P_Baremes!$D$5:$D$400="")+($E46>=P_Baremes!$D$5:$D$400))>0)*(((P_Baremes!$E$5:$E$400="")+($E46<P_Baremes!$E$5:$E$400))>0)*P_Baremes!$H$5:$H$400),SUMPRODUCT((P_Baremes!$A$5:$A$400=$A46)*(P_Baremes!$B$5:$B$400="MODALITE")*(P_Baremes!$C$5:$C$400=$E46)*P_Baremes!$H$5:$H$400)))) -> 0 | N46: =IF($A46="","",P_Criteres!J7) -> 0 | O46: =IF($A46="","",P_Criteres!D7) -> 0 | P46: =IF($A46="",0,IFERROR(INDEX(P_DomPoids,MATCH($B46,P_DomCodes,0)),0)) -> 0 | Q46: =P46*G46 -> 0 | R46: =IF(J46,IF(ISNUMBER(SEARCH(","&D46&",",","&R45&",")),R45,R45&IF(R45="","",",")&D46),R45) -> 0 | S46: =IF(I46,S45&IF(S45="","",", ")&A46,S45) -> 0
A47: =IF(P_Criteres!A8="","",P_Criteres!A8) -> 0 | B47: =IF($A47="","",P_Criteres!B8) -> 0 | C47: =IF($A47="","",P_Criteres!C8) -> 0 | D47: =IF($A47="","",P_Criteres!F8) -> 0 | E47: =IF($A47="","",IFERROR(INDEX(In_Retenue,MATCH($D47,In_Cles,0)),"")) -> 0 | F47: =IF($A47="",0,ROUND(MIN(P_Scale,MAX(0,IF($L47=0,$K47,$M47))),2)) -> 0 | G47: =IF($A47="",0,P_Criteres!E8) -> 0 | H47: =ROUND(F47*G47,2) -> 0 | I47: =IF($A47="",FALSE,AND(P_Criteres!G8="Oui",ISNUMBER(P_Criteres!H8),F47<=N(P_Criteres!H8))) -> 0 | J47: =IF($A47="",FALSE,AND(OR(P_Criteres!G8="Oui",P_Criteres!K8="Oui"),$E47="")) -> 0 | K47: {=IF($A47="",0,MIN(IF(P_Baremes!$A$5:$A$400=$A47,P_Baremes!$H$5:$H$400)))} -> 0 | L47: =IF($A47="",0,IF($O47="NUM",IF(ISNUMBER($E47),SUMPRODUCT((P_Baremes!$A$5:$A$400=$A47)*(P_Baremes!$B$5:$B$400="PLAGE")*(((P_Baremes!$D$5:$D$400="")+($E47>=P_Baremes!$D$5:$D$400))>0)*(((P_Baremes!$E$5:$E$400="")+($E47<P_Baremes!$E$5:$E$400))>0)),0),SUMPRODUCT((P_Baremes!$A$5:$A$400=$A47)*(P_Baremes!$B$5:$B$400="MODALITE")*(P_Baremes!$C$5:$C$400=$E47)))) -> 0 | M47: =IF($A47="",0,IF($L47=0,0,IF($O47="NUM",SUMPRODUCT((P_Baremes!$A$5:$A$400=$A47)*(P_Baremes!$B$5:$B$400="PLAGE")*(((P_Baremes!$D$5:$D$400="")+($E47>=P_Baremes!$D$5:$D$400))>0)*(((P_Baremes!$E$5:$E$400="")+($E47<P_Baremes!$E$5:$E$400))>0)*P_Baremes!$H$5:$H$400),SUMPRODUCT((P_Baremes!$A$5:$A$400=$A47)*(P_Baremes!$B$5:$B$400="MODALITE")*(P_Baremes!$C$5:$C$400=$E47)*P_Baremes!$H$5:$H$400)))) -> 0 | N47: =IF($A47="","",P_Criteres!J8) -> 0 | O47: =IF($A47="","",P_Criteres!D8) -> 0 | P47: =IF($A47="",0,IFERROR(INDEX(P_DomPoids,MATCH($B47,P_DomCodes,0)),0)) -> 0 | Q47: =P47*G47 -> 0 | R47: =IF(J47,IF(ISNUMBER(SEARCH(","&D47&",",","&R46&",")),R46,R46&IF(R46="","",",")&D47),R46) -> 0 | S47: =IF(I47,S46&IF(S46="","",", ")&A47,S46) -> 0
A48: =IF(P_Criteres!A9="","",P_Criteres!A9) -> 0 | B48: =IF($A48="","",P_Criteres!B9) -> 0 | C48: =IF($A48="","",P_Criteres!C9) -> 0 | D48: =IF($A48="","",P_Criteres!F9) -> 0 | E48: =IF($A48="","",IFERROR(INDEX(In_Retenue,MATCH($D48,In_Cles,0)),"")) -> 0 | F48: =IF($A48="",0,ROUND(MIN(P_Scale,MAX(0,IF($L48=0,$K48,$M48))),2)) -> 0 | G48: =IF($A48="",0,P_Criteres!E9) -> 0 | H48: =ROUND(F48*G48,2) -> 0 | I48: =IF($A48="",FALSE,AND(P_Criteres!G9="Oui",ISNUMBER(P_Criteres!H9),F48<=N(P_Criteres!H9))) -> 0 | J48: =IF($A48="",FALSE,AND(OR(P_Criteres!G9="Oui",P_Criteres!K9="Oui"),$E48="")) -> 0 | K48: {=IF($A48="",0,MIN(IF(P_Baremes!$A$5:$A$400=$A48,P_Baremes!$H$5:$H$400)))} -> 0 | L48: =IF($A48="",0,IF($O48="NUM",IF(ISNUMBER($E48),SUMPRODUCT((P_Baremes!$A$5:$A$400=$A48)*(P_Baremes!$B$5:$B$400="PLAGE")*(((P_Baremes!$D$5:$D$400="")+($E48>=P_Baremes!$D$5:$D$400))>0)*(((P_Baremes!$E$5:$E$400="")+($E48<P_Baremes!$E$5:$E$400))>0)),0),SUMPRODUCT((P_Baremes!$A$5:$A$400=$A48)*(P_Baremes!$B$5:$B$400="MODALITE")*(P_Baremes!$C$5:$C$400=$E48)))) -> 0 | M48: =IF($A48="",0,IF($L48=0,0,IF($O48="NUM",SUMPRODUCT((P_Baremes!$A$5:$A$400=$A48)*(P_Baremes!$B$5:$B$400="PLAGE")*(((P_Baremes!$D$5:$D$400="")+($E48>=P_Baremes!$D$5:$D$400))>0)*(((P_Baremes!$E$5:$E$400="")+($E48<P_Baremes!$E$5:$E$400))>0)*P_Baremes!$H$5:$H$400),SUMPRODUCT((P_Baremes!$A$5:$A$400=$A48)*(P_Baremes!$B$5:$B$400="MODALITE")*(P_Baremes!$C$5:$C$400=$E48)*P_Baremes!$H$5:$H$400)))) -> 0 | N48: =IF($A48="","",P_Criteres!J9) -> 0 | O48: =IF($A48="","",P_Criteres!D9) -> 0 | P48: =IF($A48="",0,IFERROR(INDEX(P_DomPoids,MATCH($B48,P_DomCodes,0)),0)) -> 0 | Q48: =P48*G48 -> 0 | R48: =IF(J48,IF(ISNUMBER(SEARCH(","&D48&",",","&R47&",")),R47,R47&IF(R47="","",",")&D48),R47) -> 0 | S48: =IF(I48,S47&IF(S47="","",", ")&A48,S47) -> 0
A49: =IF(P_Criteres!A10="","",P_Criteres!A10) -> 0 | B49: =IF($A49="","",P_Criteres!B10) -> 0 | C49: =IF($A49="","",P_Criteres!C10) -> 0 | D49: =IF($A49="","",P_Criteres!F10) -> 0 | E49: =IF($A49="","",IFERROR(INDEX(In_Retenue,MATCH($D49,In_Cles,0)),"")) -> 0 | F49: =IF($A49="",0,ROUND(MIN(P_Scale,MAX(0,IF($L49=0,$K49,$M49))),2)) -> 0 | G49: =IF($A49="",0,P_Criteres!E10) -> 0 | H49: =ROUND(F49*G49,2) -> 0 | I49: =IF($A49="",FALSE,AND(P_Criteres!G10="Oui",ISNUMBER(P_Criteres!H10),F49<=N(P_Criteres!H10))) -> 0 | J49: =IF($A49="",FALSE,AND(OR(P_Criteres!G10="Oui",P_Criteres!K10="Oui"),$E49="")) -> 0 | K49: {=IF($A49="",0,MIN(IF(P_Baremes!$A$5:$A$400=$A49,P_Baremes!$H$5:$H$400)))} -> 0 | L49: =IF($A49="",0,IF($O49="NUM",IF(ISNUMBER($E49),SUMPRODUCT((P_Baremes!$A$5:$A$400=$A49)*(P_Baremes!$B$5:$B$400="PLAGE")*(((P_Baremes!$D$5:$D$400="")+($E49>=P_Baremes!$D$5:$D$400))>0)*(((P_Baremes!$E$5:$E$400="")+($E49<P_Baremes!$E$5:$E$400))>0)),0),SUMPRODUCT((P_Baremes!$A$5:$A$400=$A49)*(P_Baremes!$B$5:$B$400="MODALITE")*(P_Baremes!$C$5:$C$400=$E49)))) -> 0 | M49: =IF($A49="",0,IF($L49=0,0,IF($O49="NUM",SUMPRODUCT((P_Baremes!$A$5:$A$400=$A49)*(P_Baremes!$B$5:$B$400="PLAGE")*(((P_Baremes!$D$5:$D$400="")+($E49>=P_Baremes!$D$5:$D$400))>0)*(((P_Baremes!$E$5:$E$400="")+($E49<P_Baremes!$E$5:$E$400))>0)*P_Baremes!$H$5:$H$400),SUMPRODUCT((P_Baremes!$A$5:$A$400=$A49)*(P_Baremes!$B$5:$B$400="MODALITE")*(P_Baremes!$C$5:$C$400=$E49)*P_Baremes!$H$5:$H$400)))) -> 0 | N49: =IF($A49="","",P_Criteres!J10) -> 0 | O49: =IF($A49="","",P_Criteres!D10) -> 0 | P49: =IF($A49="",0,IFERROR(INDEX(P_DomPoids,MATCH($B49,P_DomCodes,0)),0)) -> 0 | Q49: =P49*G49 -> 0 | R49: =IF(J49,IF(ISNUMBER(SEARCH(","&D49&",",","&R48&",")),R48,R48&IF(R48="","",",")&D49),R48) -> 0 | S49: =IF(I49,S48&IF(S48="","",", ")&A49,S48) -> 0
A50: =IF(P_Criteres!A11="","",P_Criteres!A11) -> 0 | B50: =IF($A50="","",P_Criteres!B11) -> 0 | C50: =IF($A50="","",P_Criteres!C11) -> 0 | D50: =IF($A50="","",P_Criteres!F11) -> 0 | E50: =IF($A50="","",IFERROR(INDEX(In_Retenue,MATCH($D50,In_Cles,0)),"")) -> 0 | F50: =IF($A50="",0,ROUND(MIN(P_Scale,MAX(0,IF($L50=0,$K50,$M50))),2)) -> 0 | G50: =IF($A50="",0,P_Criteres!E11) -> 0 | H50: =ROUND(F50*G50,2) -> 0 | I50: =IF($A50="",FALSE,AND(P_Criteres!G11="Oui",ISNUMBER(P_Criteres!H11),F50<=N(P_Criteres!H11))) -> 0 | J50: =IF($A50="",FALSE,AND(OR(P_Criteres!G11="Oui",P_Criteres!K11="Oui"),$E50="")) -> 0 | K50: {=IF($A50="",0,MIN(IF(P_Baremes!$A$5:$A$400=$A50,P_Baremes!$H$5:$H$400)))} -> 0 | L50: =IF($A50="",0,IF($O50="NUM",IF(ISNUMBER($E50),SUMPRODUCT((P_Baremes!$A$5:$A$400=$A50)*(P_Baremes!$B$5:$B$400="PLAGE")*(((P_Baremes!$D$5:$D$400="")+($E50>=P_Baremes!$D$5:$D$400))>0)*(((P_Baremes!$E$5:$E$400="")+($E50<P_Baremes!$E$5:$E$400))>0)),0),SUMPRODUCT((P_Baremes!$A$5:$A$400=$A50)*(P_Baremes!$B$5:$B$400="MODALITE")*(P_Baremes!$C$5:$C$400=$E50)))) -> 0 | M50: =IF($A50="",0,IF($L50=0,0,IF($O50="NUM",SUMPRODUCT((P_Baremes!$A$5:$A$400=$A50)*(P_Baremes!$B$5:$B$400="PLAGE")*(((P_Baremes!$D$5:$D$400="")+($E50>=P_Baremes!$D$5:$D$400))>0)*(((P_Baremes!$E$5:$E$400="")+($E50<P_Baremes!$E$5:$E$400))>0)*P_Baremes!$H$5:$H$400),SUMPRODUCT((P_Baremes!$A$5:$A$400=$A50)*(P_Baremes!$B$5:$B$400="MODALITE")*(P_Baremes!$C$5:$C$400=$E50)*P_Baremes!$H$5:$H$400)))) -> 0 | N50: =IF($A50="","",P_Criteres!J11) -> 0 | O50: =IF($A50="","",P_Criteres!D11) -> 0 | P50: =IF($A50="",0,IFERROR(INDEX(P_DomPoids,MATCH($B50,P_DomCodes,0)),0)) -> 0 | Q50: =P50*G50 -> 0 | R50: =IF(J50,IF(ISNUMBER(SEARCH(","&D50&",",","&R49&",")),R49,R49&IF(R49="","",",")&D50),R49) -> 0 | S50: =IF(I50,S49&IF(S49="","",", ")&A50,S49) -> 0
A51: =IF(P_Criteres!A12="","",P_Criteres!A12) -> 0 | B51: =IF($A51="","",P_Criteres!B12) -> 0 | C51: =IF($A51="","",P_Criteres!C12) -> 0 | D51: =IF($A51="","",P_Criteres!F12) -> 0 | E51: =IF($A51="","",IFERROR(INDEX(In_Retenue,MATCH($D51,In_Cles,0)),"")) -> 0 | F51: =IF($A51="",0,ROUND(MIN(P_Scale,MAX(0,IF($L51=0,$K51,$M51))),2)) -> 0 | G51: =IF($A51="",0,P_Criteres!E12) -> 0 | H51: =ROUND(F51*G51,2) -> 0 | I51: =IF($A51="",FALSE,AND(P_Criteres!G12="Oui",ISNUMBER(P_Criteres!H12),F51<=N(P_Criteres!H12))) -> 0 | J51: =IF($A51="",FALSE,AND(OR(P_Criteres!G12="Oui",P_Criteres!K12="Oui"),$E51="")) -> 0 | K51: {=IF($A51="",0,MIN(IF(P_Baremes!$A$5:$A$400=$A51,P_Baremes!$H$5:$H$400)))} -> 0 | L51: =IF($A51="",0,IF($O51="NUM",IF(ISNUMBER($E51),SUMPRODUCT((P_Baremes!$A$5:$A$400=$A51)*(P_Baremes!$B$5:$B$400="PLAGE")*(((P_Baremes!$D$5:$D$400="")+($E51>=P_Baremes!$D$5:$D$400))>0)*(((P_Baremes!$E$5:$E$400="")+($E51<P_Baremes!$E$5:$E$400))>0)),0),SUMPRODUCT((P_Baremes!$A$5:$A$400=$A51)*(P_Baremes!$B$5:$B$400="MODALITE")*(P_Baremes!$C$5:$C$400=$E51)))) -> 0 | M51: =IF($A51="",0,IF($L51=0,0,IF($O51="NUM",SUMPRODUCT((P_Baremes!$A$5:$A$400=$A51)*(P_Baremes!$B$5:$B$400="PLAGE")*(((P_Baremes!$D$5:$D$400="")+($E51>=P_Baremes!$D$5:$D$400))>0)*(((P_Baremes!$E$5:$E$400="")+($E51<P_Baremes!$E$5:$E$400))>0)*P_Baremes!$H$5:$H$400),SUMPRODUCT((P_Baremes!$A$5:$A$400=$A51)*(P_Baremes!$B$5:$B$400="MODALITE")*(P_Baremes!$C$5:$C$400=$E51)*P_Baremes!$H$5:$H$400)))) -> 0 | N51: =IF($A51="","",P_Criteres!J12) -> 0 | O51: =IF($A51="","",P_Criteres!D12) -> 0 | P51: =IF($A51="",0,IFERROR(INDEX(P_DomPoids,MATCH($B51,P_DomCodes,0)),0)) -> 0 | Q51: =P51*G51 -> 0 | R51: =IF(J51,IF(ISNUMBER(SEARCH(","&D51&",",","&R50&",")),R50,R50&IF(R50="","",",")&D51),R50) -> 0 | S51: =IF(I51,S50&IF(S50="","",", ")&A51,S50) -> 0
A52: =IF(P_Criteres!A13="","",P_Criteres!A13) -> 0 | B52: =IF($A52="","",P_Criteres!B13) -> 0 | C52: =IF($A52="","",P_Criteres!C13) -> 0 | D52: =IF($A52="","",P_Criteres!F13) -> 0 | E52: =IF($A52="","",IFERROR(INDEX(In_Retenue,MATCH($D52,In_Cles,0)),"")) -> 0 | F52: =IF($A52="",0,ROUND(MIN(P_Scale,MAX(0,IF($L52=0,$K52,$M52))),2)) -> 0 | G52: =IF($A52="",0,P_Criteres!E13) -> 0 | H52: =ROUND(F52*G52,2) -> 0 | I52: =IF($A52="",FALSE,AND(P_Criteres!G13="Oui",ISNUMBER(P_Criteres!H13),F52<=N(P_Criteres!H13))) -> 0 | J52: =IF($A52="",FALSE,AND(OR(P_Criteres!G13="Oui",P_Criteres!K13="Oui"),$E52="")) -> 0 | K52: {=IF($A52="",0,MIN(IF(P_Baremes!$A$5:$A$400=$A52,P_Baremes!$H$5:$H$400)))} -> 0 | L52: =IF($A52="",0,IF($O52="NUM",IF(ISNUMBER($E52),SUMPRODUCT((P_Baremes!$A$5:$A$400=$A52)*(P_Baremes!$B$5:$B$400="PLAGE")*(((P_Baremes!$D$5:$D$400="")+($E52>=P_Baremes!$D$5:$D$400))>0)*(((P_Baremes!$E$5:$E$400="")+($E52<P_Baremes!$E$5:$E$400))>0)),0),SUMPRODUCT((P_Baremes!$A$5:$A$400=$A52)*(P_Baremes!$B$5:$B$400="MODALITE")*(P_Baremes!$C$5:$C$400=$E52)))) -> 0 | M52: =IF($A52="",0,IF($L52=0,0,IF($O52="NUM",SUMPRODUCT((P_Baremes!$A$5:$A$400=$A52)*(P_Baremes!$B$5:$B$400="PLAGE")*(((P_Baremes!$D$5:$D$400="")+($E52>=P_Baremes!$D$5:$D$400))>0)*(((P_Baremes!$E$5:$E$400="")+($E52<P_Baremes!$E$5:$E$400))>0)*P_Baremes!$H$5:$H$400),SUMPRODUCT((P_Baremes!$A$5:$A$400=$A52)*(P_Baremes!$B$5:$B$400="MODALITE")*(P_Baremes!$C$5:$C$400=$E52)*P_Baremes!$H$5:$H$400)))) -> 0 | N52: =IF($A52="","",P_Criteres!J13) -> 0 | O52: =IF($A52="","",P_Criteres!D13) -> 0 | P52: =IF($A52="",0,IFERROR(INDEX(P_DomPoids,MATCH($B52,P_DomCodes,0)),0)) -> 0 | Q52: =P52*G52 -> 0 | R52: =IF(J52,IF(ISNUMBER(SEARCH(","&D52&",",","&R51&",")),R51,R51&IF(R51="","",",")&D52),R51) -> 0 | S52: =IF(I52,S51&IF(S51="","",", ")&A52,S51) -> 0
A53: =IF(P_Criteres!A14="","",P_Criteres!A14) -> 0 | B53: =IF($A53="","",P_Criteres!B14) -> 0 | C53: =IF($A53="","",P_Criteres!C14) -> 0 | D53: =IF($A53="","",P_Criteres!F14) -> 0 | E53: =IF($A53="","",IFERROR(INDEX(In_Retenue,MATCH($D53,In_Cles,0)),"")) -> 0 | F53: =IF($A53="",0,ROUND(MIN(P_Scale,MAX(0,IF($L53=0,$K53,$M53))),2)) -> 0 | G53: =IF($A53="",0,P_Criteres!E14) -> 0 | H53: =ROUND(F53*G53,2) -> 0 | I53: =IF($A53="",FALSE,AND(P_Criteres!G14="Oui",ISNUMBER(P_Criteres!H14),F53<=N(P_Criteres!H14))) -> 0 | J53: =IF($A53="",FALSE,AND(OR(P_Criteres!G14="Oui",P_Criteres!K14="Oui"),$E53="")) -> 0 | K53: {=IF($A53="",0,MIN(IF(P_Baremes!$A$5:$A$400=$A53,P_Baremes!$H$5:$H$400)))} -> 0 | L53: =IF($A53="",0,IF($O53="NUM",IF(ISNUMBER($E53),SUMPRODUCT((P_Baremes!$A$5:$A$400=$A53)*(P_Baremes!$B$5:$B$400="PLAGE")*(((P_Baremes!$D$5:$D$400="")+($E53>=P_Baremes!$D$5:$D$400))>0)*(((P_Baremes!$E$5:$E$400="")+($E53<P_Baremes!$E$5:$E$400))>0)),0),SUMPRODUCT((P_Baremes!$A$5:$A$400=$A53)*(P_Baremes!$B$5:$B$400="MODALITE")*(P_Baremes!$C$5:$C$400=$E53)))) -> 0 | M53: =IF($A53="",0,IF($L53=0,0,IF($O53="NUM",SUMPRODUCT((P_Baremes!$A$5:$A$400=$A53)*(P_Baremes!$B$5:$B$400="PLAGE")*(((P_Baremes!$D$5:$D$400="")+($E53>=P_Baremes!$D$5:$D$400))>0)*(((P_Baremes!$E$5:$E$400="")+($E53<P_Baremes!$E$5:$E$400))>0)*P_Baremes!$H$5:$H$400),SUMPRODUCT((P_Baremes!$A$5:$A$400=$A53)*(P_Baremes!$B$5:$B$400="MODALITE")*(P_Baremes!$C$5:$C$400=$E53)*P_Baremes!$H$5:$H$400)))) -> 0 | N53: =IF($A53="","",P_Criteres!J14) -> 0 | O53: =IF($A53="","",P_Criteres!D14) -> 0 | P53: =IF($A53="",0,IFERROR(INDEX(P_DomPoids,MATCH($B53,P_DomCodes,0)),0)) -> 0 | Q53: =P53*G53 -> 0 | R53: =IF(J53,IF(ISNUMBER(SEARCH(","&D53&",",","&R52&",")),R52,R52&IF(R52="","",",")&D53),R52) -> 0 | S53: =IF(I53,S52&IF(S52="","",", ")&A53,S52) -> 0
A54: =IF(P_Criteres!A15="","",P_Criteres!A15) -> 0 | B54: =IF($A54="","",P_Criteres!B15) -> 0 | C54: =IF($A54="","",P_Criteres!C15) -> 0 | D54: =IF($A54="","",P_Criteres!F15) -> 0 | E54: =IF($A54="","",IFERROR(INDEX(In_Retenue,MATCH($D54,In_Cles,0)),"")) -> 0 | F54: =IF($A54="",0,ROUND(MIN(P_Scale,MAX(0,IF($L54=0,$K54,$M54))),2)) -> 0 | G54: =IF($A54="",0,P_Criteres!E15) -> 0 | H54: =ROUND(F54*G54,2) -> 0 | I54: =IF($A54="",FALSE,AND(P_Criteres!G15="Oui",ISNUMBER(P_Criteres!H15),F54<=N(P_Criteres!H15))) -> 0 | J54: =IF($A54="",FALSE,AND(OR(P_Criteres!G15="Oui",P_Criteres!K15="Oui"),$E54="")) -> 0 | K54: {=IF($A54="",0,MIN(IF(P_Baremes!$A$5:$A$400=$A54,P_Baremes!$H$5:$H$400)))} -> 0 | L54: =IF($A54="",0,IF($O54="NUM",IF(ISNUMBER($E54),SUMPRODUCT((P_Baremes!$A$5:$A$400=$A54)*(P_Baremes!$B$5:$B$400="PLAGE")*(((P_Baremes!$D$5:$D$400="")+($E54>=P_Baremes!$D$5:$D$400))>0)*(((P_Baremes!$E$5:$E$400="")+($E54<P_Baremes!$E$5:$E$400))>0)),0),SUMPRODUCT((P_Baremes!$A$5:$A$400=$A54)*(P_Baremes!$B$5:$B$400="MODALITE")*(P_Baremes!$C$5:$C$400=$E54)))) -> 0 | M54: =IF($A54="",0,IF($L54=0,0,IF($O54="NUM",SUMPRODUCT((P_Baremes!$A$5:$A$400=$A54)*(P_Baremes!$B$5:$B$400="PLAGE")*(((P_Baremes!$D$5:$D$400="")+($E54>=P_Baremes!$D$5:$D$400))>0)*(((P_Baremes!$E$5:$E$400="")+($E54<P_Baremes!$E$5:$E$400))>0)*P_Baremes!$H$5:$H$400),SUMPRODUCT((P_Baremes!$A$5:$A$400=$A54)*(P_Baremes!$B$5:$B$400="MODALITE")*(P_Baremes!$C$5:$C$400=$E54)*P_Baremes!$H$5:$H$400)))) -> 0 | N54: =IF($A54="","",P_Criteres!J15) -> 0 | O54: =IF($A54="","",P_Criteres!D15) -> 0 | P54: =IF($A54="",0,IFERROR(INDEX(P_DomPoids,MATCH($B54,P_DomCodes,0)),0)) -> 0 | Q54: =P54*G54 -> 0 | R54: =IF(J54,IF(ISNUMBER(SEARCH(","&D54&",",","&R53&",")),R53,R53&IF(R53="","",",")&D54),R53) -> 0 | S54: =IF(I54,S53&IF(S53="","",", ")&A54,S53) -> 0
A55: =IF(P_Criteres!A16="","",P_Criteres!A16) -> 0 | B55: =IF($A55="","",P_Criteres!B16) -> 0 | C55: =IF($A55="","",P_Criteres!C16) -> 0 | D55: =IF($A55="","",P_Criteres!F16) -> 0 | E55: =IF($A55="","",IFERROR(INDEX(In_Retenue,MATCH($D55,In_Cles,0)),"")) -> 0 | F55: =IF($A55="",0,ROUND(MIN(P_Scale,MAX(0,IF($L55=0,$K55,$M55))),2)) -> 0 | G55: =IF($A55="",0,P_Criteres!E16) -> 0 | H55: =ROUND(F55*G55,2) -> 0 | I55: =IF($A55="",FALSE,AND(P_Criteres!G16="Oui",ISNUMBER(P_Criteres!H16),F55<=N(P_Criteres!H16))) -> 0 | J55: =IF($A55="",FALSE,AND(OR(P_Criteres!G16="Oui",P_Criteres!K16="Oui"),$E55="")) -> 0 | K55: {=IF($A55="",0,MIN(IF(P_Baremes!$A$5:$A$400=$A55,P_Baremes!$H$5:$H$400)))} -> 0 | L55: =IF($A55="",0,IF($O55="NUM",IF(ISNUMBER($E55),SUMPRODUCT((P_Baremes!$A$5:$A$400=$A55)*(P_Baremes!$B$5:$B$400="PLAGE")*(((P_Baremes!$D$5:$D$400="")+($E55>=P_Baremes!$D$5:$D$400))>0)*(((P_Baremes!$E$5:$E$400="")+($E55<P_Baremes!$E$5:$E$400))>0)),0),SUMPRODUCT((P_Baremes!$A$5:$A$400=$A55)*(P_Baremes!$B$5:$B$400="MODALITE")*(P_Baremes!$C$5:$C$400=$E55)))) -> 0 | M55: =IF($A55="",0,IF($L55=0,0,IF($O55="NUM",SUMPRODUCT((P_Baremes!$A$5:$A$400=$A55)*(P_Baremes!$B$5:$B$400="PLAGE")*(((P_Baremes!$D$5:$D$400="")+($E55>=P_Baremes!$D$5:$D$400))>0)*(((P_Baremes!$E$5:$E$400="")+($E55<P_Baremes!$E$5:$E$400))>0)*P_Baremes!$H$5:$H$400),SUMPRODUCT((P_Baremes!$A$5:$A$400=$A55)*(P_Baremes!$B$5:$B$400="MODALITE")*(P_Baremes!$C$5:$C$400=$E55)*P_Baremes!$H$5:$H$400)))) -> 0 | N55: =IF($A55="","",P_Criteres!J16) -> 0 | O55: =IF($A55="","",P_Criteres!D16) -> 0 | P55: =IF($A55="",0,IFERROR(INDEX(P_DomPoids,MATCH($B55,P_DomCodes,0)),0)) -> 0 | Q55: =P55*G55 -> 0 | R55: =IF(J55,IF(ISNUMBER(SEARCH(","&D55&",",","&R54&",")),R54,R54&IF(R54="","",",")&D55),R54) -> 0 | S55: =IF(I55,S54&IF(S54="","",", ")&A55,S54) -> 0
... A103: =IF(P_Criteres!A64="","",P_Criteres!A64) -> 0 | B103: =IF($A103="","",P_Criteres!B64) -> 0 | C103: =IF($A103="","",P_Criteres!C64) -> 0 | D103: =IF($A103="","",P_Criteres!F64) -> 0 | E103: =IF($A103="","",IFERROR(INDEX(In_Retenue,MATCH($D103,In_Cles,0)),"")) -> 0 | F103: =IF($A103="",0,ROUND(MIN(P_Scale,MAX(0,IF($L103=0,$K103,$M103))),2)) -> 0 | G103: =IF($A103="",0,P_Criteres!E64) -> 0 | H103: =ROUND(F103*G103,2) -> 0 | I103: =IF($A103="",FALSE,AND(P_Criteres!G64="Oui",ISNUMBER(P_Criteres!H64),F103<=N(P_Criteres!H64))) -> 0 | J103: =IF($A103="",FALSE,AND(OR(P_Criteres!G64="Oui",P_Criteres!K64="Oui"),$E103="")) -> 0 | K103: {=IF($A103="",0,MIN(IF(P_Baremes!$A$5:$A$400=$A103,P_Baremes!$H$5:$H$400)))} -> 0 | L103: =IF($A103="",0,IF($O103="NUM",IF(ISNUMBER($E103),SUMPRODUCT((P_Baremes!$A$5:$A$400=$A103)*(P_Baremes!$B$5:$B$400="PLAGE")*(((P_Baremes!$D$5:$D$400="")+($E103>=P_Baremes!$D$5:$D$400))>0)*(((P_Baremes!$E$5:$E$400="")+($E103<P_Baremes!$E$5:$E$400))>0)),0),SUMPRODUCT((P_Baremes!$A$5:$A$400=$A103)*(P_Baremes!$B$5:$B$400="MODALITE")*(P_Baremes!$C$5:$C$400=$E103)))) -> 0 | M103: =IF($A103="",0,IF($L103=0,0,IF($O103="NUM",SUMPRODUCT((P_Baremes!$A$5:$A$400=$A103)*(P_Baremes!$B$5:$B$400="PLAGE")*(((P_Baremes!$D$5:$D$400="")+($E103>=P_Baremes!$D$5:$D$400))>0)*(((P_Baremes!$E$5:$E$400="")+($E103<P_Baremes!$E$5:$E$400))>0)*P_Baremes!$H$5:$H$400),SUMPRODUCT((P_Baremes!$A$5:$A$400=$A103)*(P_Baremes!$B$5:$B$400="MODALITE")*(P_Baremes!$C$5:$C$400=$E103)*P_Baremes!$H$5:$H$400)))) -> 0 | N103: =IF($A103="","",P_Criteres!J64) -> 0 | O103: =IF($A103="","",P_Criteres!D64) -> 0 | P103: =IF($A103="",0,IFERROR(INDEX(P_DomPoids,MATCH($B103,P_DomCodes,0)),0)) -> 0 | Q103: =P103*G103 -> 0 | R103: =IF(J103,IF(ISNUMBER(SEARCH(","&D103&",",","&R102&",")),R102,R102&IF(R102="","",",")&D103),R102) -> 0 | S103: =IF(I103,S102&IF(S102="","",", ")&A103,S102) -> 0
A106: Détail des alertes D5
A107: Code | B107: Libellé | C107: Sévérité | D107: Opérateur | E107: Clé | F107: Valeur | G107: Valeur réf. | H107: Déclenchée | I107: Non exclue (donnée absente) | J107: Malus appliqué | K107: Comité | L107: Clé numérique manquante | M107: Cumul manquantes | N107: Cumul alertes
A108: =IF(P_Alertes!A5="","",P_Alertes!A5) -> 0 | B108: =IF($A108="","",P_Alertes!B5) -> 0 | C108: =IF($A108="","",P_Alertes!C5) -> 0 | D108: =IF($A108="","",P_Alertes!G5) -> 0 | E108: =IF($A108="","",P_Alertes!F5) -> 0 | F108: =IF($A108="","",IFERROR(INDEX(In_Retenue,MATCH($E108,In_Cles,0)),"")) -> 0 | G108: =IF($A108="","",IF(P_Alertes!H5="","",P_Alertes!H5)) -> 0 | H108: =IF($A108="",FALSE,IF(D108="isTrue",F108=TRUE,IF(D108="isFalse",F108=FALSE,IF(D108="eq",F108=G108,IF(D108="neq",F108<>G108,IF(D108="gt",AND(ISNUMBER(F108),ISNUMBER(G108),N(F108)>N(G108)),IF(D108="gte",AND(ISNUMBER(F108),ISNUMBER(G108),N(F108)>=N(G108)),IF(D108="lt",AND(ISNUMBER(F108),ISNUMBER(G108),N(F108)<N(G108)),IF(D108="lte",AND(ISNUMBER(F108),ISNUMBER(G108),N(F108)<=N(G108)),FALSE))))))))) -> 0 | I108: =IF($A108="",FALSE,AND(NOT(H108),C108<>"BLOCKING",L108)) -> 0 | J108: =IF(OR(H108,I108),N(P_Alertes!D5),0) -> 0 | K108: =IF($A108="",FALSE,AND(OR(H108,I108),P_Alertes!I5="Oui")) -> 0 | L108: =IF($A108="",FALSE,AND(OR(D108="gt",D108="gte",D108="lt",D108="lte"),F108="")) -> 0 | M108: =IF(L108,IF(ISNUMBER(SEARCH(","&E108&",",","&R103&",")),R103,R103&IF(R103="","",",")&E108),R103) -> 0 | N108: =IF(OR(H108,I108),""&IF(""="","",", ")&A108,"") -> 0
A109: =IF(P_Alertes!A6="","",P_Alertes!A6) -> 0 | B109: =IF($A109="","",P_Alertes!B6) -> 0 | C109: =IF($A109="","",P_Alertes!C6) -> 0 | D109: =IF($A109="","",P_Alertes!G6) -> 0 | E109: =IF($A109="","",P_Alertes!F6) -> 0 | F109: =IF($A109="","",IFERROR(INDEX(In_Retenue,MATCH($E109,In_Cles,0)),"")) -> 0 | G109: =IF($A109="","",IF(P_Alertes!H6="","",P_Alertes!H6)) -> 0 | H109: =IF($A109="",FALSE,IF(D109="isTrue",F109=TRUE,IF(D109="isFalse",F109=FALSE,IF(D109="eq",F109=G109,IF(D109="neq",F109<>G109,IF(D109="gt",AND(ISNUMBER(F109),ISNUMBER(G109),N(F109)>N(G109)),IF(D109="gte",AND(ISNUMBER(F109),ISNUMBER(G109),N(F109)>=N(G109)),IF(D109="lt",AND(ISNUMBER(F109),ISNUMBER(G109),N(F109)<N(G109)),IF(D109="lte",AND(ISNUMBER(F109),ISNUMBER(G109),N(F109)<=N(G109)),FALSE))))))))) -> 0 | I109: =IF($A109="",FALSE,AND(NOT(H109),C109<>"BLOCKING",L109)) -> 0 | J109: =IF(OR(H109,I109),N(P_Alertes!D6),0) -> 0 | K109: =IF($A109="",FALSE,AND(OR(H109,I109),P_Alertes!I6="Oui")) -> 0 | L109: =IF($A109="",FALSE,AND(OR(D109="gt",D109="gte",D109="lt",D109="lte"),F109="")) -> 0 | M109: =IF(L109,IF(ISNUMBER(SEARCH(","&E109&",",","&M108&",")),M108,M108&IF(M108="","",",")&E109),M108) -> 0 | N109: =IF(OR(H109,I109),N108&IF(N108="","",", ")&A109,N108) -> 0
A110: =IF(P_Alertes!A7="","",P_Alertes!A7) -> 0 | B110: =IF($A110="","",P_Alertes!B7) -> 0 | C110: =IF($A110="","",P_Alertes!C7) -> 0 | D110: =IF($A110="","",P_Alertes!G7) -> 0 | E110: =IF($A110="","",P_Alertes!F7) -> 0 | F110: =IF($A110="","",IFERROR(INDEX(In_Retenue,MATCH($E110,In_Cles,0)),"")) -> 0 | G110: =IF($A110="","",IF(P_Alertes!H7="","",P_Alertes!H7)) -> 0 | H110: =IF($A110="",FALSE,IF(D110="isTrue",F110=TRUE,IF(D110="isFalse",F110=FALSE,IF(D110="eq",F110=G110,IF(D110="neq",F110<>G110,IF(D110="gt",AND(ISNUMBER(F110),ISNUMBER(G110),N(F110)>N(G110)),IF(D110="gte",AND(ISNUMBER(F110),ISNUMBER(G110),N(F110)>=N(G110)),IF(D110="lt",AND(ISNUMBER(F110),ISNUMBER(G110),N(F110)<N(G110)),IF(D110="lte",AND(ISNUMBER(F110),ISNUMBER(G110),N(F110)<=N(G110)),FALSE))))))))) -> 0 | I110: =IF($A110="",FALSE,AND(NOT(H110),C110<>"BLOCKING",L110)) -> 0 | J110: =IF(OR(H110,I110),N(P_Alertes!D7),0) -> 0 | K110: =IF($A110="",FALSE,AND(OR(H110,I110),P_Alertes!I7="Oui")) -> 0 | L110: =IF($A110="",FALSE,AND(OR(D110="gt",D110="gte",D110="lt",D110="lte"),F110="")) -> 0 | M110: =IF(L110,IF(ISNUMBER(SEARCH(","&E110&",",","&M109&",")),M109,M109&IF(M109="","",",")&E110),M109) -> 0 | N110: =IF(OR(H110,I110),N109&IF(N109="","",", ")&A110,N109) -> 0
A111: =IF(P_Alertes!A8="","",P_Alertes!A8) -> 0 | B111: =IF($A111="","",P_Alertes!B8) -> 0 | C111: =IF($A111="","",P_Alertes!C8) -> 0 | D111: =IF($A111="","",P_Alertes!G8) -> 0 | E111: =IF($A111="","",P_Alertes!F8) -> 0 | F111: =IF($A111="","",IFERROR(INDEX(In_Retenue,MATCH($E111,In_Cles,0)),"")) -> 0 | G111: =IF($A111="","",IF(P_Alertes!H8="","",P_Alertes!H8)) -> 0 | H111: =IF($A111="",FALSE,IF(D111="isTrue",F111=TRUE,IF(D111="isFalse",F111=FALSE,IF(D111="eq",F111=G111,IF(D111="neq",F111<>G111,IF(D111="gt",AND(ISNUMBER(F111),ISNUMBER(G111),N(F111)>N(G111)),IF(D111="gte",AND(ISNUMBER(F111),ISNUMBER(G111),N(F111)>=N(G111)),IF(D111="lt",AND(ISNUMBER(F111),ISNUMBER(G111),N(F111)<N(G111)),IF(D111="lte",AND(ISNUMBER(F111),ISNUMBER(G111),N(F111)<=N(G111)),FALSE))))))))) -> 0 | I111: =IF($A111="",FALSE,AND(NOT(H111),C111<>"BLOCKING",L111)) -> 0 | J111: =IF(OR(H111,I111),N(P_Alertes!D8),0) -> 0 | K111: =IF($A111="",FALSE,AND(OR(H111,I111),P_Alertes!I8="Oui")) -> 0 | L111: =IF($A111="",FALSE,AND(OR(D111="gt",D111="gte",D111="lt",D111="lte"),F111="")) -> 0 | M111: =IF(L111,IF(ISNUMBER(SEARCH(","&E111&",",","&M110&",")),M110,M110&IF(M110="","",",")&E111),M110) -> 0 | N111: =IF(OR(H111,I111),N110&IF(N110="","",", ")&A111,N110) -> 0
A112: =IF(P_Alertes!A9="","",P_Alertes!A9) -> 0 | B112: =IF($A112="","",P_Alertes!B9) -> 0 | C112: =IF($A112="","",P_Alertes!C9) -> 0 | D112: =IF($A112="","",P_Alertes!G9) -> 0 | E112: =IF($A112="","",P_Alertes!F9) -> 0 | F112: =IF($A112="","",IFERROR(INDEX(In_Retenue,MATCH($E112,In_Cles,0)),"")) -> 0 | G112: =IF($A112="","",IF(P_Alertes!H9="","",P_Alertes!H9)) -> 0 | H112: =IF($A112="",FALSE,IF(D112="isTrue",F112=TRUE,IF(D112="isFalse",F112=FALSE,IF(D112="eq",F112=G112,IF(D112="neq",F112<>G112,IF(D112="gt",AND(ISNUMBER(F112),ISNUMBER(G112),N(F112)>N(G112)),IF(D112="gte",AND(ISNUMBER(F112),ISNUMBER(G112),N(F112)>=N(G112)),IF(D112="lt",AND(ISNUMBER(F112),ISNUMBER(G112),N(F112)<N(G112)),IF(D112="lte",AND(ISNUMBER(F112),ISNUMBER(G112),N(F112)<=N(G112)),FALSE))))))))) -> 0 | I112: =IF($A112="",FALSE,AND(NOT(H112),C112<>"BLOCKING",L112)) -> 0 | J112: =IF(OR(H112,I112),N(P_Alertes!D9),0) -> 0 | K112: =IF($A112="",FALSE,AND(OR(H112,I112),P_Alertes!I9="Oui")) -> 0 | L112: =IF($A112="",FALSE,AND(OR(D112="gt",D112="gte",D112="lt",D112="lte"),F112="")) -> 0 | M112: =IF(L112,IF(ISNUMBER(SEARCH(","&E112&",",","&M111&",")),M111,M111&IF(M111="","",",")&E112),M111) -> 0 | N112: =IF(OR(H112,I112),N111&IF(N111="","",", ")&A112,N111) -> 0
A113: =IF(P_Alertes!A10="","",P_Alertes!A10) -> 0 | B113: =IF($A113="","",P_Alertes!B10) -> 0 | C113: =IF($A113="","",P_Alertes!C10) -> 0 | D113: =IF($A113="","",P_Alertes!G10) -> 0 | E113: =IF($A113="","",P_Alertes!F10) -> 0 | F113: =IF($A113="","",IFERROR(INDEX(In_Retenue,MATCH($E113,In_Cles,0)),"")) -> 0 | G113: =IF($A113="","",IF(P_Alertes!H10="","",P_Alertes!H10)) -> 0 | H113: =IF($A113="",FALSE,IF(D113="isTrue",F113=TRUE,IF(D113="isFalse",F113=FALSE,IF(D113="eq",F113=G113,IF(D113="neq",F113<>G113,IF(D113="gt",AND(ISNUMBER(F113),ISNUMBER(G113),N(F113)>N(G113)),IF(D113="gte",AND(ISNUMBER(F113),ISNUMBER(G113),N(F113)>=N(G113)),IF(D113="lt",AND(ISNUMBER(F113),ISNUMBER(G113),N(F113)<N(G113)),IF(D113="lte",AND(ISNUMBER(F113),ISNUMBER(G113),N(F113)<=N(G113)),FALSE))))))))) -> 0 | I113: =IF($A113="",FALSE,AND(NOT(H113),C113<>"BLOCKING",L113)) -> 0 | J113: =IF(OR(H113,I113),N(P_Alertes!D10),0) -> 0 | K113: =IF($A113="",FALSE,AND(OR(H113,I113),P_Alertes!I10="Oui")) -> 0 | L113: =IF($A113="",FALSE,AND(OR(D113="gt",D113="gte",D113="lt",D113="lte"),F113="")) -> 0 | M113: =IF(L113,IF(ISNUMBER(SEARCH(","&E113&",",","&M112&",")),M112,M112&IF(M112="","",",")&E113),M112) -> 0 | N113: =IF(OR(H113,I113),N112&IF(N112="","",", ")&A113,N112) -> 0
A114: =IF(P_Alertes!A11="","",P_Alertes!A11) -> 0 | B114: =IF($A114="","",P_Alertes!B11) -> 0 | C114: =IF($A114="","",P_Alertes!C11) -> 0 | D114: =IF($A114="","",P_Alertes!G11) -> 0 | E114: =IF($A114="","",P_Alertes!F11) -> 0 | F114: =IF($A114="","",IFERROR(INDEX(In_Retenue,MATCH($E114,In_Cles,0)),"")) -> 0 | G114: =IF($A114="","",IF(P_Alertes!H11="","",P_Alertes!H11)) -> 0 | H114: =IF($A114="",FALSE,IF(D114="isTrue",F114=TRUE,IF(D114="isFalse",F114=FALSE,IF(D114="eq",F114=G114,IF(D114="neq",F114<>G114,IF(D114="gt",AND(ISNUMBER(F114),ISNUMBER(G114),N(F114)>N(G114)),IF(D114="gte",AND(ISNUMBER(F114),ISNUMBER(G114),N(F114)>=N(G114)),IF(D114="lt",AND(ISNUMBER(F114),ISNUMBER(G114),N(F114)<N(G114)),IF(D114="lte",AND(ISNUMBER(F114),ISNUMBER(G114),N(F114)<=N(G114)),FALSE))))))))) -> 0 | I114: =IF($A114="",FALSE,AND(NOT(H114),C114<>"BLOCKING",L114)) -> 0 | J114: =IF(OR(H114,I114),N(P_Alertes!D11),0) -> 0 | K114: =IF($A114="",FALSE,AND(OR(H114,I114),P_Alertes!I11="Oui")) -> 0 | L114: =IF($A114="",FALSE,AND(OR(D114="gt",D114="gte",D114="lt",D114="lte"),F114="")) -> 0 | M114: =IF(L114,IF(ISNUMBER(SEARCH(","&E114&",",","&M113&",")),M113,M113&IF(M113="","",",")&E114),M113) -> 0 | N114: =IF(OR(H114,I114),N113&IF(N113="","",", ")&A114,N113) -> 0
A115: =IF(P_Alertes!A12="","",P_Alertes!A12) -> 0 | B115: =IF($A115="","",P_Alertes!B12) -> 0 | C115: =IF($A115="","",P_Alertes!C12) -> 0 | D115: =IF($A115="","",P_Alertes!G12) -> 0 | E115: =IF($A115="","",P_Alertes!F12) -> 0 | F115: =IF($A115="","",IFERROR(INDEX(In_Retenue,MATCH($E115,In_Cles,0)),"")) -> 0 | G115: =IF($A115="","",IF(P_Alertes!H12="","",P_Alertes!H12)) -> 0 | H115: =IF($A115="",FALSE,IF(D115="isTrue",F115=TRUE,IF(D115="isFalse",F115=FALSE,IF(D115="eq",F115=G115,IF(D115="neq",F115<>G115,IF(D115="gt",AND(ISNUMBER(F115),ISNUMBER(G115),N(F115)>N(G115)),IF(D115="gte",AND(ISNUMBER(F115),ISNUMBER(G115),N(F115)>=N(G115)),IF(D115="lt",AND(ISNUMBER(F115),ISNUMBER(G115),N(F115)<N(G115)),IF(D115="lte",AND(ISNUMBER(F115),ISNUMBER(G115),N(F115)<=N(G115)),FALSE))))))))) -> 0 | I115: =IF($A115="",FALSE,AND(NOT(H115),C115<>"BLOCKING",L115)) -> 0 | J115: =IF(OR(H115,I115),N(P_Alertes!D12),0) -> 0 | K115: =IF($A115="",FALSE,AND(OR(H115,I115),P_Alertes!I12="Oui")) -> 0 | L115: =IF($A115="",FALSE,AND(OR(D115="gt",D115="gte",D115="lt",D115="lte"),F115="")) -> 0 | M115: =IF(L115,IF(ISNUMBER(SEARCH(","&E115&",",","&M114&",")),M114,M114&IF(M114="","",",")&E115),M114) -> 0 | N115: =IF(OR(H115,I115),N114&IF(N114="","",", ")&A115,N114) -> 0
A116: =IF(P_Alertes!A13="","",P_Alertes!A13) -> 0 | B116: =IF($A116="","",P_Alertes!B13) -> 0 | C116: =IF($A116="","",P_Alertes!C13) -> 0 | D116: =IF($A116="","",P_Alertes!G13) -> 0 | E116: =IF($A116="","",P_Alertes!F13) -> 0 | F116: =IF($A116="","",IFERROR(INDEX(In_Retenue,MATCH($E116,In_Cles,0)),"")) -> 0 | G116: =IF($A116="","",IF(P_Alertes!H13="","",P_Alertes!H13)) -> 0 | H116: =IF($A116="",FALSE,IF(D116="isTrue",F116=TRUE,IF(D116="isFalse",F116=FALSE,IF(D116="eq",F116=G116,IF(D116="neq",F116<>G116,IF(D116="gt",AND(ISNUMBER(F116),ISNUMBER(G116),N(F116)>N(G116)),IF(D116="gte",AND(ISNUMBER(F116),ISNUMBER(G116),N(F116)>=N(G116)),IF(D116="lt",AND(ISNUMBER(F116),ISNUMBER(G116),N(F116)<N(G116)),IF(D116="lte",AND(ISNUMBER(F116),ISNUMBER(G116),N(F116)<=N(G116)),FALSE))))))))) -> 0 | I116: =IF($A116="",FALSE,AND(NOT(H116),C116<>"BLOCKING",L116)) -> 0 | J116: =IF(OR(H116,I116),N(P_Alertes!D13),0) -> 0 | K116: =IF($A116="",FALSE,AND(OR(H116,I116),P_Alertes!I13="Oui")) -> 0 | L116: =IF($A116="",FALSE,AND(OR(D116="gt",D116="gte",D116="lt",D116="lte"),F116="")) -> 0 | M116: =IF(L116,IF(ISNUMBER(SEARCH(","&E116&",",","&M115&",")),M115,M115&IF(M115="","",",")&E116),M115) -> 0 | N116: =IF(OR(H116,I116),N115&IF(N115="","",", ")&A116,N115) -> 0
A117: =IF(P_Alertes!A14="","",P_Alertes!A14) -> 0 | B117: =IF($A117="","",P_Alertes!B14) -> 0 | C117: =IF($A117="","",P_Alertes!C14) -> 0 | D117: =IF($A117="","",P_Alertes!G14) -> 0 | E117: =IF($A117="","",P_Alertes!F14) -> 0 | F117: =IF($A117="","",IFERROR(INDEX(In_Retenue,MATCH($E117,In_Cles,0)),"")) -> 0 | G117: =IF($A117="","",IF(P_Alertes!H14="","",P_Alertes!H14)) -> 0 | H117: =IF($A117="",FALSE,IF(D117="isTrue",F117=TRUE,IF(D117="isFalse",F117=FALSE,IF(D117="eq",F117=G117,IF(D117="neq",F117<>G117,IF(D117="gt",AND(ISNUMBER(F117),ISNUMBER(G117),N(F117)>N(G117)),IF(D117="gte",AND(ISNUMBER(F117),ISNUMBER(G117),N(F117)>=N(G117)),IF(D117="lt",AND(ISNUMBER(F117),ISNUMBER(G117),N(F117)<N(G117)),IF(D117="lte",AND(ISNUMBER(F117),ISNUMBER(G117),N(F117)<=N(G117)),FALSE))))))))) -> 0 | I117: =IF($A117="",FALSE,AND(NOT(H117),C117<>"BLOCKING",L117)) -> 0 | J117: =IF(OR(H117,I117),N(P_Alertes!D14),0) -> 0 | K117: =IF($A117="",FALSE,AND(OR(H117,I117),P_Alertes!I14="Oui")) -> 0 | L117: =IF($A117="",FALSE,AND(OR(D117="gt",D117="gte",D117="lt",D117="lte"),F117="")) -> 0 | M117: =IF(L117,IF(ISNUMBER(SEARCH(","&E117&",",","&M116&",")),M116,M116&IF(M116="","",",")&E117),M116) -> 0 | N117: =IF(OR(H117,I117),N116&IF(N116="","",", ")&A117,N116) -> 0
A118: =IF(P_Alertes!A15="","",P_Alertes!A15) -> 0 | B118: =IF($A118="","",P_Alertes!B15) -> 0 | C118: =IF($A118="","",P_Alertes!C15) -> 0 | D118: =IF($A118="","",P_Alertes!G15) -> 0 | E118: =IF($A118="","",P_Alertes!F15) -> 0 | F118: =IF($A118="","",IFERROR(INDEX(In_Retenue,MATCH($E118,In_Cles,0)),"")) -> 0 | G118: =IF($A118="","",IF(P_Alertes!H15="","",P_Alertes!H15)) -> 0 | H118: =IF($A118="",FALSE,IF(D118="isTrue",F118=TRUE,IF(D118="isFalse",F118=FALSE,IF(D118="eq",F118=G118,IF(D118="neq",F118<>G118,IF(D118="gt",AND(ISNUMBER(F118),ISNUMBER(G118),N(F118)>N(G118)),IF(D118="gte",AND(ISNUMBER(F118),ISNUMBER(G118),N(F118)>=N(G118)),IF(D118="lt",AND(ISNUMBER(F118),ISNUMBER(G118),N(F118)<N(G118)),IF(D118="lte",AND(ISNUMBER(F118),ISNUMBER(G118),N(F118)<=N(G118)),FALSE))))))))) -> 0 | I118: =IF($A118="",FALSE,AND(NOT(H118),C118<>"BLOCKING",L118)) -> 0 | J118: =IF(OR(H118,I118),N(P_Alertes!D15),0) -> 0 | K118: =IF($A118="",FALSE,AND(OR(H118,I118),P_Alertes!I15="Oui")) -> 0 | L118: =IF($A118="",FALSE,AND(OR(D118="gt",D118="gte",D118="lt",D118="lte"),F118="")) -> 0 | M118: =IF(L118,IF(ISNUMBER(SEARCH(","&E118&",",","&M117&",")),M117,M117&IF(M117="","",",")&E118),M117) -> 0 | N118: =IF(OR(H118,I118),N117&IF(N117="","",", ")&A118,N117) -> 0
A119: =IF(P_Alertes!A16="","",P_Alertes!A16) -> 0 | B119: =IF($A119="","",P_Alertes!B16) -> 0 | C119: =IF($A119="","",P_Alertes!C16) -> 0 | D119: =IF($A119="","",P_Alertes!G16) -> 0 | E119: =IF($A119="","",P_Alertes!F16) -> 0 | F119: =IF($A119="","",IFERROR(INDEX(In_Retenue,MATCH($E119,In_Cles,0)),"")) -> 0 | G119: =IF($A119="","",IF(P_Alertes!H16="","",P_Alertes!H16)) -> 0 | H119: =IF($A119="",FALSE,IF(D119="isTrue",F119=TRUE,IF(D119="isFalse",F119=FALSE,IF(D119="eq",F119=G119,IF(D119="neq",F119<>G119,IF(D119="gt",AND(ISNUMBER(F119),ISNUMBER(G119),N(F119)>N(G119)),IF(D119="gte",AND(ISNUMBER(F119),ISNUMBER(G119),N(F119)>=N(G119)),IF(D119="lt",AND(ISNUMBER(F119),ISNUMBER(G119),N(F119)<N(G119)),IF(D119="lte",AND(ISNUMBER(F119),ISNUMBER(G119),N(F119)<=N(G119)),FALSE))))))))) -> 0 | I119: =IF($A119="",FALSE,AND(NOT(H119),C119<>"BLOCKING",L119)) -> 0 | J119: =IF(OR(H119,I119),N(P_Alertes!D16),0) -> 0 | K119: =IF($A119="",FALSE,AND(OR(H119,I119),P_Alertes!I16="Oui")) -> 0 | L119: =IF($A119="",FALSE,AND(OR(D119="gt",D119="gte",D119="lt",D119="lte"),F119="")) -> 0 | M119: =IF(L119,IF(ISNUMBER(SEARCH(","&E119&",",","&M118&",")),M118,M118&IF(M118="","",",")&E119),M118) -> 0 | N119: =IF(OR(H119,I119),N118&IF(N118="","",", ")&A119,N118) -> 0
A120: =IF(P_Alertes!A17="","",P_Alertes!A17) -> 0 | B120: =IF($A120="","",P_Alertes!B17) -> 0 | C120: =IF($A120="","",P_Alertes!C17) -> 0 | D120: =IF($A120="","",P_Alertes!G17) -> 0 | E120: =IF($A120="","",P_Alertes!F17) -> 0 | F120: =IF($A120="","",IFERROR(INDEX(In_Retenue,MATCH($E120,In_Cles,0)),"")) -> 0 | G120: =IF($A120="","",IF(P_Alertes!H17="","",P_Alertes!H17)) -> 0 | H120: =IF($A120="",FALSE,IF(D120="isTrue",F120=TRUE,IF(D120="isFalse",F120=FALSE,IF(D120="eq",F120=G120,IF(D120="neq",F120<>G120,IF(D120="gt",AND(ISNUMBER(F120),ISNUMBER(G120),N(F120)>N(G120)),IF(D120="gte",AND(ISNUMBER(F120),ISNUMBER(G120),N(F120)>=N(G120)),IF(D120="lt",AND(ISNUMBER(F120),ISNUMBER(G120),N(F120)<N(G120)),IF(D120="lte",AND(ISNUMBER(F120),ISNUMBER(G120),N(F120)<=N(G120)),FALSE))))))))) -> 0 | I120: =IF($A120="",FALSE,AND(NOT(H120),C120<>"BLOCKING",L120)) -> 0 | J120: =IF(OR(H120,I120),N(P_Alertes!D17),0) -> 0 | K120: =IF($A120="",FALSE,AND(OR(H120,I120),P_Alertes!I17="Oui")) -> 0 | L120: =IF($A120="",FALSE,AND(OR(D120="gt",D120="gte",D120="lt",D120="lte"),F120="")) -> 0 | M120: =IF(L120,IF(ISNUMBER(SEARCH(","&E120&",",","&M119&",")),M119,M119&IF(M119="","",",")&E120),M119) -> 0 | N120: =IF(OR(H120,I120),N119&IF(N119="","",", ")&A120,N119) -> 0
... A137: =IF(P_Alertes!A34="","",P_Alertes!A34) -> 0 | B137: =IF($A137="","",P_Alertes!B34) -> 0 | C137: =IF($A137="","",P_Alertes!C34) -> 0 | D137: =IF($A137="","",P_Alertes!G34) -> 0 | E137: =IF($A137="","",P_Alertes!F34) -> 0 | F137: =IF($A137="","",IFERROR(INDEX(In_Retenue,MATCH($E137,In_Cles,0)),"")) -> 0 | G137: =IF($A137="","",IF(P_Alertes!H34="","",P_Alertes!H34)) -> 0 | H137: =IF($A137="",FALSE,IF(D137="isTrue",F137=TRUE,IF(D137="isFalse",F137=FALSE,IF(D137="eq",F137=G137,IF(D137="neq",F137<>G137,IF(D137="gt",AND(ISNUMBER(F137),ISNUMBER(G137),N(F137)>N(G137)),IF(D137="gte",AND(ISNUMBER(F137),ISNUMBER(G137),N(F137)>=N(G137)),IF(D137="lt",AND(ISNUMBER(F137),ISNUMBER(G137),N(F137)<N(G137)),IF(D137="lte",AND(ISNUMBER(F137),ISNUMBER(G137),N(F137)<=N(G137)),FALSE))))))))) -> 0 | I137: =IF($A137="",FALSE,AND(NOT(H137),C137<>"BLOCKING",L137)) -> 0 | J137: =IF(OR(H137,I137),N(P_Alertes!D34),0) -> 0 | K137: =IF($A137="",FALSE,AND(OR(H137,I137),P_Alertes!I34="Oui")) -> 0 | L137: =IF($A137="",FALSE,AND(OR(D137="gt",D137="gte",D137="lt",D137="lte"),F137="")) -> 0 | M137: =IF(L137,IF(ISNUMBER(SEARCH(","&E137&",",","&M136&",")),M136,M136&IF(M136="","",",")&E137),M136) -> 0 | N137: =IF(OR(H137,I137),N136&IF(N136="","",", ")&A137,N136) -> 0

Sheet Calculateurs
A1: Calculateurs — alimentent automatiquement les données dérivées (Saisie, colonne « Valeur calculée »)
A2: Une valeur saisie directement dans l'onglet Saisie prime toujours sur ces calculs.
A4: A. Chaîne d'autorisations
A5: Nature du programme | B5: CONSTRUCTION
A7: Code | B7: Pièce | C7: Exigible | D7: Obtenue | E7: Bloque travaux | F7: Bloque livraison | G7: Manquante
A8: =IF(P_Referentiels!A6="","",P_Referentiels!A6) -> 0 | B8: =IF(A8="","",P_Referentiels!B6) -> 0 | C8: =IF(A8="",FALSE,IF($B$5="LOTISSEMENT",P_Referentiels!D6,IF($B$5="CONSTRUCTION",P_Referentiels!E6,P_Referentiels!F6))="Oui") -> 0 | E8: =IF(A8="",FALSE,P_Referentiels!G6="Oui") -> 0 | F8: =IF(A8="",FALSE,P_Referentiels!H6="Oui") -> 0 | G8: =AND(C8,D8<>"Oui") -> 0
A9: =IF(P_Referentiels!A7="","",P_Referentiels!A7) -> 0 | B9: =IF(A9="","",P_Referentiels!B7) -> 0 | C9: =IF(A9="",FALSE,IF($B$5="LOTISSEMENT",P_Referentiels!D7,IF($B$5="CONSTRUCTION",P_Referentiels!E7,P_Referentiels!F7))="Oui") -> 0 | E9: =IF(A9="",FALSE,P_Referentiels!G7="Oui") -> 0 | F9: =IF(A9="",FALSE,P_Referentiels!H7="Oui") -> 0 | G9: =AND(C9,D9<>"Oui") -> 0
A10: =IF(P_Referentiels!A8="","",P_Referentiels!A8) -> 0 | B10: =IF(A10="","",P_Referentiels!B8) -> 0 | C10: =IF(A10="",FALSE,IF($B$5="LOTISSEMENT",P_Referentiels!D8,IF($B$5="CONSTRUCTION",P_Referentiels!E8,P_Referentiels!F8))="Oui") -> 0 | E10: =IF(A10="",FALSE,P_Referentiels!G8="Oui") -> 0 | F10: =IF(A10="",FALSE,P_Referentiels!H8="Oui") -> 0 | G10: =AND(C10,D10<>"Oui") -> 0
A11: =IF(P_Referentiels!A9="","",P_Referentiels!A9) -> 0 | B11: =IF(A11="","",P_Referentiels!B9) -> 0 | C11: =IF(A11="",FALSE,IF($B$5="LOTISSEMENT",P_Referentiels!D9,IF($B$5="CONSTRUCTION",P_Referentiels!E9,P_Referentiels!F9))="Oui") -> 0 | E11: =IF(A11="",FALSE,P_Referentiels!G9="Oui") -> 0 | F11: =IF(A11="",FALSE,P_Referentiels!H9="Oui") -> 0 | G11: =AND(C11,D11<>"Oui") -> 0
A12: =IF(P_Referentiels!A10="","",P_Referentiels!A10) -> 0 | B12: =IF(A12="","",P_Referentiels!B10) -> 0 | C12: =IF(A12="",FALSE,IF($B$5="LOTISSEMENT",P_Referentiels!D10,IF($B$5="CONSTRUCTION",P_Referentiels!E10,P_Referentiels!F10))="Oui") -> 0 | E12: =IF(A12="",FALSE,P_Referentiels!G10="Oui") -> 0 | F12: =IF(A12="",FALSE,P_Referentiels!H10="Oui") -> 0 | G12: =AND(C12,D12<>"Oui") -> 0
A13: =IF(P_Referentiels!A11="","",P_Referentiels!A11) -> 0 | B13: =IF(A13="","",P_Referentiels!B11) -> 0 | C13: =IF(A13="",FALSE,IF($B$5="LOTISSEMENT",P_Referentiels!D11,IF($B$5="CONSTRUCTION",P_Referentiels!E11,P_Referentiels!F11))="Oui") -> 0 | E13: =IF(A13="",FALSE,P_Referentiels!G11="Oui") -> 0 | F13: =IF(A13="",FALSE,P_Referentiels!H11="Oui") -> 0 | G13: =AND(C13,D13<>"Oui") -> 0
A14: =IF(P_Referentiels!A12="","",P_Referentiels!A12) -> 0 | B14: =IF(A14="","",P_Referentiels!B12) -> 0 | C14: =IF(A14="",FALSE,IF($B$5="LOTISSEMENT",P_Referentiels!D12,IF($B$5="CONSTRUCTION",P_Referentiels!E12,P_Referentiels!F12))="Oui") -> 0 | E14: =IF(A14="",FALSE,P_Referentiels!G12="Oui") -> 0 | F14: =IF(A14="",FALSE,P_Referentiels!H12="Oui") -> 0 | G14: =AND(C14,D14<>"Oui") -> 0
A15: =IF(P_Referentiels!A13="","",P_Referentiels!A13) -> 0 | B15: =IF(A15="","",P_Referentiels!B13) -> 0 | C15: =IF(A15="",FALSE,IF($B$5="LOTISSEMENT",P_Referentiels!D13,IF($B$5="CONSTRUCTION",P_Referentiels!E13,P_Referentiels!F13))="Oui") -> 0 | E15: =IF(A15="",FALSE,P_Referentiels!G13="Oui") -> 0 | F15: =IF(A15="",FALSE,P_Referentiels!H13="Oui") -> 0 | G15: =AND(C15,D15<>"Oui") -> 0
A16: =IF(P_Referentiels!A14="","",P_Referentiels!A14) -> 0 | B16: =IF(A16="","",P_Referentiels!B14) -> 0 | C16: =IF(A16="",FALSE,IF($B$5="LOTISSEMENT",P_Referentiels!D14,IF($B$5="CONSTRUCTION",P_Referentiels!E14,P_Referentiels!F14))="Oui") -> 0 | E16: =IF(A16="",FALSE,P_Referentiels!G14="Oui") -> 0 | F16: =IF(A16="",FALSE,P_Referentiels!H14="Oui") -> 0 | G16: =AND(C16,D16<>"Oui") -> 0
A17: =IF(P_Referentiels!A15="","",P_Referentiels!A15) -> 0 | B17: =IF(A17="","",P_Referentiels!B15) -> 0 | C17: =IF(A17="",FALSE,IF($B$5="LOTISSEMENT",P_Referentiels!D15,IF($B$5="CONSTRUCTION",P_Referentiels!E15,P_Referentiels!F15))="Oui") -> 0 | E17: =IF(A17="",FALSE,P_Referentiels!G15="Oui") -> 0 | F17: =IF(A17="",FALSE,P_Referentiels!H15="Oui") -> 0 | G17: =AND(C17,D17<>"Oui") -> 0
A18: =IF(P_Referentiels!A16="","",P_Referentiels!A16) -> 0 | B18: =IF(A18="","",P_Referentiels!B16) -> 0 | C18: =IF(A18="",FALSE,IF($B$5="LOTISSEMENT",P_Referentiels!D16,IF($B$5="CONSTRUCTION",P_Referentiels!E16,P_Referentiels!F16))="Oui") -> 0 | E18: =IF(A18="",FALSE,P_Referentiels!G16="Oui") -> 0 | F18: =IF(A18="",FALSE,P_Referentiels!H16="Oui") -> 0 | G18: =AND(C18,D18<>"Oui") -> 0
A19: =IF(P_Referentiels!A17="","",P_Referentiels!A17) -> 0 | B19: =IF(A19="","",P_Referentiels!B17) -> 0 | C19: =IF(A19="",FALSE,IF($B$5="LOTISSEMENT",P_Referentiels!D17,IF($B$5="CONSTRUCTION",P_Referentiels!E17,P_Referentiels!F17))="Oui") -> 0 | E19: =IF(A19="",FALSE,P_Referentiels!G17="Oui") -> 0 | F19: =IF(A19="",FALSE,P_Referentiels!H17="Oui") -> 0 | G19: =AND(C19,D19<>"Oui") -> 0
... A31: =IF(P_Referentiels!A29="","",P_Referentiels!A29) -> 0 | B31: =IF(A31="","",P_Referentiels!B29) -> 0 | C31: =IF(A31="",FALSE,IF($B$5="LOTISSEMENT",P_Referentiels!D29,IF($B$5="CONSTRUCTION",P_Referentiels!E29,P_Referentiels!F29))="Oui") -> 0 | E31: =IF(A31="",FALSE,P_Referentiels!G29="Oui") -> 0 | F31: =IF(A31="",FALSE,P_Referentiels!H29="Oui") -> 0 | G31: =AND(C31,D31<>"Oui") -> 0
A33: Complétude de la chaîne (%) | C33: =IF(SUMPRODUCT((C8:C31=TRUE)*1)=0,100,ROUND(SUMPRODUCT((C8:C31=TRUE)*(D8:D31="Oui"))/SUMPRODUCT((C8:C31=TRUE)*1)*100,2)) -> 0
A34: Verrou de travaux (pièce indispensable manquante) | C34: =SUMPRODUCT((G8:G31=TRUE)*(E8:E31=TRUE))>0 -> 0
A35: Saisie de la chaîne effectuée ? | C35: =COUNTIF(D8:D31,"Oui")+COUNTIF(D8:D31,"Non")>0 -> 0
A38: B. Ventes sécurisées (financement de l'acquéreur)
A39: Valeur commercialisable totale (MAD) | D39: vide = somme des prix des lots ci-dessous
A41: Lot | B41: Statut de financement acquéreur | C41: Prix (MAD) | D41: Engagé juridiquement | E41: Facteur | F41: Renseigné | G41: À risque
E42: =IF(B42="",0,IFERROR(VLOOKUP(B42,R_FinTbl,3,FALSE),0.2)) -> 0 | F42: =B42<>"" -> 0 | G42: =AND(B42<>"",D42<>"Non",E42<=0.4) -> 0
E43: =IF(B43="",0,IFERROR(VLOOKUP(B43,R_FinTbl,3,FALSE),0.2)) -> 0 | F43: =B43<>"" -> 0 | G43: =AND(B43<>"",D43<>"Non",E43<=0.4) -> 0
E44: =IF(B44="",0,IFERROR(VLOOKUP(B44,R_FinTbl,3,FALSE),0.2)) -> 0 | F44: =B44<>"" -> 0 | G44: =AND(B44<>"",D44<>"Non",E44<=0.4) -> 0
E45: =IF(B45="",0,IFERROR(VLOOKUP(B45,R_FinTbl,3,FALSE),0.2)) -> 0 | F45: =B45<>"" -> 0 | G45: =AND(B45<>"",D45<>"Non",E45<=0.4) -> 0
E46: =IF(B46="",0,IFERROR(VLOOKUP(B46,R_FinTbl,3,FALSE),0.2)) -> 0 | F46: =B46<>"" -> 0 | G46: =AND(B46<>"",D46<>"Non",E46<=0.4) -> 0
E47: =IF(B47="",0,IFERROR(VLOOKUP(B47,R_FinTbl,3,FALSE),0.2)) -> 0 | F47: =B47<>"" -> 0 | G47: =AND(B47<>"",D47<>"Non",E47<=0.4) -> 0
E48: =IF(B48="",0,IFERROR(VLOOKUP(B48,R_FinTbl,3,FALSE),0.2)) -> 0 | F48: =B48<>"" -> 0 | G48: =AND(B48<>"",D48<>"Non",E48<=0.4) -> 0
E49: =IF(B49="",0,IFERROR(VLOOKUP(B49,R_FinTbl,3,FALSE),0.2)) -> 0 | F49: =B49<>"" -> 0 | G49: =AND(B49<>"",D49<>"Non",E49<=0.4) -> 0
E50: =IF(B50="",0,IFERROR(VLOOKUP(B50,R_FinTbl,3,FALSE),0.2)) -> 0 | F50: =B50<>"" -> 0 | G50: =AND(B50<>"",D50<>"Non",E50<=0.4) -> 0
E51: =IF(B51="",0,IFERROR(VLOOKUP(B51,R_FinTbl,3,FALSE),0.2)) -> 0 | F51: =B51<>"" -> 0 | G51: =AND(B51<>"",D51<>"Non",E51<=0.4) -> 0
E52: =IF(B52="",0,IFERROR(VLOOKUP(B52,R_FinTbl,3,FALSE),0.2)) -> 0 | F52: =B52<>"" -> 0 | G52: =AND(B52<>"",D52<>"Non",E52<=0.4) -> 0
E53: =IF(B53="",0,IFERROR(VLOOKUP(B53,R_FinTbl,3,FALSE),0.2)) -> 0 | F53: =B53<>"" -> 0 | G53: =AND(B53<>"",D53<>"Non",E53<=0.4) -> 0
... E81: =IF(B81="",0,IFERROR(VLOOKUP(B81,R_FinTbl,3,FALSE),0.2)) -> 0 | F81: =B81<>"" -> 0 | G81: =AND(B81<>"",D81<>"Non",E81<=0.4) -> 0
A83: Chiffre d'affaires engagé (MAD) | C83: =SUMPRODUCT((F42:F81=TRUE)*(D42:D81<>"Non")*C42:C81) -> 0
A84: Chiffre d'affaires sécurisé (MAD) | C84: =SUMPRODUCT((F42:F81=TRUE)*(D42:D81<>"Non")*C42:C81*E42:E81) -> 0
A85: Taux de ventes sécurisées (%) | C85: =IF(SUMPRODUCT((F42:F81=TRUE)*1)=0,"",IF(IF(C39="",SUM(C42:C81),C39)>0,ROUND(C84/IF(C39="",SUM(C42:C81),C39)*100,2),"")) -> 0
A86: Financement acquéreurs à risque (≥ 40 % des lots renseignés) | C86: =IF(SUMPRODUCT((F42:F81=TRUE)*1)=0,"",AND(C83>0,SUMPRODUCT((G42:G81=TRUE)*1)/SUMPRODUCT((F42:F81=TRUE)*1)>=0.4)) -> 0
A89: C. Mainlevée partielle et prix de désengagement
A90: Quotité de désengagement convenue (%)
A91: Encours de crédit adossé au programme (MAD)
A92: Valeur commercialisable totale (MAD)
A93: Quotité d'équilibre (%) = encours / valeur | C93: =IF(AND(ISNUMBER(C91),ISNUMBER(C92)),IF(C92>0,ROUND(C91/C92*100,2),""),"") -> 0
A94: Écart quotité appliquée − équilibre (points) | C94: =IF(AND(ISNUMBER(C90),ISNUMBER(C91),ISNUMBER(C92)),IF(AND(C91>0,C92>0),ROUND(C90-C91/C92*100,2),""),"") -> 0
A95: Quotité sous-tarifée ? | C95: =IF(C94="","",C94<0) -> 0
A96: Quotité recommandée (équilibre + 10 %) | C96: =IF(C93="","",ROUND(MIN(100,C93*1.1),2)) -> 0
A99: D. Division des risques
A100: Fonds propres prudentiels de l'établissement (MAD)
A101: Limite par contrepartie / groupe (% des fonds propres) | C101: 20
A102: Seuil « grand risque » (% des fonds propres) | C102: 5
A104: Concours | C104: Encours tiré (MAD) | D104: Non tiré (MAD) | E104: CCF (0–1) | F104: Exposition
F105: =MAX(0,N(C105))+MAX(0,N(D105))*IF(E105="",1,MIN(1,MAX(0,E105))) -> 0
F106: =MAX(0,N(C106))+MAX(0,N(D106))*IF(E106="",1,MIN(1,MAX(0,E106))) -> 0
F107: =MAX(0,N(C107))+MAX(0,N(D107))*IF(E107="",1,MIN(1,MAX(0,E107))) -> 0
F108: =MAX(0,N(C108))+MAX(0,N(D108))*IF(E108="",1,MIN(1,MAX(0,E108))) -> 0
F109: =MAX(0,N(C109))+MAX(0,N(D109))*IF(E109="",1,MIN(1,MAX(0,E109))) -> 0
F110: =MAX(0,N(C110))+MAX(0,N(D110))*IF(E110="",1,MIN(1,MAX(0,E110))) -> 0
F111: =MAX(0,N(C111))+MAX(0,N(D111))*IF(E111="",1,MIN(1,MAX(0,E111))) -> 0
F112: =MAX(0,N(C112))+MAX(0,N(D112))*IF(E112="",1,MIN(1,MAX(0,E112))) -> 0
F113: =MAX(0,N(C113))+MAX(0,N(D113))*IF(E113="",1,MIN(1,MAX(0,E113))) -> 0
F114: =MAX(0,N(C114))+MAX(0,N(D114))*IF(E114="",1,MIN(1,MAX(0,E114))) -> 0
A116: Exposition agrégée (MAD) | C116: =SUM(F105:F114) -> 0
A117: Limite (MAD) | C117: =IF(ISNUMBER(C100),ROUND(C100*C101/100,2),"") -> 0
A118: Ratio exposition / fonds propres (%) | C118: =IF(AND(ISNUMBER(C100),N(C100)>0),ROUND(C116/C100*100,2),"") -> 0
A119: Marge disponible avant limite (MAD) | C119: =IF(C117="","",MAX(0,C117-C116)) -> 0
A120: Limite dépassée ? | C120: =IF(AND(ISNUMBER(C100),N(C100)>0),C116>C117,"") -> 0
A121: Grand risque ? | C121: =IF(AND(ISNUMBER(C100),N(C100)>0),C116>=C100*C102/100,"") -> 0

Sheet Portefeuille
A1: Scoring de portefeuille
A2: Une ligne par dossier. Les valeurs Oui/Non pour les booléens. Macro : ScorerPortefeuille (Alt+F8) — remplit les colonnes de résultat à droite.
A3: Identité | F3: Données d'entrée (mêmes clés que l'onglet Saisie)
A4: Référence | B4: Nom du projet | C4: Segment | D4: Zone | E4: Classe BAM | F4: promoter_completed_projects | G4: promoter_gearing | H4: governance_quality | I4: mono_project_concentration | J4: promoter_type | K4: equity_injected_ratio | L4: land_permits_status | M4: market_positioning | N4: technical_complexity | O4: progress_vs_plan | P4: sav_litigation | Q4: macro_sensitivity | R4: land_cost_ratio | S4: authorization_completeness_pct | T4: pre_sale_rate | U4: sales_vs_plan | V4: dso_days | W4: cash_coverage | X4: funding_gap_pct | Y4: stock_rotation_months | Z4: stressed_margin_pct | AA4: secured_sales_rate | AB4: gross_margin_pct | AC4: ltc | AD4: ltv_stressed | AE4: guarantee_coverage | AF4: first_rank | AG4: interest_coverage | AH4: release_quotity_gap_pts | AI4: dpd_days | AJ4: construction_delay_months | AK4: project_stopped_months | AL4: restructured | AM4: legal_exposure | AN4: equity_negative | AO4: funding_gap_persistent | AP4: works_authorization_blocked | AQ4: buyers_financing_at_risk | AR4: release_underpriced | AS4: division_limit_breach | AT4: Score final | AU4: Décision | AV4: Classe interne | AW4: Malus D5 | AX4: Dossier complet | AY4: D1 | AZ4: D2 | BA4: D3 | BB4: D4 | BC4: Score éco. | BD4: Note sûretés | BE4: PD indicative | BF4: Alertes
A5: EXEMPLE-1 | B5: Dossier solide, classe saine | E5: SAIN | F5: 8 | G5: 85 | H5: claire | I5: 35 | J5: structure | K5: 100 | L5: definitives | M5: aligne | N5: standard | O5: 100 | P5: faible | Q5: faible | R5: 22 | S5: 100 | T5: 62 | U5: 100 | V5: 90 | W5: 1.35 | X5: 0 | Y5: 16 | Z5: 18 | AA5: 55 | AB5: 27 | AC5: 61 | AD5: 65 | AE5: 125 | AF5: oui | AG5: 3.2 | AH5: 5 | AI5: 0 | AJ5: 0 | AK5: 0 | AL5: no | AM5: clear | AN5: Non | AO5: Non | AP5: Non | AQ5: Non | AR5: Non | AS5: Non
A6: EXEMPLE-2 | B6: Dossier intermédiaire (score moyen) | C6: intermediaire | D6: casa_peripherie | E6: SAIN | F6: 2 | G6: 120 | H6: partielle | I6: 50 | J6: regional | K6: 90 | L6: partielles | M6: moyen | N6: moyenne | O6: 90 | P6: moyen | Q6: moyenne | R6: 30 | S6: 70 | T6: 35 | U6: 90 | V6: 180 | W6: 1.1 | X6: 5 | Y6: 24 | Z6: 12 | AA6: 30 | AB6: 20 | AC6: 70 | AD6: 78 | AE6: 100 | AF6: oui | AG6: 2 | AH6: -5 | AI6: 0 | AJ6: 0 | AK6: 0 | AL6: no | AM6: clear | AN6: Non | AO6: Non | AP6: Non | AQ6: Non | AR6: Non | AS6: Non
A7: EXEMPLE-3 | B7: Non 1er rang + restructuration : malus cumulés | E7: SAIN | F7: 8 | G7: 85 | H7: claire | I7: 35 | J7: structure | K7: 100 | L7: definitives | M7: aligne | N7: standard | O7: 100 | P7: faible | Q7: faible | R7: 22 | S7: 100 | T7: 62 | U7: 100 | V7: 90 | W7: 1.35 | X7: 0 | Y7: 16 | Z7: 18 | AA7: 55 | AB7: 27 | AC7: 61 | AD7: 65 | AE7: 125 | AF7: non | AG7: 3.2 | AH7: 5 | AI7: 0 | AJ7: 0 | AK7: 0 | AL7: yes | AM7: clear | AN7: Non | AO7: Non | AP7: Non | AQ7: Non | AR7: Non | AS7: Non

Sheet Stress
A1: Stress test sur le dossier courant (onglet Saisie)
A2: Chocs appliqués aux données primitives par identités comptables (marge, LTV, LTC) — mêmes règles que l'application. Macro : LancerStress.
A3: Score de base | D3: Décision de base
A4: Scénario | B4: Libellé | C4: Prix −% | D4: Coût +% | E4: Retard (mois) | F4: Ventes −% | G4: Taux +bps | H4: Préventes −pts | I4: Retard paiement +j | J4: Score final | K4: Décision | L4: Δ vs base
A5: price10 | B5: Prix −10 % | C5: 10 | D5: 0 | E5: 0 | F5: 0 | G5: 0 | H5: 0 | I5: 0
A6: price15 | B6: Prix −15 % | C6: 15 | D6: 0 | E6: 0 | F6: 0 | G6: 0 | H6: 0 | I6: 0
A7: cost10 | B7: Coût +10 % | C7: 0 | D7: 10 | E7: 0 | F7: 0 | G7: 0 | H7: 0 | I7: 0
A8: delay6 | B8: Retard +6 mois | C8: 0 | D8: 0 | E8: 6 | F8: 0 | G8: 0 | H8: 0 | I8: 0
A9: sales20 | B9: Ventes −20 % | C9: 0 | D9: 0 | E9: 0 | F9: 20 | G9: 0 | H9: 0 | I9: 0
A10: rate200 | B10: Taux +200 bps | C10: 0 | D10: 0 | E10: 0 | F10: 0 | G10: 200 | H10: 0 | I10: 0
A11: severe | B11: Sévère combiné | C11: 15 | D11: 10 | E11: 6 | F11: 20 | G11: 200 | H11: 0 | I11: 0

Sheet Tests
A1: Autotests — cas de référence issus du moteur de production
A2: Les résultats attendus proviennent de l'exécution du moteur de l'application sur le modèle v4.0.0. Macro : ExecuterAutotests (tolérance 0,02 point).
A3: Identité | F3: Données d'entrée (mêmes clés que l'onglet Saisie)
A4: Cas | B4: Description | C4: Segment | D4: Zone | E4: Classe BAM | F4: promoter_completed_projects | G4: promoter_gearing | H4: governance_quality | I4: mono_project_concentration | J4: promoter_type | K4: equity_injected_ratio | L4: land_permits_status | M4: market_positioning | N4: technical_complexity | O4: progress_vs_plan | P4: sav_litigation | Q4: macro_sensitivity | R4: land_cost_ratio | S4: authorization_completeness_pct | T4: pre_sale_rate | U4: sales_vs_plan | V4: dso_days | W4: cash_coverage | X4: funding_gap_pct | Y4: stock_rotation_months | Z4: stressed_margin_pct | AA4: secured_sales_rate | AB4: gross_margin_pct | AC4: ltc | AD4: ltv_stressed | AE4: guarantee_coverage | AF4: first_rank | AG4: interest_coverage | AH4: release_quotity_gap_pts | AI4: dpd_days | AJ4: construction_delay_months | AK4: project_stopped_months | AL4: restructured | AM4: legal_exposure | AN4: equity_negative | AO4: funding_gap_persistent | AP4: works_authorization_blocked | AQ4: buyers_financing_at_risk | AR4: release_underpriced | AS4: division_limit_breach | AT4: Attendu : score final | AU4: Attendu : décision | AV4: Attendu : classe interne | AW4: Attendu : malus | AX4: Attendu : incomplet | AY4: Attendu : score éco. | AZ4: Attendu : D1 | BA4: Attendu : D2 | BB4: Attendu : D3 | BC4: Attendu : D4 | BD4: Attendu : note sûretés | BE4: Obtenu : score final | BF4: Obtenu : décision | BG4: Statut
A5: T01 | B5: Dossier solide, classe saine | E5: SAIN | F5: 8 | G5: 85 | H5: claire | I5: 35 | J5: structure | K5: 100 | L5: definitives | M5: aligne | N5: standard | O5: 100 | P5: faible | Q5: faible | R5: 22 | S5: 100 | T5: 62 | U5: 100 | V5: 90 | W5: 1.35 | X5: 0 | Y5: 16 | Z5: 18 | AA5: 55 | AB5: 27 | AC5: 61 | AD5: 65 | AE5: 125 | AF5: oui | AG5: 3.2 | AH5: 5 | AI5: 0 | AJ5: 0 | AK5: 0 | AL5: no | AM5: clear | AN5: Non | AO5: Non | AP5: Non | AQ5: Non | AR5: Non | AS5: Non | AT5: 98.56 | AU5: GO | AV5: Sain | AW5: 0 | AX5: Non | AY5: 98.56 | AZ5: 100 | BA5: 100 | BB5: 100 | BC5: 94 | BD5: 100
A6: T02 | B6: Solide, segment touristique + zone Marrakech (ajustements) | C6: touristique | D6: marrakech | E6: SAIN | F6: 8 | G6: 85 | H6: claire | I6: 35 | J6: structure | K6: 100 | L6: definitives | M6: aligne | N6: standard | O6: 100 | P6: faible | Q6: faible | R6: 22 | S6: 100 | T6: 62 | U6: 100 | V6: 90 | W6: 1.35 | X6: 0 | Y6: 16 | Z6: 18 | AA6: 55 | AB6: 27 | AC6: 61 | AD6: 65 | AE6: 125 | AF6: oui | AG6: 3.2 | AH6: 5 | AI6: 0 | AJ6: 0 | AK6: 0 | AL6: no | AM6: clear | AN6: Non | AO6: Non | AP6: Non | AQ6: Non | AR6: Non | AS6: Non | AT6: 84.76 | AU6: GO | AV6: Sain | AW6: 0 | AX6: Non | AY6: 98.56 | AZ6: 100 | BA6: 100 | BB6: 100 | BC6: 94 | BD6: 100
A7: T03 | B7: Dossier intermédiaire (score moyen) | C7: intermediaire | D7: casa_peripherie | E7: SAIN | F7: 2 | G7: 120 | H7: partielle | I7: 50 | J7: regional | K7: 90 | L7: partielles | M7: moyen | N7: moyenne | O7: 90 | P7: moyen | Q7: moyenne | R7: 30 | S7: 70 | T7: 35 | U7: 90 | V7: 180 | W7: 1.1 | X7: 5 | Y7: 24 | Z7: 12 | AA7: 30 | AB7: 20 | AC7: 70 | AD7: 78 | AE7: 100 | AF7: oui | AG7: 2 | AH7: -5 | AI7: 0 | AJ7: 0 | AK7: 0 | AL7: no | AM7: clear | AN7: Non | AO7: Non | AP7: Non | AQ7: Non | AR7: Non | AS7: Non | AT7: 54.86 | AU7: WATCH_LIST | AV7: Sensible probable | AW7: 0 | AX7: Non | AY7: 60.96 | AZ7: 60 | BA7: 60 | BB7: 60 | BC7: 64 | BD7: 68
A8: T04 | B8: Dossier intermédiaire dégradé (cash 0,9 + impasse persistante) | E8: SAIN | F8: 2 | G8: 120 | H8: partielle | I8: 50 | J8: regional | K8: 90 | L8: partielles | M8: moyen | N8: moyenne | O8: 90 | P8: moyen | Q8: moyenne | R8: 30 | S8: 70 | T8: 35 | U8: 90 | V8: 180 | W8: 0.9 | X8: 5 | Y8: 24 | Z8: 12 | AA8: 30 | AB8: 20 | AC8: 70 | AD8: 78 | AE8: 100 | AF8: oui | AG8: 2 | AH8: -5 | AI8: 0 | AJ8: 0 | AK8: 0 | AL8: no | AM8: clear | AN8: Non | AO8: Oui | AP8: Non | AQ8: Non | AR8: Non | AS8: Non | AT8: 12.86 | AU8: NO_GO | AV8: Sensible | AW8: 45 | AX8: Non | AY8: 57.86 | AZ8: 60 | BA8: 60 | BB8: 50 | BC8: 64 | BD8: 68
A9: T05 | B9: Impayé 120 j : alerte bloquante, souffrance | E9: SAIN | F9: 8 | G9: 85 | H9: claire | I9: 35 | J9: structure | K9: 100 | L9: definitives | M9: aligne | N9: standard | O9: 100 | P9: faible | Q9: faible | R9: 22 | S9: 100 | T9: 62 | U9: 100 | V9: 90 | W9: 1.35 | X9: 0 | Y9: 16 | Z9: 18 | AA9: 55 | AB9: 27 | AC9: 61 | AD9: 65 | AE9: 125 | AF9: oui | AG9: 3.2 | AH9: 5 | AI9: 120 | AJ9: 0 | AK9: 0 | AL9: no | AM9: clear | AN9: Non | AO9: Non | AP9: Non | AQ9: Non | AR9: Non | AS9: Non | AT9: 98.56 | AU9: NO_GO | AV9: Souffrance | AW9: 0 | AX9: Non | AY9: 98.56 | AZ9: 100 | BA9: 100 | BB9: 100 | BC9: 94 | BD9: 100
A10: T06 | B10: Cash coverage 0,99 : alerte -25 | E10: SAIN | F10: 8 | G10: 85 | H10: claire | I10: 35 | J10: structure | K10: 100 | L10: definitives | M10: aligne | N10: standard | O10: 100 | P10: faible | Q10: faible | R10: 22 | S10: 100 | T10: 62 | U10: 100 | V10: 90 | W10: 0.99 | X10: 0 | Y10: 16 | Z10: 18 | AA10: 55 | AB10: 27 | AC10: 61 | AD10: 65 | AE10: 125 | AF10: oui | AG10: 3.2 | AH10: 5 | AI10: 0 | AJ10: 0 | AK10: 0 | AL10: no | AM10: clear | AN10: Non | AO10: Non | AP10: Non | AQ10: Non | AR10: Non | AS10: Non | AT10: 67.98 | AU10: GO_WITH_CONDITIONS | AV10: Surveillance | AW10: 25 | AX10: Non | AY10: 92.98 | AZ10: 100 | BA10: 100 | BB10: 82 | BC10: 94 | BD10: 100
A11: T07 | B11: Cash coverage absent : dossier incomplet | E11: SAIN | F11: 8 | G11: 85 | H11: claire | I11: 35 | J11: structure | K11: 100 | L11: definitives | M11: aligne | N11: standard | O11: 100 | P11: faible | Q11: faible | R11: 22 | S11: 100 | T11: 62 | U11: 100 | V11: 90 | X11: 0 | Y11: 16 | Z11: 18 | AA11: 55 | AB11: 27 | AC11: 61 | AD11: 65 | AE11: 125 | AF11: oui | AG11: 3.2 | AH11: 5 | AI11: 0 | AJ11: 0 | AK11: 0 | AL11: no | AM11: clear | AN11: Non | AO11: Non | AP11: Non | AQ11: Non | AR11: Non | AS11: Non | AT11: 67.98 | AU11: DOSSIER_INCOMPLET | AV11: Dossier incomplet | AW11: 25 | AX11: Oui | AY11: 92.98 | AZ11: 100 | BA11: 100 | BB11: 82 | BC11: 94 | BD11: 100
A12: T08 | B12: Classe pré-douteuse : défaut avéré | E12: PRE_DOUTEUX | F12: 8 | G12: 85 | H12: claire | I12: 35 | J12: structure | K12: 100 | L12: definitives | M12: aligne | N12: standard | O12: 100 | P12: faible | Q12: faible | R12: 22 | S12: 100 | T12: 62 | U12: 100 | V12: 90 | W12: 1.35 | X12: 0 | Y12: 16 | Z12: 18 | AA12: 55 | AB12: 27 | AC12: 61 | AD12: 65 | AE12: 125 | AF12: oui | AG12: 3.2 | AH12: 5 | AI12: 0 | AJ12: 0 | AK12: 0 | AL12: no | AM12: clear | AN12: Non | AO12: Non | AP12: Non | AQ12: Non | AR12: Non | AS12: Non | AT12: 68.99 | AU12: NO_GO | AV12: Défaut avéré | AW12: 0 | AX12: Non | AY12: 98.56 | AZ12: 100 | BA12: 100 | BB12: 100 | BC12: 94 | BD12: 100
A13: T09 | B13: Classe contentieux CTX : score 0 | E13: CTX | F13: 8 | G13: 85 | H13: claire | I13: 35 | J13: structure | K13: 100 | L13: definitives | M13: aligne | N13: standard | O13: 100 | P13: faible | Q13: faible | R13: 22 | S13: 100 | T13: 62 | U13: 100 | V13: 90 | W13: 1.35 | X13: 0 | Y13: 16 | Z13: 18 | AA13: 55 | AB13: 27 | AC13: 61 | AD13: 65 | AE13: 125 | AF13: oui | AG13: 3.2 | AH13: 5 | AI13: 0 | AJ13: 0 | AK13: 0 | AL13: no | AM13: clear | AN13: Non | AO13: Non | AP13: Non | AQ13: Non | AR13: Non | AS13: Non | AT13: 0 | AU13: NO_GO | AV13: Souffrance | AW13: 0 | AX13: Non | AY13: 98.56 | AZ13: 100 | BA13: 100 | BB13: 100 | BC13: 94 | BD13: 100
A14: T10 | B14: Classe sensible : coefficient 0,9 | E14: SENSIBLE | F14: 8 | G14: 85 | H14: claire | I14: 35 | J14: structure | K14: 100 | L14: definitives | M14: aligne | N14: standard | O14: 100 | P14: faible | Q14: faible | R14: 22 | S14: 100 | T14: 62 | U14: 100 | V14: 90 | W14: 1.35 | X14: 0 | Y14: 16 | Z14: 18 | AA14: 55 | AB14: 27 | AC14: 61 | AD14: 65 | AE14: 125 | AF14: oui | AG14: 3.2 | AH14: 5 | AI14: 0 | AJ14: 0 | AK14: 0 | AL14: no | AM14: clear | AN14: Non | AO14: Non | AP14: Non | AQ14: Non | AR14: Non | AS14: Non | AT14: 88.7 | AU14: GO | AV14: Sain | AW14: 0 | AX14: Non | AY14: 98.56 | AZ14: 100 | BA14: 100 | BB14: 100 | BC14: 94 | BD14: 100
A15: T11 | B15: Apport 50 % : gate franchi | E15: SAIN | F15: 8 | G15: 85 | H15: claire | I15: 35 | J15: structure | K15: 50 | L15: definitives | M15: aligne | N15: standard | O15: 100 | P15: faible | Q15: faible | R15: 22 | S15: 100 | T15: 62 | U15: 100 | V15: 90 | W15: 1.35 | X15: 0 | Y15: 16 | Z15: 18 | AA15: 55 | AB15: 27 | AC15: 61 | AD15: 65 | AE15: 125 | AF15: oui | AG15: 3.2 | AH15: 5 | AI15: 0 | AJ15: 0 | AK15: 0 | AL15: no | AM15: clear | AN15: Non | AO15: Non | AP15: Non | AQ15: Non | AR15: Non | AS15: Non | AT15: 95.19 | AU15: NO_GO | AV15: Sain | AW15: 0 | AX15: Non | AY15: 95.19 | AZ15: 86.5 | BA15: 100 | BB15: 100 | BC15: 94 | BD15: 100
A16: T12 | B16: Non 1er rang + restructuration : malus cumulés | E16: SAIN | F16: 8 | G16: 85 | H16: claire | I16: 35 | J16: structure | K16: 100 | L16: definitives | M16: aligne | N16: standard | O16: 100 | P16: faible | Q16: faible | R16: 22 | S16: 100 | T16: 62 | U16: 100 | V16: 90 | W16: 1.35 | X16: 0 | Y16: 16 | Z16: 18 | AA16: 55 | AB16: 27 | AC16: 61 | AD16: 65 | AE16: 125 | AF16: non | AG16: 3.2 | AH16: 5 | AI16: 0 | AJ16: 0 | AK16: 0 | AL16: yes | AM16: clear | AN16: Non | AO16: Non | AP16: Non | AQ16: Non | AR16: Non | AS16: Non | AT16: 46.4 | AU16: NO_GO | AV16: Sensible | AW16: 50 | AX16: Non | AY16: 96.4 | AZ16: 100 | BA16: 100 | BB16: 100 | BC16: 85 | BD16: 82
A17: T13 | B17: Segment et zone hors référentiel | C17: segment_inconnu | D17: zone_inconnue | E17: SAIN | F17: 8 | G17: 85 | H17: claire | I17: 35 | J17: structure | K17: 100 | L17: definitives | M17: aligne | N17: standard | O17: 100 | P17: faible | Q17: faible | R17: 22 | S17: 100 | T17: 62 | U17: 100 | V17: 90 | W17: 1.35 | X17: 0 | Y17: 16 | Z17: 18 | AA17: 55 | AB17: 27 | AC17: 61 | AD17: 65 | AE17: 125 | AF17: oui | AG17: 3.2 | AH17: 5 | AI17: 0 | AJ17: 0 | AK17: 0 | AL17: no | AM17: clear | AN17: Non | AO17: Non | AP17: Non | AQ17: Non | AR17: Non | AS17: Non | AT17: 98.56 | AU17: GO | AV17: Sain | AW17: 0 | AX17: Non | AY17: 98.56 | AZ17: 100 | BA17: 100 | BB17: 100 | BC17: 94 | BD17: 100
A18: T14 | B18: Classe non renseignée : dossier incomplet | F18: 8 | G18: 85 | H18: claire | I18: 35 | J18: structure | K18: 100 | L18: definitives | M18: aligne | N18: standard | O18: 100 | P18: faible | Q18: faible | R18: 22 | S18: 100 | T18: 62 | U18: 100 | V18: 90 | W18: 1.35 | X18: 0 | Y18: 16 | Z18: 18 | AA18: 55 | AB18: 27 | AC18: 61 | AD18: 65 | AE18: 125 | AF18: oui | AG18: 3.2 | AH18: 5 | AI18: 0 | AJ18: 0 | AK18: 0 | AL18: no | AM18: clear | AN18: Non | AO18: Non | AP18: Non | AQ18: Non | AR18: Non | AS18: Non | AT18: 98.56 | AU18: DOSSIER_INCOMPLET | AV18: Dossier incomplet | AW18: 0 | AX18: Oui | AY18: 98.56 | AZ18: 100 | BA18: 100 | BB18: 100 | BC18: 94 | BD18: 100
A19: T15 | B19: Autorisation indispensable manquante (verrou de tirage) | E19: SAIN | F19: 8 | G19: 85 | H19: claire | I19: 35 | J19: structure | K19: 100 | L19: definitives | M19: aligne | N19: standard | O19: 100 | P19: faible | Q19: faible | R19: 22 | S19: 40 | T19: 62 | U19: 100 | V19: 90 | W19: 1.35 | X19: 0 | Y19: 16 | Z19: 18 | AA19: 55 | AB19: 27 | AC19: 61 | AD19: 65 | AE19: 125 | AF19: oui | AG19: 3.2 | AH19: 5 | AI19: 0 | AJ19: 0 | AK19: 0 | AL19: no | AM19: clear | AN19: Non | AO19: Non | AP19: Oui | AQ19: Non | AR19: Non | AS19: Non | AT19: 81.76 | AU19: GO | AV19: Sain | AW19: 15 | AX19: Non | AY19: 96.76 | AZ19: 100 | BA19: 91 | BB19: 100 | BC19: 94 | BD19: 100
A20: T16 | B20: Gouvernance non renseignée (qualitatif : note plancher) | E20: SAIN | F20: 8 | G20: 85 | I20: 35 | J20: structure | K20: 100 | L20: definitives | M20: aligne | N20: standard | O20: 100 | P20: faible | Q20: faible | R20: 22 | S20: 100 | T20: 62 | U20: 100 | V20: 90 | W20: 1.35 | X20: 0 | Y20: 16 | Z20: 18 | AA20: 55 | AB20: 27 | AC20: 61 | AD20: 65 | AE20: 125 | AF20: oui | AG20: 3.2 | AH20: 5 | AI20: 0 | AJ20: 0 | AK20: 0 | AL20: no | AM20: clear | AN20: Non | AO20: Non | AP20: Non | AQ20: Non | AR20: Non | AS20: Non | AT20: 95.19 | AU20: GO | AV20: Sain | AW20: 0 | AX20: Non | AY20: 95.19 | AZ20: 86.5 | BA20: 100 | BB20: 100 | BC20: 94 | BD20: 100
A21: T17 | B21: Retard chantier 8 mois + prix de mainlevée sous-tarifé | E21: SAIN | F21: 8 | G21: 85 | H21: claire | I21: 35 | J21: structure | K21: 100 | L21: definitives | M21: aligne | N21: standard | O21: 100 | P21: faible | Q21: faible | R21: 22 | S21: 100 | T21: 62 | U21: 100 | V21: 90 | W21: 1.35 | X21: 0 | Y21: 16 | Z21: 18 | AA21: 55 | AB21: 27 | AC21: 61 | AD21: 65 | AE21: 125 | AF21: oui | AG21: 3.2 | AH21: -15 | AI21: 0 | AJ21: 8 | AK21: 0 | AL21: no | AM21: clear | AN21: Non | AO21: Non | AP21: Non | AQ21: Non | AR21: Oui | AS21: Non | AT21: 67.48 | AU21: GO_WITH_CONDITIONS | AV21: Surveillance | AW21: 30 | AX21: Non | AY21: 97.48 | AZ21: 100 | BA21: 100 | BB21: 100 | BC21: 89.5 | BD21: 91
A22: T18 | B22: Retard de paiement (dpd_days) absent : dossier incomplet | E22: SAIN | F22: 8 | G22: 85 | H22: claire | I22: 35 | J22: structure | K22: 100 | L22: definitives | M22: aligne | N22: standard | O22: 100 | P22: faible | Q22: faible | R22: 22 | S22: 100 | T22: 62 | U22: 100 | V22: 90 | W22: 1.35 | X22: 0 | Y22: 16 | Z22: 18 | AA22: 55 | AB22: 27 | AC22: 61 | AD22: 65 | AE22: 125 | AF22: oui | AG22: 3.2 | AH22: 5 | AJ22: 0 | AK22: 0 | AL22: no | AM22: clear | AN22: Non | AO22: Non | AP22: Non | AQ22: Non | AR22: Non | AS22: Non | AT22: 98.56 | AU22: DOSSIER_INCOMPLET | AV22: Dossier incomplet | AW22: 0 | AX22: Oui | AY22: 98.56 | AZ22: 100 | BA22: 100 | BB22: 100 | BC22: 94 | BD22: 100
A23: T19 | B23: Litige : alerte bloquante CTX | E23: SAIN | F23: 8 | G23: 85 | H23: claire | I23: 35 | J23: structure | K23: 100 | L23: definitives | M23: aligne | N23: standard | O23: 100 | P23: faible | Q23: faible | R23: 22 | S23: 100 | T23: 62 | U23: 100 | V23: 90 | W23: 1.35 | X23: 0 | Y23: 16 | Z23: 18 | AA23: 55 | AB23: 27 | AC23: 61 | AD23: 65 | AE23: 125 | AF23: oui | AG23: 3.2 | AH23: 5 | AI23: 0 | AJ23: 0 | AK23: 0 | AL23: no | AM23: litigation | AN23: Non | AO23: Non | AP23: Non | AQ23: Non | AR23: Non | AS23: Non | AT23: 98.56 | AU23: NO_GO | AV23: Souffrance | AW23: 0 | AX23: Non | AY23: 98.56 | AZ23: 100 | BA23: 100 | BB23: 100 | BC23: 94 | BD23: 100
A24: T20 | B24: Projet en difficulté (dégradé + non 1er rang) | C24: villas | D24: regions_interieures | E24: SENSIBLE | F24: 2 | G24: 120 | H24: partielle | I24: 50 | J24: regional | K24: 90 | L24: partielles | M24: moyen | N24: moyenne | O24: 90 | P24: moyen | Q24: moyenne | R24: 30 | S24: 70 | T24: 35 | U24: 90 | V24: 180 | W24: 0.95 | X24: 5 | Y24: 24 | Z24: 12 | AA24: 30 | AB24: 12 | AC24: 85 | AD24: 78 | AE24: 100 | AF24: non | AG24: 2 | AH24: -5 | AI24: 0 | AJ24: 0 | AK24: 0 | AL24: no | AM24: clear | AN24: Non | AO24: Non | AP24: Non | AQ24: Non | AR24: Non | AS24: Non | AT24: 0 | AU24: NO_GO | AV24: Sensible | AW24: 50 | AX24: Non | AY24: 51.5 | AZ24: 60 | BA24: 60 | BB24: 50 | BC24: 37.5 | BD24: 50

Sheet Historique
A1: Historique des calculs (journal)
A2: Alimenté par les macros (ScorerDossier, ScorerPortefeuille). La version du modèle est tracée sur chaque ligne.
A4: Date / heure | B4: Utilisateur | C4: Dossier | D4: Version du modèle | E4: Score final | F4: Décision | G4: Classe interne | H4: Malus D5 | I4: Dossier complet

Sheet P_General
A1: Paramètres généraux du modèle
A2: Cellules bleues = paramétrables. Toute modification doit être validée (macro ValiderModele) et versionnée.
A3: Paramètre | B3: Valeur
A4: Version du modèle | B4: v4.0.0
A5: Publié le | B5: 2026-09-28
A6: Échelle de notation des critères | B6: 10
A7: Seuil GO (score final ≥) | B7: 75
A8: Seuil GO sous conditions (≥) | B8: 65
A9: Seuil Watch list (≥) | B9: 50
A10: PD proxy — constante a | B10: 2.223
A11: PD proxy — coefficient b | B11: 0.0802
A12: Clé critique additionnelle | B12: dpd_days
A14: Domaines de notation
A15: Code | B15: Nom | C15: Poids
A16: D1 | B16: Sponsor & Gouvernance | C16: 0.25
A17: D2 | B17: Qualité intrinsèque du projet | C17: 0.2
A18: D3 | B18: Commercial & Cash-flow | C18: 0.31
A19: D4 | B19: Structuration financière & LGD | C19: 0.24
A25: Classes réglementaires (ordre de sévérité croissante)
A26: Code | B26: Libellé | C26: Défaut avéré | D26: Bloque GO | E26: Coefficient BAM
A27: SAIN | B27: Créance saine | C27: Non | D27: Non | E27: 1
A28: SENSIBLE | B28: Créance sensible (surveillance) | C28: Non | D28: Non | E28: 0.9
A29: PRE_DOUTEUX | B29: Pré-douteuse | C29: Oui | D29: Non | E29: 0.7
A30: DOUTEUX | B30: Douteuse | C30: Oui | D30: Non | E30: 0.4
A31: COMPROMIS | B31: Compromise | C31: Oui | D31: Non | E31: 0.2
A32: CTX | B32: Contentieux | C32: Oui | D32: Oui | E32: 0
A38: Grilles de pondération par phase (challenger — non adoptées)
A39: Phase | B39: D1 | C39: D2 | D39: D3 | E39: D4
A40: PRE_DEVELOPMENT | B40: 0.25 | C40: 0.3 | D40: 0.2 | E40: 0.25
A41: CONSTRUCTION | B41: 0.2 | C41: 0.25 | D41: 0.25 | E41: 0.3
A42: ECOULEMENT | B42: 0.15 | C42: 0.1 | D42: 0.35 | E42: 0.4
A44: Repères de retard de paiement (jours)
A45: Seuil pré-douteux | B45: 90
A46: Seuil douteux | B46: 180
A47: Seuil compromis | B47: 360

Sheet P_Criteres
A1: Critères de notation (29 dans la v4.0.0 — jusqu'à 60 lignes)
A2: Ajouter un critère = compléter une ligne + ses barèmes (P_Baremes) + sa clé dans Saisie. Poids du domaine : somme = 100 %.
A4: Code | B4: Domaine | C4: Libellé | D4: Type | E4: Poids | F4: Clé d'entrée | G4: Gate | H4: Seuil gate | I4: Jalon gate | J4: Famille | K4: Critique | L4: Unité
A5: D1C1 | B5: D1 | C5: Projets similaires livrés (5 ans) | D5: NUM | E5: 0.2 | F5: promoter_completed_projects | G5: Non | J5: ECONOMIC | K5: Non | L5: ratio/%
A6: D1C2 | B6: D1 | C6: Gearing promoteur (dettes nettes / FP) | D6: NUM | E6: 0.25 | F6: promoter_gearing | G6: Non | J6: ECONOMIC | K6: Non | L6: ratio/%
A7: D1C3 | B7: D1 | C7: Gouvernance & structure juridique | D7: QUAL | E7: 0.15 | F7: governance_quality | G7: Non | J7: ECONOMIC | K7: Non | L7: modalité
A8: D1C4 | B8: D1 | C8: Concentration mono-projet (CA projet / CA total) | D8: NUM | E8: 0.15 | F8: mono_project_concentration | G8: Non | J8: ECONOMIC | K8: Non | L8: ratio/%
A9: D1C5 | B9: D1 | C9: Typologie promoteur | D9: QUAL | E9: 0.1 | F9: promoter_type | G9: Non | J9: ECONOMIC | K9: Non | L9: modalité
A10: D1C6 | B10: D1 | C10: Apport effectif (injecté / prévu) | D10: NUM | E10: 0.15 | F10: equity_injected_ratio | G10: Oui | H10: 1 | I10: SIGNATURE | J10: ECONOMIC | K10: Non | L10: ratio/%
A11: D2C1 | B11: D2 | C11: Foncier & autorisations | D11: QUAL | E11: 0.1 | F11: land_permits_status | G11: Oui | H11: 1 | I11: TIRAGE | J11: ECONOMIC | K11: Non | L11: modalité
A12: D2C2 | B12: D2 | C12: Marché & positionnement | D12: QUAL | E12: 0.2 | F12: market_positioning | G12: Non | J12: ECONOMIC | K12: Non | L12: modalité
A13: D2C3 | B13: D2 | C13: Complexité technique | D13: QUAL | E13: 0.15 | F13: technical_complexity | G13: Non | J13: ECONOMIC | K13: Non | L13: modalité
A14: D2C4 | B14: D2 | C14: Avancement vs planning | D14: NUM | E14: 0.15 | F14: progress_vs_plan | G14: Non | J14: ECONOMIC | K14: Non | L14: ratio/%
A15: D2C5 | B15: D2 | C15: Litiges clients / SAV | D15: QUAL | E15: 0.1 | F15: sav_litigation | G15: Non | J15: ECONOMIC | K15: Non | L15: modalité
A16: D2C6 | B16: D2 | C16: Sensibilité macro / subvention | D16: QUAL | E16: 0.1 | F16: macro_sensitivity | G16: Non | J16: ECONOMIC | K16: Non | L16: modalité
A17: D2C7 | B17: D2 | C17: Coût foncier / CA | D17: NUM | E17: 0.1 | F17: land_cost_ratio | G17: Non | J17: ECONOMIC | K17: Non | L17: ratio/%
A18: D2C8 | B18: D2 | C18: Chaîne d'autorisations (complétude) | D18: NUM | E18: 0.1 | F18: authorization_completeness_pct | G18: Non | I18: TIRAGE | J18: ECONOMIC | K18: Non | L18: %
A19: D3C1 | B19: D3 | C19: Préventes sécurisées (encaissées / CA) | D19: NUM | E19: 0.15 | F19: pre_sale_rate | G19: Non | J19: ECONOMIC | K19: Oui | L19: ratio/%
A20: D3C2 | B20: D3 | C20: Ventes vs planning | D20: NUM | E20: 0.1 | F20: sales_vs_plan | G20: Non | J20: ECONOMIC | K20: Non | L20: ratio/%
A21: D3C3 | B21: D3 | C21: DSO (jours) | D21: NUM | E21: 0.1 | F21: dso_days | G21: Non | J21: ECONOMIC | K21: Non | L21: ratio/%
A22: D3C4 | B22: D3 | C22: Cash coverage (cash / échéances) | D22: NUM | E22: 0.2 | F22: cash_coverage | G22: Non | J22: ECONOMIC | K22: Oui | L22: ratio/%
A23: D3C5 | B23: D3 | C23: Impasse brute | D23: NUM | E23: 0.15 | F23: funding_gap_pct | G23: Non | J23: ECONOMIC | K23: Oui | L23: ratio/%
A24: D3C6 | B24: D3 | C24: Rotation stock (mois) | D24: NUM | E24: 0.1 | F24: stock_rotation_months | G24: Non | J24: ECONOMIC | K24: Non | L24: ratio/%
A25: D3C7 | B25: D3 | C25: Marge brute stressée (prix -10%) | D25: NUM | E25: 0.1 | F25: stressed_margin_pct | G25: Non | J25: ECONOMIC | K25: Non | L25: ratio/%
A26: D3C8 | B26: D3 | C26: Ventes sécurisées (financement acquéreur) | D26: NUM | E26: 0.1 | F26: secured_sales_rate | G26: Non | J26: ECONOMIC | K26: Non | L26: %
A27: D4C1 | B27: D4 | C27: Marge brute (CA - coûts directs)/CA | D27: NUM | E27: 0.2 | F27: gross_margin_pct | G27: Non | J27: ECONOMIC | K27: Oui | L27: ratio/%
A28: D4C2 | B28: D4 | C28: LTC (dette / coût total) | D28: NUM | E28: 0.15 | F28: ltc | G28: Non | J28: ECONOMIC | K28: Non | L28: ratio/%
A29: D4C3 | B29: D4 | C29: LTV stressée (dette / valeur×0,90) | D29: NUM | E29: 0.2 | F29: ltv_stressed | G29: Non | J29: GUARANTEE | K29: Non | L29: ratio/%
A30: D4C4 | B30: D4 | C30: Couverture garanties réalisable | D30: NUM | E30: 0.15 | F30: guarantee_coverage | G30: Non | J30: GUARANTEE | K30: Non | L30: ratio/%
... A33: D4C7 | B33: D4 | C33: Quotité de désengagement vs équilibre | D33: NUM | E33: 0.05 | F33: release_quotity_gap_pts | G33: Non | J33: GUARANTEE | K33: Non | L33: pts

Sheet P_Baremes
A1: Barèmes de notation
A2: PLAGE : borne basse incluse (≥ Min), borne haute exclue (< Max) ; cellule vide = illimité. MODALITE : valeur exacte saisie. Note de 1 à 10.
A4: Critère | B4: Type | C4: Valeur (modalité) | D4: Min (≥) | E4: Max (<) | F4: Libellé | G4: Ordre | H4: Note
A5: D1C1 | B5: PLAGE | E5: 1 | F5: < 1 (critique) | G5: 0 | H5: 1
A6: D1C1 | B6: PLAGE | D6: 1 | E6: 3 | F6: 1 à < 3 (vigilance) | G6: 1 | H6: 6
A7: D1C1 | B7: PLAGE | D7: 3 | F7: ≥ 3 (favorable) | G7: 2 | H7: 10
A8: D1C2 | B8: PLAGE | E8: 100 | F8: < 100 (favorable) | G8: 0 | H8: 10
A9: D1C2 | B9: PLAGE | D9: 100 | E9: 150 | F9: 100 à < 150 (vigilance) | G9: 1 | H9: 6
A10: D1C2 | B10: PLAGE | D10: 150 | F10: ≥ 150 (critique) | G10: 2 | H10: 1
A11: D1C3 | B11: MODALITE | C11: opaque | F11: Opaque | G11: 0 | H11: 1
A12: D1C3 | B12: MODALITE | C12: partielle | F12: Partielle | G12: 1 | H12: 6
A13: D1C3 | B13: MODALITE | C13: claire | F13: Claire / structurée | G13: 2 | H13: 10
A14: D1C4 | B14: PLAGE | E14: 40 | F14: < 40 (favorable) | G14: 0 | H14: 10
A15: D1C4 | B15: PLAGE | D15: 40 | E15: 60 | F15: 40 à < 60 (vigilance) | G15: 1 | H15: 6
A16: D1C4 | B16: PLAGE | D16: 60 | F16: ≥ 60 (critique) | G16: 2 | H16: 1
A17: D1C5 | B17: MODALITE | C17: opportuniste | F17: Opportuniste | G17: 0 | H17: 2
A18: D1C5 | B18: MODALITE | C18: regional | F18: Régional | G18: 1 | H18: 6
A19: D1C5 | B19: MODALITE | C19: structure | F19: Structuré | G19: 2 | H19: 10
A20: D1C6 | B20: PLAGE | E20: 80 | F20: < 80 (critique) | G20: 0 | H20: 1
A21: D1C6 | B21: PLAGE | D21: 80 | E21: 100 | F21: 80 à < 100 (vigilance) | G21: 1 | H21: 6
A22: D1C6 | B22: PLAGE | D22: 100 | F22: ≥ 100 (favorable) | G22: 2 | H22: 10
A23: D2C1 | B23: MODALITE | C23: absentes | F23: Titre non purgé / autorisations absentes | G23: 0 | H23: 1
A24: D2C1 | B24: MODALITE | C24: partielles | F24: Partielles | G24: 1 | H24: 6
A25: D2C1 | B25: MODALITE | C25: definitives | F25: Titre purgé + autorisations définitives | G25: 2 | H25: 10
A26: D2C2 | B26: MODALITE | C26: sur_positionne | F26: Sur-positionné / sur-offre | G26: 0 | H26: 2
A27: D2C2 | B27: MODALITE | C27: moyen | F27: Correct | G27: 1 | H27: 6
A28: D2C2 | B28: MODALITE | C28: aligne | F28: Aligné / forte demande | G28: 2 | H28: 10
A29: D2C3 | B29: MODALITE | C29: elevee | F29: Élevée | G29: 0 | H29: 2
A30: D2C3 | B30: MODALITE | C30: moyenne | F30: Moyenne | G30: 1 | H30: 6
A31: D2C3 | B31: MODALITE | C31: standard | F31: Standard | G31: 2 | H31: 10
A32: D2C4 | B32: PLAGE | E32: 80 | F32: < 80 (critique) | G32: 0 | H32: 1
A33: D2C4 | B33: PLAGE | D33: 80 | E33: 100 | F33: 80 à < 100 (vigilance) | G33: 1 | H33: 6
A34: D2C4 | B34: PLAGE | D34: 100 | F34: ≥ 100 (favorable) | G34: 2 | H34: 10
A35: D2C5 | B35: MODALITE | C35: eleve | F35: Élevé | G35: 0 | H35: 2
A36: D2C5 | B36: MODALITE | C36: moyen | F36: Moyen | G36: 1 | H36: 6
A37: D2C5 | B37: MODALITE | C37: faible | F37: Faible | G37: 2 | H37: 10
A38: D2C6 | B38: MODALITE | C38: elevee | F38: Élevée | G38: 0 | H38: 2
A39: D2C6 | B39: MODALITE | C39: moyenne | F39: Moyenne | G39: 1 | H39: 6
A40: D2C6 | B40: MODALITE | C40: faible | F40: Faible | G40: 2 | H40: 10
A41: D2C7 | B41: PLAGE | E41: 25 | F41: < 25 (favorable) | G41: 0 | H41: 10
A42: D2C7 | B42: PLAGE | D42: 25 | E42: 35 | F42: 25 à < 35 (vigilance) | G42: 1 | H42: 6
A43: D2C7 | B43: PLAGE | D43: 35 | F43: ≥ 35 (critique) | G43: 2 | H43: 1
A44: D2C8 | B44: PLAGE | E44: 50 | F44: < 50 % (critique) | G44: 0 | H44: 1
A45: D2C8 | B45: PLAGE | D45: 50 | E45: 100 | F45: 50 à < 100 % (vigilance) | G45: 1 | H45: 6
A46: D2C8 | B46: PLAGE | D46: 100 | F46: ≥ 100 % (favorable) | G46: 2 | H46: 10
A47: D3C1 | B47: PLAGE | E47: 25 | F47: < 25 (critique) | G47: 0 | H47: 1
A48: D3C1 | B48: PLAGE | D48: 25 | E48: 40 | F48: 25 à < 40 (vigilance) | G48: 1 | H48: 6
A49: D3C1 | B49: PLAGE | D49: 40 | F49: ≥ 40 (favorable) | G49: 2 | H49: 10
A50: D3C2 | B50: PLAGE | E50: 80 | F50: < 80 (critique) | G50: 0 | H50: 1
A51: D3C2 | B51: PLAGE | D51: 80 | E51: 100 | F51: 80 à < 100 (vigilance) | G51: 1 | H51: 6
A52: D3C2 | B52: PLAGE | D52: 100 | F52: ≥ 100 (favorable) | G52: 2 | H52: 10
A53: D3C3 | B53: PLAGE | E53: 120 | F53: < 120 (favorable) | G53: 0 | H53: 10
A54: D3C3 | B54: PLAGE | D54: 120 | E54: 240 | F54: 120 à < 240 (vigilance) | G54: 1 | H54: 6
A55: D3C3 | B55: PLAGE | D55: 240 | F55: ≥ 240 (critique) | G55: 2 | H55: 1
A56: D3C4 | B56: PLAGE | E56: 1 | F56: < 1 (critique) | G56: 0 | H56: 1
A57: D3C4 | B57: PLAGE | D57: 1 | E57: 1.2 | F57: 1 à < 1,2 (vigilance) | G57: 1 | H57: 6
A58: D3C4 | B58: PLAGE | D58: 1.2 | F58: ≥ 1,2 (favorable) | G58: 2 | H58: 10
A59: D3C5 | B59: PLAGE | E59: 0.0001 | F59: ≤ 0 — aucune impasse (favorable) | G59: 0 | H59: 10
A60: D3C5 | B60: PLAGE | D60: 0.0001 | E60: 10 | F60: > 0 à < 10 (vigilance) | G60: 1 | H60: 6
A61: D3C5 | B61: PLAGE | D61: 10 | F61: ≥ 10 (critique) | G61: 2 | H61: 1
A62: D3C6 | B62: PLAGE | E62: 18 | F62: < 18 (favorable) | G62: 0 | H62: 10
A63: D3C6 | B63: PLAGE | D63: 18 | E63: 30 | F63: 18 à < 30 (vigilance) | G63: 1 | H63: 6
A64: D3C6 | B64: PLAGE | D64: 30 | F64: ≥ 30 (critique) | G64: 2 | H64: 1
A65: D3C7 | B65: PLAGE | E65: 10 | F65: < 10 (critique) | G65: 0 | H65: 1
A66: D3C7 | B66: PLAGE | D66: 10 | E66: 15 | F66: 10 à < 15 (vigilance) | G66: 1 | H66: 6
A67: D3C7 | B67: PLAGE | D67: 15 | F67: ≥ 15 (favorable) | G67: 2 | H67: 10
A68: D3C8 | B68: PLAGE | E68: 25 | F68: < 25 % (critique) | G68: 0 | H68: 1
A69: D3C8 | B69: PLAGE | D69: 25 | E69: 40 | F69: 25 à < 40 % (vigilance) | G69: 1 | H69: 6
A70: D3C8 | B70: PLAGE | D70: 40 | F70: ≥ 40 % (favorable) | G70: 2 | H70: 10
A71: D4C1 | B71: PLAGE | E71: 15 | F71: < 15 (critique) | G71: 0 | H71: 1
A72: D4C1 | B72: PLAGE | D72: 15 | E72: 25 | F72: 15 à < 25 (vigilance) | G72: 1 | H72: 6
A73: D4C1 | B73: PLAGE | D73: 25 | F73: ≥ 25 (favorable) | G73: 2 | H73: 10
A74: D4C2 | B74: PLAGE | E74: 60 | F74: < 60 (favorable) | G74: 0 | H74: 10
A75: D4C2 | B75: PLAGE | D75: 60 | E75: 80 | F75: 60 à < 80 (vigilance) | G75: 1 | H75: 6
A76: D4C2 | B76: PLAGE | D76: 80 | F76: ≥ 80 (critique) | G76: 2 | H76: 1
A77: D4C3 | B77: PLAGE | E77: 70 | F77: < 70 (favorable) | G77: 0 | H77: 10
A78: D4C3 | B78: PLAGE | D78: 70 | E78: 85 | F78: 70 à < 85 (vigilance) | G78: 1 | H78: 6
A79: D4C3 | B79: PLAGE | D79: 85 | F79: ≥ 85 (critique) | G79: 2 | H79: 1
A80: D4C4 | B80: PLAGE | E80: 90 | F80: < 90 (critique) | G80: 0 | H80: 1
A81: D4C4 | B81: PLAGE | D81: 90 | E81: 120 | F81: 90 à < 120 (vigilance) | G81: 1 | H81: 6
A82: D4C4 | B82: PLAGE | D82: 120 | F82: ≥ 120 (favorable) | G82: 2 | H82: 10
A83: D4C5 | B83: MODALITE | C83: non | F83: Non 1er rang | G83: 0 | H83: 1
A84: D4C5 | B84: MODALITE | C84: oui | F84: 1er rang | G84: 1 | H84: 10
A85: D4C6 | B85: PLAGE | E85: 1.5 | F85: < 1,5 (critique) | G85: 0 | H85: 1
A86: D4C6 | B86: PLAGE | D86: 1.5 | E86: 3 | F86: 1,5 à < 3 (vigilance) | G86: 1 | H86: 6
A87: D4C6 | B87: PLAGE | D87: 3 | F87: ≥ 3 (favorable) | G87: 2 | H87: 10
A88: D4C7 | B88: PLAGE | E88: -10 | F88: < −10 pts (critique) | G88: 0 | H88: 1
A89: D4C7 | B89: PLAGE | D89: -10 | E89: 0 | F89: −10 à < 0 pt (vigilance) | G89: 1 | H89: 6
A90: D4C7 | B90: PLAGE | D90: 0 | F90: ≥ 0 pt (favorable) | G90: 2 | H90: 10

Sheet P_Alertes
A1: Couche D5 — alertes (red flags)
A2: Règle simple : Clé / Opérateur / Valeur. Opérateurs : isTrue, isFalse, eq, neq, gt, gte, lt, lte. BLOCKING = souffrance automatique (malus 0).
A4: Code | B4: Libellé | C4: Sévérité | D4: Malus | E4: Domaines | F4: Clé d'entrée | G4: Opérateur | H4: Valeur réf. | I4: Comité | J4: Effet | K4: Référence réglementaire / interne
A5: RF_ACQUEREURS_NON_FINANCES | B5: Financement acquéreur majoritairement non sécurisé | C5: MEDIUM | D5: 10 | E5: D3,D5 | F5: buyers_financing_at_risk | G5: isTrue | I5: Non | J5: HYPOTHESIS | K5: Liquidité des ventes — solvabilité acquéreur
A6: RF_AUTORISATION_TIRAGE | B6: Autorisation indispensable aux travaux non levée | C6: HIGH | D6: 15 | E6: D2,D5 | F6: works_authorization_blocked | G6: isTrue | I6: Non | J6: SURVEILLANCE | K6: Loi 25-90 (lotissements) ; loi 12-90 (urbanisme) ; ANCFCC
A7: RF_CASH_LT_ECH | B7: Cash coverage < 1,0x | C7: HIGH | D7: 25 | E7: D3,D5 | F7: cash_coverage | G7: lt | H7: 1 | I7: Non | J7: HYPOTHESIS
A8: RF_DIVISION_RISQUES | B8: Limite de division des risques dépassée | C8: MEDIUM | D8: 0 | E8: D5 | F8: division_limit_breach | G8: isTrue | I8: Oui | J8: REGULATORY | K8: Division des risques — limite par contrepartie / groupe d'intérêt
A9: RF_FP_NEG | B9: Fonds propres négatifs | C9: HIGH | D9: 25 | E9: D4,D5 | F9: equity_negative | G9: isTrue | I9: Non | J9: HYPOTHESIS
A10: RF_IMPASSE_PERSIST | B10: Impasse de trésorerie persistante | C10: HIGH | D10: 20 | E10: D3,D5 | F10: funding_gap_persistent | G10: isTrue | I10: Non | J10: HYPOTHESIS
A11: RF_IMPAYE_90J | B11: Impayé ≥ 90 jours (souffrance automatique) | C11: BLOCKING | D11: 0 | E11: D5 | F11: dpd_days | G11: gte | H11: 90 | I11: Non | J11: REGULATORY | K11: 1/W art.5 ; art.34
A12: RF_LITIGE | B12: Action en justice / contentieux (CTX) | C12: BLOCKING | D12: 0 | E12: D5 | F12: legal_exposure | G12: eq | H12: litigation | I12: Non | J12: REGULATORY | K12: 1/W art.12.8
A13: RF_MAINLEVEE_SOUS_TARIFEE | B13: Prix de mainlevée sous-tarifé | C13: HIGH | D13: 15 | E13: D4,D5 | F13: release_underpriced | G13: isTrue | I13: Oui | J13: SURVEILLANCE | K13: Politique interne — mainlevées partielles
A14: RF_NON_1ER_RANG | B14: Garantie non 1er rang | C14: MEDIUM | D14: 25 | E14: D4,D5 | F14: first_rank | G14: eq | H14: non | I14: Non | J14: SURVEILLANCE
A15: RF_PROJET_ARRET_12M | B15: Projet à l'arrêt ≥ 12 mois (souffrance automatique) | C15: BLOCKING | D15: 0 | E15: D5 | F15: project_stopped_months | G15: gte | H15: 12 | I15: Non | J15: REGULATORY | K15: 1/W art.12.7
A16: RF_RESTRUCT | B16: Première restructuration | C16: MEDIUM | D16: 25 | E16: D5 | F16: restructured | G16: eq | H16: yes | I16: Oui | J16: REGULATORY | K16: 1/W art.17-31
A17: RF_RETARD_6M | B17: Retard chantier ≥ 6 mois | C17: HIGH | D17: 15 | E17: D2,D5 | F17: construction_delay_months | G17: gte | H17: 6 | I17: Oui | J17: SURVEILLANCE | K17: 1/W art.12.7

Sheet P_Ajustements
A1: Ajustements segment (α) et zone (β)
A2: S_ajusté = S_éco × (1 + α + β). Un segment ou une zone hors de ces listes est signalé, jamais assimilé à un risque neutre.
A4: Segment | B4: Libellé | C4: α | E4: Zone | F4: Libellé | G4: β
A5: social | B5: Logement social | C5: 0 | E5: casa_centre | F5: Casablanca — centre | G5: 0
A6: intermediaire | B6: Logement intermédiaire | C6: -0.05 | E6: casa_peripherie | F6: Casablanca — périphérie | G6: -0.05
A7: moyen_haut | B7: Moyen-haut standing | C7: 0 | E7: rabat_centre | F7: Rabat — centre | G7: 0.02
A8: touristique | B8: Touristique / hôtelier | C8: -0.07 | E8: rabat_peripherie | F8: Rabat — périphérie | G8: 0
A9: bureaux | B9: Bureaux | C9: -0.05 | E9: tanger | F9: Tanger | G9: 0
A10: commerces | B10: Commerces | C10: -0.03 | E10: marrakech | F10: Marrakech | G10: -0.07
A11: villas | B11: Villas | C11: -0.04 | E11: agadir | F11: Agadir | G11: 0
E12: fes_oriental | F12: Fès / Oriental | G12: -0.03
E13: regions_interieures | F13: Régions intérieures | G13: -0.05

Sheet P_Referentiels
A1: Référentiels métier (pratique marocaine)
A2: Équivalents des référentiels administrables de l'application. Modifiables ici sans macro.
A4: Chaîne d'autorisations
A5: Code | B5: Pièce | C5: Jalon | D5: Lotissement | E5: Construction | F5: Mixte | G5: Bloque travaux | H5: Bloque livraison | I5: Référence
A6: note_renseignement | B6: Note de renseignements urbanistiques | C6: ETUDE | D6: Oui | E6: Oui | F6: Oui | G6: Non | H6: Non | I6: Urbanisme — agence urbaine
A7: titre_foncier_purge | B7: Titre foncier purgé (sans inscription contraignante) | C7: OCTROI | D7: Oui | E7: Oui | F7: Oui | G7: Oui | H7: Non | I7: ANCFCC — conservation foncière
A8: autorisation_lotir | B8: Autorisation de lotir | C8: TIRAGE | D8: Oui | E8: Non | F8: Oui | G8: Oui | H8: Non | I8: Loi 25-90 relative aux lotissements
A9: permis_construire | B9: Permis de construire | C9: TIRAGE | D9: Non | E9: Oui | F9: Oui | G9: Oui | H9: Non | I9: Loi 12-90 relative à l'urbanisme
A10: autorisation_morcellement | B10: Autorisation de morcellement / éclatement du titre | C10: TIRAGE | D10: Oui | E10: Non | F10: Oui | G10: Non | H10: Non | I10: ANCFCC — morcellement du titre mère
A11: reception_provisoire | B11: Réception provisoire des travaux | C11: TIRAGE | D11: Oui | E11: Oui | F11: Oui | G11: Non | H11: Oui
A12: permis_habiter | B12: Permis d'habiter | C12: TIRAGE | D12: Non | E12: Oui | F12: Oui | G12: Non | H12: Oui | I12: Loi 12-90
A13: certificat_conformite | B13: Certificat de conformité | C13: TIRAGE | D13: Oui | E13: Oui | F13: Oui | G13: Non | H13: Oui
A14: reception_definitive | B14: Réception définitive | C14: TIRAGE | D14: Oui | E14: Oui | F14: Oui | G14: Non | H14: Non
A32: Financement de l'acquéreur
A33: Code | B33: Libellé | C33: Facteur de sécurisation
A34: fonds_propres | B34: Autofinancement (fonds propres acquéreur) | C34: 1
A35: credit_debloque | B35: Crédit acquéreur débloqué | C35: 1
A36: credit_accorde | B36: Crédit accordé (accord de principe / offre) | C36: 0.8
A37: credit_en_cours | B37: Demande de crédit en cours d'instruction | C37: 0.4
A38: non_instruit | B38: Financement non instruit | C38: 0.2
A39: credit_refuse | B39: Crédit refusé | C39: 0
A48: Natures de concours (information — contrôle de tirage)
A49: Code | B49: Libellé | C49: Situation de travaux visée requise
A50: avance_foncier | B50: Avance sur acquisition du foncier | C50: Non
A51: credit_accompagnement | B51: Crédit d'accompagnement / de construction | C51: Oui
A52: credit_amenagement | B52: Crédit d'aménagement (lotissement / VRD) | C52: Oui
A53: credit_in_fine | B53: Crédit in fine | C53: Non
A54: caution_marche | B54: Caution / engagement par signature | C54: Non
A56: Dispositifs d'aide à l'acquéreur (information)
A57: aide_directe_logement | B57: Aide directe au logement
A58: fogarim | B58: FOGARIM
A59: damane_assakane | B59: Damane Assakane
A60: aucun | B60: Aucun dispositif
