Workbook
Name Calc_Actif: P_General!$E$4
Name Calc_Arret: Calculateurs!$C$125:$C$127
Name Calc_Auth: Calculateurs!$D$8:$D$31
Name Calc_Concours: Calculateurs!$A$105:$E$114
Name Calc_Cout: Calculateurs!$C$187:$C$188
Name Calc_Desist: Calculateurs!$C$183:$C$184
Name Calc_Equip: Calculateurs!$A$164:$H$171
Name Calc_EquipParam: Calculateurs!$C$158:$C$161
Name Calc_Lots: Calculateurs!$A$42:$D$81
Name Calc_Mainlevee: Calculateurs!$C$90:$C$92
Name Calc_Mixte: Calculateurs!$C$178:$C$180
Name Calc_Plan: Calculateurs!$A$140:$D$151
Name Calc_PlanDate: Calculateurs!$C$138
Name Calc_Tirage: Calculateurs!$C$132:$C$134
Name Calc_Valeur: Calculateurs!$C$39
Name In_Calc: Saisie!$F$13:$F$92
Name In_Cles: Saisie!$B$13:$B$92
Name In_Etat: Saisie!$I$13:$I$92
Name In_Retenue: Saisie!$G$13:$G$92
Name In_Saisie: Saisie!$E$13:$E$92
Name P_Classes: P_General!$A$27:$E$36
Name P_ClsCodes: P_General!$A$27:$A$36
Name P_Date: P_General!$B$5
Name P_DecTbl: P_General!$A$52:$B$56
Name P_DomCodes: P_General!$A$16:$A$23
Name P_DomNoms: P_General!$B$16:$B$23
Name P_DomPoids: P_General!$C$16:$C$23
Name P_DPD1: P_General!$B$45
Name P_DPD2: P_General!$B$46
Name P_DPD3: P_General!$B$47
Name P_ExtraKey: P_General!$B$12
Name P_GO: P_General!$B$7
Name P_GWC: P_General!$B$8
Name P_PDa: P_General!$B$10
Name P_PDb: P_General!$B$11
Name P_PhaseCodes: P_General!$A$40:$A$42
Name P_PhaseHdr: P_General!$B$39:$I$39
Name P_PhaseTbl: P_General!$A$40:$I$42
Name P_Scale: P_General!$B$6
Name P_SegCodes: P_Ajustements!$A$5:$A$24
Name P_SegLabels: P_Ajustements!$B$5:$B$11
Name P_SegLabelsAll: P_Ajustements!$B$5:$B$24
Name P_SegTbl: P_Ajustements!$A$5:$C$24
Name P_Version: P_General!$B$4
Name P_WATCH: P_General!$B$9
Name P_ZoneCodes: P_Ajustements!$E$5:$E$24
Name P_ZoneLabels: P_Ajustements!$F$5:$F$13
Name P_ZoneLabelsAll: P_Ajustements!$F$5:$F$24
Name P_ZoneTbl: P_Ajustements!$E$5:$G$24
Name R_AuthCodes: P_Referentiels!$A$6:$A$29
Name R_AuthTbl: P_Referentiels!$A$6:$I$29
Name R_FinCodes: P_Referentiels!$A$34:$A$45
Name R_FinTbl: P_Referentiels!$A$34:$C$45
Name R_ModCode: P_Referentiels!$B$66:$B$75
Name R_ModKey: P_Referentiels!$A$66:$A$75
Name R_ModLab: P_Referentiels!$C$66:$C$75
Name Res_Adj: Resultat!$C$11
Name Res_Alertes: Resultat!$C$26
Name Res_AlertesLib: Resultat!$P$137
Name Res_ClasseInt: Resultat!$C$8

Sheet Accueil
B1: Outil de scoring — Promotion immobilière
B2: ="Modèle PI_PROMOTION "&P_Version&" (publié le "&P_Date&") · outil 5.1 du 05/10/2026" -> Modèle PI_PROMOTION v5.0.0 (publié le 2026-10-01) · outil 5.1 du 05/10/2026
B4: Dossier en cours
B5: Référence · projet | C5: =IF(Saisie!C4="","(aucun dossier — commencez par l'onglet Saisie)",Saisie!C4&" — "&Saisie!C5) -> EXEMPLE — Dossier d'exemple — à remplacer (ruban « Scoring PI » › Nouveau dossier)
B6: Score final / 100 | C6: =Res_ScoreFinal -> 68.46
B7: Décision | C7: =IFERROR(VLOOKUP(Res_Decision,P_DecTbl,2,FALSE),Res_Decision) -> Favorable sous conditions
B8: Classe interne | C8: =Res_ClasseInt -> Surveillance
B9: Critères renseignés | C9: =Saisie!I7 -> 37 / 37
B10: Données décisionnelles manquantes | C10: =Saisie!I8 -> 0
C11: → Ouvrir la fiche de résultat
B13: Comment faire
B14: 1. Nouveau dossier | C14: Ruban « Scoring PI » › Nouveau dossier : vide la saisie et les calculateurs. Sans macros : effacez les cellules jaunes de l'onglet Saisie.
B15: 2. Renseigner la saisie | C15: Identité du dossier puis données, dans les cellules jaunes (listes en clair). Laissez vide une donnée inconnue. La colonne « État » signale ce qui manque ; le résultat se met à jour en direct en haut de la feuille.
B16: 3. Calculateurs (facultatif) | C16: Autorisations, ventes sécurisées, mainlevée, division des risques, arrêt de chantier, déblocages, équipements exigés, programme mixte : ils calculent 16 données de la saisie (votre saisie directe prime).
B17: 4. Lire et imprimer la fiche | C17: Décision, notes, données manquantes, conditions à lever, alertes, points d'attention. Imprimable sur une page (Ctrl+P) ; ruban › Exporter la fiche en PDF.
B18: 5. Enregistrer le dossier | C18: Ruban › Enregistrer le dossier : il est rangé dans l'onglet Portefeuille (même référence = mise à jour). Ruban › Ouvrir un dossier pour le recharger.
B19: 6. Aller plus loin | C19: Stress test (7 scénarios), scoring de tout le portefeuille, journal des calculs (onglet Historique), aide détaillée (onglet Aide).
B21: Macros et ruban « Scoring PI »
B22: Fichier .xlsm | C22: Les macros et l'onglet de ruban « Scoring PI » sont intégrés : rien à installer. Si Excel indique que les macros sont bloquées (fichier reçu par e-mail ou téléchargé) : fermez le fichier, clic droit › Propriétés › cochez « Débloquer » › OK, rouvrez-le puis cliquez « Activer le contenu ».
B23: Sans macros | C23: Le calcul (saisie, fiche, résultat) fonctionne sans macros, y compris dans le fichier .xlsx : seules les actions du ruban (nouveau dossier, enregistrer, PDF, stress, portefeuille) sont indisponibles.
B25: Bon à savoir
B26: Vide ≠ 0 | C26: Une donnée vide est « absente » : note plancher, ou « dossier incomplet » si elle est décisionnelle. Ne saisissez jamais 0 ou « Non » à la place d'une donnée inconnue.
B27: Pourcentages | C27: Saisir les pourcentages en points : 62 pour 62 %. Une valeur comme 0,62 est signalée dans la colonne « État ».
B28: Feuilles protégées | C28: Seules les cellules jaunes sont modifiables (protection sans mot de passe : Révision › Ôter la protection si besoin).
B29: Paramètres du modèle | C29: Onglets P_* masqués : ruban › Paramètres (afficher / masquer). Toute modification : Valider le modèle, puis informer le propriétaire du modèle.
B30: Décision officielle | C30: Ce classeur est un outil d'aide (simulation, préparation de comité, formation). La décision officielle se prend dans l'application.

Sheet Saisie
A1: Saisie du dossier
A2: Renseignez les cellules jaunes (listes déroulantes en clair). Laissez VIDE une donnée inconnue : elle n'améliore jamais le résultat. La colonne « État » signale ce qui manque.
H3: Résultat en direct
A4: Référence dossier | C4: EXEMPLE | H4: Score final (0–100) | I4: =Res_ScoreFinal -> 68.46
A5: Nom du projet | C5: Dossier d'exemple — à remplacer (ruban « Scoring PI » › Nouveau dossier) | H5: Décision | I5: =IFERROR(VLOOKUP(Res_Decision,P_DecTbl,2,FALSE),Res_Decision) -> Favorable sous conditions
A6: Segment | C6: Moyen-haut standing | D6: =IF(C6="","",IFERROR(INDEX(P_SegCodes,MATCH(C6,P_SegLabelsAll,0)),C6)) -> moyen_haut | H6: Classe interne | I6: =Res_ClasseInt -> Surveillance
A7: Zone | C7: Casablanca — centre | D7: =IF(C7="","",IFERROR(INDEX(P_ZoneCodes,MATCH(C7,P_ZoneLabelsAll,0)),C7)) -> casa_centre | H7: Critères renseignés | I7: =SUMPRODUCT((G13:G49<>"")*1)&" / 37" -> 37 / 37
A8: Classe réglementaire BAM | C8: SAIN | E8: =IFERROR(IF(NOT(ISNUMBER(INDEX(In_Retenue,MATCH("dpd_days",In_Cles,0)))),"",IF(INDEX(In_Retenue,MATCH("dpd_days",In_Cles,0))>=P_DPD3,"COMPROMIS",IF(INDEX(In_Retenue,MATCH("dpd_days",In_Cles,0))>=P_DPD2,"DOUTEUX",IF(INDEX(In_Retenue,MATCH("dpd_days",In_Cles,0))>=P_DPD1,"PRE_DOUTEUX","SAIN")))),"") -> SAIN | F8: =IF(OR(C8="",E8=""),"",IF(MATCH(C8,P_ClsCodes,0)<MATCH(E8,P_ClsCodes,0),"⚠ Moins sévère que le retard","Cohérente avec le retard")) -> Cohérente avec le retard | H8: Données décisionnelles manquantes | I8: =COUNTIF(I13:I92,"⚠ Manquant*") -> 0
A9: Phase du projet (challenger) | C9: CONSTRUCTION | H9: Valeurs à vérifier (%) | I9: =COUNTIF(I13:I92,"⚠ En %*")+COUNTIF(I13:I92,"⚠ Valeur hors*") -> 0
A10: Version du modèle | C10: =P_Version&" — "&P_Date -> v5.0.0 — 2026-10-01 | H10: → Ouvrir la fiche de résultat | I10: =IF(Calc_Actif,"","⚠ Calculateurs désactivés")
A12: Section | B12: Clé technique | C12: Donnée | D12: Type | E12: Votre saisie | F12: Calculé (Calculateurs) | G12: Valeur utilisée | H12: Unité / aide | I12: État
A13: D1 — Sponsor & Gouvernance | B13: promoter_completed_projects | C13: Projets similaires livrés (5 ans) | D13: NUM | E13: 8 | G13: =IF(E13<>"",E13,IF(F13="","",F13)) -> 8 | H13: nombre de projets (ex. 8) | I13: =IF(FALSE*ISNUMBER(G13)*(N(G13)>0)*(N(G13)<1),"⚠ En % : saisir 62 pour 62 %",IF(G13<>"","✔ Renseigné",IF(OR(COUNTIFS(P_Criteres!$F$5:$F$64,B13,P_Criteres!$G$5:$G$64,"Oui")>0,COUNTIFS(P_Criteres!$F$5:$F$64,B13,P_Criteres!$K$5:$K$64,"Oui")>0,B13=P_ExtraKey),"⚠ Manquant — décisionnel","○ Non renseigné"))) -> ✔ Renseigné
A14: D1 — Sponsor & Gouvernance | B14: promoter_gearing | C14: Gearing promoteur (dettes nettes / FP) | D14: NUM | E14: 85 | G14: =IF(E14<>"",E14,IF(F14="","",F14)) -> 85 | H14: % (dettes / fonds propres, ex. 85) | I14: =IF(TRUE*ISNUMBER(G14)*(N(G14)>0)*(N(G14)<1),"⚠ En % : saisir 62 pour 62 %",IF(G14<>"","✔ Renseigné",IF(OR(COUNTIFS(P_Criteres!$F$5:$F$64,B14,P_Criteres!$G$5:$G$64,"Oui")>0,COUNTIFS(P_Criteres!$F$5:$F$64,B14,P_Criteres!$K$5:$K$64,"Oui")>0,B14=P_ExtraKey),"⚠ Manquant — décisionnel","○ Non renseigné"))) -> ✔ Renseigné
A15: D1 — Sponsor & Gouvernance | B15: governance_quality | C15: Gouvernance & structure juridique | D15: QUAL | E15: Claire / structurée | G15: =IF(E15<>"",IF(SUMPRODUCT((P_Baremes!$A$5:$A$400="D1C3")*(P_Baremes!$F$5:$F$400=E15))>0,INDEX(P_Baremes!$C$5:$C$400,SUMPRODUCT(MAX((P_Baremes!$A$5:$A$400="D1C3")*(P_Baremes!$F$5:$F$400=E15)*(ROW(P_Baremes!$A$5:$A$400)-4)))),E15),IF(F15="","",F15)) -> claire | H15: choisir dans la liste | I15: =IF(FALSE*ISNUMBER(G15)*(N(G15)>0)*(N(G15)<1),"⚠ En % : saisir 62 pour 62 %",IF(AND(E15<>"",COUNTIFS(P_Baremes!$A$5:$A$400,"D1C3",P_Baremes!$C$5:$C$400,G15)=0),"⚠ Valeur hors liste",IF(G15<>"","✔ Renseigné",IF(OR(COUNTIFS(P_Criteres!$F$5:$F$64,B15,P_Criteres!$G$5:$G$64,"Oui")>0,COUNTIFS(P_Criteres!$F$5:$F$64,B15,P_Criteres!$K$5:$K$64,"Oui")>0,B15=P_ExtraKey),"⚠ Manquant — décisionnel","○ Non renseigné")))) -> ✔ Renseigné
A16: D1 — Sponsor & Gouvernance | B16: mono_project_concentration | C16: Concentration mono-projet (CA projet / CA total) | D16: NUM | E16: 35 | G16: =IF(E16<>"",E16,IF(F16="","",F16)) -> 35 | H16: % (ex. 35) | I16: =IF(TRUE*ISNUMBER(G16)*(N(G16)>0)*(N(G16)<1),"⚠ En % : saisir 62 pour 62 %",IF(G16<>"","✔ Renseigné",IF(OR(COUNTIFS(P_Criteres!$F$5:$F$64,B16,P_Criteres!$G$5:$G$64,"Oui")>0,COUNTIFS(P_Criteres!$F$5:$F$64,B16,P_Criteres!$K$5:$K$64,"Oui")>0,B16=P_ExtraKey),"⚠ Manquant — décisionnel","○ Non renseigné"))) -> ✔ Renseigné
A17: D1 — Sponsor & Gouvernance | B17: promoter_type | C17: Typologie promoteur | D17: QUAL | E17: Structuré | G17: =IF(E17<>"",IF(SUMPRODUCT((P_Baremes!$A$5:$A$400="D1C5")*(P_Baremes!$F$5:$F$400=E17))>0,INDEX(P_Baremes!$C$5:$C$400,SUMPRODUCT(MAX((P_Baremes!$A$5:$A$400="D1C5")*(P_Baremes!$F$5:$F$400=E17)*(ROW(P_Baremes!$A$5:$A$400)-4)))),E17),IF(F17="","",F17)) -> structure | H17: choisir dans la liste | I17: =IF(FALSE*ISNUMBER(G17)*(N(G17)>0)*(N(G17)<1),"⚠ En % : saisir 62 pour 62 %",IF(AND(E17<>"",COUNTIFS(P_Baremes!$A$5:$A$400,"D1C5",P_Baremes!$C$5:$C$400,G17)=0),"⚠ Valeur hors liste",IF(G17<>"","✔ Renseigné",IF(OR(COUNTIFS(P_Criteres!$F$5:$F$64,B17,P_Criteres!$G$5:$G$64,"Oui")>0,COUNTIFS(P_Criteres!$F$5:$F$64,B17,P_Criteres!$K$5:$K$64,"Oui")>0,B17=P_ExtraKey),"⚠ Manquant — décisionnel","○ Non renseigné")))) -> ✔ Renseigné
A18: D1 — Sponsor & Gouvernance | B18: equity_injected_ratio | C18: Apport effectif (injecté / prévu) | D18: NUM | E18: 100 | G18: =IF(E18<>"",E18,IF(F18="","",F18)) -> 100 | H18: % (ex. 100) | I18: =IF(TRUE*ISNUMBER(G18)*(N(G18)>0)*(N(G18)<1),"⚠ En % : saisir 62 pour 62 %",IF(G18<>"","✔ Renseigné",IF(OR(COUNTIFS(P_Criteres!$F$5:$F$64,B18,P_Criteres!$G$5:$G$64,"Oui")>0,COUNTIFS(P_Criteres!$F$5:$F$64,B18,P_Criteres!$K$5:$K$64,"Oui")>0,B18=P_ExtraKey),"⚠ Manquant — décisionnel","○ Non renseigné"))) -> ✔ Renseigné
A19: D2 — Qualité intrinsèque du projet | B19: land_permits_status | C19: Foncier & autorisations | D19: QUAL | E19: Titre purgé + autorisations définitives | G19: =IF(E19<>"",IF(SUMPRODUCT((P_Baremes!$A$5:$A$400="D2C1")*(P_Baremes!$F$5:$F$400=E19))>0,INDEX(P_Baremes!$C$5:$C$400,SUMPRODUCT(MAX((P_Baremes!$A$5:$A$400="D2C1")*(P_Baremes!$F$5:$F$400=E19)*(ROW(P_Baremes!$A$5:$A$400)-4)))),E19),IF(F19="","",F19)) -> definitives | H19: choisir dans la liste | I19: =IF(FALSE*ISNUMBER(G19)*(N(G19)>0)*(N(G19)<1),"⚠ En % : saisir 62 pour 62 %",IF(AND(E19<>"",COUNTIFS(P_Baremes!$A$5:$A$400,"D2C1",P_Baremes!$C$5:$C$400,G19)=0),"⚠ Valeur hors liste",IF(G19<>"","✔ Renseigné",IF(OR(COUNTIFS(P_Criteres!$F$5:$F$64,B19,P_Criteres!$G$5:$G$64,"Oui")>0,COUNTIFS(P_Criteres!$F$5:$F$64,B19,P_Criteres!$K$5:$K$64,"Oui")>0,B19=P_ExtraKey),"⚠ Manquant — décisionnel","○ Non renseigné")))) -> ✔ Renseigné
A20: D2 — Qualité intrinsèque du projet | B20: market_positioning | C20: Marché & positionnement | D20: QUAL | E20: Aligné / forte demande | G20: =IF(E20<>"",IF(SUMPRODUCT((P_Baremes!$A$5:$A$400="D2C2")*(P_Baremes!$F$5:$F$400=E20))>0,INDEX(P_Baremes!$C$5:$C$400,SUMPRODUCT(MAX((P_Baremes!$A$5:$A$400="D2C2")*(P_Baremes!$F$5:$F$400=E20)*(ROW(P_Baremes!$A$5:$A$400)-4)))),E20),IF(F20="","",F20)) -> aligne | H20: choisir dans la liste | I20: =IF(FALSE*ISNUMBER(G20)*(N(G20)>0)*(N(G20)<1),"⚠ En % : saisir 62 pour 62 %",IF(AND(E20<>"",COUNTIFS(P_Baremes!$A$5:$A$400,"D2C2",P_Baremes!$C$5:$C$400,G20)=0),"⚠ Valeur hors liste",IF(G20<>"","✔ Renseigné",IF(OR(COUNTIFS(P_Criteres!$F$5:$F$64,B20,P_Criteres!$G$5:$G$64,"Oui")>0,COUNTIFS(P_Criteres!$F$5:$F$64,B20,P_Criteres!$K$5:$K$64,"Oui")>0,B20=P_ExtraKey),"⚠ Manquant — décisionnel","○ Non renseigné")))) -> ✔ Renseigné
A21: D2 — Qualité intrinsèque du projet | B21: technical_complexity | C21: Complexité technique | D21: QUAL | E21: Standard | G21: =IF(E21<>"",IF(SUMPRODUCT((P_Baremes!$A$5:$A$400="D2C3")*(P_Baremes!$F$5:$F$400=E21))>0,INDEX(P_Baremes!$C$5:$C$400,SUMPRODUCT(MAX((P_Baremes!$A$5:$A$400="D2C3")*(P_Baremes!$F$5:$F$400=E21)*(ROW(P_Baremes!$A$5:$A$400)-4)))),E21),IF(F21="","",F21)) -> standard | H21: choisir dans la liste | I21: =IF(FALSE*ISNUMBER(G21)*(N(G21)>0)*(N(G21)<1),"⚠ En % : saisir 62 pour 62 %",IF(AND(E21<>"",COUNTIFS(P_Baremes!$A$5:$A$400,"D2C3",P_Baremes!$C$5:$C$400,G21)=0),"⚠ Valeur hors liste",IF(G21<>"","✔ Renseigné",IF(OR(COUNTIFS(P_Criteres!$F$5:$F$64,B21,P_Criteres!$G$5:$G$64,"Oui")>0,COUNTIFS(P_Criteres!$F$5:$F$64,B21,P_Criteres!$K$5:$K$64,"Oui")>0,B21=P_ExtraKey),"⚠ Manquant — décisionnel","○ Non renseigné")))) -> ✔ Renseigné
A22: D2 — Qualité intrinsèque du projet | B22: progress_vs_plan | C22: Avancement vs planning | D22: NUM | E22: 100 | G22: =IF(E22<>"",E22,IF(F22="","",F22)) -> 100 | H22: % (ex. 100) | I22: =IF(TRUE*ISNUMBER(G22)*(N(G22)>0)*(N(G22)<1),"⚠ En % : saisir 62 pour 62 %",IF(G22<>"","✔ Renseigné",IF(OR(COUNTIFS(P_Criteres!$F$5:$F$64,B22,P_Criteres!$G$5:$G$64,"Oui")>0,COUNTIFS(P_Criteres!$F$5:$F$64,B22,P_Criteres!$K$5:$K$64,"Oui")>0,B22=P_ExtraKey),"⚠ Manquant — décisionnel","○ Non renseigné"))) -> ✔ Renseigné
A23: D2 — Qualité intrinsèque du projet | B23: sav_litigation | C23: Litiges clients / SAV | D23: QUAL | E23: Faible | G23: =IF(E23<>"",IF(SUMPRODUCT((P_Baremes!$A$5:$A$400="D2C5")*(P_Baremes!$F$5:$F$400=E23))>0,INDEX(P_Baremes!$C$5:$C$400,SUMPRODUCT(MAX((P_Baremes!$A$5:$A$400="D2C5")*(P_Baremes!$F$5:$F$400=E23)*(ROW(P_Baremes!$A$5:$A$400)-4)))),E23),IF(F23="","",F23)) -> faible | H23: choisir dans la liste | I23: =IF(FALSE*ISNUMBER(G23)*(N(G23)>0)*(N(G23)<1),"⚠ En % : saisir 62 pour 62 %",IF(AND(E23<>"",COUNTIFS(P_Baremes!$A$5:$A$400,"D2C5",P_Baremes!$C$5:$C$400,G23)=0),"⚠ Valeur hors liste",IF(G23<>"","✔ Renseigné",IF(OR(COUNTIFS(P_Criteres!$F$5:$F$64,B23,P_Criteres!$G$5:$G$64,"Oui")>0,COUNTIFS(P_Criteres!$F$5:$F$64,B23,P_Criteres!$K$5:$K$64,"Oui")>0,B23=P_ExtraKey),"⚠ Manquant — décisionnel","○ Non renseigné")))) -> ✔ Renseigné
A24: D2 — Qualité intrinsèque du projet | B24: macro_sensitivity | C24: Sensibilité macro / subvention | D24: QUAL | E24: Faible | G24: =IF(E24<>"",IF(SUMPRODUCT((P_Baremes!$A$5:$A$400="D2C6")*(P_Baremes!$F$5:$F$400=E24))>0,INDEX(P_Baremes!$C$5:$C$400,SUMPRODUCT(MAX((P_Baremes!$A$5:$A$400="D2C6")*(P_Baremes!$F$5:$F$400=E24)*(ROW(P_Baremes!$A$5:$A$400)-4)))),E24),IF(F24="","",F24)) -> faible | H24: choisir dans la liste | I24: =IF(FALSE*ISNUMBER(G24)*(N(G24)>0)*(N(G24)<1),"⚠ En % : saisir 62 pour 62 %",IF(AND(E24<>"",COUNTIFS(P_Baremes!$A$5:$A$400,"D2C6",P_Baremes!$C$5:$C$400,G24)=0),"⚠ Valeur hors liste",IF(G24<>"","✔ Renseigné",IF(OR(COUNTIFS(P_Criteres!$F$5:$F$64,B24,P_Criteres!$G$5:$G$64,"Oui")>0,COUNTIFS(P_Criteres!$F$5:$F$64,B24,P_Criteres!$K$5:$K$64,"Oui")>0,B24=P_ExtraKey),"⚠ Manquant — décisionnel","○ Non renseigné")))) -> ✔ Renseigné
A25: D2 — Qualité intrinsèque du projet | B25: land_cost_ratio | C25: Coût foncier / CA | D25: NUM | E25: 22 | G25: =IF(E25<>"",E25,IF(F25="","",F25)) -> 22 | H25: % (ex. 22) | I25: =IF(TRUE*ISNUMBER(G25)*(N(G25)>0)*(N(G25)<1),"⚠ En % : saisir 62 pour 62 %",IF(G25<>"","✔ Renseigné",IF(OR(COUNTIFS(P_Criteres!$F$5:$F$64,B25,P_Criteres!$G$5:$G$64,"Oui")>0,COUNTIFS(P_Criteres!$F$5:$F$64,B25,P_Criteres!$K$5:$K$64,"Oui")>0,B25=P_ExtraKey),"⚠ Manquant — décisionnel","○ Non renseigné"))) -> ✔ Renseigné
A26: D2 — Qualité intrinsèque du projet | B26: authorization_completeness_pct | C26: Chaîne d'autorisations (complétude) | D26: NUM | E26: 100 | F26: =IF(Calc_Actif,IF(Calculateurs!C35,Calculateurs!C33,""),"") | G26: =IF(E26<>"",E26,IF(F26="","",F26)) -> 100 | H26: % — calculé par l'onglet Calculateurs ; votre saisie prime | I26: =IF(TRUE*ISNUMBER(G26)*(N(G26)>0)*(N(G26)<1),"⚠ En % : saisir 62 pour 62 %",IF(G26<>"","✔ Renseigné",IF(OR(COUNTIFS(P_Criteres!$F$5:$F$64,B26,P_Criteres!$G$5:$G$64,"Oui")>0,COUNTIFS(P_Criteres!$F$5:$F$64,B26,P_Criteres!$K$5:$K$64,"Oui")>0,B26=P_ExtraKey),"⚠ Manquant — décisionnel","○ Non renseigné"))) -> ✔ Renseigné
A27: D2 — Qualité intrinsèque du projet | B27: regional_market_tension | C27: Tension du marché régional | D27: QUAL | E27: Marché porteur (demande soutenue) | G27: =IF(E27<>"",IF(SUMPRODUCT((P_Baremes!$A$5:$A$400="D2C9")*(P_Baremes!$F$5:$F$400=E27))>0,INDEX(P_Baremes!$C$5:$C$400,SUMPRODUCT(MAX((P_Baremes!$A$5:$A$400="D2C9")*(P_Baremes!$F$5:$F$400=E27)*(ROW(P_Baremes!$A$5:$A$400)-4)))),E27),IF(F27="","",F27)) -> porteur | H27: choisir dans la liste | I27: =IF(FALSE*ISNUMBER(G27)*(N(G27)>0)*(N(G27)<1),"⚠ En % : saisir 62 pour 62 %",IF(AND(E27<>"",COUNTIFS(P_Baremes!$A$5:$A$400,"D2C9",P_Baremes!$C$5:$C$400,G27)=0),"⚠ Valeur hors liste",IF(G27<>"","✔ Renseigné",IF(OR(COUNTIFS(P_Criteres!$F$5:$F$64,B27,P_Criteres!$G$5:$G$64,"Oui")>0,COUNTIFS(P_Criteres!$F$5:$F$64,B27,P_Criteres!$K$5:$K$64,"Oui")>0,B27=P_ExtraKey),"⚠ Manquant — décisionnel","○ Non renseigné")))) -> ✔ Renseigné
A28: D2 — Qualité intrinsèque du projet | B28: contractor_quality | C28: Entreprise de travaux et garanties de marché | D28: QUAL | E28: Entreprise qualifiée et classée, marché forfaitaire avec caution de bonne exécution et retenue de garantie | G28: =IF(E28<>"",IF(SUMPRODUCT((P_Baremes!$A$5:$A$400="D2C10")*(P_Baremes!$F$5:$F$400=E28))>0,INDEX(P_Baremes!$C$5:$C$400,SUMPRODUCT(MAX((P_Baremes!$A$5:$A$400="D2C10")*(P_Baremes!$F$5:$F$400=E28)*(ROW(P_Baremes!$A$5:$A$400)-4)))),E28),IF(F28="","",F28)) -> qualifiee_garantie | H28: choisir dans la liste | I28: =IF(FALSE*ISNUMBER(G28)*(N(G28)>0)*(N(G28)<1),"⚠ En % : saisir 62 pour 62 %",IF(AND(E28<>"",COUNTIFS(P_Baremes!$A$5:$A$400,"D2C10",P_Baremes!$C$5:$C$400,G28)=0),"⚠ Valeur hors liste",IF(G28<>"","✔ Renseigné",IF(OR(COUNTIFS(P_Criteres!$F$5:$F$64,B28,P_Criteres!$G$5:$G$64,"Oui")>0,COUNTIFS(P_Criteres!$F$5:$F$64,B28,P_Criteres!$K$5:$K$64,"Oui")>0,B28=P_ExtraKey),"⚠ Manquant — décisionnel","○ Non renseigné")))) -> ✔ Renseigné
A29: D2 — Qualité intrinsèque du projet | B29: equipment_unbudgeted_pct | C29: Équipements exigés non budgétés (% du coût) | D29: NUM | E29: 0 | F29: =IF(Calc_Actif,Calculateurs!C173,"") | G29: =IF(E29<>"",E29,IF(F29="","",F29)) -> 0 | H29: % du coût — calculé par l'onglet Calculateurs ; votre saisie prime | I29: =IF(TRUE*ISNUMBER(G29)*(N(G29)>0)*(N(G29)<1),"⚠ En % : saisir 62 pour 62 %",IF(G29<>"","✔ Renseigné",IF(OR(COUNTIFS(P_Criteres!$F$5:$F$64,B29,P_Criteres!$G$5:$G$64,"Oui")>0,COUNTIFS(P_Criteres!$F$5:$F$64,B29,P_Criteres!$K$5:$K$64,"Oui")>0,B29=P_ExtraKey),"⚠ Manquant — décisionnel","○ Non renseigné"))) -> ✔ Renseigné
A30: D2 — Qualité intrinsèque du projet | B30: tranche_dependency | C30: Autonomie du périmètre financé (tranche) | D30: QUAL | E30: Financement du programme entier | G30: =IF(E30<>"",IF(SUMPRODUCT((P_Baremes!$A$5:$A$400="D2C12")*(P_Baremes!$F$5:$F$400=E30))>0,INDEX(P_Baremes!$C$5:$C$400,SUMPRODUCT(MAX((P_Baremes!$A$5:$A$400="D2C12")*(P_Baremes!$F$5:$F$400=E30)*(ROW(P_Baremes!$A$5:$A$400)-4)))),E30),IF(F30="","",F30)) -> programme_entier | H30: choisir dans la liste | I30: =IF(FALSE*ISNUMBER(G30)*(N(G30)>0)*(N(G30)<1),"⚠ En % : saisir 62 pour 62 %",IF(AND(E30<>"",COUNTIFS(P_Baremes!$A$5:$A$400,"D2C12",P_Baremes!$C$5:$C$400,G30)=0),"⚠ Valeur hors liste",IF(G30<>"","✔ Renseigné",IF(OR(COUNTIFS(P_Criteres!$F$5:$F$64,B30,P_Criteres!$G$5:$G$64,"Oui")>0,COUNTIFS(P_Criteres!$F$5:$F$64,B30,P_Criteres!$K$5:$K$64,"Oui")>0,B30=P_ExtraKey),"⚠ Manquant — décisionnel","○ Non renseigné")))) -> ✔ Renseigné
A31: D3 — Commercial & Cash-flow | B31: pre_sale_rate | C31: Préventes sécurisées (encaissées / CA) | D31: NUM | E31: 62 | G31: =IF(E31<>"",E31,IF(F31="","",F31)) -> 62 | H31: % (ex. 62) | I31: =IF(TRUE*ISNUMBER(G31)*(N(G31)>0)*(N(G31)<1),"⚠ En % : saisir 62 pour 62 %",IF(G31<>"","✔ Renseigné",IF(OR(COUNTIFS(P_Criteres!$F$5:$F$64,B31,P_Criteres!$G$5:$G$64,"Oui")>0,COUNTIFS(P_Criteres!$F$5:$F$64,B31,P_Criteres!$K$5:$K$64,"Oui")>0,B31=P_ExtraKey),"⚠ Manquant — décisionnel","○ Non renseigné"))) -> ✔ Renseigné
A32: D3 — Commercial & Cash-flow | B32: sales_vs_plan | C32: Ventes vs planning | D32: NUM | E32: 100 | G32: =IF(E32<>"",E32,IF(F32="","",F32)) -> 100 | H32: % (ex. 100) | I32: =IF(TRUE*ISNUMBER(G32)*(N(G32)>0)*(N(G32)<1),"⚠ En % : saisir 62 pour 62 %",IF(G32<>"","✔ Renseigné",IF(OR(COUNTIFS(P_Criteres!$F$5:$F$64,B32,P_Criteres!$G$5:$G$64,"Oui")>0,COUNTIFS(P_Criteres!$F$5:$F$64,B32,P_Criteres!$K$5:$K$64,"Oui")>0,B32=P_ExtraKey),"⚠ Manquant — décisionnel","○ Non renseigné"))) -> ✔ Renseigné
A33: D3 — Commercial & Cash-flow | B33: dso_days | C33: DSO (jours) | D33: NUM | E33: 90 | G33: =IF(E33<>"",E33,IF(F33="","",F33)) -> 90 | H33: jours (ex. 90) | I33: =IF(FALSE*ISNUMBER(G33)*(N(G33)>0)*(N(G33)<1),"⚠ En % : saisir 62 pour 62 %",IF(G33<>"","✔ Renseigné",IF(OR(COUNTIFS(P_Criteres!$F$5:$F$64,B33,P_Criteres!$G$5:$G$64,"Oui")>0,COUNTIFS(P_Criteres!$F$5:$F$64,B33,P_Criteres!$K$5:$K$64,"Oui")>0,B33=P_ExtraKey),"⚠ Manquant — décisionnel","○ Non renseigné"))) -> ✔ Renseigné
A34: D3 — Commercial & Cash-flow | B34: cash_coverage | C34: Cash coverage (cash / échéances) | D34: NUM | E34: 0.99 | G34: =IF(E34<>"",E34,IF(F34="","",F34)) -> 0.99 | H34: ratio (ex. 1,2) | I34: =IF(FALSE*ISNUMBER(G34)*(N(G34)>0)*(N(G34)<1),"⚠ En % : saisir 62 pour 62 %",IF(G34<>"","✔ Renseigné",IF(OR(COUNTIFS(P_Criteres!$F$5:$F$64,B34,P_Criteres!$G$5:$G$64,"Oui")>0,COUNTIFS(P_Criteres!$F$5:$F$64,B34,P_Criteres!$K$5:$K$64,"Oui")>0,B34=P_ExtraKey),"⚠ Manquant — décisionnel","○ Non renseigné"))) -> ✔ Renseigné
A35: D3 — Commercial & Cash-flow | B35: funding_gap_pct | C35: Impasse brute | D35: NUM | E35: 0 | G35: =IF(E35<>"",E35,IF(F35="","",F35)) -> 0 | H35: % (ex. 0) | I35: =IF(TRUE*ISNUMBER(G35)*(N(G35)>0)*(N(G35)<1),"⚠ En % : saisir 62 pour 62 %",IF(G35<>"","✔ Renseigné",IF(OR(COUNTIFS(P_Criteres!$F$5:$F$64,B35,P_Criteres!$G$5:$G$64,"Oui")>0,COUNTIFS(P_Criteres!$F$5:$F$64,B35,P_Criteres!$K$5:$K$64,"Oui")>0,B35=P_ExtraKey),"⚠ Manquant — décisionnel","○ Non renseigné"))) -> ✔ Renseigné
A36: D3 — Commercial & Cash-flow | B36: stock_rotation_months | C36: Rotation stock (mois) | D36: NUM | E36: 16 | G36: =IF(E36<>"",E36,IF(F36="","",F36)) -> 16 | H36: mois (ex. 16) | I36: =IF(FALSE*ISNUMBER(G36)*(N(G36)>0)*(N(G36)<1),"⚠ En % : saisir 62 pour 62 %",IF(G36<>"","✔ Renseigné",IF(OR(COUNTIFS(P_Criteres!$F$5:$F$64,B36,P_Criteres!$G$5:$G$64,"Oui")>0,COUNTIFS(P_Criteres!$F$5:$F$64,B36,P_Criteres!$K$5:$K$64,"Oui")>0,B36=P_ExtraKey),"⚠ Manquant — décisionnel","○ Non renseigné"))) -> ✔ Renseigné
A37: D3 — Commercial & Cash-flow | B37: stressed_margin_pct | C37: Marge brute stressée (prix -10%) | D37: NUM | E37: 18 | G37: =IF(E37<>"",E37,IF(F37="","",F37)) -> 18 | H37: % (ex. 18) | I37: =IF(TRUE*ISNUMBER(G37)*(N(G37)>0)*(N(G37)<1),"⚠ En % : saisir 62 pour 62 %",IF(G37<>"","✔ Renseigné",IF(OR(COUNTIFS(P_Criteres!$F$5:$F$64,B37,P_Criteres!$G$5:$G$64,"Oui")>0,COUNTIFS(P_Criteres!$F$5:$F$64,B37,P_Criteres!$K$5:$K$64,"Oui")>0,B37=P_ExtraKey),"⚠ Manquant — décisionnel","○ Non renseigné"))) -> ✔ Renseigné
A38: D3 — Commercial & Cash-flow | B38: secured_sales_rate | C38: Ventes sécurisées (financement acquéreur) | D38: NUM | E38: 55 | F38: =IF(Calc_Actif,Calculateurs!C85,"") | G38: =IF(E38<>"",E38,IF(F38="","",F38)) -> 55 | H38: % — calculé par l'onglet Calculateurs ; votre saisie prime | I38: =IF(TRUE*ISNUMBER(G38)*(N(G38)>0)*(N(G38)<1),"⚠ En % : saisir 62 pour 62 %",IF(G38<>"","✔ Renseigné",IF(OR(COUNTIFS(P_Criteres!$F$5:$F$64,B38,P_Criteres!$G$5:$G$64,"Oui")>0,COUNTIFS(P_Criteres!$F$5:$F$64,B38,P_Criteres!$K$5:$K$64,"Oui")>0,B38=P_ExtraKey),"⚠ Manquant — décisionnel","○ Non renseigné"))) -> ✔ Renseigné
A39: D3 — Commercial & Cash-flow | B39: slow_liquidity_share_pct | C39: Part du CA en produits à écoulement lent | D39: NUM | E39: 5 | F39: =IF(Calc_Actif,Calculateurs!C181,"") | G39: =IF(E39<>"",E39,IF(F39="","",F39)) -> 5 | H39: % du CA — calculé par l'onglet Calculateurs ; votre saisie prime | I39: =IF(TRUE*ISNUMBER(G39)*(N(G39)>0)*(N(G39)<1),"⚠ En % : saisir 62 pour 62 %",IF(G39<>"","✔ Renseigné",IF(OR(COUNTIFS(P_Criteres!$F$5:$F$64,B39,P_Criteres!$G$5:$G$64,"Oui")>0,COUNTIFS(P_Criteres!$F$5:$F$64,B39,P_Criteres!$K$5:$K$64,"Oui")>0,B39=P_ExtraKey),"⚠ Manquant — décisionnel","○ Non renseigné"))) -> ✔ Renseigné
A40: D3 — Commercial & Cash-flow | B40: cancellation_rate_pct | C40: Taux de désistement des réservations | D40: NUM | E40: 3 | F40: =IF(Calc_Actif,Calculateurs!C185,"") | G40: =IF(E40<>"",E40,IF(F40="","",F40)) -> 3 | H40: % — calculé par l'onglet Calculateurs ; votre saisie prime | I40: =IF(TRUE*ISNUMBER(G40)*(N(G40)>0)*(N(G40)<1),"⚠ En % : saisir 62 pour 62 %",IF(G40<>"","✔ Renseigné",IF(OR(COUNTIFS(P_Criteres!$F$5:$F$64,B40,P_Criteres!$G$5:$G$64,"Oui")>0,COUNTIFS(P_Criteres!$F$5:$F$64,B40,P_Criteres!$K$5:$K$64,"Oui")>0,B40=P_ExtraKey),"⚠ Manquant — décisionnel","○ Non renseigné"))) -> ✔ Renseigné
A41: D4 — Structuration financière & LGD | B41: gross_margin_pct | C41: Marge brute (CA - coûts directs)/CA | D41: NUM | E41: 27 | G41: =IF(E41<>"",E41,IF(F41="","",F41)) -> 27 | H41: % (ex. 27) | I41: =IF(TRUE*ISNUMBER(G41)*(N(G41)>0)*(N(G41)<1),"⚠ En % : saisir 62 pour 62 %",IF(G41<>"","✔ Renseigné",IF(OR(COUNTIFS(P_Criteres!$F$5:$F$64,B41,P_Criteres!$G$5:$G$64,"Oui")>0,COUNTIFS(P_Criteres!$F$5:$F$64,B41,P_Criteres!$K$5:$K$64,"Oui")>0,B41=P_ExtraKey),"⚠ Manquant — décisionnel","○ Non renseigné"))) -> ✔ Renseigné
A42: D4 — Structuration financière & LGD | B42: ltc | C42: LTC (dette / coût total) | D42: NUM | E42: 61 | G42: =IF(E42<>"",E42,IF(F42="","",F42)) -> 61 | H42: % (ex. 61) | I42: =IF(TRUE*ISNUMBER(G42)*(N(G42)>0)*(N(G42)<1),"⚠ En % : saisir 62 pour 62 %",IF(G42<>"","✔ Renseigné",IF(OR(COUNTIFS(P_Criteres!$F$5:$F$64,B42,P_Criteres!$G$5:$G$64,"Oui")>0,COUNTIFS(P_Criteres!$F$5:$F$64,B42,P_Criteres!$K$5:$K$64,"Oui")>0,B42=P_ExtraKey),"⚠ Manquant — décisionnel","○ Non renseigné"))) -> ✔ Renseigné
A43: D4 — Structuration financière & LGD | B43: ltv_stressed | C43: LTV stressée (dette / valeur×0,90) | D43: NUM | E43: 65 | G43: =IF(E43<>"",E43,IF(F43="","",F43)) -> 65 | H43: % (ex. 65) | I43: =IF(TRUE*ISNUMBER(G43)*(N(G43)>0)*(N(G43)<1),"⚠ En % : saisir 62 pour 62 %",IF(G43<>"","✔ Renseigné",IF(OR(COUNTIFS(P_Criteres!$F$5:$F$64,B43,P_Criteres!$G$5:$G$64,"Oui")>0,COUNTIFS(P_Criteres!$F$5:$F$64,B43,P_Criteres!$K$5:$K$64,"Oui")>0,B43=P_ExtraKey),"⚠ Manquant — décisionnel","○ Non renseigné"))) -> ✔ Renseigné
A44: D4 — Structuration financière & LGD | B44: guarantee_coverage | C44: Couverture garanties réalisable | D44: NUM | E44: 125 | G44: =IF(E44<>"",E44,IF(F44="","",F44)) -> 125 | H44: % (ex. 125) | I44: =IF(TRUE*ISNUMBER(G44)*(N(G44)>0)*(N(G44)<1),"⚠ En % : saisir 62 pour 62 %",IF(G44<>"","✔ Renseigné",IF(OR(COUNTIFS(P_Criteres!$F$5:$F$64,B44,P_Criteres!$G$5:$G$64,"Oui")>0,COUNTIFS(P_Criteres!$F$5:$F$64,B44,P_Criteres!$K$5:$K$64,"Oui")>0,B44=P_ExtraKey),"⚠ Manquant — décisionnel","○ Non renseigné"))) -> ✔ Renseigné
A45: D4 — Structuration financière & LGD | B45: first_rank | C45: Rang bancaire 1er rang | D45: QUAL | E45: 1er rang | G45: =IF(E45<>"",IF(SUMPRODUCT((P_Baremes!$A$5:$A$400="D4C5")*(P_Baremes!$F$5:$F$400=E45))>0,INDEX(P_Baremes!$C$5:$C$400,SUMPRODUCT(MAX((P_Baremes!$A$5:$A$400="D4C5")*(P_Baremes!$F$5:$F$400=E45)*(ROW(P_Baremes!$A$5:$A$400)-4)))),E45),IF(F45="","",F45)) -> oui | H45: choisir dans la liste | I45: =IF(FALSE*ISNUMBER(G45)*(N(G45)>0)*(N(G45)<1),"⚠ En % : saisir 62 pour 62 %",IF(AND(E45<>"",COUNTIFS(P_Baremes!$A$5:$A$400,"D4C5",P_Baremes!$C$5:$C$400,G45)=0),"⚠ Valeur hors liste",IF(G45<>"","✔ Renseigné",IF(OR(COUNTIFS(P_Criteres!$F$5:$F$64,B45,P_Criteres!$G$5:$G$64,"Oui")>0,COUNTIFS(P_Criteres!$F$5:$F$64,B45,P_Criteres!$K$5:$K$64,"Oui")>0,B45=P_ExtraKey),"⚠ Manquant — décisionnel","○ Non renseigné")))) -> ✔ Renseigné
A46: D4 — Structuration financière & LGD | B46: interest_coverage | C46: Interest coverage (EBITDA / charges fin.) | D46: NUM | E46: 3.2 | G46: =IF(E46<>"",E46,IF(F46="","",F46)) -> 3.2 | H46: ratio (ex. 3,2) | I46: =IF(FALSE*ISNUMBER(G46)*(N(G46)>0)*(N(G46)<1),"⚠ En % : saisir 62 pour 62 %",IF(G46<>"","✔ Renseigné",IF(OR(COUNTIFS(P_Criteres!$F$5:$F$64,B46,P_Criteres!$G$5:$G$64,"Oui")>0,COUNTIFS(P_Criteres!$F$5:$F$64,B46,P_Criteres!$K$5:$K$64,"Oui")>0,B46=P_ExtraKey),"⚠ Manquant — décisionnel","○ Non renseigné"))) -> ✔ Renseigné
A47: D4 — Structuration financière & LGD | B47: release_quotity_gap_pts | C47: Quotité de désengagement vs équilibre | D47: NUM | E47: 5 | F47: =IF(Calc_Actif,Calculateurs!C94,"") | G47: =IF(E47<>"",E47,IF(F47="","",F47)) -> 5 | H47: points — calculé par l'onglet Calculateurs ; votre saisie prime | I47: =IF(FALSE*ISNUMBER(G47)*(N(G47)>0)*(N(G47)<1),"⚠ En % : saisir 62 pour 62 %",IF(G47<>"","✔ Renseigné",IF(OR(COUNTIFS(P_Criteres!$F$5:$F$64,B47,P_Criteres!$G$5:$G$64,"Oui")>0,COUNTIFS(P_Criteres!$F$5:$F$64,B47,P_Criteres!$K$5:$K$64,"Oui")>0,B47=P_ExtraKey),"⚠ Manquant — décisionnel","○ Non renseigné"))) -> ✔ Renseigné
A48: D4 — Structuration financière & LGD | B48: drawdown_vs_progress_pct | C48: Déblocages vs avancement certifié | D48: NUM | E48: 98 | F48: =IF(Calc_Actif,Calculateurs!C135,"") | G48: =IF(E48<>"",E48,IF(F48="","",F48)) -> 98 | H48: % — calculé par l'onglet Calculateurs ; votre saisie prime | I48: =IF(TRUE*ISNUMBER(G48)*(N(G48)>0)*(N(G48)<1),"⚠ En % : saisir 62 pour 62 %",IF(G48<>"","✔ Renseigné",IF(OR(COUNTIFS(P_Criteres!$F$5:$F$64,B48,P_Criteres!$G$5:$G$64,"Oui")>0,COUNTIFS(P_Criteres!$F$5:$F$64,B48,P_Criteres!$K$5:$K$64,"Oui")>0,B48=P_ExtraKey),"⚠ Manquant — décisionnel","○ Non renseigné"))) -> ✔ Renseigné
A49: D4 — Structuration financière & LGD | B49: cost_overrun_pct | C49: Dépassement du coût à terminaison | D49: NUM | E49: 2 | F49: =IF(Calc_Actif,Calculateurs!C189,"") | G49: =IF(E49<>"",E49,IF(F49="","",F49)) -> 2 | H49: % — calculé par l'onglet Calculateurs ; votre saisie prime | I49: =IF(TRUE*ISNUMBER(G49)*(N(G49)>0)*(N(G49)<1),"⚠ En % : saisir 62 pour 62 %",IF(G49<>"","✔ Renseigné",IF(OR(COUNTIFS(P_Criteres!$F$5:$F$64,B49,P_Criteres!$G$5:$G$64,"Oui")>0,COUNTIFS(P_Criteres!$F$5:$F$64,B49,P_Criteres!$K$5:$K$64,"Oui")>0,B49=P_ExtraKey),"⚠ Manquant — décisionnel","○ Non renseigné"))) -> ✔ Renseigné
A50: Alertes D5 | B50: dpd_days | C50: Retard de paiement (jours) | D50: NUM | E50: 0 | G50: =IF(E50<>"",E50,IF(F50="","",F50)) -> 0 | H50: jours | I50: =IF(FALSE*ISNUMBER(G50)*(N(G50)>0)*(N(G50)<1),"⚠ En % : saisir 62 pour 62 %",IF(G50<>"","✔ Renseigné",IF(OR(COUNTIFS(P_Criteres!$F$5:$F$64,B50,P_Criteres!$G$5:$G$64,"Oui")>0,COUNTIFS(P_Criteres!$F$5:$F$64,B50,P_Criteres!$K$5:$K$64,"Oui")>0,B50=P_ExtraKey),"⚠ Manquant — décisionnel","○ Non renseigné"))) -> ✔ Renseigné
A51: Alertes D5 | B51: construction_delay_months | C51: Retard chantier (mois) | D51: NUM | E51: 0 | G51: =IF(E51<>"",E51,IF(F51="","",F51)) -> 0 | H51: mois | I51: =IF(FALSE*ISNUMBER(G51)*(N(G51)>0)*(N(G51)<1),"⚠ En % : saisir 62 pour 62 %",IF(G51<>"","✔ Renseigné",IF(OR(COUNTIFS(P_Criteres!$F$5:$F$64,B51,P_Criteres!$G$5:$G$64,"Oui")>0,COUNTIFS(P_Criteres!$F$5:$F$64,B51,P_Criteres!$K$5:$K$64,"Oui")>0,B51=P_ExtraKey),"⚠ Manquant — décisionnel","○ Non renseigné"))) -> ✔ Renseigné
A52: Alertes D5 | B52: project_stopped_months | C52: Arrêt du projet (mois) | D52: NUM | E52: 0 | F52: =IF(Calc_Actif,Calculateurs!C128,"") | G52: =IF(E52<>"",E52,IF(F52="","",F52)) -> 0 | H52: mois — calculé par l'onglet Calculateurs ; votre saisie prime | I52: =IF(FALSE*ISNUMBER(G52)*(N(G52)>0)*(N(G52)<1),"⚠ En % : saisir 62 pour 62 %",IF(G52<>"","✔ Renseigné",IF(OR(COUNTIFS(P_Criteres!$F$5:$F$64,B52,P_Criteres!$G$5:$G$64,"Oui")>0,COUNTIFS(P_Criteres!$F$5:$F$64,B52,P_Criteres!$K$5:$K$64,"Oui")>0,B52=P_ExtraKey),"⚠ Manquant — décisionnel","○ Non renseigné"))) -> ✔ Renseigné
A53: Alertes D5 | B53: restructured | C53: Créance restructurée | D53: QUAL | E53: Non | G53: =IF(E53<>"",IF(SUMPRODUCT((R_ModKey="restructured")*(R_ModLab=E53))>0,INDEX(R_ModCode,SUMPRODUCT(MAX((R_ModKey="restructured")*(R_ModLab=E53)*(ROW(R_ModKey)-65)))),E53),IF(F53="","",F53)) -> no | H53: choisir dans la liste | I53: =IF(FALSE*ISNUMBER(G53)*(N(G53)>0)*(N(G53)<1),"⚠ En % : saisir 62 pour 62 %",IF(AND(E53<>"",COUNTIFS(R_ModKey,"restructured",R_ModCode,G53)=0),"⚠ Valeur hors liste",IF(G53<>"","✔ Renseigné",IF(OR(COUNTIFS(P_Criteres!$F$5:$F$64,B53,P_Criteres!$G$5:$G$64,"Oui")>0,COUNTIFS(P_Criteres!$F$5:$F$64,B53,P_Criteres!$K$5:$K$64,"Oui")>0,B53=P_ExtraKey),"⚠ Manquant — décisionnel","○ Non renseigné")))) -> ✔ Renseigné
A54: Alertes D5 | B54: legal_exposure | C54: Exposition juridique | D54: QUAL | E54: Aucun litige | G54: =IF(E54<>"",IF(SUMPRODUCT((R_ModKey="legal_exposure")*(R_ModLab=E54))>0,INDEX(R_ModCode,SUMPRODUCT(MAX((R_ModKey="legal_exposure")*(R_ModLab=E54)*(ROW(R_ModKey)-65)))),E54),IF(F54="","",F54)) -> clear | H54: choisir dans la liste | I54: =IF(FALSE*ISNUMBER(G54)*(N(G54)>0)*(N(G54)<1),"⚠ En % : saisir 62 pour 62 %",IF(AND(E54<>"",COUNTIFS(R_ModKey,"legal_exposure",R_ModCode,G54)=0),"⚠ Valeur hors liste",IF(G54<>"","✔ Renseigné",IF(OR(COUNTIFS(P_Criteres!$F$5:$F$64,B54,P_Criteres!$G$5:$G$64,"Oui")>0,COUNTIFS(P_Criteres!$F$5:$F$64,B54,P_Criteres!$K$5:$K$64,"Oui")>0,B54=P_ExtraKey),"⚠ Manquant — décisionnel","○ Non renseigné")))) -> ✔ Renseigné
A55: Alertes D5 | B55: equity_negative | C55: Fonds propres négatifs | D55: BOOL | E55: Non | G55: =IF(E55<>"",IF(E55="Oui",TRUE,IF(E55="Non",FALSE,"")),IF(F55="","",IF(F55="Oui",TRUE,IF(F55="Non",FALSE,"")))) -> FALSE | H55: Oui / Non | I55: =IF(FALSE*ISNUMBER(G55)*(N(G55)>0)*(N(G55)<1),"⚠ En % : saisir 62 pour 62 %",IF(G55<>"","✔ Renseigné",IF(OR(COUNTIFS(P_Criteres!$F$5:$F$64,B55,P_Criteres!$G$5:$G$64,"Oui")>0,COUNTIFS(P_Criteres!$F$5:$F$64,B55,P_Criteres!$K$5:$K$64,"Oui")>0,B55=P_ExtraKey),"⚠ Manquant — décisionnel","○ Non renseigné"))) -> ✔ Renseigné
A56: Alertes D5 | B56: funding_gap_persistent | C56: Impasse de trésorerie persistante | D56: BOOL | E56: Non | G56: =IF(E56<>"",IF(E56="Oui",TRUE,IF(E56="Non",FALSE,"")),IF(F56="","",IF(F56="Oui",TRUE,IF(F56="Non",FALSE,"")))) -> FALSE | H56: Oui / Non | I56: =IF(FALSE*ISNUMBER(G56)*(N(G56)>0)*(N(G56)<1),"⚠ En % : saisir 62 pour 62 %",IF(G56<>"","✔ Renseigné",IF(OR(COUNTIFS(P_Criteres!$F$5:$F$64,B56,P_Criteres!$G$5:$G$64,"Oui")>0,COUNTIFS(P_Criteres!$F$5:$F$64,B56,P_Criteres!$K$5:$K$64,"Oui")>0,B56=P_ExtraKey),"⚠ Manquant — décisionnel","○ Non renseigné"))) -> ✔ Renseigné
A57: Alertes D5 | B57: works_authorization_blocked | C57: Autorisation de travaux bloquante | D57: BOOL | E57: Non | F57: =IF(Calc_Actif,IF(Calculateurs!C35,IF(Calculateurs!C34,"Oui","Non"),""),"") | G57: =IF(E57<>"",IF(E57="Oui",TRUE,IF(E57="Non",FALSE,"")),IF(F57="","",IF(F57="Oui",TRUE,IF(F57="Non",FALSE,"")))) -> FALSE | H57: Oui / Non — calculé par l'onglet Calculateurs ; votre saisie prime | I57: =IF(FALSE*ISNUMBER(G57)*(N(G57)>0)*(N(G57)<1),"⚠ En % : saisir 62 pour 62 %",IF(G57<>"","✔ Renseigné",IF(OR(COUNTIFS(P_Criteres!$F$5:$F$64,B57,P_Criteres!$G$5:$G$64,"Oui")>0,COUNTIFS(P_Criteres!$F$5:$F$64,B57,P_Criteres!$K$5:$K$64,"Oui")>0,B57=P_ExtraKey),"⚠ Manquant — décisionnel","○ Non renseigné"))) -> ✔ Renseigné
A58: Alertes D5 | B58: buyers_financing_at_risk | C58: Financement des acquéreurs à risque | D58: BOOL | E58: Non | F58: =IF(Calc_Actif,IF(Calculateurs!C86="","",IF(Calculateurs!C86,"Oui","Non")),"") | G58: =IF(E58<>"",IF(E58="Oui",TRUE,IF(E58="Non",FALSE,"")),IF(F58="","",IF(F58="Oui",TRUE,IF(F58="Non",FALSE,"")))) -> FALSE | H58: Oui / Non — calculé par l'onglet Calculateurs ; votre saisie prime | I58: =IF(FALSE*ISNUMBER(G58)*(N(G58)>0)*(N(G58)<1),"⚠ En % : saisir 62 pour 62 %",IF(G58<>"","✔ Renseigné",IF(OR(COUNTIFS(P_Criteres!$F$5:$F$64,B58,P_Criteres!$G$5:$G$64,"Oui")>0,COUNTIFS(P_Criteres!$F$5:$F$64,B58,P_Criteres!$K$5:$K$64,"Oui")>0,B58=P_ExtraKey),"⚠ Manquant — décisionnel","○ Non renseigné"))) -> ✔ Renseigné
A59: Alertes D5 | B59: release_underpriced | C59: Mainlevée sous-tarifée | D59: BOOL | E59: Non | F59: =IF(Calc_Actif,IF(Calculateurs!C95="","",IF(Calculateurs!C95,"Oui","Non")),"") | G59: =IF(E59<>"",IF(E59="Oui",TRUE,IF(E59="Non",FALSE,"")),IF(F59="","",IF(F59="Oui",TRUE,IF(F59="Non",FALSE,"")))) -> FALSE | H59: Oui / Non — calculé par l'onglet Calculateurs ; votre saisie prime | I59: =IF(FALSE*ISNUMBER(G59)*(N(G59)>0)*(N(G59)<1),"⚠ En % : saisir 62 pour 62 %",IF(G59<>"","✔ Renseigné",IF(OR(COUNTIFS(P_Criteres!$F$5:$F$64,B59,P_Criteres!$G$5:$G$64,"Oui")>0,COUNTIFS(P_Criteres!$F$5:$F$64,B59,P_Criteres!$K$5:$K$64,"Oui")>0,B59=P_ExtraKey),"⚠ Manquant — décisionnel","○ Non renseigné"))) -> ✔ Renseigné
A60: Alertes D5 | B60: division_limit_breach | C60: Limite de division des risques dépassée | D60: BOOL | E60: Non | F60: =IF(Calc_Actif,IF(Calculateurs!C120="","",IF(Calculateurs!C120,"Oui","Non")),"") | G60: =IF(E60<>"",IF(E60="Oui",TRUE,IF(E60="Non",FALSE,"")),IF(F60="","",IF(F60="Oui",TRUE,IF(F60="Non",FALSE,"")))) -> FALSE | H60: Oui / Non — calculé par l'onglet Calculateurs ; votre saisie prime | I60: =IF(FALSE*ISNUMBER(G60)*(N(G60)>0)*(N(G60)<1),"⚠ En % : saisir 62 pour 62 %",IF(G60<>"","✔ Renseigné",IF(OR(COUNTIFS(P_Criteres!$F$5:$F$64,B60,P_Criteres!$G$5:$G$64,"Oui")>0,COUNTIFS(P_Criteres!$F$5:$F$64,B60,P_Criteres!$K$5:$K$64,"Oui")>0,B60=P_ExtraKey),"⚠ Manquant — décisionnel","○ Non renseigné"))) -> ✔ Renseigné
A61: Alertes D5 | B61: drawdown_ahead_of_works | C61: Déblocages en avance sur les travaux | D61: BOOL | E61: Non | F61: =IF(Calc_Actif,IF(Calculateurs!C136="","",IF(Calculateurs!C136,"Oui","Non")),"") | G61: =IF(E61<>"",IF(E61="Oui",TRUE,IF(E61="Non",FALSE,"")),IF(F61="","",IF(F61="Oui",TRUE,IF(F61="Non",FALSE,"")))) -> FALSE | H61: Oui / Non — calculé par l'onglet Calculateurs ; votre saisie prime | I61: =IF(FALSE*ISNUMBER(G61)*(N(G61)>0)*(N(G61)<1),"⚠ En % : saisir 62 pour 62 %",IF(G61<>"","✔ Renseigné",IF(OR(COUNTIFS(P_Criteres!$F$5:$F$64,B61,P_Criteres!$G$5:$G$64,"Oui")>0,COUNTIFS(P_Criteres!$F$5:$F$64,B61,P_Criteres!$K$5:$K$64,"Oui")>0,B61=P_ExtraKey),"⚠ Manquant — décisionnel","○ Non renseigné"))) -> ✔ Renseigné
A62: Alertes D5 | B62: drawdown_schedule_late | C62: Plan de tirage en retard | D62: BOOL | E62: Non | F62: =IF(Calc_Actif,IF(Calculateurs!C154="","",IF(Calculateurs!C154,"Oui","Non")),"") | G62: =IF(E62<>"",IF(E62="Oui",TRUE,IF(E62="Non",FALSE,"")),IF(F62="","",IF(F62="Oui",TRUE,IF(F62="Non",FALSE,"")))) -> FALSE | H62: Oui / Non — calculé par l'onglet Calculateurs ; votre saisie prime | I62: =IF(FALSE*ISNUMBER(G62)*(N(G62)>0)*(N(G62)<1),"⚠ En % : saisir 62 pour 62 %",IF(G62<>"","✔ Renseigné",IF(OR(COUNTIFS(P_Criteres!$F$5:$F$64,B62,P_Criteres!$G$5:$G$64,"Oui")>0,COUNTIFS(P_Criteres!$F$5:$F$64,B62,P_Criteres!$K$5:$K$64,"Oui")>0,B62=P_ExtraKey),"⚠ Manquant — décisionnel","○ Non renseigné"))) -> ✔ Renseigné
A63: Alertes D5 | B63: equipment_delivery_at_risk | C63: Équipement exigé en retard (réception) | D63: BOOL | E63: Non | F63: =IF(Calc_Actif,IF(Calculateurs!C174="","",IF(Calculateurs!C174,"Oui","Non")),"") | G63: =IF(E63<>"",IF(E63="Oui",TRUE,IF(E63="Non",FALSE,"")),IF(F63="","",IF(F63="Oui",TRUE,IF(F63="Non",FALSE,"")))) -> FALSE | H63: Oui / Non — calculé par l'onglet Calculateurs ; votre saisie prime | I63: =IF(FALSE*ISNUMBER(G63)*(N(G63)>0)*(N(G63)<1),"⚠ En % : saisir 62 pour 62 %",IF(G63<>"","✔ Renseigné",IF(OR(COUNTIFS(P_Criteres!$F$5:$F$64,B63,P_Criteres!$G$5:$G$64,"Oui")>0,COUNTIFS(P_Criteres!$F$5:$F$64,B63,P_Criteres!$K$5:$K$64,"Oui")>0,B63=P_ExtraKey),"⚠ Manquant — décisionnel","○ Non renseigné"))) -> ✔ Renseigné
A64: Alertes D5 | B64: component_exit_unsecured | C64: Composante commerciale / hôtelière sans preneur | D64: BOOL | E64: Non | G64: =IF(E64<>"",IF(E64="Oui",TRUE,IF(E64="Non",FALSE,"")),IF(F64="","",IF(F64="Oui",TRUE,IF(F64="Non",FALSE,"")))) -> FALSE | H64: Oui / Non | I64: =IF(FALSE*ISNUMBER(G64)*(N(G64)>0)*(N(G64)<1),"⚠ En % : saisir 62 pour 62 %",IF(G64<>"","✔ Renseigné",IF(OR(COUNTIFS(P_Criteres!$F$5:$F$64,B64,P_Criteres!$G$5:$G$64,"Oui")>0,COUNTIFS(P_Criteres!$F$5:$F$64,B64,P_Criteres!$K$5:$K$64,"Oui")>0,B64=P_ExtraKey),"⚠ Manquant — décisionnel","○ Non renseigné"))) -> ✔ Renseigné
G65: =IF(E65<>"",E65,IF(F65="","",F65))
G66: =IF(E66<>"",E66,IF(F66="","",F66))
G67: =IF(E67<>"",E67,IF(F67="","",F67))
G68: =IF(E68<>"",E68,IF(F68="","",F68))
G69: =IF(E69<>"",E69,IF(F69="","",F69))
G70: =IF(E70<>"",E70,IF(F70="","",F70))
G71: =IF(E71<>"",E71,IF(F71="","",F71))
G72: =IF(E72<>"",E72,IF(F72="","",F72))
G73: =IF(E73<>"",E73,IF(F73="","",F73))
G74: =IF(E74<>"",E74,IF(F74="","",F74))
G75: =IF(E75<>"",E75,IF(F75="","",F75))
G76: =IF(E76<>"",E76,IF(F76="","",F76))
... G92: =IF(E92<>"",E92,IF(F92="","",F92))

Sheet Fiche
A1: ="Fiche de scoring — "&IF(Saisie!C4="","(dossier sans référence)",Saisie!C4) -> Fiche de scoring — EXEMPLE
A2: =IF(Saisie!C5="","",Saisie!C5) -> Dossier d'exemple — à remplacer (ruban « Scoring PI » › Nouveau dossier)
A3: ="Modèle PI_PROMOTION "&P_Version&" · outil 5.1" -> Modèle PI_PROMOTION v5.0.0 · outil 5.1 | E3: Calculé le | F3: =TODAY() -> 46300
A5: Score final / 100 | B5: Décision | D5: Classe interne
A6: =Res_ScoreFinal -> 68.46 | B6: =IFERROR(VLOOKUP(Res_Decision,P_DecTbl,2,FALSE),Res_Decision) -> Favorable sous conditions | D6: =Res_ClasseInt -> Surveillance
A9: Principaux éléments
A10: Segment · zone | B10: =IF(Saisie!C6="","(segment non renseigné)",Saisie!C6)&" · "&IF(Saisie!C7="","(zone non renseignée)",Saisie!C7) -> Moyen-haut standing · Casablanca — centre
A11: Classe réglementaire BAM | B11: =IF(Saisie!C8="","(non renseignée — dossier incomplet)",IFERROR(VLOOKUP(Saisie!C8,P_Classes,2,FALSE),Saisie!C8)) -> Créance saine
A12: Note économique · note de sûretés | B12: =FIXED(Res_EcoScore,1)&" / 100 · sûretés : "&IF(ISNUMBER(Res_GuarScore),FIXED(Res_GuarScore,1)&" / 100","n/a") -> 92.5 / 100 · sûretés : 100.0 / 100
A13: Malus des alertes | B13: =FIXED(Res_Malus,0)&" point(s)" -> 25 point(s)
A14: PD indicative (non calibrée) | B14: =IF(ISNUMBER(Res_PD),FIXED(Res_PD*100,1)&" %","n/d (dossier incomplet)") -> 3.7 %
A15: Critères renseignés | B15: =Saisie!I7 -> 37 / 37
A16: Données décisionnelles manquantes | B16: =IF(Res_Manquantes="","Aucune",Res_Manquantes) -> Aucune
A17: Conditions à lever | B17: =IF(Res_Conditions="","Aucune",Res_Conditions) -> Aucune
A18: Alertes déclenchées | B18: =IF(Res_AlertesLib="","Aucune",Res_AlertesLib) -> Cash coverage < 1,0x
A19: Retour en comité requis | B19: =IF(Res_Comite,"Oui","Non") -> Non
A21: Scores par domaine
A22: Domaine | B22: Score / 100 | C22: Poids | D22: Contribution
A23: =IF(Resultat!$A$32="","",Resultat!$A$32&" — "&Resultat!$B$32) -> D1 — Sponsor & Gouvernance | B23: =IF(Resultat!$A$32="","",Resultat!$C$32) -> 100 | C23: =IF(Resultat!$A$32="","",Resultat!$D$32) -> 0.25 | D23: =IF(Resultat!$A$32="","",Resultat!$E$32) -> 25
A24: =IF(Resultat!$A$33="","",Resultat!$A$33&" — "&Resultat!$B$33) -> D2 — Qualité intrinsèque du projet | B24: =IF(Resultat!$A$33="","",Resultat!$C$33) -> 100 | C24: =IF(Resultat!$A$33="","",Resultat!$D$33) -> 0.2 | D24: =IF(Resultat!$A$33="","",Resultat!$E$33) -> 20
A25: =IF(Resultat!$A$34="","",Resultat!$A$34&" — "&Resultat!$B$34) -> D3 — Commercial & Cash-flow | B25: =IF(Resultat!$A$34="","",Resultat!$C$34) -> 82 | C25: =IF(Resultat!$A$34="","",Resultat!$D$34) -> 0.31 | D25: =IF(Resultat!$A$34="","",Resultat!$E$34) -> 25.42
A26: =IF(Resultat!$A$35="","",Resultat!$A$35&" — "&Resultat!$B$35) -> D4 — Structuration financière & LGD | B26: =IF(Resultat!$A$35="","",Resultat!$C$35) -> 96 | C26: =IF(Resultat!$A$35="","",Resultat!$D$35) -> 0.24 | D26: =IF(Resultat!$A$35="","",Resultat!$E$35) -> 23.04
A27: =IF(Resultat!$A$36="","",Resultat!$A$36&" — "&Resultat!$B$36) | B27: =IF(Resultat!$A$36="","",Resultat!$C$36) | C27: =IF(Resultat!$A$36="","",Resultat!$D$36) | D27: =IF(Resultat!$A$36="","",Resultat!$E$36)
A28: =IF(Resultat!$A$37="","",Resultat!$A$37&" — "&Resultat!$B$37) | B28: =IF(Resultat!$A$37="","",Resultat!$C$37) | C28: =IF(Resultat!$A$37="","",Resultat!$D$37) | D28: =IF(Resultat!$A$37="","",Resultat!$E$37)
A29: =IF(Resultat!$A$38="","",Resultat!$A$38&" — "&Resultat!$B$38) | B29: =IF(Resultat!$A$38="","",Resultat!$C$38) | C29: =IF(Resultat!$A$38="","",Resultat!$D$38) | D29: =IF(Resultat!$A$38="","",Resultat!$E$38)
A30: =IF(Resultat!$A$39="","",Resultat!$A$39&" — "&Resultat!$B$39) | B30: =IF(Resultat!$A$39="","",Resultat!$C$39) | C30: =IF(Resultat!$A$39="","",Resultat!$D$39) | D30: =IF(Resultat!$A$39="","",Resultat!$E$39)
A32: Points d'attention — les 5 notes les plus basses
A33: Critère | B33: Domaine | C33: Valeur retenue | E33: Note / 10
A34: =IF(I34="","",INDEX(Resultat!$C$44:$C$103,I34)) -> Cash coverage (cash / échéances) | B34: =IF(I34="","",IFERROR(INDEX(P_DomNoms,MATCH(INDEX(Resultat!$B$44:$B$103,I34),P_DomCodes,0)),"")) -> Commercial & Cash-flow | C34: =IF(I34="","",INDEX(Resultat!$V$44:$V$103,I34)) -> 0.99 | E34: =IF(I34="","",INDEX(Resultat!$F$44:$F$103,I34)) -> 1 | H34: =IFERROR(SMALL(Resultat!$U$44:$U$103,1),"") -> 1.000065 | I34: =IF(H34="","",MATCH(H34,Resultat!$U$44:$U$103,0)) -> 22
A35: =IF(I35="","",INDEX(Resultat!$C$44:$C$103,I35)) -> LTC (dette / coût total) | B35: =IF(I35="","",IFERROR(INDEX(P_DomNoms,MATCH(INDEX(Resultat!$B$44:$B$103,I35),P_DomCodes,0)),"")) -> Structuration financière & LGD | C35: =IF(I35="","",INDEX(Resultat!$V$44:$V$103,I35)) -> 61 | E35: =IF(I35="","",INDEX(Resultat!$F$44:$F$103,I35)) -> 6 | H35: =IFERROR(SMALL(Resultat!$U$44:$U$103,2),"") -> 6.000073 | I35: =IF(H35="","",MATCH(H35,Resultat!$U$44:$U$103,0)) -> 30
A36: =IF(I36="","",INDEX(Resultat!$C$44:$C$103,I36)) -> Projets similaires livrés (5 ans) | B36: =IF(I36="","",IFERROR(INDEX(P_DomNoms,MATCH(INDEX(Resultat!$B$44:$B$103,I36),P_DomCodes,0)),"")) -> Sponsor & Gouvernance | C36: =IF(I36="","",INDEX(Resultat!$V$44:$V$103,I36)) -> 8 | E36: =IF(I36="","",INDEX(Resultat!$F$44:$F$103,I36)) -> 10 | H36: =IFERROR(SMALL(Resultat!$U$44:$U$103,3),"") -> 10.000044 | I36: =IF(H36="","",MATCH(H36,Resultat!$U$44:$U$103,0)) -> 1
A37: =IF(I37="","",INDEX(Resultat!$C$44:$C$103,I37)) -> Gearing promoteur (dettes nettes / FP) | B37: =IF(I37="","",IFERROR(INDEX(P_DomNoms,MATCH(INDEX(Resultat!$B$44:$B$103,I37),P_DomCodes,0)),"")) -> Sponsor & Gouvernance | C37: =IF(I37="","",INDEX(Resultat!$V$44:$V$103,I37)) -> 85 | E37: =IF(I37="","",INDEX(Resultat!$F$44:$F$103,I37)) -> 10 | H37: =IFERROR(SMALL(Resultat!$U$44:$U$103,4),"") -> 10.000045 | I37: =IF(H37="","",MATCH(H37,Resultat!$U$44:$U$103,0)) -> 2
A38: =IF(I38="","",INDEX(Resultat!$C$44:$C$103,I38)) -> Gouvernance & structure juridique | B38: =IF(I38="","",IFERROR(INDEX(P_DomNoms,MATCH(INDEX(Resultat!$B$44:$B$103,I38),P_DomCodes,0)),"")) -> Sponsor & Gouvernance | C38: =IF(I38="","",INDEX(Resultat!$V$44:$V$103,I38)) -> Claire / structurée | E38: =IF(I38="","",INDEX(Resultat!$F$44:$F$103,I38)) -> 10 | H38: =IFERROR(SMALL(Resultat!$U$44:$U$103,5),"") -> 10.000046 | I38: =IF(H38="","",MATCH(H38,Resultat!$U$44:$U$103,0)) -> 3
A40: Outil indicatif. La décision officielle se prend dans l'application (circuit de validation, comité). Détail du calcul : onglet Resultat.

Sheet Calculateurs
A1: Calculateurs — alimentent automatiquement les données dérivées (Saisie, colonne « Valeur calculée »)
A2: Une valeur saisie directement dans l'onglet Saisie prime toujours sur ces calculs.
A4: A. Chaîne d'autorisations
A5: Nature du programme | B5: CONSTRUCTION
A7: Code | B7: Pièce | C7: Exigible | D7: Obtenue | E7: Bloque travaux | F7: Bloque livraison | G7: Manquante
A8: =IF(P_Referentiels!A6="","",P_Referentiels!A6) -> note_renseignement | B8: =IF(A8="","",P_Referentiels!B6) -> Note de renseignements urbanistiques | C8: =IF(A8="",FALSE,IF($B$5="LOTISSEMENT",P_Referentiels!D6,IF($B$5="CONSTRUCTION",P_Referentiels!E6,P_Referentiels!F6))="Oui") -> TRUE | E8: =IF(A8="",FALSE,P_Referentiels!G6="Oui") -> FALSE | F8: =IF(A8="",FALSE,P_Referentiels!H6="Oui") -> FALSE | G8: =AND(C8,D8<>"Oui") -> TRUE
A9: =IF(P_Referentiels!A7="","",P_Referentiels!A7) -> titre_foncier_purge | B9: =IF(A9="","",P_Referentiels!B7) -> Titre foncier purgé (sans inscription contraignante) | C9: =IF(A9="",FALSE,IF($B$5="LOTISSEMENT",P_Referentiels!D7,IF($B$5="CONSTRUCTION",P_Referentiels!E7,P_Referentiels!F7))="Oui") -> TRUE | E9: =IF(A9="",FALSE,P_Referentiels!G7="Oui") -> TRUE | F9: =IF(A9="",FALSE,P_Referentiels!H7="Oui") -> FALSE | G9: =AND(C9,D9<>"Oui") -> TRUE
A10: =IF(P_Referentiels!A8="","",P_Referentiels!A8) -> autorisation_lotir | B10: =IF(A10="","",P_Referentiels!B8) -> Autorisation de lotir | C10: =IF(A10="",FALSE,IF($B$5="LOTISSEMENT",P_Referentiels!D8,IF($B$5="CONSTRUCTION",P_Referentiels!E8,P_Referentiels!F8))="Oui") -> FALSE | E10: =IF(A10="",FALSE,P_Referentiels!G8="Oui") -> TRUE | F10: =IF(A10="",FALSE,P_Referentiels!H8="Oui") -> FALSE | G10: =AND(C10,D10<>"Oui") -> FALSE
A11: =IF(P_Referentiels!A9="","",P_Referentiels!A9) -> permis_construire | B11: =IF(A11="","",P_Referentiels!B9) -> Permis de construire | C11: =IF(A11="",FALSE,IF($B$5="LOTISSEMENT",P_Referentiels!D9,IF($B$5="CONSTRUCTION",P_Referentiels!E9,P_Referentiels!F9))="Oui") -> TRUE | E11: =IF(A11="",FALSE,P_Referentiels!G9="Oui") -> TRUE | F11: =IF(A11="",FALSE,P_Referentiels!H9="Oui") -> FALSE | G11: =AND(C11,D11<>"Oui") -> TRUE
A12: =IF(P_Referentiels!A10="","",P_Referentiels!A10) -> autorisation_morcellement | B12: =IF(A12="","",P_Referentiels!B10) -> Autorisation de morcellement / éclatement du titre | C12: =IF(A12="",FALSE,IF($B$5="LOTISSEMENT",P_Referentiels!D10,IF($B$5="CONSTRUCTION",P_Referentiels!E10,P_Referentiels!F10))="Oui") -> FALSE | E12: =IF(A12="",FALSE,P_Referentiels!G10="Oui") -> FALSE | F12: =IF(A12="",FALSE,P_Referentiels!H10="Oui") -> FALSE | G12: =AND(C12,D12<>"Oui") -> FALSE
A13: =IF(P_Referentiels!A11="","",P_Referentiels!A11) -> reception_provisoire | B13: =IF(A13="","",P_Referentiels!B11) -> Réception provisoire des travaux | C13: =IF(A13="",FALSE,IF($B$5="LOTISSEMENT",P_Referentiels!D11,IF($B$5="CONSTRUCTION",P_Referentiels!E11,P_Referentiels!F11))="Oui") -> TRUE | E13: =IF(A13="",FALSE,P_Referentiels!G11="Oui") -> FALSE | F13: =IF(A13="",FALSE,P_Referentiels!H11="Oui") -> TRUE | G13: =AND(C13,D13<>"Oui") -> TRUE
A14: =IF(P_Referentiels!A12="","",P_Referentiels!A12) -> permis_habiter | B14: =IF(A14="","",P_Referentiels!B12) -> Permis d'habiter | C14: =IF(A14="",FALSE,IF($B$5="LOTISSEMENT",P_Referentiels!D12,IF($B$5="CONSTRUCTION",P_Referentiels!E12,P_Referentiels!F12))="Oui") -> TRUE | E14: =IF(A14="",FALSE,P_Referentiels!G12="Oui") -> FALSE | F14: =IF(A14="",FALSE,P_Referentiels!H12="Oui") -> TRUE | G14: =AND(C14,D14<>"Oui") -> TRUE
A15: =IF(P_Referentiels!A13="","",P_Referentiels!A13) -> certificat_conformite | B15: =IF(A15="","",P_Referentiels!B13) -> Certificat de conformité | C15: =IF(A15="",FALSE,IF($B$5="LOTISSEMENT",P_Referentiels!D13,IF($B$5="CONSTRUCTION",P_Referentiels!E13,P_Referentiels!F13))="Oui") -> TRUE | E15: =IF(A15="",FALSE,P_Referentiels!G13="Oui") -> FALSE | F15: =IF(A15="",FALSE,P_Referentiels!H13="Oui") -> TRUE | G15: =AND(C15,D15<>"Oui") -> TRUE
A16: =IF(P_Referentiels!A14="","",P_Referentiels!A14) -> reception_definitive | B16: =IF(A16="","",P_Referentiels!B14) -> Réception définitive | C16: =IF(A16="",FALSE,IF($B$5="LOTISSEMENT",P_Referentiels!D14,IF($B$5="CONSTRUCTION",P_Referentiels!E14,P_Referentiels!F14))="Oui") -> TRUE | E16: =IF(A16="",FALSE,P_Referentiels!G14="Oui") -> FALSE | F16: =IF(A16="",FALSE,P_Referentiels!H14="Oui") -> FALSE | G16: =AND(C16,D16<>"Oui") -> TRUE
A17: =IF(P_Referentiels!A15="","",P_Referentiels!A15) | B17: =IF(A17="","",P_Referentiels!B15) | C17: =IF(A17="",FALSE,IF($B$5="LOTISSEMENT",P_Referentiels!D15,IF($B$5="CONSTRUCTION",P_Referentiels!E15,P_Referentiels!F15))="Oui") -> FALSE | E17: =IF(A17="",FALSE,P_Referentiels!G15="Oui") -> FALSE | F17: =IF(A17="",FALSE,P_Referentiels!H15="Oui") -> FALSE | G17: =AND(C17,D17<>"Oui") -> FALSE
A18: =IF(P_Referentiels!A16="","",P_Referentiels!A16) | B18: =IF(A18="","",P_Referentiels!B16) | C18: =IF(A18="",FALSE,IF($B$5="LOTISSEMENT",P_Referentiels!D16,IF($B$5="CONSTRUCTION",P_Referentiels!E16,P_Referentiels!F16))="Oui") -> FALSE | E18: =IF(A18="",FALSE,P_Referentiels!G16="Oui") -> FALSE | F18: =IF(A18="",FALSE,P_Referentiels!H16="Oui") -> FALSE | G18: =AND(C18,D18<>"Oui") -> FALSE
A19: =IF(P_Referentiels!A17="","",P_Referentiels!A17) | B19: =IF(A19="","",P_Referentiels!B17) | C19: =IF(A19="",FALSE,IF($B$5="LOTISSEMENT",P_Referentiels!D17,IF($B$5="CONSTRUCTION",P_Referentiels!E17,P_Referentiels!F17))="Oui") -> FALSE | E19: =IF(A19="",FALSE,P_Referentiels!G17="Oui") -> FALSE | F19: =IF(A19="",FALSE,P_Referentiels!H17="Oui") -> FALSE | G19: =AND(C19,D19<>"Oui") -> FALSE
... A31: =IF(P_Referentiels!A29="","",P_Referentiels!A29) | B31: =IF(A31="","",P_Referentiels!B29) | C31: =IF(A31="",FALSE,IF($B$5="LOTISSEMENT",P_Referentiels!D29,IF($B$5="CONSTRUCTION",P_Referentiels!E29,P_Referentiels!F29))="Oui") -> FALSE | E31: =IF(A31="",FALSE,P_Referentiels!G29="Oui") -> FALSE | F31: =IF(A31="",FALSE,P_Referentiels!H29="Oui") -> FALSE | G31: =AND(C31,D31<>"Oui") -> FALSE
A33: Complétude de la chaîne (%) | C33: =IF(SUMPRODUCT((C8:C31=TRUE)*1)=0,100,ROUND(SUMPRODUCT((C8:C31=TRUE)*(D8:D31="Oui"))/SUMPRODUCT((C8:C31=TRUE)*1)*100,2)) -> 0
A34: Verrou de travaux (pièce indispensable manquante) | C34: =SUMPRODUCT((G8:G31=TRUE)*(E8:E31=TRUE))>0 -> TRUE
A35: Saisie de la chaîne effectuée ? | C35: =COUNTIF(D8:D31,"Oui")+COUNTIF(D8:D31,"Non")>0 -> FALSE
A38: B. Ventes sécurisées (financement de l'acquéreur)
A39: Valeur commercialisable totale (MAD) | D39: vide = somme des prix des lots ci-dessous
A41: Lot | B41: Statut de financement acquéreur | C41: Prix (MAD) | D41: Engagé juridiquement | E41: Facteur | F41: Renseigné | G41: À risque
E42: =IF(B42="",0,IFERROR(VLOOKUP(B42,R_FinTbl,3,FALSE),0.2)) -> 0 | F42: =B42<>"" -> FALSE | G42: =AND(B42<>"",D42<>"Non",E42<=0.4) -> FALSE
E43: =IF(B43="",0,IFERROR(VLOOKUP(B43,R_FinTbl,3,FALSE),0.2)) -> 0 | F43: =B43<>"" -> FALSE | G43: =AND(B43<>"",D43<>"Non",E43<=0.4) -> FALSE
E44: =IF(B44="",0,IFERROR(VLOOKUP(B44,R_FinTbl,3,FALSE),0.2)) -> 0 | F44: =B44<>"" -> FALSE | G44: =AND(B44<>"",D44<>"Non",E44<=0.4) -> FALSE
E45: =IF(B45="",0,IFERROR(VLOOKUP(B45,R_FinTbl,3,FALSE),0.2)) -> 0 | F45: =B45<>"" -> FALSE | G45: =AND(B45<>"",D45<>"Non",E45<=0.4) -> FALSE
E46: =IF(B46="",0,IFERROR(VLOOKUP(B46,R_FinTbl,3,FALSE),0.2)) -> 0 | F46: =B46<>"" -> FALSE | G46: =AND(B46<>"",D46<>"Non",E46<=0.4) -> FALSE
E47: =IF(B47="",0,IFERROR(VLOOKUP(B47,R_FinTbl,3,FALSE),0.2)) -> 0 | F47: =B47<>"" -> FALSE | G47: =AND(B47<>"",D47<>"Non",E47<=0.4) -> FALSE
E48: =IF(B48="",0,IFERROR(VLOOKUP(B48,R_FinTbl,3,FALSE),0.2)) -> 0 | F48: =B48<>"" -> FALSE | G48: =AND(B48<>"",D48<>"Non",E48<=0.4) -> FALSE
E49: =IF(B49="",0,IFERROR(VLOOKUP(B49,R_FinTbl,3,FALSE),0.2)) -> 0 | F49: =B49<>"" -> FALSE | G49: =AND(B49<>"",D49<>"Non",E49<=0.4) -> FALSE
E50: =IF(B50="",0,IFERROR(VLOOKUP(B50,R_FinTbl,3,FALSE),0.2)) -> 0 | F50: =B50<>"" -> FALSE | G50: =AND(B50<>"",D50<>"Non",E50<=0.4) -> FALSE
E51: =IF(B51="",0,IFERROR(VLOOKUP(B51,R_FinTbl,3,FALSE),0.2)) -> 0 | F51: =B51<>"" -> FALSE | G51: =AND(B51<>"",D51<>"Non",E51<=0.4) -> FALSE
E52: =IF(B52="",0,IFERROR(VLOOKUP(B52,R_FinTbl,3,FALSE),0.2)) -> 0 | F52: =B52<>"" -> FALSE | G52: =AND(B52<>"",D52<>"Non",E52<=0.4) -> FALSE
E53: =IF(B53="",0,IFERROR(VLOOKUP(B53,R_FinTbl,3,FALSE),0.2)) -> 0 | F53: =B53<>"" -> FALSE | G53: =AND(B53<>"",D53<>"Non",E53<=0.4) -> FALSE
... E81: =IF(B81="",0,IFERROR(VLOOKUP(B81,R_FinTbl,3,FALSE),0.2)) -> 0 | F81: =B81<>"" -> FALSE | G81: =AND(B81<>"",D81<>"Non",E81<=0.4) -> FALSE
A83: Chiffre d'affaires engagé (MAD) | C83: =SUMPRODUCT((F42:F81=TRUE)*(D42:D81<>"Non")*C42:C81) -> 0
A84: Chiffre d'affaires sécurisé (MAD) | C84: =SUMPRODUCT((F42:F81=TRUE)*(D42:D81<>"Non")*C42:C81*E42:E81) -> 0
A85: Taux de ventes sécurisées (%) | C85: =IF(SUMPRODUCT((F42:F81=TRUE)*1)=0,"",IF(IF(C39="",SUM(C42:C81),C39)>0,ROUND(C84/IF(C39="",SUM(C42:C81),C39)*100,2),""))
A86: Financement acquéreurs à risque (≥ 40 % des lots renseignés) | C86: =IF(SUMPRODUCT((F42:F81=TRUE)*1)=0,"",AND(C83>0,SUMPRODUCT((G42:G81=TRUE)*1)/SUMPRODUCT((F42:F81=TRUE)*1)>=0.4))
A89: C. Mainlevée partielle et prix de désengagement
A90: Quotité de désengagement convenue (%)
A91: Encours de crédit adossé au programme (MAD)
A92: Valeur commercialisable totale (MAD)
A93: Quotité d'équilibre (%) = encours / valeur | C93: =IF(AND(ISNUMBER(C91),ISNUMBER(C92)),IF(C92>0,ROUND(C91/C92*100,2),""),"")
A94: Écart quotité appliquée − équilibre (points) | C94: =IF(AND(ISNUMBER(C90),ISNUMBER(C91),ISNUMBER(C92)),IF(AND(C91>0,C92>0),ROUND(C90-C91/C92*100,2),""),"")
A95: Quotité sous-tarifée ? | C95: =IF(C94="","",C94<0)
A96: Quotité recommandée (équilibre + 10 %) | C96: =IF(C93="","",ROUND(MIN(100,C93*1.1),2))
A99: D. Division des risques
A100: Fonds propres prudentiels de l'établissement (MAD)
A101: Limite par contrepartie / groupe (% des fonds propres) | C101: 20
A102: Seuil « grand risque » (% des fonds propres) | C102: 5
A104: Concours | C104: Encours tiré (MAD) | D104: Non tiré (MAD) | E104: CCF (0–1) | F104: Exposition
F105: =MAX(0,N(C105))+MAX(0,N(D105))*IF(E105="",1,MIN(1,MAX(0,E105))) -> 0
F106: =MAX(0,N(C106))+MAX(0,N(D106))*IF(E106="",1,MIN(1,MAX(0,E106))) -> 0
F107: =MAX(0,N(C107))+MAX(0,N(D107))*IF(E107="",1,MIN(1,MAX(0,E107))) -> 0
F108: =MAX(0,N(C108))+MAX(0,N(D108))*IF(E108="",1,MIN(1,MAX(0,E108))) -> 0
F109: =MAX(0,N(C109))+MAX(0,N(D109))*IF(E109="",1,MIN(1,MAX(0,E109))) -> 0
F110: =MAX(0,N(C110))+MAX(0,N(D110))*IF(E110="",1,MIN(1,MAX(0,E110))) -> 0
F111: =MAX(0,N(C111))+MAX(0,N(D111))*IF(E111="",1,MIN(1,MAX(0,E111))) -> 0
F112: =MAX(0,N(C112))+MAX(0,N(D112))*IF(E112="",1,MIN(1,MAX(0,E112))) -> 0
F113: =MAX(0,N(C113))+MAX(0,N(D113))*IF(E113="",1,MIN(1,MAX(0,E113))) -> 0
F114: =MAX(0,N(C114))+MAX(0,N(D114))*IF(E114="",1,MIN(1,MAX(0,E114))) -> 0
A116: Exposition agrégée (MAD) | C116: =SUM(F105:F114) -> 0
A117: Limite (MAD) | C117: =IF(ISNUMBER(C100),ROUND(C100*C101/100,2),"")
A118: Ratio exposition / fonds propres (%) | C118: =IF(AND(ISNUMBER(C100),N(C100)>0),ROUND(C116/C100*100,2),"")
A119: Marge disponible avant limite (MAD) | C119: =IF(C117="","",MAX(0,C117-C116))
A120: Limite dépassée ? | C120: =IF(AND(ISNUMBER(C100),N(C100)>0),C116>C117,"")
A121: Grand risque ? | C121: =IF(AND(ISNUMBER(C100),N(C100)>0),C116>=C100*C102/100,"")
A124: E. Arrêt de chantier
A125: Date de début de l'arrêt en cours
A126: Date de reprise effective (vide si toujours à l'arrêt)
A127: Date d'évaluation (vide = aujourd'hui)
A128: Durée de l'arrêt en cours (mois) | C128: =IF(OR(NOT(ISNUMBER(C125)),ISNUMBER(C126)),"",MAX(0,INT((IF(ISNUMBER(C127),C127,TODAY())-C125)/30.4375))) | D128: ≥ 12 mois : alerte bloquante « projet à l'arrêt » (souffrance automatique). Un arrêt terminé n'alimente plus la donnée.
A131: F. Déblocages selon l'avancement et le calendrier (v5)
A132: Montant autorisé des crédits de travaux (MAD)
A133: Cumul débloqué sur ces crédits (MAD)
A134: Avancement certifié (%) — situation visée, sinon tranches, sinon visite
A135: Déblocages vs avancement certifié (%) | C135: =IF(AND(ISNUMBER(C132),ISNUMBER(C133),ISNUMBER(C134)),IF(N(C132)<=0,"",IF(C133<=0,0,IF(C132*C134/100<=0,999,MIN(999,ROUND(C133/(C132*C134/100)*100,2))))),"")
A136: Tirages en avance sur les travaux ? (≥ 115 %) | C136: =IF(C135="","",C135>=115)
A138: Date d'évaluation du plan de tirage (vide = aujourd'hui)
A139: Jalon du plan de tirage | B139: Date prévue | C139: Montant prévu (MAD) | D139: Débloqué (MAD) | E139: Prévu échu | F139: Débloqué retenu
E140: =IF(AND(ISNUMBER(B140),B140<=IF(ISNUMBER($C$138),$C$138,TODAY())),N(C140),0) -> 0 | F140: =IF(AND(ISNUMBER(B140),B140<=IF(ISNUMBER($C$138),$C$138,TODAY())),MIN(N(D140),N(C140)),0) -> 0
E141: =IF(AND(ISNUMBER(B141),B141<=IF(ISNUMBER($C$138),$C$138,TODAY())),N(C141),0) -> 0 | F141: =IF(AND(ISNUMBER(B141),B141<=IF(ISNUMBER($C$138),$C$138,TODAY())),MIN(N(D141),N(C141)),0) -> 0
E142: =IF(AND(ISNUMBER(B142),B142<=IF(ISNUMBER($C$138),$C$138,TODAY())),N(C142),0) -> 0 | F142: =IF(AND(ISNUMBER(B142),B142<=IF(ISNUMBER($C$138),$C$138,TODAY())),MIN(N(D142),N(C142)),0) -> 0
E143: =IF(AND(ISNUMBER(B143),B143<=IF(ISNUMBER($C$138),$C$138,TODAY())),N(C143),0) -> 0 | F143: =IF(AND(ISNUMBER(B143),B143<=IF(ISNUMBER($C$138),$C$138,TODAY())),MIN(N(D143),N(C143)),0) -> 0
E144: =IF(AND(ISNUMBER(B144),B144<=IF(ISNUMBER($C$138),$C$138,TODAY())),N(C144),0) -> 0 | F144: =IF(AND(ISNUMBER(B144),B144<=IF(ISNUMBER($C$138),$C$138,TODAY())),MIN(N(D144),N(C144)),0) -> 0
E145: =IF(AND(ISNUMBER(B145),B145<=IF(ISNUMBER($C$138),$C$138,TODAY())),N(C145),0) -> 0 | F145: =IF(AND(ISNUMBER(B145),B145<=IF(ISNUMBER($C$138),$C$138,TODAY())),MIN(N(D145),N(C145)),0) -> 0
E146: =IF(AND(ISNUMBER(B146),B146<=IF(ISNUMBER($C$138),$C$138,TODAY())),N(C146),0) -> 0 | F146: =IF(AND(ISNUMBER(B146),B146<=IF(ISNUMBER($C$138),$C$138,TODAY())),MIN(N(D146),N(C146)),0) -> 0
E147: =IF(AND(ISNUMBER(B147),B147<=IF(ISNUMBER($C$138),$C$138,TODAY())),N(C147),0) -> 0 | F147: =IF(AND(ISNUMBER(B147),B147<=IF(ISNUMBER($C$138),$C$138,TODAY())),MIN(N(D147),N(C147)),0) -> 0
E148: =IF(AND(ISNUMBER(B148),B148<=IF(ISNUMBER($C$138),$C$138,TODAY())),N(C148),0) -> 0 | F148: =IF(AND(ISNUMBER(B148),B148<=IF(ISNUMBER($C$138),$C$138,TODAY())),MIN(N(D148),N(C148)),0) -> 0
E149: =IF(AND(ISNUMBER(B149),B149<=IF(ISNUMBER($C$138),$C$138,TODAY())),N(C149),0) -> 0 | F149: =IF(AND(ISNUMBER(B149),B149<=IF(ISNUMBER($C$138),$C$138,TODAY())),MIN(N(D149),N(C149)),0) -> 0
E150: =IF(AND(ISNUMBER(B150),B150<=IF(ISNUMBER($C$138),$C$138,TODAY())),N(C150),0) -> 0 | F150: =IF(AND(ISNUMBER(B150),B150<=IF(ISNUMBER($C$138),$C$138,TODAY())),MIN(N(D150),N(C150)),0) -> 0
E151: =IF(AND(ISNUMBER(B151),B151<=IF(ISNUMBER($C$138),$C$138,TODAY())),N(C151),0) -> 0 | F151: =IF(AND(ISNUMBER(B151),B151<=IF(ISNUMBER($C$138),$C$138,TODAY())),MIN(N(D151),N(C151)),0) -> 0
A153: Montant prévu non débloqué à date (%) | C153: =IF(SUM(E140:E151)<=0,"",ROUND((SUM(E140:E151)-SUM(F140:F151))/SUM(E140:E151)*100,2))
A154: Plan de tirage en retard ? (≥ 25 %) | C154: =IF(C153="","",C153>=25)
A157: G. Équipements exigés (mosquée, école, voirie…) (v5)
A158: Obligations déclarées | D158: vide = non déclarées : donnée absente (note plancher)
A159: Coût total du programme (MAD)
...

Sheet Portefeuille
A1: Scoring de portefeuille
A2: Une ligne par dossier (ruban › Enregistrer le dossier ajoute ou met à jour la ligne du dossier en cours ; Ouvrir un dossier le recharge). Ruban › Scorer le portefeuille remplit les colonnes de résultat à droite. Booléens : Oui / Non.
A3: Identité | F3: Données d'entrée (mêmes clés que l'onglet Saisie)
A4: Référence | B4: Nom du projet | C4: Segment | D4: Zone | E4: Classe BAM | F4: promoter_completed_projects | G4: promoter_gearing | H4: governance_quality | I4: mono_project_concentration | J4: promoter_type | K4: equity_injected_ratio | L4: land_permits_status | M4: market_positioning | N4: technical_complexity | O4: progress_vs_plan | P4: sav_litigation | Q4: macro_sensitivity | R4: land_cost_ratio | S4: authorization_completeness_pct | T4: regional_market_tension | U4: contractor_quality | V4: equipment_unbudgeted_pct | W4: tranche_dependency | X4: pre_sale_rate | Y4: sales_vs_plan | Z4: dso_days | AA4: cash_coverage | AB4: funding_gap_pct | AC4: stock_rotation_months | AD4: stressed_margin_pct | AE4: secured_sales_rate | AF4: slow_liquidity_share_pct | AG4: cancellation_rate_pct | AH4: gross_margin_pct | AI4: ltc | AJ4: ltv_stressed | AK4: guarantee_coverage | AL4: first_rank | AM4: interest_coverage | AN4: release_quotity_gap_pts | AO4: drawdown_vs_progress_pct | AP4: cost_overrun_pct | AQ4: dpd_days | AR4: construction_delay_months | AS4: project_stopped_months | AT4: restructured | AU4: legal_exposure | AV4: equity_negative | AW4: funding_gap_persistent | AX4: works_authorization_blocked | AY4: buyers_financing_at_risk | AZ4: release_underpriced | BA4: division_limit_breach | BB4: drawdown_ahead_of_works | BC4: drawdown_schedule_late | BD4: equipment_delivery_at_risk | BE4: component_exit_unsecured | BF4: Score final | BG4: Décision | BH4: Classe interne | BI4: Malus D5 | BJ4: Dossier complet | BK4: D1 | BL4: D2 | BM4: D3 | BN4: D4 | BO4: Score éco. | BP4: Note sûretés | BQ4: PD indicative | BR4: Alertes | BS4: Données manquantes | BT4: Conditions
A5: EXEMPLE-1 | B5: Dossier solide, classe saine | E5: SAIN | F5: 8 | G5: 85 | H5: claire | I5: 35 | J5: structure | K5: 100 | L5: definitives | M5: aligne | N5: standard | O5: 100 | P5: faible | Q5: faible | R5: 22 | S5: 100 | T5: porteur | U5: qualifiee_garantie | V5: 0 | W5: programme_entier | X5: 62 | Y5: 100 | Z5: 90 | AA5: 1.35 | AB5: 0 | AC5: 16 | AD5: 18 | AE5: 55 | AF5: 5 | AG5: 3 | AH5: 27 | AI5: 61 | AJ5: 65 | AK5: 125 | AL5: oui | AM5: 3.2 | AN5: 5 | AO5: 98 | AP5: 2 | AQ5: 0 | AR5: 0 | AS5: 0 | AT5: no | AU5: clear | AV5: Non | AW5: Non | AX5: Non | AY5: Non | AZ5: Non | BA5: Non | BB5: Non | BC5: Non | BD5: Non | BE5: Non
A6: EXEMPLE-2 | B6: Dossier intermédiaire (score moyen) | C6: intermediaire | D6: casa_peripherie | E6: SAIN | F6: 2 | G6: 120 | H6: partielle | I6: 50 | J6: regional | K6: 90 | L6: partielles | M6: moyen | N6: moyenne | O6: 90 | P6: moyen | Q6: moyenne | R6: 30 | S6: 70 | T6: equilibre | U6: qualifiee | V6: 1.5 | W6: dependante_financee | X6: 35 | Y6: 90 | Z6: 180 | AA6: 1.1 | AB6: 5 | AC6: 24 | AD6: 12 | AE6: 30 | AF6: 25 | AG6: 12 | AH6: 20 | AI6: 70 | AJ6: 78 | AK6: 100 | AL6: oui | AM6: 2 | AN6: -5 | AO6: 108 | AP6: 7 | AQ6: 0 | AR6: 0 | AS6: 0 | AT6: no | AU6: clear | AV6: Non | AW6: Non | AX6: Non | AY6: Non | AZ6: Non | BA6: Non | BB6: Non | BC6: Non | BD6: Non | BE6: Non
A7: EXEMPLE-3 | B7: Non 1er rang + restructuration : malus cumulés | E7: SAIN | F7: 8 | G7: 85 | H7: claire | I7: 35 | J7: structure | K7: 100 | L7: definitives | M7: aligne | N7: standard | O7: 100 | P7: faible | Q7: faible | R7: 22 | S7: 100 | T7: porteur | U7: qualifiee_garantie | V7: 0 | W7: programme_entier | X7: 62 | Y7: 100 | Z7: 90 | AA7: 1.35 | AB7: 0 | AC7: 16 | AD7: 18 | AE7: 55 | AF7: 5 | AG7: 3 | AH7: 27 | AI7: 61 | AJ7: 65 | AK7: 125 | AL7: non | AM7: 3.2 | AN7: 5 | AO7: 98 | AP7: 2 | AQ7: 0 | AR7: 0 | AS7: 0 | AT7: yes | AU7: clear | AV7: Non | AW7: Non | AX7: Non | AY7: Non | AZ7: Non | BA7: Non | BB7: Non | BC7: Non | BD7: Non | BE7: Non

Sheet Stress
A1: Stress test sur le dossier courant (onglet Saisie)
A2: Chocs appliqués aux données primitives par identités comptables (marge, LTV, LTC) — mêmes règles que l'application. Macro : LancerStress.
A3: Score de base | D3: Décision de base
A4: Scénario | B4: Libellé | C4: Prix −% | D4: Coût +% | E4: Retard (mois) | F4: Ventes −% | G4: Taux +bps | H4: Préventes −pts | I4: Retard paiement +j | J4: Score final | K4: Décision | L4: Δ vs base
A5: price10 | B5: Prix −10 % | C5: 10 | D5: 0 | E5: 0 | F5: 0 | G5: 0 | H5: 0 | I5: 0
A6: price15 | B6: Prix −15 % | C6: 15 | D6: 0 | E6: 0 | F6: 0 | G6: 0 | H6: 0 | I6: 0
A7: cost10 | B7: Coût +10 % | C7: 0 | D7: 10 | E7: 0 | F7: 0 | G7: 0 | H7: 0 | I7: 0
A8: delay6 | B8: Retard +6 mois | C8: 0 | D8: 0 | E8: 6 | F8: 0 | G8: 0 | H8: 0 | I8: 0
A9: sales20 | B9: Ventes −20 % | C9: 0 | D9: 0 | E9: 0 | F9: 20 | G9: 0 | H9: 0 | I9: 0
A10: rate200 | B10: Taux +200 bps | C10: 0 | D10: 0 | E10: 0 | F10: 0 | G10: 200 | H10: 0 | I10: 0
A11: severe | B11: Sévère combiné | C11: 15 | D11: 10 | E11: 6 | F11: 20 | G11: 200 | H11: 0 | I11: 0

Sheet Resultat
A1: Résultat du scoring
A2: ="Modèle "&P_Version&" — "&Saisie!C4&" "&Saisie!C5 -> Modèle v5.0.0 — EXEMPLE Dossier d'exemple — à remplacer (ruban « Scoring PI » › Nouveau dossier)
A3: Calcul pas à pas (lecture seule). La synthèse lisible est dans l'onglet Fiche.
E5: (interne) | F5: Challengers (indicatifs — score officiel inchangé)
A6: Score final (0–100) | C6: =IF(E28,0,ROUND(MIN(100,MAX(0,C13*C14)),2)) -> 68.46 | F6: Phase du projet | H6: =IF(Saisie!C9="","(non renseignée)",Saisie!C9) -> CONSTRUCTION
A7: Décision | C7: =IF(E28,"NO_GO",IF(E21,"NO_GO",IF(E22,"NO_GO",IF(E23,"DOSSIER_INCOMPLET",IF(E20,"NO_GO",IF(C6>=P_GO,"GO",IF(C6>=P_GWC,"GO_WITH_CONDITIONS",IF(C6>=P_WATCH,"WATCH_LIST","NO_GO")))))))) -> GO_WITH_CONDITIONS | F7: Score éco. avec pondération de phase | H7: =IF(Saisie!C9="","",IF(SUM(F32:F39)=0,"",ROUND(SUM(G32:G39)/SUM(F32:F39),2))) -> 94.3
A8: Classe interne | C8: =IF(E28,"Souffrance",IF(E21,"Souffrance",IF(E22,"Défaut avéré",IF(E23,"Dossier incomplet",IF(C6>=P_GO,"Sain",IF(C6>=P_GWC,"Surveillance",IF(C6>=P_WATCH,"Sensible probable","Sensible"))))))) -> Surveillance | F8: Écart vs score éco. officiel | H8: =IF(H7="","",ROUND(H7-C10,2)) -> 0.84
A9: PD proxy (indicative, non calibrée) | C9: =IF(E23,"n/d",ROUND(1/(1+EXP(-(P_PDa-P_PDb*C6))),4)) -> 0.0367 | F9: Score ajusté sans coefficients territoriaux | H9: =ROUND(MIN(100,MAX(0,C10)),2) -> 93.46
A10: Score économique S_éco (avant ajustement) | C10: =IF(SUM(D32:D39)=0,0,ROUND(SUM(E32:E39)/SUM(D32:D39),2)) -> 93.46 | F10: Effet des coefficients segment / zone | H10: =ROUND(C11-H9,2) -> 0
A11: Score ajusté S_adj = S_éco×(1+α+β) | C11: =ROUND(MIN(100,MAX(0,C10*(1+C17+C18))),2) -> 93.46
A12: Malus cumulés D5 (points) | C12: =SUM(J108:J137) -> 25
A13: Score après pénalités | C13: =ROUND(MIN(100,MAX(0,C11-C12)),2) -> 68.46
A14: Coefficient réglementaire BAM | C14: =IF(Saisie!C8="",1,IFERROR(VLOOKUP(Saisie!C8,P_Classes,5,FALSE),1)) -> 1
A15: Note économique (capacité de remboursement) | C15: =IFERROR(ROUND(SUMPRODUCT($Q$44:$Q$103*($N$44:$N$103<>"GUARANTEE")*$F$44:$F$103)/SUMPRODUCT($Q$44:$Q$103*($N$44:$N$103<>"GUARANTEE"))/P_Scale*100,2),C10) -> 92.47
A16: Note de sûretés (perte en cas de défaut) | C16: =IFERROR(ROUND(SUMPRODUCT($Q$44:$Q$103*($N$44:$N$103="GUARANTEE")*$F$44:$F$103)/SUMPRODUCT($Q$44:$Q$103*($N$44:$N$103="GUARANTEE"))/P_Scale*100,2),"n/a") -> 100
A17: α segment | C17: =IF(Saisie!$D$6="",0,IFERROR(VLOOKUP(Saisie!$D$6,P_SegTbl,3,FALSE),0)) -> 0
A18: β zone | C18: =IF(Saisie!$D$7="",0,IFERROR(VLOOKUP(Saisie!$D$7,P_ZoneTbl,3,FALSE),0)) -> 0
A19: Segment / zone hors référentiel | C19: =IF(E19,"Oui — à signaler","Non") -> Non | E19: =OR(AND(Saisie!$D$6<>"",ISNA(MATCH(Saisie!$D$6,P_SegCodes,0))),AND(Saisie!$D$7<>"",ISNA(MATCH(Saisie!$D$7,P_ZoneCodes,0)))) -> FALSE
A20: Critère éliminatoire (gate) franchi | C20: =IF(E20,"Oui","Non") -> Non | E20: =OR(I44:I103) -> FALSE
A21: Alerte bloquante (souffrance automatique) | C21: =IF(E21,"Oui","Non") -> Non | E21: =SUMPRODUCT((C108:C137="BLOCKING")*(H108:H137=TRUE))>0 -> FALSE
A22: Défaut avéré (classe réglementaire) | C22: =IF(E22,"Oui","Non") -> Non | E22: =OR(IFERROR(VLOOKUP(Saisie!C8,P_Classes,3,FALSE)="Oui",FALSE),Saisie!C8="CTX") -> FALSE
A23: Dossier incomplet (donnée décisionnelle absente) | C23: =IF(E23,"Oui","Non") -> Non | E23: =OR(Saisie!C8="",J43,SUMPRODUCT((J44:J103=TRUE)*1)>0,SUMPRODUCT((L108:L137=TRUE)*1)>0) -> FALSE
A24: Données décisionnelles manquantes | C24: =IF(C6=C6,O137,"")
A25: Conditions (critères éliminatoires franchis) | C25: =S103
A26: Alertes déclenchées / non exclues | C26: =N137 -> RF_CASH_LT_ECH
A27: Retour en comité requis | C27: =IF(E27,"Oui","Non") -> Non | E27: =OR(K108:K137) -> FALSE
A28: Classe bloquante (contentieux) | C28: =IF(E28,"Oui","Non") -> Non | E28: =OR(IFERROR(VLOOKUP(Saisie!C8,P_Classes,4,FALSE)="Oui",FALSE),Saisie!C8="CTX") -> FALSE
A30: Scores par domaine
A31: Code | B31: Domaine | C31: Score /100 | D31: Poids | E31: Contribution | F31: Poids phase | G31: Contribution phase
A32: =IF(P_General!A16="","",P_General!A16) -> D1 | B32: =IF($A32="","",P_General!B16) -> Sponsor & Gouvernance | C32: =IF($A32="",0,IF(SUMIF($B$44:$B$103,$A32,$G$44:$G$103)>0,ROUND(SUMIF($B$44:$B$103,$A32,$H$44:$H$103)/SUMIF($B$44:$B$103,$A32,$G$44:$G$103)/P_Scale*100,2),0)) -> 100 | D32: =IF($A32="",0,P_General!C16) -> 0.25 | E32: =IF($A32="",0,ROUND(C32*D32,2)) -> 25 | F32: =IF($A32="",0,IFERROR(INDEX(P_PhaseTbl,MATCH(Saisie!$C$9,P_PhaseCodes,0),MATCH($A32,P_PhaseHdr,0)+1),0)) -> 0.2 | G32: =ROUND(C32*F32,2) -> 20
A33: =IF(P_General!A17="","",P_General!A17) -> D2 | B33: =IF($A33="","",P_General!B17) -> Qualité intrinsèque du projet | C33: =IF($A33="",0,IF(SUMIF($B$44:$B$103,$A33,$G$44:$G$103)>0,ROUND(SUMIF($B$44:$B$103,$A33,$H$44:$H$103)/SUMIF($B$44:$B$103,$A33,$G$44:$G$103)/P_Scale*100,2),0)) -> 100 | D33: =IF($A33="",0,P_General!C17) -> 0.2 | E33: =IF($A33="",0,ROUND(C33*D33,2)) -> 20 | F33: =IF($A33="",0,IFERROR(INDEX(P_PhaseTbl,MATCH(Saisie!$C$9,P_PhaseCodes,0),MATCH($A33,P_PhaseHdr,0)+1),0)) -> 0.25 | G33: =ROUND(C33*F33,2) -> 25
A34: =IF(P_General!A18="","",P_General!A18) -> D3 | B34: =IF($A34="","",P_General!B18) -> Commercial & Cash-flow | C34: =IF($A34="",0,IF(SUMIF($B$44:$B$103,$A34,$G$44:$G$103)>0,ROUND(SUMIF($B$44:$B$103,$A34,$H$44:$H$103)/SUMIF($B$44:$B$103,$A34,$G$44:$G$103)/P_Scale*100,2),0)) -> 82 | D34: =IF($A34="",0,P_General!C18) -> 0.31 | E34: =IF($A34="",0,ROUND(C34*D34,2)) -> 25.42 | F34: =IF($A34="",0,IFERROR(INDEX(P_PhaseTbl,MATCH(Saisie!$C$9,P_PhaseCodes,0),MATCH($A34,P_PhaseHdr,0)+1),0)) -> 0.25 | G34: =ROUND(C34*F34,2) -> 20.5
A35: =IF(P_General!A19="","",P_General!A19) -> D4 | B35: =IF($A35="","",P_General!B19) -> Structuration financière & LGD | C35: =IF($A35="",0,IF(SUMIF($B$44:$B$103,$A35,$G$44:$G$103)>0,ROUND(SUMIF($B$44:$B$103,$A35,$H$44:$H$103)/SUMIF($B$44:$B$103,$A35,$G$44:$G$103)/P_Scale*100,2),0)) -> 96 | D35: =IF($A35="",0,P_General!C19) -> 0.24 | E35: =IF($A35="",0,ROUND(C35*D35,2)) -> 23.04 | F35: =IF($A35="",0,IFERROR(INDEX(P_PhaseTbl,MATCH(Saisie!$C$9,P_PhaseCodes,0),MATCH($A35,P_PhaseHdr,0)+1),0)) -> 0.3 | G35: =ROUND(C35*F35,2) -> 28.8
A36: =IF(P_General!A20="","",P_General!A20) | B36: =IF($A36="","",P_General!B20) | C36: =IF($A36="",0,IF(SUMIF($B$44:$B$103,$A36,$G$44:$G$103)>0,ROUND(SUMIF($B$44:$B$103,$A36,$H$44:$H$103)/SUMIF($B$44:$B$103,$A36,$G$44:$G$103)/P_Scale*100,2),0)) -> 0 | D36: =IF($A36="",0,P_General!C20) -> 0 | E36: =IF($A36="",0,ROUND(C36*D36,2)) -> 0 | F36: =IF($A36="",0,IFERROR(INDEX(P_PhaseTbl,MATCH(Saisie!$C$9,P_PhaseCodes,0),MATCH($A36,P_PhaseHdr,0)+1),0)) -> 0 | G36: =ROUND(C36*F36,2) -> 0
A37: =IF(P_General!A21="","",P_General!A21) | B37: =IF($A37="","",P_General!B21) | C37: =IF($A37="",0,IF(SUMIF($B$44:$B$103,$A37,$G$44:$G$103)>0,ROUND(SUMIF($B$44:$B$103,$A37,$H$44:$H$103)/SUMIF($B$44:$B$103,$A37,$G$44:$G$103)/P_Scale*100,2),0)) -> 0 | D37: =IF($A37="",0,P_General!C21) -> 0 | E37: =IF($A37="",0,ROUND(C37*D37,2)) -> 0 | F37: =IF($A37="",0,IFERROR(INDEX(P_PhaseTbl,MATCH(Saisie!$C$9,P_PhaseCodes,0),MATCH($A37,P_PhaseHdr,0)+1),0)) -> 0 | G37: =ROUND(C37*F37,2) -> 0
A38: =IF(P_General!A22="","",P_General!A22) | B38: =IF($A38="","",P_General!B22) | C38: =IF($A38="",0,IF(SUMIF($B$44:$B$103,$A38,$G$44:$G$103)>0,ROUND(SUMIF($B$44:$B$103,$A38,$H$44:$H$103)/SUMIF($B$44:$B$103,$A38,$G$44:$G$103)/P_Scale*100,2),0)) -> 0 | D38: =IF($A38="",0,P_General!C22) -> 0 | E38: =IF($A38="",0,ROUND(C38*D38,2)) -> 0 | F38: =IF($A38="",0,IFERROR(INDEX(P_PhaseTbl,MATCH(Saisie!$C$9,P_PhaseCodes,0),MATCH($A38,P_PhaseHdr,0)+1),0)) -> 0 | G38: =ROUND(C38*F38,2) -> 0
A39: =IF(P_General!A23="","",P_General!A23) | B39: =IF($A39="","",P_General!B23) | C39: =IF($A39="",0,IF(SUMIF($B$44:$B$103,$A39,$G$44:$G$103)>0,ROUND(SUMIF($B$44:$B$103,$A39,$H$44:$H$103)/SUMIF($B$44:$B$103,$A39,$G$44:$G$103)/P_Scale*100,2),0)) -> 0 | D39: =IF($A39="",0,P_General!C23) -> 0 | E39: =IF($A39="",0,ROUND(C39*D39,2)) -> 0 | F39: =IF($A39="",0,IFERROR(INDEX(P_PhaseTbl,MATCH(Saisie!$C$9,P_PhaseCodes,0),MATCH($A39,P_PhaseHdr,0)+1),0)) -> 0 | G39: =ROUND(C39*F39,2) -> 0
A41: Détail par critère (explicabilité)
A42: Code | B42: Domaine | C42: Critère | D42: Clé | E42: Valeur | F42: Note /10 | G42: Poids | H42: Pondéré | I42: Gate franchi | J42: Donnée critique manquante | K42: Note plancher | L42: Nb correspondances | M42: Note brute | N42: Famille | O42: Type | P42: Poids domaine | Q42: Poids effectif | R42: Cumul manquantes | S42: Cumul conditions | T42: Libellés manquants | U42: Rang (lecture) | V42: Valeur en clair
A43: (clé additionnelle) | D43: =P_ExtraKey -> dpd_days | E43: =IF(D43="","",IFERROR(INDEX(In_Retenue,MATCH(D43,In_Cles,0)),"")) -> 0 | J43: =AND(D43<>"",E43="") -> FALSE | R43: =IF(J43,D43,"") | S43: ="" | T43: =IF(J43,IFERROR(INDEX(Saisie!$C$13:$C$92,MATCH(D43,In_Cles,0)),D43),"")
A44: =IF(P_Criteres!A5="","",P_Criteres!A5) -> D1C1 | B44: =IF($A44="","",P_Criteres!B5) -> D1 | C44: =IF($A44="","",P_Criteres!C5) -> Projets similaires livrés (5 ans) | D44: =IF($A44="","",P_Criteres!F5) -> promoter_completed_projects | E44: =IF($A44="","",IFERROR(INDEX(In_Retenue,MATCH($D44,In_Cles,0)),"")) -> 8 | F44: =IF($A44="",0,ROUND(MIN(P_Scale,MAX(0,IF($L44=0,$K44,$M44))),2)) -> 10 | G44: =IF($A44="",0,P_Criteres!E5) -> 0.2 | H44: =ROUND(F44*G44,2) -> 2 | I44: =IF($A44="",FALSE,AND(P_Criteres!G5="Oui",ISNUMBER(P_Criteres!H5),F44<=N(P_Criteres!H5))) -> FALSE | J44: =IF($A44="",FALSE,AND(OR(P_Criteres!G5="Oui",P_Criteres!K5="Oui"),$E44="")) -> FALSE | K44: {=IF($A44="",0,MIN(IF(P_Baremes!$A$5:$A$400=$A44,P_Baremes!$H$5:$H$400)))} -> 1 | L44: =IF($A44="",0,IF($O44="NUM",IF(ISNUMBER($E44),SUMPRODUCT((P_Baremes!$A$5:$A$400=$A44)*(P_Baremes!$B$5:$B$400="PLAGE")*(((P_Baremes!$D$5:$D$400="")+($E44>=P_Baremes!$D$5:$D$400))>0)*(((P_Baremes!$E$5:$E$400="")+($E44<P_Baremes!$E$5:$E$400))>0)),0),SUMPRODUCT((P_Baremes!$A$5:$A$400=$A44)*(P_Baremes!$B$5:$B$400="MODALITE")*(P_Baremes!$C$5:$C$400=$E44)))) -> 1 | M44: =IF($A44="",0,IF($L44=0,0,IF($O44="NUM",SUMPRODUCT((P_Baremes!$A$5:$A$400=$A44)*(P_Baremes!$B$5:$B$400="PLAGE")*(((P_Baremes!$D$5:$D$400="")+($E44>=P_Baremes!$D$5:$D$400))>0)*(((P_Baremes!$E$5:$E$400="")+($E44<P_Baremes!$E$5:$E$400))>0)*P_Baremes!$H$5:$H$400),SUMPRODUCT((P_Baremes!$A$5:$A$400=$A44)*(P_Baremes!$B$5:$B$400="MODALITE")*(P_Baremes!$C$5:$C$400=$E44)*P_Baremes!$H$5:$H$400)))) -> 10 | N44: =IF($A44="","",P_Criteres!J5) -> ECONOMIC | O44: =IF($A44="","",P_Criteres!D5) -> NUM | P44: =IF($A44="",0,IFERROR(INDEX(P_DomPoids,MATCH($B44,P_DomCodes,0)),0)) -> 0.25 | Q44: =P44*G44 -> 0.05 | R44: =IF(J44,IF(ISNUMBER(SEARCH(","&D44&",",","&R43&",")),R43,R43&IF(R43="","",",")&D44),R43) | S44: =IF(I44,S43&IF(S43="","","; ")&"Lever la condition « "&C44&" » avant "&SUBSTITUTE(LOWER(IF(P_Criteres!I5="","TIRAGE",P_Criteres!I5)),"etude","étude"),S43) | T44: =IF(AND(J44,NOT(ISNUMBER(SEARCH(","&D44&",",","&R43&",")))),T43&IF(T43="","",", ")&IFERROR(INDEX(Saisie!$C$13:$C$92,MATCH(D44,In_Cles,0)),D44),T43) | U44: =IF(OR($A44="",N(G44)<=0),"",F44+ROW()/1000000) -> 10.000044 | V44: =IF($A44="","",IF($E44="","(non renseignée)",IF($O44="QUAL",IFERROR(INDEX(P_Baremes!$F$5:$F$400,SUMPRODUCT(MAX((P_Baremes!$A$5:$A$400=$A44)*(P_Baremes!$B$5:$B$400="MODALITE")*(P_Baremes!$C$5:$C$400=$E44)*(ROW(P_Baremes!$A$5:$A$400)-4)))),$E44),$E44))) -> 8
A45: =IF(P_Criteres!A6="","",P_Criteres!A6) -> D1C2 | B45: =IF($A45="","",P_Criteres!B6) -> D1 | C45: =IF($A45="","",P_Criteres!C6) -> Gearing promoteur (dettes nettes / FP) | D45: =IF($A45="","",P_Criteres!F6) -> promoter_gearing | E45: =IF($A45="","",IFERROR(INDEX(In_Retenue,MATCH($D45,In_Cles,0)),"")) -> 85 | F45: =IF($A45="",0,ROUND(MIN(P_Scale,MAX(0,IF($L45=0,$K45,$M45))),2)) -> 10 | G45: =IF($A45="",0,P_Criteres!E6) -> 0.25 | H45: =ROUND(F45*G45,2) -> 2.5 | I45: =IF($A45="",FALSE,AND(P_Criteres!G6="Oui",ISNUMBER(P_Criteres!H6),F45<=N(P_Criteres!H6))) -> FALSE | J45: =IF($A45="",FALSE,AND(OR(P_Criteres!G6="Oui",P_Criteres!K6="Oui"),$E45="")) -> FALSE | K45: {=IF($A45="",0,MIN(IF(P_Baremes!$A$5:$A$400=$A45,P_Baremes!$H$5:$H$400)))} -> 1 | L45: =IF($A45="",0,IF($O45="NUM",IF(ISNUMBER($E45),SUMPRODUCT((P_Baremes!$A$5:$A$400=$A45)*(P_Baremes!$B$5:$B$400="PLAGE")*(((P_Baremes!$D$5:$D$400="")+($E45>=P_Baremes!$D$5:$D$400))>0)*(((P_Baremes!$E$5:$E$400="")+($E45<P_Baremes!$E$5:$E$400))>0)),0),SUMPRODUCT((P_Baremes!$A$5:$A$400=$A45)*(P_Baremes!$B$5:$B$400="MODALITE")*(P_Baremes!$C$5:$C$400=$E45)))) -> 1 | M45: =IF($A45="",0,IF($L45=0,0,IF($O45="NUM",SUMPRODUCT((P_Baremes!$A$5:$A$400=$A45)*(P_Baremes!$B$5:$B$400="PLAGE")*(((P_Baremes!$D$5:$D$400="")+($E45>=P_Baremes!$D$5:$D$400))>0)*(((P_Baremes!$E$5:$E$400="")+($E45<P_Baremes!$E$5:$E$400))>0)*P_Baremes!$H$5:$H$400),SUMPRODUCT((P_Baremes!$A$5:$A$400=$A45)*(P_Baremes!$B$5:$B$400="MODALITE")*(P_Baremes!$C$5:$C$400=$E45)*P_Baremes!$H$5:$H$400)))) -> 10 | N45: =IF($A45="","",P_Criteres!J6) -> ECONOMIC | O45: =IF($A45="","",P_Criteres!D6) -> NUM | P45: =IF($A45="",0,IFERROR(INDEX(P_DomPoids,MATCH($B45,P_DomCodes,0)),0)) -> 0.25 | Q45: =P45*G45 -> 0.0625 | R45: =IF(J45,IF(ISNUMBER(SEARCH(","&D45&",",","&R44&",")),R44,R44&IF(R44="","",",")&D45),R44) | S45: =IF(I45,S44&IF(S44="","","; ")&"Lever la condition « "&C45&" » avant "&SUBSTITUTE(LOWER(IF(P_Criteres!I6="","TIRAGE",P_Criteres!I6)),"etude","étude"),S44) | T45: =IF(AND(J45,NOT(ISNUMBER(SEARCH(","&D45&",",","&R44&",")))),T44&IF(T44="","",", ")&IFERROR(INDEX(Saisie!$C$13:$C$92,MATCH(D45,In_Cles,0)),D45),T44) | U45: =IF(OR($A45="",N(G45)<=0),"",F45+ROW()/1000000) -> 10.000045 | V45: =IF($A45="","",IF($E45="","(non renseignée)",IF($O45="QUAL",IFERROR(INDEX(P_Baremes!$F$5:$F$400,SUMPRODUCT(MAX((P_Baremes!$A$5:$A$400=$A45)*(P_Baremes!$B$5:$B$400="MODALITE")*(P_Baremes!$C$5:$C$400=$E45)*(ROW(P_Baremes!$A$5:$A$400)-4)))),$E45),$E45))) -> 85
A46: =IF(P_Criteres!A7="","",P_Criteres!A7) -> D1C3 | B46: =IF($A46="","",P_Criteres!B7) -> D1 | C46: =IF($A46="","",P_Criteres!C7) -> Gouvernance & structure juridique | D46: =IF($A46="","",P_Criteres!F7) -> governance_quality | E46: =IF($A46="","",IFERROR(INDEX(In_Retenue,MATCH($D46,In_Cles,0)),"")) -> claire | F46: =IF($A46="",0,ROUND(MIN(P_Scale,MAX(0,IF($L46=0,$K46,$M46))),2)) -> 10 | G46: =IF($A46="",0,P_Criteres!E7) -> 0.15 | H46: =ROUND(F46*G46,2) -> 1.5 | I46: =IF($A46="",FALSE,AND(P_Criteres!G7="Oui",ISNUMBER(P_Criteres!H7),F46<=N(P_Criteres!H7))) -> FALSE | J46: =IF($A46="",FALSE,AND(OR(P_Criteres!G7="Oui",P_Criteres!K7="Oui"),$E46="")) -> FALSE | K46: {=IF($A46="",0,MIN(IF(P_Baremes!$A$5:$A$400=$A46,P_Baremes!$H$5:$H$400)))} -> 1 | L46: =IF($A46="",0,IF($O46="NUM",IF(ISNUMBER($E46),SUMPRODUCT((P_Baremes!$A$5:$A$400=$A46)*(P_Baremes!$B$5:$B$400="PLAGE")*(((P_Baremes!$D$5:$D$400="")+($E46>=P_Baremes!$D$5:$D$400))>0)*(((P_Baremes!$E$5:$E$400="")+($E46<P_Baremes!$E$5:$E$400))>0)),0),SUMPRODUCT((P_Baremes!$A$5:$A$400=$A46)*(P_Baremes!$B$5:$B$400="MODALITE")*(P_Baremes!$C$5:$C$400=$E46)))) -> 1 | M46: =IF($A46="",0,IF($L46=0,0,IF($O46="NUM",SUMPRODUCT((P_Baremes!$A$5:$A$400=$A46)*(P_Baremes!$B$5:$B$400="PLAGE")*(((P_Baremes!$D$5:$D$400="")+($E46>=P_Baremes!$D$5:$D$400))>0)*(((P_Baremes!$E$5:$E$400="")+($E46<P_Baremes!$E$5:$E$400))>0)*P_Baremes!$H$5:$H$400),SUMPRODUCT((P_Baremes!$A$5:$A$400=$A46)*(P_Baremes!$B$5:$B$400="MODALITE")*(P_Baremes!$C$5:$C$400=$E46)*P_Baremes!$H$5:$H$400)))) -> 10 | N46: =IF($A46="","",P_Criteres!J7) -> ECONOMIC | O46: =IF($A46="","",P_Criteres!D7) -> QUAL | P46: =IF($A46="",0,IFERROR(INDEX(P_DomPoids,MATCH($B46,P_DomCodes,0)),0)) -> 0.25 | Q46: =P46*G46 -> 0.0375 | R46: =IF(J46,IF(ISNUMBER(SEARCH(","&D46&",",","&R45&",")),R45,R45&IF(R45="","",",")&D46),R45) | S46: =IF(I46,S45&IF(S45="","","; ")&"Lever la condition « "&C46&" » avant "&SUBSTITUTE(LOWER(IF(P_Criteres!I7="","TIRAGE",P_Criteres!I7)),"etude","étude"),S45) | T46: =IF(AND(J46,NOT(ISNUMBER(SEARCH(","&D46&",",","&R45&",")))),T45&IF(T45="","",", ")&IFERROR(INDEX(Saisie!$C$13:$C$92,MATCH(D46,In_Cles,0)),D46),T45) | U46: =IF(OR($A46="",N(G46)<=0),"",F46+ROW()/1000000) -> 10.000046 | V46: =IF($A46="","",IF($E46="","(non renseignée)",IF($O46="QUAL",IFERROR(INDEX(P_Baremes!$F$5:$F$400,SUMPRODUCT(MAX((P_Baremes!$A$5:$A$400=$A46)*(P_Baremes!$B$5:$B$400="MODALITE")*(P_Baremes!$C$5:$C$400=$E46)*(ROW(P_Baremes!$A$5:$A$400)-4)))),$E46),$E46))) -> Claire / structurée
A47: =IF(P_Criteres!A8="","",P_Criteres!A8) -> D1C4 | B47: =IF($A47="","",P_Criteres!B8) -> D1 | C47: =IF($A47="","",P_Criteres!C8) -> Concentration mono-projet (CA projet / CA total) | D47: =IF($A47="","",P_Criteres!F8) -> mono_project_concentration | E47: =IF($A47="","",IFERROR(INDEX(In_Retenue,MATCH($D47,In_Cles,0)),"")) -> 35 | F47: =IF($A47="",0,ROUND(MIN(P_Scale,MAX(0,IF($L47=0,$K47,$M47))),2)) -> 10 | G47: =IF($A47="",0,P_Criteres!E8) -> 0.15 | H47: =ROUND(F47*G47,2) -> 1.5 | I47: =IF($A47="",FALSE,AND(P_Criteres!G8="Oui",ISNUMBER(P_Criteres!H8),F47<=N(P_Criteres!H8))) -> FALSE | J47: =IF($A47="",FALSE,AND(OR(P_Criteres!G8="Oui",P_Criteres!K8="Oui"),$E47="")) -> FALSE | K47: {=IF($A47="",0,MIN(IF(P_Baremes!$A$5:$A$400=$A47,P_Baremes!$H$5:$H$400)))} -> 1 | L47: =IF($A47="",0,IF($O47="NUM",IF(ISNUMBER($E47),SUMPRODUCT((P_Baremes!$A$5:$A$400=$A47)*(P_Baremes!$B$5:$B$400="PLAGE")*(((P_Baremes!$D$5:$D$400="")+($E47>=P_Baremes!$D$5:$D$400))>0)*(((P_Baremes!$E$5:$E$400="")+($E47<P_Baremes!$E$5:$E$400))>0)),0),SUMPRODUCT((P_Baremes!$A$5:$A$400=$A47)*(P_Baremes!$B$5:$B$400="MODALITE")*(P_Baremes!$C$5:$C$400=$E47)))) -> 1 | M47: =IF($A47="",0,IF($L47=0,0,IF($O47="NUM",SUMPRODUCT((P_Baremes!$A$5:$A$400=$A47)*(P_Baremes!$B$5:$B$400="PLAGE")*(((P_Baremes!$D$5:$D$400="")+($E47>=P_Baremes!$D$5:$D$400))>0)*(((P_Baremes!$E$5:$E$400="")+($E47<P_Baremes!$E$5:$E$400))>0)*P_Baremes!$H$5:$H$400),SUMPRODUCT((P_Baremes!$A$5:$A$400=$A47)*(P_Baremes!$B$5:$B$400="MODALITE")*(P_Baremes!$C$5:$C$400=$E47)*P_Baremes!$H$5:$H$400)))) -> 10 | N47: =IF($A47="","",P_Criteres!J8) -> ECONOMIC | O47: =IF($A47="","",P_Criteres!D8) -> NUM | P47: =IF($A47="",0,IFERROR(INDEX(P_DomPoids,MATCH($B47,P_DomCodes,0)),0)) -> 0.25 | Q47: =P47*G47 -> 0.0375 | R47: =IF(J47,IF(ISNUMBER(SEARCH(","&D47&",",","&R46&",")),R46,R46&IF(R46="","",",")&D47),R46) | S47: =IF(I47,S46&IF(S46="","","; ")&"Lever la condition « "&C47&" » avant "&SUBSTITUTE(LOWER(IF(P_Criteres!I8="","TIRAGE",P_Criteres!I8)),"etude","étude"),S46) | T47: =IF(AND(J47,NOT(ISNUMBER(SEARCH(","&D47&",",","&R46&",")))),T46&IF(T46="","",", ")&IFERROR(INDEX(Saisie!$C$13:$C$92,MATCH(D47,In_Cles,0)),D47),T46) | U47: =IF(OR($A47="",N(G47)<=0),"",F47+ROW()/1000000) -> 10.000047 | V47: =IF($A47="","",IF($E47="","(non renseignée)",IF($O47="QUAL",IFERROR(INDEX(P_Baremes!$F$5:$F$400,SUMPRODUCT(MAX((P_Baremes!$A$5:$A$400=$A47)*(P_Baremes!$B$5:$B$400="MODALITE")*(P_Baremes!$C$5:$C$400=$E47)*(ROW(P_Baremes!$A$5:$A$400)-4)))),$E47),$E47))) -> 35
A48: =IF(P_Criteres!A9="","",P_Criteres!A9) -> D1C5 | B48: =IF($A48="","",P_Criteres!B9) -> D1 | C48: =IF($A48="","",P_Criteres!C9) -> Typologie promoteur | D48: =IF($A48="","",P_Criteres!F9) -> promoter_type | E48: =IF($A48="","",IFERROR(INDEX(In_Retenue,MATCH($D48,In_Cles,0)),"")) -> structure | F48: =IF($A48="",0,ROUND(MIN(P_Scale,MAX(0,IF($L48=0,$K48,$M48))),2)) -> 10 | G48: =IF($A48="",0,P_Criteres!E9) -> 0.1 | H48: =ROUND(F48*G48,2) -> 1 | I48: =IF($A48="",FALSE,AND(P_Criteres!G9="Oui",ISNUMBER(P_Criteres!H9),F48<=N(P_Criteres!H9))) -> FALSE | J48: =IF($A48="",FALSE,AND(OR(P_Criteres!G9="Oui",P_Criteres!K9="Oui"),$E48="")) -> FALSE | K48: {=IF($A48="",0,MIN(IF(P_Baremes!$A$5:$A$400=$A48,P_Baremes!$H$5:$H$400)))} -> 2 | L48: =IF($A48="",0,IF($O48="NUM",IF(ISNUMBER($E48),SUMPRODUCT((P_Baremes!$A$5:$A$400=$A48)*(P_Baremes!$B$5:$B$400="PLAGE")*(((P_Baremes!$D$5:$D$400="")+($E48>=P_Baremes!$D$5:$D$400))>0)*(((P_Baremes!$E$5:$E$400="")+($E48<P_Baremes!$E$5:$E$400))>0)),0),SUMPRODUCT((P_Baremes!$A$5:$A$400=$A48)*(P_Baremes!$B$5:$B$400="MODALITE")*(P_Baremes!$C$5:$C$400=$E48)))) -> 1 | M48: =IF($A48="",0,IF($L48=0,0,IF($O48="NUM",SUMPRODUCT((P_Baremes!$A$5:$A$400=$A48)*(P_Baremes!$B$5:$B$400="PLAGE")*(((P_Baremes!$D$5:$D$400="")+($E48>=P_Baremes!$D$5:$D$400))>0)*(((P_Baremes!$E$5:$E$400="")+($E48<P_Baremes!$E$5:$E$400))>0)*P_Baremes!$H$5:$H$400),SUMPRODUCT((P_Baremes!$A$5:$A$400=$A48)*(P_Baremes!$B$5:$B$400="MODALITE")*(P_Baremes!$C$5:$C$400=$E48)*P_Baremes!$H$5:$H$400)))) -> 10 | N48: =IF($A48="","",P_Criteres!J9) -> ECONOMIC | O48: =IF($A48="","",P_Criteres!D9) -> QUAL | P48: =IF($A48="",0,IFERROR(INDEX(P_DomPoids,MATCH($B48,P_DomCodes,0)),0)) -> 0.25 | Q48: =P48*G48 -> 0.025 | R48: =IF(J48,IF(ISNUMBER(SEARCH(","&D48&",",","&R47&",")),R47,R47&IF(R47="","",",")&D48),R47) | S48: =IF(I48,S47&IF(S47="","","; ")&"Lever la condition « "&C48&" » avant "&SUBSTITUTE(LOWER(IF(P_Criteres!I9="","TIRAGE",P_Criteres!I9)),"etude","étude"),S47) | T48: =IF(AND(J48,NOT(ISNUMBER(SEARCH(","&D48&",",","&R47&",")))),T47&IF(T47="","",", ")&IFERROR(INDEX(Saisie!$C$13:$C$92,MATCH(D48,In_Cles,0)),D48),T47) | U48: =IF(OR($A48="",N(G48)<=0),"",F48+ROW()/1000000) -> 10.000048 | V48: =IF($A48="","",IF($E48="","(non renseignée)",IF($O48="QUAL",IFERROR(INDEX(P_Baremes!$F$5:$F$400,SUMPRODUCT(MAX((P_Baremes!$A$5:$A$400=$A48)*(P_Baremes!$B$5:$B$400="MODALITE")*(P_Baremes!$C$5:$C$400=$E48)*(ROW(P_Baremes!$A$5:$A$400)-4)))),$E48),$E48))) -> Structuré
A49: =IF(P_Criteres!A10="","",P_Criteres!A10) -> D1C6 | B49: =IF($A49="","",P_Criteres!B10) -> D1 | C49: =IF($A49="","",P_Criteres!C10) -> Apport effectif (injecté / prévu) | D49: =IF($A49="","",P_Criteres!F10) -> equity_injected_ratio | E49: =IF($A49="","",IFERROR(INDEX(In_Retenue,MATCH($D49,In_Cles,0)),"")) -> 100 | F49: =IF($A49="",0,ROUND(MIN(P_Scale,MAX(0,IF($L49=0,$K49,$M49))),2)) -> 10 | G49: =IF($A49="",0,P_Criteres!E10) -> 0.15 | H49: =ROUND(F49*G49,2) -> 1.5 | I49: =IF($A49="",FALSE,AND(P_Criteres!G10="Oui",ISNUMBER(P_Criteres!H10),F49<=N(P_Criteres!H10))) -> FALSE | J49: =IF($A49="",FALSE,AND(OR(P_Criteres!G10="Oui",P_Criteres!K10="Oui"),$E49="")) -> FALSE | K49: {=IF($A49="",0,MIN(IF(P_Baremes!$A$5:$A$400=$A49,P_Baremes!$H$5:$H$400)))} -> 1 | L49: =IF($A49="",0,IF($O49="NUM",IF(ISNUMBER($E49),SUMPRODUCT((P_Baremes!$A$5:$A$400=$A49)*(P_Baremes!$B$5:$B$400="PLAGE")*(((P_Baremes!$D$5:$D$400="")+($E49>=P_Baremes!$D$5:$D$400))>0)*(((P_Baremes!$E$5:$E$400="")+($E49<P_Baremes!$E$5:$E$400))>0)),0),SUMPRODUCT((P_Baremes!$A$5:$A$400=$A49)*(P_Baremes!$B$5:$B$400="MODALITE")*(P_Baremes!$C$5:$C$400=$E49)))) -> 1 | M49: =IF($A49="",0,IF($L49=0,0,IF($O49="NUM",SUMPRODUCT((P_Baremes!$A$5:$A$400=$A49)*(P_Baremes!$B$5:$B$400="PLAGE")*(((P_Baremes!$D$5:$D$400="")+($E49>=P_Baremes!$D$5:$D$400))>0)*(((P_Baremes!$E$5:$E$400="")+($E49<P_Baremes!$E$5:$E$400))>0)*P_Baremes!$H$5:$H$400),SUMPRODUCT((P_Baremes!$A$5:$A$400=$A49)*(P_Baremes!$B$5:$B$400="MODALITE")*(P_Baremes!$C$5:$C$400=$E49)*P_Baremes!$H$5:$H$400)))) -> 10 | N49: =IF($A49="","",P_Criteres!J10) -> ECONOMIC | O49: =IF($A49="","",P_Criteres!D10) -> NUM | P49: =IF($A49="",0,IFERROR(INDEX(P_DomPoids,MATCH($B49,P_DomCodes,0)),0)) -> 0.25 | Q49: =P49*G49 -> 0.0375 | R49: =IF(J49,IF(ISNUMBER(SEARCH(","&D49&",",","&R48&",")),R48,R48&IF(R48="","",",")&D49),R48) | S49: =IF(I49,S48&IF(S48="","","; ")&"Lever la condition « "&C49&" » avant "&SUBSTITUTE(LOWER(IF(P_Criteres!I10="","TIRAGE",P_Criteres!I10)),"etude","étude"),S48) | T49: =IF(AND(J49,NOT(ISNUMBER(SEARCH(","&D49&",",","&R48&",")))),T48&IF(T48="","",", ")&IFERROR(INDEX(Saisie!$C$13:$C$92,MATCH(D49,In_Cles,0)),D49),T48) | U49: =IF(OR($A49="",N(G49)<=0),"",F49+ROW()/1000000) -> 10.000049 | V49: =IF($A49="","",IF($E49="","(non renseignée)",IF($O49="QUAL",IFERROR(INDEX(P_Baremes!$F$5:$F$400,SUMPRODUCT(MAX((P_Baremes!$A$5:$A$400=$A49)*(P_Baremes!$B$5:$B$400="MODALITE")*(P_Baremes!$C$5:$C$400=$E49)*(ROW(P_Baremes!$A$5:$A$400)-4)))),$E49),$E49))) -> 100
A50: =IF(P_Criteres!A11="","",P_Criteres!A11) -> D2C1 | B50: =IF($A50="","",P_Criteres!B11) -> D2 | C50: =IF($A50="","",P_Criteres!C11) -> Foncier & autorisations | D50: =IF($A50="","",P_Criteres!F11) -> land_permits_status | E50: =IF($A50="","",IFERROR(INDEX(In_Retenue,MATCH($D50,In_Cles,0)),"")) -> definitives | F50: =IF($A50="",0,ROUND(MIN(P_Scale,MAX(0,IF($L50=0,$K50,$M50))),2)) -> 10 | G50: =IF($A50="",0,P_Criteres!E11) -> 0.1 | H50: =ROUND(F50*G50,2) -> 1 | I50: =IF($A50="",FALSE,AND(P_Criteres!G11="Oui",ISNUMBER(P_Criteres!H11),F50<=N(P_Criteres!H11))) -> FALSE | J50: =IF($A50="",FALSE,AND(OR(P_Criteres!G11="Oui",P_Criteres!K11="Oui"),$E50="")) -> FALSE | K50: {=IF($A50="",0,MIN(IF(P_Baremes!$A$5:$A$400=$A50,P_Baremes!$H$5:$H$400)))} -> 1 | L50: =IF($A50="",0,IF($O50="NUM",IF(ISNUMBER($E50),SUMPRODUCT((P_Baremes!$A$5:$A$400=$A50)*(P_Baremes!$B$5:$B$400="PLAGE")*(((P_Baremes!$D$5:$D$400="")+($E50>=P_Baremes!$D$5:$D$400))>0)*(((P_Baremes!$E$5:$E$400="")+($E50<P_Baremes!$E$5:$E$400))>0)),0),SUMPRODUCT((P_Baremes!$A$5:$A$400=$A50)*(P_Baremes!$B$5:$B$400="MODALITE")*(P_Baremes!$C$5:$C$400=$E50)))) -> 1 | M50: =IF($A50="",0,IF($L50=0,0,IF($O50="NUM",SUMPRODUCT((P_Baremes!$A$5:$A$400=$A50)*(P_Baremes!$B$5:$B$400="PLAGE")*(((P_Baremes!$D$5:$D$400="")+($E50>=P_Baremes!$D$5:$D$400))>0)*(((P_Baremes!$E$5:$E$400="")+($E50<P_Baremes!$E$5:$E$400))>0)*P_Baremes!$H$5:$H$400),SUMPRODUCT((P_Baremes!$A$5:$A$400=$A50)*(P_Baremes!$B$5:$B$400="MODALITE")*(P_Baremes!$C$5:$C$400=$E50)*P_Baremes!$H$5:$H$400)))) -> 10 | N50: =IF($A50="","",P_Criteres!J11) -> ECONOMIC | O50: =IF($A50="","",P_Criteres!D11) -> QUAL | P50: =IF($A50="",0,IFERROR(INDEX(P_DomPoids,MATCH($B50,P_DomCodes,0)),0)) -> 0.2 | Q50: =P50*G50 -> 0.02 | R50: =IF(J50,IF(ISNUMBER(SEARCH(","&D50&",",","&R49&",")),R49,R49&IF(R49="","",",")&D50),R49) | S50: =IF(I50,S49&IF(S49="","","; ")&"Lever la condition « "&C50&" » avant "&SUBSTITUTE(LOWER(IF(P_Criteres!I11="","TIRAGE",P_Criteres!I11)),"etude","étude"),S49) | T50: =IF(AND(J50,NOT(ISNUMBER(SEARCH(","&D50&",",","&R49&",")))),T49&IF(T49="","",", ")&IFERROR(INDEX(Saisie!$C$13:$C$92,MATCH(D50,In_Cles,0)),D50),T49) | U50: =IF(OR($A50="",N(G50)<=0),"",F50+ROW()/1000000) -> 10.00005 | V50: =IF($A50="","",IF($E50="","(non renseignée)",IF($O50="QUAL",IFERROR(INDEX(P_Baremes!$F$5:$F$400,SUMPRODUCT(MAX((P_Baremes!$A$5:$A$400=$A50)*(P_Baremes!$B$5:$B$400="MODALITE")*(P_Baremes!$C$5:$C$400=$E50)*(ROW(P_Baremes!$A$5:$A$400)-4)))),$E50),$E50))) -> Titre purgé + autorisations définitives
A51: =IF(P_Criteres!A12="","",P_Criteres!A12) -> D2C2 | B51: =IF($A51="","",P_Criteres!B12) -> D2 | C51: =IF($A51="","",P_Criteres!C12) -> Marché & positionnement | D51: =IF($A51="","",P_Criteres!F12) -> market_positioning | E51: =IF($A51="","",IFERROR(INDEX(In_Retenue,MATCH($D51,In_Cles,0)),"")) -> aligne | F51: =IF($A51="",0,ROUND(MIN(P_Scale,MAX(0,IF($L51=0,$K51,$M51))),2)) -> 10 | G51: =IF($A51="",0,P_Criteres!E12) -> 0.15 | H51: =ROUND(F51*G51,2) -> 1.5 | I51: =IF($A51="",FALSE,AND(P_Criteres!G12="Oui",ISNUMBER(P_Criteres!H12),F51<=N(P_Criteres!H12))) -> FALSE | J51: =IF($A51="",FALSE,AND(OR(P_Criteres!G12="Oui",P_Criteres!K12="Oui"),$E51="")) -> FALSE | K51: {=IF($A51="",0,MIN(IF(P_Baremes!$A$5:$A$400=$A51,P_Baremes!$H$5:$H$400)))} -> 2 | L51: =IF($A51="",0,IF($O51="NUM",IF(ISNUMBER($E51),SUMPRODUCT((P_Baremes!$A$5:$A$400=$A51)*(P_Baremes!$B$5:$B$400="PLAGE")*(((P_Baremes!$D$5:$D$400="")+($E51>=P_Baremes!$D$5:$D$400))>0)*(((P_Baremes!$E$5:$E$400="")+($E51<P_Baremes!$E$5:$E$400))>0)),0),SUMPRODUCT((P_Baremes!$A$5:$A$400=$A51)*(P_Baremes!$B$5:$B$400="MODALITE")*(P_Baremes!$C$5:$C$400=$E51)))) -> 1 | M51: =IF($A51="",0,IF($L51=0,0,IF($O51="NUM",SUMPRODUCT((P_Baremes!$A$5:$A$400=$A51)*(P_Baremes!$B$5:$B$400="PLAGE")*(((P_Baremes!$D$5:$D$400="")+($E51>=P_Baremes!$D$5:$D$400))>0)*(((P_Baremes!$E$5:$E$400="")+($E51<P_Baremes!$E$5:$E$400))>0)*P_Baremes!$H$5:$H$400),SUMPRODUCT((P_Baremes!$A$5:$A$400=$A51)*(P_Baremes!$B$5:$B$400="MODALITE")*(P_Baremes!$C$5:$C$400=$E51)*P_Baremes!$H$5:$H$400)))) -> 10 | N51: =IF($A51="","",P_Criteres!J12) -> ECONOMIC | O51: =IF($A51="","",P_Criteres!D12) -> QUAL | P51: =IF($A51="",0,IFERROR(INDEX(P_DomPoids,MATCH($B51,P_DomCodes,0)),0)) -> 0.2 | Q51: =P51*G51 -> 0.03 | R51: =IF(J51,IF(ISNUMBER(SEARCH(","&D51&",",","&R50&",")),R50,R50&IF(R50="","",",")&D51),R50) | S51: =IF(I51,S50&IF(S50="","","; ")&"Lever la condition « "&C51&" » avant "&SUBSTITUTE(LOWER(IF(P_Criteres!I12="","TIRAGE",P_Criteres!I12)),"etude","étude"),S50) | T51: =IF(AND(J51,NOT(ISNUMBER(SEARCH(","&D51&",",","&R50&",")))),T50&IF(T50="","",", ")&IFERROR(INDEX(Saisie!$C$13:$C$92,MATCH(D51,In_Cles,0)),D51),T50) | U51: =IF(OR($A51="",N(G51)<=0),"",F51+ROW()/1000000) -> 10.000051 | V51: =IF($A51="","",IF($E51="","(non renseignée)",IF($O51="QUAL",IFERROR(INDEX(P_Baremes!$F$5:$F$400,SUMPRODUCT(MAX((P_Baremes!$A$5:$A$400=$A51)*(P_Baremes!$B$5:$B$400="MODALITE")*(P_Baremes!$C$5:$C$400=$E51)*(ROW(P_Baremes!$A$5:$A$400)-4)))),$E51),$E51))) -> Aligné / forte demande
A52: =IF(P_Criteres!A13="","",P_Criteres!A13) -> D2C3 | B52: =IF($A52="","",P_Criteres!B13) -> D2 | C52: =IF($A52="","",P_Criteres!C13) -> Complexité technique | D52: =IF($A52="","",P_Criteres!F13) -> technical_complexity | E52: =IF($A52="","",IFERROR(INDEX(In_Retenue,MATCH($D52,In_Cles,0)),"")) -> standard | F52: =IF($A52="",0,ROUND(MIN(P_Scale,MAX(0,IF($L52=0,$K52,$M52))),2)) -> 10 | G52: =IF($A52="",0,P_Criteres!E13) -> 0.1 | H52: =ROUND(F52*G52,2) -> 1 | I52: =IF($A52="",FALSE,AND(P_Criteres!G13="Oui",ISNUMBER(P_Criteres!H13),F52<=N(P_Criteres!H13))) -> FALSE | J52: =IF($A52="",FALSE,AND(OR(P_Criteres!G13="Oui",P_Criteres!K13="Oui"),$E52="")) -> FALSE | K52: {=IF($A52="",0,MIN(IF(P_Baremes!$A$5:$A$400=$A52,P_Baremes!$H$5:$H$400)))} -> 2 | L52: =IF($A52="",0,IF($O52="NUM",IF(ISNUMBER($E52),SUMPRODUCT((P_Baremes!$A$5:$A$400=$A52)*(P_Baremes!$B$5:$B$400="PLAGE")*(((P_Baremes!$D$5:$D$400="")+($E52>=P_Baremes!$D$5:$D$400))>0)*(((P_Baremes!$E$5:$E$400="")+($E52<P_Baremes!$E$5:$E$400))>0)),0),SUMPRODUCT((P_Baremes!$A$5:$A$400=$A52)*(P_Baremes!$B$5:$B$400="MODALITE")*(P_Baremes!$C$5:$C$400=$E52)))) -> 1 | M52: =IF($A52="",0,IF($L52=0,0,IF($O52="NUM",SUMPRODUCT((P_Baremes!$A$5:$A$400=$A52)*(P_Baremes!$B$5:$B$400="PLAGE")*(((P_Baremes!$D$5:$D$400="")+($E52>=P_Baremes!$D$5:$D$400))>0)*(((P_Baremes!$E$5:$E$400="")+($E52<P_Baremes!$E$5:$E$400))>0)*P_Baremes!$H$5:$H$400),SUMPRODUCT((P_Baremes!$A$5:$A$400=$A52)*(P_Baremes!$B$5:$B$400="MODALITE")*(P_Baremes!$C$5:$C$400=$E52)*P_Baremes!$H$5:$H$400)))) -> 10 | N52: =IF($A52="","",P_Criteres!J13) -> ECONOMIC | O52: =IF($A52="","",P_Criteres!D13) -> QUAL | P52: =IF($A52="",0,IFERROR(INDEX(P_DomPoids,MATCH($B52,P_DomCodes,0)),0)) -> 0.2 | Q52: =P52*G52 -> 0.02 | R52: =IF(J52,IF(ISNUMBER(SEARCH(","&D52&",",","&R51&",")),R51,R51&IF(R51="","",",")&D52),R51) | S52: =IF(I52,S51&IF(S51="","","; ")&"Lever la condition « "&C52&" » avant "&SUBSTITUTE(LOWER(IF(P_Criteres!I13="","TIRAGE",P_Criteres!I13)),"etude","étude"),S51) | T52: =IF(AND(J52,NOT(ISNUMBER(SEARCH(","&D52&",",","&R51&",")))),T51&IF(T51="","",", ")&IFERROR(INDEX(Saisie!$C$13:$C$92,MATCH(D52,In_Cles,0)),D52),T51) | U52: =IF(OR($A52="",N(G52)<=0),"",F52+ROW()/1000000) -> 10.000052 | V52: =IF($A52="","",IF($E52="","(non renseignée)",IF($O52="QUAL",IFERROR(INDEX(P_Baremes!$F$5:$F$400,SUMPRODUCT(MAX((P_Baremes!$A$5:$A$400=$A52)*(P_Baremes!$B$5:$B$400="MODALITE")*(P_Baremes!$C$5:$C$400=$E52)*(ROW(P_Baremes!$A$5:$A$400)-4)))),$E52),$E52))) -> Standard
A53: =IF(P_Criteres!A14="","",P_Criteres!A14) -> D2C4 | B53: =IF($A53="","",P_Criteres!B14) -> D2 | C53: =IF($A53="","",P_Criteres!C14) -> Avancement vs planning | D53: =IF($A53="","",P_Criteres!F14) -> progress_vs_plan | E53: =IF($A53="","",IFERROR(INDEX(In_Retenue,MATCH($D53,In_Cles,0)),"")) -> 100 | F53: =IF($A53="",0,ROUND(MIN(P_Scale,MAX(0,IF($L53=0,$K53,$M53))),2)) -> 10 | G53: =IF($A53="",0,P_Criteres!E14) -> 0.1 | H53: =ROUND(F53*G53,2) -> 1 | I53: =IF($A53="",FALSE,AND(P_Criteres!G14="Oui",ISNUMBER(P_Criteres!H14),F53<=N(P_Criteres!H14))) -> FALSE | J53: =IF($A53="",FALSE,AND(OR(P_Criteres!G14="Oui",P_Criteres!K14="Oui"),$E53="")) -> FALSE | K53: {=IF($A53="",0,MIN(IF(P_Baremes!$A$5:$A$400=$A53,P_Baremes!$H$5:$H$400)))} -> 1 | L53: =IF($A53="",0,IF($O53="NUM",IF(ISNUMBER($E53),SUMPRODUCT((P_Baremes!$A$5:$A$400=$A53)*(P_Baremes!$B$5:$B$400="PLAGE")*(((P_Baremes!$D$5:$D$400="")+($E53>=P_Baremes!$D$5:$D$400))>0)*(((P_Baremes!$E$5:$E$400="")+($E53<P_Baremes!$E$5:$E$400))>0)),0),SUMPRODUCT((P_Baremes!$A$5:$A$400=$A53)*(P_Baremes!$B$5:$B$400="MODALITE")*(P_Baremes!$C$5:$C$400=$E53)))) -> 1 | M53: =IF($A53="",0,IF($L53=0,0,IF($O53="NUM",SUMPRODUCT((P_Baremes!$A$5:$A$400=$A53)*(P_Baremes!$B$5:$B$400="PLAGE")*(((P_Baremes!$D$5:$D$400="")+($E53>=P_Baremes!$D$5:$D$400))>0)*(((P_Baremes!$E$5:$E$400="")+($E53<P_Baremes!$E$5:$E$400))>0)*P_Baremes!$H$5:$H$400),SUMPRODUCT((P_Baremes!$A$5:$A$400=$A53)*(P_Baremes!$B$5:$B$400="MODALITE")*(P_Baremes!$C$5:$C$400=$E53)*P_Baremes!$H$5:$H$400)))) -> 10 | N53: =IF($A53="","",P_Criteres!J14) -> ECONOMIC | O53: =IF($A53="","",P_Criteres!D14) -> NUM | P53: =IF($A53="",0,IFERROR(INDEX(P_DomPoids,MATCH($B53,P_DomCodes,0)),0)) -> 0.2 | Q53: =P53*G53 -> 0.02 | R53: =IF(J53,IF(ISNUMBER(SEARCH(","&D53&",",","&R52&",")),R52,R52&IF(R52="","",",")&D53),R52) | S53: =IF(I53,S52&IF(S52="","","; ")&"Lever la condition « "&C53&" » avant "&SUBSTITUTE(LOWER(IF(P_Criteres!I14="","TIRAGE",P_Criteres!I14)),"etude","étude"),S52) | T53: =IF(AND(J53,NOT(ISNUMBER(SEARCH(","&D53&",",","&R52&",")))),T52&IF(T52="","",", ")&IFERROR(INDEX(Saisie!$C$13:$C$92,MATCH(D53,In_Cles,0)),D53),T52) | U53: =IF(OR($A53="",N(G53)<=0),"",F53+ROW()/1000000) -> 10.000053 | V53: =IF($A53="","",IF($E53="","(non renseignée)",IF($O53="QUAL",IFERROR(INDEX(P_Baremes!$F$5:$F$400,SUMPRODUCT(MAX((P_Baremes!$A$5:$A$400=$A53)*(P_Baremes!$B$5:$B$400="MODALITE")*(P_Baremes!$C$5:$C$400=$E53)*(ROW(P_Baremes!$A$5:$A$400)-4)))),$E53),$E53))) -> 100
A54: =IF(P_Criteres!A15="","",P_Criteres!A15) -> D2C5 | B54: =IF($A54="","",P_Criteres!B15) -> D2 | C54: =IF($A54="","",P_Criteres!C15) -> Litiges clients / SAV | D54: =IF($A54="","",P_Criteres!F15) -> sav_litigation | E54: =IF($A54="","",IFERROR(INDEX(In_Retenue,MATCH($D54,In_Cles,0)),"")) -> faible | F54: =IF($A54="",0,ROUND(MIN(P_Scale,MAX(0,IF($L54=0,$K54,$M54))),2)) -> 10 | G54: =IF($A54="",0,P_Criteres!E15) -> 0.05 | H54: =ROUND(F54*G54,2) -> 0.5 | I54: =IF($A54="",FALSE,AND(P_Criteres!G15="Oui",ISNUMBER(P_Criteres!H15),F54<=N(P_Criteres!H15))) -> FALSE | J54: =IF($A54="",FALSE,AND(OR(P_Criteres!G15="Oui",P_Criteres!K15="Oui"),$E54="")) -> FALSE | K54: {=IF($A54="",0,MIN(IF(P_Baremes!$A$5:$A$400=$A54,P_Baremes!$H$5:$H$400)))} -> 2 | L54: =IF($A54="",0,IF($O54="NUM",IF(ISNUMBER($E54),SUMPRODUCT((P_Baremes!$A$5:$A$400=$A54)*(P_Baremes!$B$5:$B$400="PLAGE")*(((P_Baremes!$D$5:$D$400="")+($E54>=P_Baremes!$D$5:$D$400))>0)*(((P_Baremes!$E$5:$E$400="")+($E54<P_Baremes!$E$5:$E$400))>0)),0),SUMPRODUCT((P_Baremes!$A$5:$A$400=$A54)*(P_Baremes!$B$5:$B$400="MODALITE")*(P_Baremes!$C$5:$C$400=$E54)))) -> 1 | M54: =IF($A54="",0,IF($L54=0,0,IF($O54="NUM",SUMPRODUCT((P_Baremes!$A$5:$A$400=$A54)*(P_Baremes!$B$5:$B$400="PLAGE")*(((P_Baremes!$D$5:$D$400="")+($E54>=P_Baremes!$D$5:$D$400))>0)*(((P_Baremes!$E$5:$E$400="")+($E54<P_Baremes!$E$5:$E$400))>0)*P_Baremes!$H$5:$H$400),SUMPRODUCT((P_Baremes!$A$5:$A$400=$A54)*(P_Baremes!$B$5:$B$400="MODALITE")*(P_Baremes!$C$5:$C$400=$E54)*P_Baremes!$H$5:$H$400)))) -> 10 | N54: =IF($A54="","",P_Criteres!J15) -> ECONOMIC | O54: =IF($A54="","",P_Criteres!D15) -> QUAL | P54: =IF($A54="",0,IFERROR(INDEX(P_DomPoids,MATCH($B54,P_DomCodes,0)),0)) -> 0.2 | Q54: =P54*G54 -> 0.01 | R54: =IF(J54,IF(ISNUMBER(SEARCH(","&D54&",",","&R53&",")),R53,R53&IF(R53="","",",")&D54),R53) | S54: =IF(I54,S53&IF(S53="","","; ")&"Lever la condition « "&C54&" » avant "&SUBSTITUTE(LOWER(IF(P_Criteres!I15="","TIRAGE",P_Criteres!I15)),"etude","étude"),S53) | T54: =IF(AND(J54,NOT(ISNUMBER(SEARCH(","&D54&",",","&R53&",")))),T53&IF(T53="","",", ")&IFERROR(INDEX(Saisie!$C$13:$C$92,MATCH(D54,In_Cles,0)),D54),T53) | U54: =IF(OR($A54="",N(G54)<=0),"",F54+ROW()/1000000) -> 10.000054 | V54: =IF($A54="","",IF($E54="","(non renseignée)",IF($O54="QUAL",IFERROR(INDEX(P_Baremes!$F$5:$F$400,SUMPRODUCT(MAX((P_Baremes!$A$5:$A$400=$A54)*(P_Baremes!$B$5:$B$400="MODALITE")*(P_Baremes!$C$5:$C$400=$E54)*(ROW(P_Baremes!$A$5:$A$400)-4)))),$E54),$E54))) -> Faible
A55: =IF(P_Criteres!A16="","",P_Criteres!A16) -> D2C6 | B55: =IF($A55="","",P_Criteres!B16) -> D2 | C55: =IF($A55="","",P_Criteres!C16) -> Sensibilité macro / subvention | D55: =IF($A55="","",P_Criteres!F16) -> macro_sensitivity | E55: =IF($A55="","",IFERROR(INDEX(In_Retenue,MATCH($D55,In_Cles,0)),"")) -> faible | F55: =IF($A55="",0,ROUND(MIN(P_Scale,MAX(0,IF($L55=0,$K55,$M55))),2)) -> 10 | G55: =IF($A55="",0,P_Criteres!E16) -> 0.05 | H55: =ROUND(F55*G55,2) -> 0.5 | I55: =IF($A55="",FALSE,AND(P_Criteres!G16="Oui",ISNUMBER(P_Criteres!H16),F55<=N(P_Criteres!H16))) -> FALSE | J55: =IF($A55="",FALSE,AND(OR(P_Criteres!G16="Oui",P_Criteres!K16="Oui"),$E55="")) -> FALSE | K55: {=IF($A55="",0,MIN(IF(P_Baremes!$A$5:$A$400=$A55,P_Baremes!$H$5:$H$400)))} -> 2 | L55: =IF($A55="",0,IF($O55="NUM",IF(ISNUMBER($E55),SUMPRODUCT((P_Baremes!$A$5:$A$400=$A55)*(P_Baremes!$B$5:$B$400="PLAGE")*(((P_Baremes!$D$5:$D$400="")+($E55>=P_Baremes!$D$5:$D$400))>0)*(((P_Baremes!$E$5:$E$400="")+($E55<P_Baremes!$E$5:$E$400))>0)),0),SUMPRODUCT((P_Baremes!$A$5:$A$400=$A55)*(P_Baremes!$B$5:$B$400="MODALITE")*(P_Baremes!$C$5:$C$400=$E55)))) -> 1 | M55: =IF($A55="",0,IF($L55=0,0,IF($O55="NUM",SUMPRODUCT((P_Baremes!$A$5:$A$400=$A55)*(P_Baremes!$B$5:$B$400="PLAGE")*(((P_Baremes!$D$5:$D$400="")+($E55>=P_Baremes!$D$5:$D$400))>0)*(((P_Baremes!$E$5:$E$400="")+($E55<P_Baremes!$E$5:$E$400))>0)*P_Baremes!$H$5:$H$400),SUMPRODUCT((P_Baremes!$A$5:$A$400=$A55)*(P_Baremes!$B$5:$B$400="MODALITE")*(P_Baremes!$C$5:$C$400=$E55)*P_Baremes!$H$5:$H$400)))) -> 10 | N55: =IF($A55="","",P_Criteres!J16) -> ECONOMIC | O55: =IF($A55="","",P_Criteres!D16) -> QUAL | P55: =IF($A55="",0,IFERROR(INDEX(P_DomPoids,MATCH($B55,P_DomCodes,0)),0)) -> 0.2 | Q55: =P55*G55 -> 0.01 | R55: =IF(J55,IF(ISNUMBER(SEARCH(","&D55&",",","&R54&",")),R54,R54&IF(R54="","",",")&D55),R54) | S55: =IF(I55,S54&IF(S54="","","; ")&"Lever la condition « "&C55&" » avant "&SUBSTITUTE(LOWER(IF(P_Criteres!I16="","TIRAGE",P_Criteres!I16)),"etude","étude"),S54) | T55: =IF(AND(J55,NOT(ISNUMBER(SEARCH(","&D55&",",","&R54&",")))),T54&IF(T54="","",", ")&IFERROR(INDEX(Saisie!$C$13:$C$92,MATCH(D55,In_Cles,0)),D55),T54) | U55: =IF(OR($A55="",N(G55)<=0),"",F55+ROW()/1000000) -> 10.000055 | V55: =IF($A55="","",IF($E55="","(non renseignée)",IF($O55="QUAL",IFERROR(INDEX(P_Baremes!$F$5:$F$400,SUMPRODUCT(MAX((P_Baremes!$A$5:$A$400=$A55)*(P_Baremes!$B$5:$B$400="MODALITE")*(P_Baremes!$C$5:$C$400=$E55)*(ROW(P_Baremes!$A$5:$A$400)-4)))),$E55),$E55))) -> Faible
... A103: =IF(P_Criteres!A64="","",P_Criteres!A64) | B103: =IF($A103="","",P_Criteres!B64) | C103: =IF($A103="","",P_Criteres!C64) | D103: =IF($A103="","",P_Criteres!F64) | E103: =IF($A103="","",IFERROR(INDEX(In_Retenue,MATCH($D103,In_Cles,0)),"")) | F103: =IF($A103="",0,ROUND(MIN(P_Scale,MAX(0,IF($L103=0,$K103,$M103))),2)) -> 0 | G103: =IF($A103="",0,P_Criteres!E64) -> 0 | H103: =ROUND(F103*G103,2) -> 0 | I103: =IF($A103="",FALSE,AND(P_Criteres!G64="Oui",ISNUMBER(P_Criteres!H64),F103<=N(P_Criteres!H64))) -> FALSE | J103: =IF($A103="",FALSE,AND(OR(P_Criteres!G64="Oui",P_Criteres!K64="Oui"),$E103="")) -> FALSE | K103: {=IF($A103="",0,MIN(IF(P_Baremes!$A$5:$A$400=$A103,P_Baremes!$H$5:$H$400)))} -> 0 | L103: =IF($A103="",0,IF($O103="NUM",IF(ISNUMBER($E103),SUMPRODUCT((P_Baremes!$A$5:$A$400=$A103)*(P_Baremes!$B$5:$B$400="PLAGE")*(((P_Baremes!$D$5:$D$400="")+($E103>=P_Baremes!$D$5:$D$400))>0)*(((P_Baremes!$E$5:$E$400="")+($E103<P_Baremes!$E$5:$E$400))>0)),0),SUMPRODUCT((P_Baremes!$A$5:$A$400=$A103)*(P_Baremes!$B$5:$B$400="MODALITE")*(P_Baremes!$C$5:$C$400=$E103)))) -> 0 | M103: =IF($A103="",0,IF($L103=0,0,IF($O103="NUM",SUMPRODUCT((P_Baremes!$A$5:$A$400=$A103)*(P_Baremes!$B$5:$B$400="PLAGE")*(((P_Baremes!$D$5:$D$400="")+($E103>=P_Baremes!$D$5:$D$400))>0)*(((P_Baremes!$E$5:$E$400="")+($E103<P_Baremes!$E$5:$E$400))>0)*P_Baremes!$H$5:$H$400),SUMPRODUCT((P_Baremes!$A$5:$A$400=$A103)*(P_Baremes!$B$5:$B$400="MODALITE")*(P_Baremes!$C$5:$C$400=$E103)*P_Baremes!$H$5:$H$400)))) -> 0 | N103: =IF($A103="","",P_Criteres!J64) | O103: =IF($A103="","",P_Criteres!D64) | P103: =IF($A103="",0,IFERROR(INDEX(P_DomPoids,MATCH($B103,P_DomCodes,0)),0)) -> 0 | Q103: =P103*G103 -> 0 | R103: =IF(J103,IF(ISNUMBER(SEARCH(","&D103&",",","&R102&",")),R102,R102&IF(R102="","",",")&D103),R102) | S103: =IF(I103,S102&IF(S102="","","; ")&"Lever la condition « "&C103&" » avant "&SUBSTITUTE(LOWER(IF(P_Criteres!I64="","TIRAGE",P_Criteres!I64)),"etude","étude"),S102) | T103: =IF(AND(J103,NOT(ISNUMBER(SEARCH(","&D103&",",","&R102&",")))),T102&IF(T102="","",", ")&IFERROR(INDEX(Saisie!$C$13:$C$92,MATCH(D103,In_Cles,0)),D103),T102) | U103: =IF(OR($A103="",N(G103)<=0),"",F103+ROW()/1000000) | V103: =IF($A103="","",IF($E103="","(non renseignée)",IF($O103="QUAL",IFERROR(INDEX(P_Baremes!$F$5:$F$400,SUMPRODUCT(MAX((P_Baremes!$A$5:$A$400=$A103)*(P_Baremes!$B$5:$B$400="MODALITE")*(P_Baremes!$C$5:$C$400=$E103)*(ROW(P_Baremes!$A$5:$A$400)-4)))),$E103),$E103)))
A106: Détail des alertes D5
A107: Code | B107: Libellé | C107: Sévérité | D107: Opérateur | E107: Clé | F107: Valeur | G107: Valeur réf. | H107: Déclenchée | I107: Non exclue (donnée absente) | J107: Malus appliqué | K107: Comité | L107: Clé numérique manquante | M107: Cumul manquantes | N107: Cumul alertes | O107: Libellés manquants | P107: Cumul libellés alertes
A108: =IF(P_Alertes!A5="","",P_Alertes!A5) -> RF_ACQUEREURS_NON_FINANCES | B108: =IF($A108="","",P_Alertes!B5) -> Financement acquéreur majoritairement non sécurisé | C108: =IF($A108="","",P_Alertes!C5) -> MEDIUM | D108: =IF($A108="","",P_Alertes!G5) -> isTrue | E108: =IF($A108="","",P_Alertes!F5) -> buyers_financing_at_risk | F108: =IF($A108="","",IFERROR(INDEX(In_Retenue,MATCH($E108,In_Cles,0)),"")) -> FALSE | G108: =IF($A108="","",IF(P_Alertes!H5="","",P_Alertes!H5)) | H108: =IF($A108="",FALSE,IF(D108="isTrue",F108=TRUE,IF(D108="isFalse",F108=FALSE,IF(D108="eq",F108=G108,IF(D108="neq",F108<>G108,IF(D108="gt",AND(ISNUMBER(F108),ISNUMBER(G108),N(F108)>N(G108)),IF(D108="gte",AND(ISNUMBER(F108),ISNUMBER(G108),N(F108)>=N(G108)),IF(D108="lt",AND(ISNUMBER(F108),ISNUMBER(G108),N(F108)<N(G108)),IF(D108="lte",AND(ISNUMBER(F108),ISNUMBER(G108),N(F108)<=N(G108)),FALSE))))))))) -> FALSE | I108: =IF($A108="",FALSE,AND(NOT(H108),C108<>"BLOCKING",L108)) -> FALSE | J108: =IF(OR(H108,I108),N(P_Alertes!D5),0) -> 0 | K108: =IF($A108="",FALSE,AND(OR(H108,I108),P_Alertes!I5="Oui")) -> FALSE | L108: =IF($A108="",FALSE,AND(OR(D108="gt",D108="gte",D108="lt",D108="lte"),F108="")) -> FALSE | M108: =IF(L108,IF(ISNUMBER(SEARCH(","&E108&",",","&R103&",")),R103,R103&IF(R103="","",",")&E108),R103) | N108: =IF(OR(H108,I108),""&IF(""="","",", ")&A108,"") | O108: =IF(AND(L108,NOT(ISNUMBER(SEARCH(","&E108&",",","&R103&",")))),T103&IF(T103="","",", ")&IFERROR(INDEX(Saisie!$C$13:$C$92,MATCH(E108,In_Cles,0)),E108),T103) | P108: =IF(OR(H108,I108),""&IF(""="","","; ")&B108&IF(I108," (donnée absente)",""),"")
A109: =IF(P_Alertes!A6="","",P_Alertes!A6) -> RF_AUTORISATION_TIRAGE | B109: =IF($A109="","",P_Alertes!B6) -> Autorisation indispensable aux travaux non levée | C109: =IF($A109="","",P_Alertes!C6) -> HIGH | D109: =IF($A109="","",P_Alertes!G6) -> isTrue | E109: =IF($A109="","",P_Alertes!F6) -> works_authorization_blocked | F109: =IF($A109="","",IFERROR(INDEX(In_Retenue,MATCH($E109,In_Cles,0)),"")) -> FALSE | G109: =IF($A109="","",IF(P_Alertes!H6="","",P_Alertes!H6)) | H109: =IF($A109="",FALSE,IF(D109="isTrue",F109=TRUE,IF(D109="isFalse",F109=FALSE,IF(D109="eq",F109=G109,IF(D109="neq",F109<>G109,IF(D109="gt",AND(ISNUMBER(F109),ISNUMBER(G109),N(F109)>N(G109)),IF(D109="gte",AND(ISNUMBER(F109),ISNUMBER(G109),N(F109)>=N(G109)),IF(D109="lt",AND(ISNUMBER(F109),ISNUMBER(G109),N(F109)<N(G109)),IF(D109="lte",AND(ISNUMBER(F109),ISNUMBER(G109),N(F109)<=N(G109)),FALSE))))))))) -> FALSE | I109: =IF($A109="",FALSE,AND(NOT(H109),C109<>"BLOCKING",L109)) -> FALSE | J109: =IF(OR(H109,I109),N(P_Alertes!D6),0) -> 0 | K109: =IF($A109="",FALSE,AND(OR(H109,I109),P_Alertes!I6="Oui")) -> FALSE | L109: =IF($A109="",FALSE,AND(OR(D109="gt",D109="gte",D109="lt",D109="lte"),F109="")) -> FALSE | M109: =IF(L109,IF(ISNUMBER(SEARCH(","&E109&",",","&M108&",")),M108,M108&IF(M108="","",",")&E109),M108) | N109: =IF(OR(H109,I109),N108&IF(N108="","",", ")&A109,N108) | O109: =IF(AND(L109,NOT(ISNUMBER(SEARCH(","&E109&",",","&M108&",")))),O108&IF(O108="","",", ")&IFERROR(INDEX(Saisie!$C$13:$C$92,MATCH(E109,In_Cles,0)),E109),O108) | P109: =IF(OR(H109,I109),P108&IF(P108="","","; ")&B109&IF(I109," (donnée absente)",""),P108)
A110: =IF(P_Alertes!A7="","",P_Alertes!A7) -> RF_CASH_LT_ECH | B110: =IF($A110="","",P_Alertes!B7) -> Cash coverage < 1,0x | C110: =IF($A110="","",P_Alertes!C7) -> HIGH | D110: =IF($A110="","",P_Alertes!G7) -> lt | E110: =IF($A110="","",P_Alertes!F7) -> cash_coverage | F110: =IF($A110="","",IFERROR(INDEX(In_Retenue,MATCH($E110,In_Cles,0)),"")) -> 0.99 | G110: =IF($A110="","",IF(P_Alertes!H7="","",P_Alertes!H7)) -> 1 | H110: =IF($A110="",FALSE,IF(D110="isTrue",F110=TRUE,IF(D110="isFalse",F110=FALSE,IF(D110="eq",F110=G110,IF(D110="neq",F110<>G110,IF(D110="gt",AND(ISNUMBER(F110),ISNUMBER(G110),N(F110)>N(G110)),IF(D110="gte",AND(ISNUMBER(F110),ISNUMBER(G110),N(F110)>=N(G110)),IF(D110="lt",AND(ISNUMBER(F110),ISNUMBER(G110),N(F110)<N(G110)),IF(D110="lte",AND(ISNUMBER(F110),ISNUMBER(G110),N(F110)<=N(G110)),FALSE))))))))) -> TRUE | I110: =IF($A110="",FALSE,AND(NOT(H110),C110<>"BLOCKING",L110)) -> FALSE | J110: =IF(OR(H110,I110),N(P_Alertes!D7),0) -> 25 | K110: =IF($A110="",FALSE,AND(OR(H110,I110),P_Alertes!I7="Oui")) -> FALSE | L110: =IF($A110="",FALSE,AND(OR(D110="gt",D110="gte",D110="lt",D110="lte"),F110="")) -> FALSE | M110: =IF(L110,IF(ISNUMBER(SEARCH(","&E110&",",","&M109&",")),M109,M109&IF(M109="","",",")&E110),M109) | N110: =IF(OR(H110,I110),N109&IF(N109="","",", ")&A110,N109) -> RF_CASH_LT_ECH | O110: =IF(AND(L110,NOT(ISNUMBER(SEARCH(","&E110&",",","&M109&",")))),O109&IF(O109="","",", ")&IFERROR(INDEX(Saisie!$C$13:$C$92,MATCH(E110,In_Cles,0)),E110),O109) | P110: =IF(OR(H110,I110),P109&IF(P109="","","; ")&B110&IF(I110," (donnée absente)",""),P109) -> Cash coverage < 1,0x
A111: =IF(P_Alertes!A8="","",P_Alertes!A8) -> RF_COMPOSANTE_SANS_PRENEUR | B111: =IF($A111="","",P_Alertes!B8) -> Composante commerciale ou hôtelière sans preneur engagé | C111: =IF($A111="","",P_Alertes!C8) -> MEDIUM | D111: =IF($A111="","",P_Alertes!G8) -> isTrue | E111: =IF($A111="","",P_Alertes!F8) -> component_exit_unsecured | F111: =IF($A111="","",IFERROR(INDEX(In_Retenue,MATCH($E111,In_Cles,0)),"")) -> FALSE | G111: =IF($A111="","",IF(P_Alertes!H8="","",P_Alertes!H8)) | H111: =IF($A111="",FALSE,IF(D111="isTrue",F111=TRUE,IF(D111="isFalse",F111=FALSE,IF(D111="eq",F111=G111,IF(D111="neq",F111<>G111,IF(D111="gt",AND(ISNUMBER(F111),ISNUMBER(G111),N(F111)>N(G111)),IF(D111="gte",AND(ISNUMBER(F111),ISNUMBER(G111),N(F111)>=N(G111)),IF(D111="lt",AND(ISNUMBER(F111),ISNUMBER(G111),N(F111)<N(G111)),IF(D111="lte",AND(ISNUMBER(F111),ISNUMBER(G111),N(F111)<=N(G111)),FALSE))))))))) -> FALSE | I111: =IF($A111="",FALSE,AND(NOT(H111),C111<>"BLOCKING",L111)) -> FALSE | J111: =IF(OR(H111,I111),N(P_Alertes!D8),0) -> 0 | K111: =IF($A111="",FALSE,AND(OR(H111,I111),P_Alertes!I8="Oui")) -> FALSE | L111: =IF($A111="",FALSE,AND(OR(D111="gt",D111="gte",D111="lt",D111="lte"),F111="")) -> FALSE | M111: =IF(L111,IF(ISNUMBER(SEARCH(","&E111&",",","&M110&",")),M110,M110&IF(M110="","",",")&E111),M110) | N111: =IF(OR(H111,I111),N110&IF(N110="","",", ")&A111,N110) -> RF_CASH_LT_ECH | O111: =IF(AND(L111,NOT(ISNUMBER(SEARCH(","&E111&",",","&M110&",")))),O110&IF(O110="","",", ")&IFERROR(INDEX(Saisie!$C$13:$C$92,MATCH(E111,In_Cles,0)),E111),O110) | P111: =IF(OR(H111,I111),P110&IF(P110="","","; ")&B111&IF(I111," (donnée absente)",""),P110) -> Cash coverage < 1,0x
A112: =IF(P_Alertes!A9="","",P_Alertes!A9) -> RF_DIVISION_RISQUES | B112: =IF($A112="","",P_Alertes!B9) -> Limite de division des risques dépassée | C112: =IF($A112="","",P_Alertes!C9) -> MEDIUM | D112: =IF($A112="","",P_Alertes!G9) -> isTrue | E112: =IF($A112="","",P_Alertes!F9) -> division_limit_breach | F112: =IF($A112="","",IFERROR(INDEX(In_Retenue,MATCH($E112,In_Cles,0)),"")) -> FALSE | G112: =IF($A112="","",IF(P_Alertes!H9="","",P_Alertes!H9)) | H112: =IF($A112="",FALSE,IF(D112="isTrue",F112=TRUE,IF(D112="isFalse",F112=FALSE,IF(D112="eq",F112=G112,IF(D112="neq",F112<>G112,IF(D112="gt",AND(ISNUMBER(F112),ISNUMBER(G112),N(F112)>N(G112)),IF(D112="gte",AND(ISNUMBER(F112),ISNUMBER(G112),N(F112)>=N(G112)),IF(D112="lt",AND(ISNUMBER(F112),ISNUMBER(G112),N(F112)<N(G112)),IF(D112="lte",AND(ISNUMBER(F112),ISNUMBER(G112),N(F112)<=N(G112)),FALSE))))))))) -> FALSE | I112: =IF($A112="",FALSE,AND(NOT(H112),C112<>"BLOCKING",L112)) -> FALSE | J112: =IF(OR(H112,I112),N(P_Alertes!D9),0) -> 0 | K112: =IF($A112="",FALSE,AND(OR(H112,I112),P_Alertes!I9="Oui")) -> FALSE | L112: =IF($A112="",FALSE,AND(OR(D112="gt",D112="gte",D112="lt",D112="lte"),F112="")) -> FALSE | M112: =IF(L112,IF(ISNUMBER(SEARCH(","&E112&",",","&M111&",")),M111,M111&IF(M111="","",",")&E112),M111) | N112: =IF(OR(H112,I112),N111&IF(N111="","",", ")&A112,N111) -> RF_CASH_LT_ECH | O112: =IF(AND(L112,NOT(ISNUMBER(SEARCH(","&E112&",",","&M111&",")))),O111&IF(O111="","",", ")&IFERROR(INDEX(Saisie!$C$13:$C$92,MATCH(E112,In_Cles,0)),E112),O111) | P112: =IF(OR(H112,I112),P111&IF(P111="","","; ")&B112&IF(I112," (donnée absente)",""),P111) -> Cash coverage < 1,0x
A113: =IF(P_Alertes!A10="","",P_Alertes!A10) -> RF_EQUIPEMENT_RECEPTION | B113: =IF($A113="","",P_Alertes!B10) -> Équipement exigé en retard (conditionne la réception) | C113: =IF($A113="","",P_Alertes!C10) -> HIGH | D113: =IF($A113="","",P_Alertes!G10) -> isTrue | E113: =IF($A113="","",P_Alertes!F10) -> equipment_delivery_at_risk | F113: =IF($A113="","",IFERROR(INDEX(In_Retenue,MATCH($E113,In_Cles,0)),"")) -> FALSE | G113: =IF($A113="","",IF(P_Alertes!H10="","",P_Alertes!H10)) | H113: =IF($A113="",FALSE,IF(D113="isTrue",F113=TRUE,IF(D113="isFalse",F113=FALSE,IF(D113="eq",F113=G113,IF(D113="neq",F113<>G113,IF(D113="gt",AND(ISNUMBER(F113),ISNUMBER(G113),N(F113)>N(G113)),IF(D113="gte",AND(ISNUMBER(F113),ISNUMBER(G113),N(F113)>=N(G113)),IF(D113="lt",AND(ISNUMBER(F113),ISNUMBER(G113),N(F113)<N(G113)),IF(D113="lte",AND(ISNUMBER(F113),ISNUMBER(G113),N(F113)<=N(G113)),FALSE))))))))) -> FALSE | I113: =IF($A113="",FALSE,AND(NOT(H113),C113<>"BLOCKING",L113)) -> FALSE | J113: =IF(OR(H113,I113),N(P_Alertes!D10),0) -> 0 | K113: =IF($A113="",FALSE,AND(OR(H113,I113),P_Alertes!I10="Oui")) -> FALSE | L113: =IF($A113="",FALSE,AND(OR(D113="gt",D113="gte",D113="lt",D113="lte"),F113="")) -> FALSE | M113: =IF(L113,IF(ISNUMBER(SEARCH(","&E113&",",","&M112&",")),M112,M112&IF(M112="","",",")&E113),M112) | N113: =IF(OR(H113,I113),N112&IF(N112="","",", ")&A113,N112) -> RF_CASH_LT_ECH | O113: =IF(AND(L113,NOT(ISNUMBER(SEARCH(","&E113&",",","&M112&",")))),O112&IF(O112="","",", ")&IFERROR(INDEX(Saisie!$C$13:$C$92,MATCH(E113,In_Cles,0)),E113),O112) | P113: =IF(OR(H113,I113),P112&IF(P112="","","; ")&B113&IF(I113," (donnée absente)",""),P112) -> Cash coverage < 1,0x
A114: =IF(P_Alertes!A11="","",P_Alertes!A11) -> RF_FP_NEG | B114: =IF($A114="","",P_Alertes!B11) -> Fonds propres négatifs | C114: =IF($A114="","",P_Alertes!C11) -> HIGH | D114: =IF($A114="","",P_Alertes!G11) -> isTrue | E114: =IF($A114="","",P_Alertes!F11) -> equity_negative | F114: =IF($A114="","",IFERROR(INDEX(In_Retenue,MATCH($E114,In_Cles,0)),"")) -> FALSE | G114: =IF($A114="","",IF(P_Alertes!H11="","",P_Alertes!H11)) | H114: =IF($A114="",FALSE,IF(D114="isTrue",F114=TRUE,IF(D114="isFalse",F114=FALSE,IF(D114="eq",F114=G114,IF(D114="neq",F114<>G114,IF(D114="gt",AND(ISNUMBER(F114),ISNUMBER(G114),N(F114)>N(G114)),IF(D114="gte",AND(ISNUMBER(F114),ISNUMBER(G114),N(F114)>=N(G114)),IF(D114="lt",AND(ISNUMBER(F114),ISNUMBER(G114),N(F114)<N(G114)),IF(D114="lte",AND(ISNUMBER(F114),ISNUMBER(G114),N(F114)<=N(G114)),FALSE))))))))) -> FALSE | I114: =IF($A114="",FALSE,AND(NOT(H114),C114<>"BLOCKING",L114)) -> FALSE | J114: =IF(OR(H114,I114),N(P_Alertes!D11),0) -> 0 | K114: =IF($A114="",FALSE,AND(OR(H114,I114),P_Alertes!I11="Oui")) -> FALSE | L114: =IF($A114="",FALSE,AND(OR(D114="gt",D114="gte",D114="lt",D114="lte"),F114="")) -> FALSE | M114: =IF(L114,IF(ISNUMBER(SEARCH(","&E114&",",","&M113&",")),M113,M113&IF(M113="","",",")&E114),M113) | N114: =IF(OR(H114,I114),N113&IF(N113="","",", ")&A114,N113) -> RF_CASH_LT_ECH | O114: =IF(AND(L114,NOT(ISNUMBER(SEARCH(","&E114&",",","&M113&",")))),O113&IF(O113="","",", ")&IFERROR(INDEX(Saisie!$C$13:$C$92,MATCH(E114,In_Cles,0)),E114),O113) | P114: =IF(OR(H114,I114),P113&IF(P113="","","; ")&B114&IF(I114," (donnée absente)",""),P113) -> Cash coverage < 1,0x
A115: =IF(P_Alertes!A12="","",P_Alertes!A12) -> RF_IMPASSE_PERSIST | B115: =IF($A115="","",P_Alertes!B12) -> Impasse de trésorerie persistante | C115: =IF($A115="","",P_Alertes!C12) -> HIGH | D115: =IF($A115="","",P_Alertes!G12) -> isTrue | E115: =IF($A115="","",P_Alertes!F12) -> funding_gap_persistent | F115: =IF($A115="","",IFERROR(INDEX(In_Retenue,MATCH($E115,In_Cles,0)),"")) -> FALSE | G115: =IF($A115="","",IF(P_Alertes!H12="","",P_Alertes!H12)) | H115: =IF($A115="",FALSE,IF(D115="isTrue",F115=TRUE,IF(D115="isFalse",F115=FALSE,IF(D115="eq",F115=G115,IF(D115="neq",F115<>G115,IF(D115="gt",AND(ISNUMBER(F115),ISNUMBER(G115),N(F115)>N(G115)),IF(D115="gte",AND(ISNUMBER(F115),ISNUMBER(G115),N(F115)>=N(G115)),IF(D115="lt",AND(ISNUMBER(F115),ISNUMBER(G115),N(F115)<N(G115)),IF(D115="lte",AND(ISNUMBER(F115),ISNUMBER(G115),N(F115)<=N(G115)),FALSE))))))))) -> FALSE | I115: =IF($A115="",FALSE,AND(NOT(H115),C115<>"BLOCKING",L115)) -> FALSE | J115: =IF(OR(H115,I115),N(P_Alertes!D12),0) -> 0 | K115: =IF($A115="",FALSE,AND(OR(H115,I115),P_Alertes!I12="Oui")) -> FALSE | L115: =IF($A115="",FALSE,AND(OR(D115="gt",D115="gte",D115="lt",D115="lte"),F115="")) -> FALSE | M115: =IF(L115,IF(ISNUMBER(SEARCH(","&E115&",",","&M114&",")),M114,M114&IF(M114="","",",")&E115),M114) | N115: =IF(OR(H115,I115),N114&IF(N114="","",", ")&A115,N114) -> RF_CASH_LT_ECH | O115: =IF(AND(L115,NOT(ISNUMBER(SEARCH(","&E115&",",","&M114&",")))),O114&IF(O114="","",", ")&IFERROR(INDEX(Saisie!$C$13:$C$92,MATCH(E115,In_Cles,0)),E115),O114) | P115: =IF(OR(H115,I115),P114&IF(P114="","","; ")&B115&IF(I115," (donnée absente)",""),P114) -> Cash coverage < 1,0x
A116: =IF(P_Alertes!A13="","",P_Alertes!A13) -> RF_IMPAYE_90J | B116: =IF($A116="","",P_Alertes!B13) -> Impayé ≥ 90 jours (souffrance automatique) | C116: =IF($A116="","",P_Alertes!C13) -> BLOCKING | D116: =IF($A116="","",P_Alertes!G13) -> gte | E116: =IF($A116="","",P_Alertes!F13) -> dpd_days | F116: =IF($A116="","",IFERROR(INDEX(In_Retenue,MATCH($E116,In_Cles,0)),"")) -> 0 | G116: =IF($A116="","",IF(P_Alertes!H13="","",P_Alertes!H13)) -> 90 | H116: =IF($A116="",FALSE,IF(D116="isTrue",F116=TRUE,IF(D116="isFalse",F116=FALSE,IF(D116="eq",F116=G116,IF(D116="neq",F116<>G116,IF(D116="gt",AND(ISNUMBER(F116),ISNUMBER(G116),N(F116)>N(G116)),IF(D116="gte",AND(ISNUMBER(F116),ISNUMBER(G116),N(F116)>=N(G116)),IF(D116="lt",AND(ISNUMBER(F116),ISNUMBER(G116),N(F116)<N(G116)),IF(D116="lte",AND(ISNUMBER(F116),ISNUMBER(G116),N(F116)<=N(G116)),FALSE))))))))) -> FALSE | I116: =IF($A116="",FALSE,AND(NOT(H116),C116<>"BLOCKING",L116)) -> FALSE | J116: =IF(OR(H116,I116),N(P_Alertes!D13),0) -> 0 | K116: =IF($A116="",FALSE,AND(OR(H116,I116),P_Alertes!I13="Oui")) -> FALSE | L116: =IF($A116="",FALSE,AND(OR(D116="gt",D116="gte",D116="lt",D116="lte"),F116="")) -> FALSE | M116: =IF(L116,IF(ISNUMBER(SEARCH(","&E116&",",","&M115&",")),M115,M115&IF(M115="","",",")&E116),M115) | N116: =IF(OR(H116,I116),N115&IF(N115="","",", ")&A116,N115) -> RF_CASH_LT_ECH | O116: =IF(AND(L116,NOT(ISNUMBER(SEARCH(","&E116&",",","&M115&",")))),O115&IF(O115="","",", ")&IFERROR(INDEX(Saisie!$C$13:$C$92,MATCH(E116,In_Cles,0)),E116),O115) | P116: =IF(OR(H116,I116),P115&IF(P115="","","; ")&B116&IF(I116," (donnée absente)",""),P115) -> Cash coverage < 1,0x
A117: =IF(P_Alertes!A14="","",P_Alertes!A14) -> RF_LITIGE | B117: =IF($A117="","",P_Alertes!B14) -> Action en justice / contentieux (CTX) | C117: =IF($A117="","",P_Alertes!C14) -> BLOCKING | D117: =IF($A117="","",P_Alertes!G14) -> eq | E117: =IF($A117="","",P_Alertes!F14) -> legal_exposure | F117: =IF($A117="","",IFERROR(INDEX(In_Retenue,MATCH($E117,In_Cles,0)),"")) -> clear | G117: =IF($A117="","",IF(P_Alertes!H14="","",P_Alertes!H14)) -> litigation | H117: =IF($A117="",FALSE,IF(D117="isTrue",F117=TRUE,IF(D117="isFalse",F117=FALSE,IF(D117="eq",F117=G117,IF(D117="neq",F117<>G117,IF(D117="gt",AND(ISNUMBER(F117),ISNUMBER(G117),N(F117)>N(G117)),IF(D117="gte",AND(ISNUMBER(F117),ISNUMBER(G117),N(F117)>=N(G117)),IF(D117="lt",AND(ISNUMBER(F117),ISNUMBER(G117),N(F117)<N(G117)),IF(D117="lte",AND(ISNUMBER(F117),ISNUMBER(G117),N(F117)<=N(G117)),FALSE))))))))) -> FALSE | I117: =IF($A117="",FALSE,AND(NOT(H117),C117<>"BLOCKING",L117)) -> FALSE | J117: =IF(OR(H117,I117),N(P_Alertes!D14),0) -> 0 | K117: =IF($A117="",FALSE,AND(OR(H117,I117),P_Alertes!I14="Oui")) -> FALSE | L117: =IF($A117="",FALSE,AND(OR(D117="gt",D117="gte",D117="lt",D117="lte"),F117="")) -> FALSE | M117: =IF(L117,IF(ISNUMBER(SEARCH(","&E117&",",","&M116&",")),M116,M116&IF(M116="","",",")&E117),M116) | N117: =IF(OR(H117,I117),N116&IF(N116="","",", ")&A117,N116) -> RF_CASH_LT_ECH | O117: =IF(AND(L117,NOT(ISNUMBER(SEARCH(","&E117&",",","&M116&",")))),O116&IF(O116="","",", ")&IFERROR(INDEX(Saisie!$C$13:$C$92,MATCH(E117,In_Cles,0)),E117),O116) | P117: =IF(OR(H117,I117),P116&IF(P116="","","; ")&B117&IF(I117," (donnée absente)",""),P116) -> Cash coverage < 1,0x
A118: =IF(P_Alertes!A15="","",P_Alertes!A15) -> RF_MAINLEVEE_SOUS_TARIFEE | B118: =IF($A118="","",P_Alertes!B15) -> Prix de mainlevée sous-tarifé | C118: =IF($A118="","",P_Alertes!C15) -> HIGH | D118: =IF($A118="","",P_Alertes!G15) -> isTrue | E118: =IF($A118="","",P_Alertes!F15) -> release_underpriced | F118: =IF($A118="","",IFERROR(INDEX(In_Retenue,MATCH($E118,In_Cles,0)),"")) -> FALSE | G118: =IF($A118="","",IF(P_Alertes!H15="","",P_Alertes!H15)) | H118: =IF($A118="",FALSE,IF(D118="isTrue",F118=TRUE,IF(D118="isFalse",F118=FALSE,IF(D118="eq",F118=G118,IF(D118="neq",F118<>G118,IF(D118="gt",AND(ISNUMBER(F118),ISNUMBER(G118),N(F118)>N(G118)),IF(D118="gte",AND(ISNUMBER(F118),ISNUMBER(G118),N(F118)>=N(G118)),IF(D118="lt",AND(ISNUMBER(F118),ISNUMBER(G118),N(F118)<N(G118)),IF(D118="lte",AND(ISNUMBER(F118),ISNUMBER(G118),N(F118)<=N(G118)),FALSE))))))))) -> FALSE | I118: =IF($A118="",FALSE,AND(NOT(H118),C118<>"BLOCKING",L118)) -> FALSE | J118: =IF(OR(H118,I118),N(P_Alertes!D15),0) -> 0 | K118: =IF($A118="",FALSE,AND(OR(H118,I118),P_Alertes!I15="Oui")) -> FALSE | L118: =IF($A118="",FALSE,AND(OR(D118="gt",D118="gte",D118="lt",D118="lte"),F118="")) -> FALSE | M118: =IF(L118,IF(ISNUMBER(SEARCH(","&E118&",",","&M117&",")),M117,M117&IF(M117="","",",")&E118),M117) | N118: =IF(OR(H118,I118),N117&IF(N117="","",", ")&A118,N117) -> RF_CASH_LT_ECH | O118: =IF(AND(L118,NOT(ISNUMBER(SEARCH(","&E118&",",","&M117&",")))),O117&IF(O117="","",", ")&IFERROR(INDEX(Saisie!$C$13:$C$92,MATCH(E118,In_Cles,0)),E118),O117) | P118: =IF(OR(H118,I118),P117&IF(P117="","","; ")&B118&IF(I118," (donnée absente)",""),P117) -> Cash coverage < 1,0x
A119: =IF(P_Alertes!A16="","",P_Alertes!A16) -> RF_NON_1ER_RANG | B119: =IF($A119="","",P_Alertes!B16) -> Garantie non 1er rang | C119: =IF($A119="","",P_Alertes!C16) -> MEDIUM | D119: =IF($A119="","",P_Alertes!G16) -> eq | E119: =IF($A119="","",P_Alertes!F16) -> first_rank | F119: =IF($A119="","",IFERROR(INDEX(In_Retenue,MATCH($E119,In_Cles,0)),"")) -> oui | G119: =IF($A119="","",IF(P_Alertes!H16="","",P_Alertes!H16)) -> non | H119: =IF($A119="",FALSE,IF(D119="isTrue",F119=TRUE,IF(D119="isFalse",F119=FALSE,IF(D119="eq",F119=G119,IF(D119="neq",F119<>G119,IF(D119="gt",AND(ISNUMBER(F119),ISNUMBER(G119),N(F119)>N(G119)),IF(D119="gte",AND(ISNUMBER(F119),ISNUMBER(G119),N(F119)>=N(G119)),IF(D119="lt",AND(ISNUMBER(F119),ISNUMBER(G119),N(F119)<N(G119)),IF(D119="lte",AND(ISNUMBER(F119),ISNUMBER(G119),N(F119)<=N(G119)),FALSE))))))))) -> FALSE | I119: =IF($A119="",FALSE,AND(NOT(H119),C119<>"BLOCKING",L119)) -> FALSE | J119: =IF(OR(H119,I119),N(P_Alertes!D16),0) -> 0 | K119: =IF($A119="",FALSE,AND(OR(H119,I119),P_Alertes!I16="Oui")) -> FALSE | L119: =IF($A119="",FALSE,AND(OR(D119="gt",D119="gte",D119="lt",D119="lte"),F119="")) -> FALSE | M119: =IF(L119,IF(ISNUMBER(SEARCH(","&E119&",",","&M118&",")),M118,M118&IF(M118="","",",")&E119),M118) | N119: =IF(OR(H119,I119),N118&IF(N118="","",", ")&A119,N118) -> RF_CASH_LT_ECH | O119: =IF(AND(L119,NOT(ISNUMBER(SEARCH(","&E119&",",","&M118&",")))),O118&IF(O118="","",", ")&IFERROR(INDEX(Saisie!$C$13:$C$92,MATCH(E119,In_Cles,0)),E119),O118) | P119: =IF(OR(H119,I119),P118&IF(P118="","","; ")&B119&IF(I119," (donnée absente)",""),P118) -> Cash coverage < 1,0x
A120: =IF(P_Alertes!A17="","",P_Alertes!A17) -> RF_PLAN_TIRAGE_RETARD | B120: =IF($A120="","",P_Alertes!B17) -> Plan de tirage en retard sur le calendrier | C120: =IF($A120="","",P_Alertes!C17) -> MEDIUM | D120: =IF($A120="","",P_Alertes!G17) -> isTrue | E120: =IF($A120="","",P_Alertes!F17) -> drawdown_schedule_late | F120: =IF($A120="","",IFERROR(INDEX(In_Retenue,MATCH($E120,In_Cles,0)),"")) -> FALSE | G120: =IF($A120="","",IF(P_Alertes!H17="","",P_Alertes!H17)) | H120: =IF($A120="",FALSE,IF(D120="isTrue",F120=TRUE,IF(D120="isFalse",F120=FALSE,IF(D120="eq",F120=G120,IF(D120="neq",F120<>G120,IF(D120="gt",AND(ISNUMBER(F120),ISNUMBER(G120),N(F120)>N(G120)),IF(D120="gte",AND(ISNUMBER(F120),ISNUMBER(G120),N(F120)>=N(G120)),IF(D120="lt",AND(ISNUMBER(F120),ISNUMBER(G120),N(F120)<N(G120)),IF(D120="lte",AND(ISNUMBER(F120),ISNUMBER(G120),N(F120)<=N(G120)),FALSE))))))))) -> FALSE | I120: =IF($A120="",FALSE,AND(NOT(H120),C120<>"BLOCKING",L120)) -> FALSE | J120: =IF(OR(H120,I120),N(P_Alertes!D17),0) -> 0 | K120: =IF($A120="",FALSE,AND(OR(H120,I120),P_Alertes!I17="Oui")) -> FALSE | L120: =IF($A120="",FALSE,AND(OR(D120="gt",D120="gte",D120="lt",D120="lte"),F120="")) -> FALSE | M120: =IF(L120,IF(ISNUMBER(SEARCH(","&E120&",",","&M119&",")),M119,M119&IF(M119="","",",")&E120),M119) | N120: =IF(OR(H120,I120),N119&IF(N119="","",", ")&A120,N119) -> RF_CASH_LT_ECH | O120: =IF(AND(L120,NOT(ISNUMBER(SEARCH(","&E120&",",","&M119&",")))),O119&IF(O119="","",", ")&IFERROR(INDEX(Saisie!$C$13:$C$92,MATCH(E120,In_Cles,0)),E120),O119) | P120: =IF(OR(H120,I120),P119&IF(P119="","","; ")&B120&IF(I120," (donnée absente)",""),P119) -> Cash coverage < 1,0x
... A137: =IF(P_Alertes!A34="","",P_Alertes!A34) | B137: =IF($A137="","",P_Alertes!B34) | C137: =IF($A137="","",P_Alertes!C34) | D137: =IF($A137="","",P_Alertes!G34) | E137: =IF($A137="","",P_Alertes!F34) | F137: =IF($A137="","",IFERROR(INDEX(In_Retenue,MATCH($E137,In_Cles,0)),"")) | G137: =IF($A137="","",IF(P_Alertes!H34="","",P_Alertes!H34)) | H137: =IF($A137="",FALSE,IF(D137="isTrue",F137=TRUE,IF(D137="isFalse",F137=FALSE,IF(D137="eq",F137=G137,IF(D137="neq",F137<>G137,IF(D137="gt",AND(ISNUMBER(F137),ISNUMBER(G137),N(F137)>N(G137)),IF(D137="gte",AND(ISNUMBER(F137),ISNUMBER(G137),N(F137)>=N(G137)),IF(D137="lt",AND(ISNUMBER(F137),ISNUMBER(G137),N(F137)<N(G137)),IF(D137="lte",AND(ISNUMBER(F137),ISNUMBER(G137),N(F137)<=N(G137)),FALSE))))))))) -> FALSE | I137: =IF($A137="",FALSE,AND(NOT(H137),C137<>"BLOCKING",L137)) -> FALSE | J137: =IF(OR(H137,I137),N(P_Alertes!D34),0) -> 0 | K137: =IF($A137="",FALSE,AND(OR(H137,I137),P_Alertes!I34="Oui")) -> FALSE | L137: =IF($A137="",FALSE,AND(OR(D137="gt",D137="gte",D137="lt",D137="lte"),F137="")) -> FALSE | M137: =IF(L137,IF(ISNUMBER(SEARCH(","&E137&",",","&M136&",")),M136,M136&IF(M136="","",",")&E137),M136) | N137: =IF(OR(H137,I137),N136&IF(N136="","",", ")&A137,N136) -> RF_CASH_LT_ECH | O137: =IF(AND(L137,NOT(ISNUMBER(SEARCH(","&E137&",",","&M136&",")))),O136&IF(O136="","",", ")&IFERROR(INDEX(Saisie!$C$13:$C$92,MATCH(E137,In_Cles,0)),E137),O136) | P137: =IF(OR(H137,I137),P136&IF(P136="","","; ")&B137&IF(I137," (donnée absente)",""),P136) -> Cash coverage < 1,0x

Sheet Historique
A1: Historique des calculs (journal)
A2: Alimenté par les macros (ScorerDossier, ScorerPortefeuille). La version du modèle est tracée sur chaque ligne.
A4: Date / heure | B4: Utilisateur | C4: Dossier | D4: Version du modèle | E4: Score final | F4: Décision | G4: Classe interne | H4: Malus D5 | I4: Dossier complet

Sheet Aide
B1: Aide — outil de scoring de la promotion immobilière
B2: ="Modèle PI_PROMOTION "&P_Version&" — publié le "&P_Date&" · outil 5.1 (05/10/2026)" -> Modèle PI_PROMOTION v5.0.0 — publié le 2026-10-01 · outil 5.1 (05/10/2026)
B4: À quoi sert ce classeur | C4: Calculer le score, la décision et la classe interne d'un dossier de promotion immobilière selon le modèle publié, hors de l'application : simulation, préparation de comité, agence, dépannage, formation. Il reproduit le moteur de production (vérifié sur 26 cas de référence).
B5: Principe | C5: Le MOTEUR est en formules Excel (onglet Resultat) : chaque note est traçable cellule par cellule et les barèmes se modifient sans code. Les macros AUTOMATISENT : nouveau dossier, enregistrer / ouvrir un dossier, export PDF, stress test, scoring de portefeuille, autotests, validation du modèle, journal.
B6: Parcours | C6: Accueil → Saisie (cellules jaunes, résultat en direct) → Fiche (synthèse imprimable). Calculateurs, Portefeuille, Stress et Historique au besoin. Resultat = calcul pas à pas.
B7: Ruban « Scoring PI » | C7: Dossier : Nouveau, Enregistrer, Ouvrir, Exporter la fiche en PDF. Analyse : Stress test, Scorer le portefeuille. Outil : Autotests, Valider le modèle, Paramètres (afficher / masquer), Aide. Sans ruban : Alt+F8 et choisir la macro (NouveauDossier, EnregistrerDossier, OuvrirDossier, ExporterPDF, LancerStress, ScorerPortefeuille, ExecuterAutotests, ValiderModele, BasculerParametres).
B8: Fichier sans macros | C8: Le fichier .xlsx calcule tout (saisie, fiche, résultat). Pour y ajouter les macros : Alt+F11 › Fichier › Importer les 6 fichiers .bas du dossier « vba », puis enregistrer au format .xlsm ; InstallerBoutons ajoute des boutons sur l'Accueil.
B9: Saisie | C9: Vide = donnée absente (jamais 0, jamais « Non »). Pourcentages en points (62 pour 62 %). Listes en clair : le code technique est déduit automatiquement. La colonne « État » indique : ✔ renseigné, ⚠ manquant — décisionnel (le dossier sera incomplet), ○ non renseigné (note plancher), ⚠ valeur à vérifier.
B10: Enregistrer les dossiers | C10: Enregistrer le dossier range les valeurs utilisées (y compris celles des calculateurs) dans le Portefeuille, avec le résultat. Ouvrir un dossier : sélectionnez sa ligne dans le Portefeuille (ou tapez sa référence) ; la saisie et les calculateurs du dossier courant sont d'abord vidés.
B11: Vérifier | C11: Ruban › Autotests : attendu « 26 / 26 cas conformes ». Valider le modèle après toute modification des paramètres.
B12: Invariants de décision | C12: Donnée manquante ≠ amélioration (note plancher ; alerte « non exclue » si sa donnée numérique manque) · Défaut avéré → NO_GO · Classe non renseignée → dossier incomplet · Aucun malus pour la division des risques (retour en comité).
B13: Ce que le classeur ne fait pas | C13: Classification BAM complète (déclencheurs qualitatifs 1/W, restructuration, effet de groupe) : la classe est saisie ; seule une suggestion fondée sur le retard est affichée. Trésorerie mensuelle, LGD, IFRS 9, workflow d'approbation, historisation multi-utilisateurs : dans l'application.
B14: Limites d'usage | C14: Classeur individuel : pas de contrôle d'accès ni de piste d'audit opposable. La décision officielle se prend dans l'application. La PD affichée est INDICATIVE et non calibrée (non affichée si le dossier est incomplet). Les grilles par phase et l'effet des coefficients territoriaux sont des challengers.
B15: Paramétrage | C15: Onglets P_* (masqués ; ruban › Paramètres) : critères, barèmes, alertes, ajustements, référentiels, seuils, libellés des décisions. Modifier = Valider le modèle + Instantané du modèle + information du propriétaire du modèle. Après ajout d'une modalité : Rafraîchir les listes.
B16: Version de l'outil | C16: Outil 5.1 du 05/10/2026 : classeur .xlsm prêt à l'emploi (macros intégrées, ruban), page d'accueil, fiche de résultat imprimable, saisie en clair avec état des données et résultat en direct, enregistrement des dossiers dans le portefeuille, feuilles protégées, valeurs visibles même en aperçu. Correction : les calculateurs du dossier courant ne faussent plus le scoring du portefeuille ni les autotests.
B18: Onglets
B19: Accueil | C19: Dossier en cours et mode d'emploi
B20: Saisie | C20: Données du dossier (cellules jaunes) et résultat en direct
B21: Fiche | C21: Synthèse lisible et imprimable
B22: Calculateurs | C22: Données dérivées : autorisations, ventes sécurisées, mainlevée, division des risques, arrêt de chantier, déblocages, équipements, programme mixte
B23: Portefeuille | C23: Dossiers enregistrés et scoring de masse
B24: Stress | C24: Chocs sur le dossier courant
B25: Resultat | C25: Calcul pas à pas (moteur)
B26: Historique | C26: Journal des calculs
B27: Tests, P_* (masqués) | C27: 26 cas de référence ; paramètres du modèle

Sheet Tests
A1: Autotests — cas de référence issus du moteur de production
A2: Les résultats attendus proviennent de l'exécution du moteur de l'application sur le modèle v5.0.0. Macro : ExecuterAutotests (tolérance 0,02 point).
A3: Identité | F3: Données d'entrée (mêmes clés que l'onglet Saisie)
A4: Cas | B4: Description | C4: Segment | D4: Zone | E4: Classe BAM | F4: promoter_completed_projects | G4: promoter_gearing | H4: governance_quality | I4: mono_project_concentration | J4: promoter_type | K4: equity_injected_ratio | L4: land_permits_status | M4: market_positioning | N4: technical_complexity | O4: progress_vs_plan | P4: sav_litigation | Q4: macro_sensitivity | R4: land_cost_ratio | S4: authorization_completeness_pct | T4: regional_market_tension | U4: contractor_quality | V4: equipment_unbudgeted_pct | W4: tranche_dependency | X4: pre_sale_rate | Y4: sales_vs_plan | Z4: dso_days | AA4: cash_coverage | AB4: funding_gap_pct | AC4: stock_rotation_months | AD4: stressed_margin_pct | AE4: secured_sales_rate | AF4: slow_liquidity_share_pct | AG4: cancellation_rate_pct | AH4: gross_margin_pct | AI4: ltc | AJ4: ltv_stressed | AK4: guarantee_coverage | AL4: first_rank | AM4: interest_coverage | AN4: release_quotity_gap_pts | AO4: drawdown_vs_progress_pct | AP4: cost_overrun_pct | AQ4: dpd_days | AR4: construction_delay_months | AS4: project_stopped_months | AT4: restructured | AU4: legal_exposure | AV4: equity_negative | AW4: funding_gap_persistent | AX4: works_authorization_blocked | AY4: buyers_financing_at_risk | AZ4: release_underpriced | BA4: division_limit_breach | BB4: drawdown_ahead_of_works | BC4: drawdown_schedule_late | BD4: equipment_delivery_at_risk | BE4: component_exit_unsecured | BF4: Attendu : score final | BG4: Attendu : décision | BH4: Attendu : classe interne | BI4: Attendu : malus | BJ4: Attendu : incomplet | BK4: Attendu : score éco. | BL4: Attendu : D1 | BM4: Attendu : D2 | BN4: Attendu : D3 | BO4: Attendu : D4 | BP4: Attendu : note sûretés | BQ4: Obtenu : score final | BR4: Obtenu : décision | BS4: Statut
A5: T01 | B5: Dossier solide, classe saine | E5: SAIN | F5: 8 | G5: 85 | H5: claire | I5: 35 | J5: structure | K5: 100 | L5: definitives | M5: aligne | N5: standard | O5: 100 | P5: faible | Q5: faible | R5: 22 | S5: 100 | T5: porteur | U5: qualifiee_garantie | V5: 0 | W5: programme_entier | X5: 62 | Y5: 100 | Z5: 90 | AA5: 1.35 | AB5: 0 | AC5: 16 | AD5: 18 | AE5: 55 | AF5: 5 | AG5: 3 | AH5: 27 | AI5: 61 | AJ5: 65 | AK5: 125 | AL5: oui | AM5: 3.2 | AN5: 5 | AO5: 98 | AP5: 2 | AQ5: 0 | AR5: 0 | AS5: 0 | AT5: no | AU5: clear | AV5: Non | AW5: Non | AX5: Non | AY5: Non | AZ5: Non | BA5: Non | BB5: Non | BC5: Non | BD5: Non | BE5: Non | BF5: 99.04 | BG5: GO | BH5: Sain | BI5: 0 | BJ5: Non | BK5: 99.04 | BL5: 100 | BM5: 100 | BN5: 100 | BO5: 96 | BP5: 100
A6: T02 | B6: Solide, segment touristique + zone Marrakech (ajustements) | C6: touristique | D6: marrakech | E6: SAIN | F6: 8 | G6: 85 | H6: claire | I6: 35 | J6: structure | K6: 100 | L6: definitives | M6: aligne | N6: standard | O6: 100 | P6: faible | Q6: faible | R6: 22 | S6: 100 | T6: porteur | U6: qualifiee_garantie | V6: 0 | W6: programme_entier | X6: 62 | Y6: 100 | Z6: 90 | AA6: 1.35 | AB6: 0 | AC6: 16 | AD6: 18 | AE6: 55 | AF6: 5 | AG6: 3 | AH6: 27 | AI6: 61 | AJ6: 65 | AK6: 125 | AL6: oui | AM6: 3.2 | AN6: 5 | AO6: 98 | AP6: 2 | AQ6: 0 | AR6: 0 | AS6: 0 | AT6: no | AU6: clear | AV6: Non | AW6: Non | AX6: Non | AY6: Non | AZ6: Non | BA6: Non | BB6: Non | BC6: Non | BD6: Non | BE6: Non | BF6: 85.17 | BG6: GO | BH6: Sain | BI6: 0 | BJ6: Non | BK6: 99.04 | BL6: 100 | BM6: 100 | BN6: 100 | BO6: 96 | BP6: 100
A7: T03 | B7: Dossier intermédiaire (score moyen) | C7: intermediaire | D7: casa_peripherie | E7: SAIN | F7: 2 | G7: 120 | H7: partielle | I7: 50 | J7: regional | K7: 90 | L7: partielles | M7: moyen | N7: moyenne | O7: 90 | P7: moyen | Q7: moyenne | R7: 30 | S7: 70 | T7: equilibre | U7: qualifiee | V7: 1.5 | W7: dependante_financee | X7: 35 | Y7: 90 | Z7: 180 | AA7: 1.1 | AB7: 5 | AC7: 24 | AD7: 12 | AE7: 30 | AF7: 25 | AG7: 12 | AH7: 20 | AI7: 70 | AJ7: 78 | AK7: 100 | AL7: oui | AM7: 2 | AN7: -5 | AO7: 108 | AP7: 7 | AQ7: 0 | AR7: 0 | AS7: 0 | AT7: no | AU7: clear | AV7: Non | AW7: Non | AX7: Non | AY7: Non | AZ7: Non | BA7: Non | BB7: Non | BC7: Non | BD7: Non | BE7: Non | BF7: 54.86 | BG7: WATCH_LIST | BH7: Sensible probable | BI7: 0 | BJ7: Non | BK7: 60.96 | BL7: 60 | BM7: 60 | BN7: 60 | BO7: 64 | BP7: 67.27
A8: T04 | B8: Dossier intermédiaire dégradé (cash 0,9 + impasse persistante) | E8: SAIN | F8: 2 | G8: 120 | H8: partielle | I8: 50 | J8: regional | K8: 90 | L8: partielles | M8: moyen | N8: moyenne | O8: 90 | P8: moyen | Q8: moyenne | R8: 30 | S8: 70 | T8: equilibre | U8: qualifiee | V8: 1.5 | W8: dependante_financee | X8: 35 | Y8: 90 | Z8: 180 | AA8: 0.9 | AB8: 5 | AC8: 24 | AD8: 12 | AE8: 30 | AF8: 25 | AG8: 12 | AH8: 20 | AI8: 70 | AJ8: 78 | AK8: 100 | AL8: oui | AM8: 2 | AN8: -5 | AO8: 108 | AP8: 7 | AQ8: 0 | AR8: 0 | AS8: 0 | AT8: no | AU8: clear | AV8: Non | AW8: Oui | AX8: Non | AY8: Non | AZ8: Non | BA8: Non | BB8: Non | BC8: Non | BD8: Non | BE8: Non | BF8: 12.86 | BG8: NO_GO | BH8: Sensible | BI8: 45 | BJ8: Non | BK8: 57.86 | BL8: 60 | BM8: 60 | BN8: 50 | BO8: 64 | BP8: 67.27
A9: T05 | B9: Impayé 120 j : alerte bloquante, souffrance | E9: SAIN | F9: 8 | G9: 85 | H9: claire | I9: 35 | J9: structure | K9: 100 | L9: definitives | M9: aligne | N9: standard | O9: 100 | P9: faible | Q9: faible | R9: 22 | S9: 100 | T9: porteur | U9: qualifiee_garantie | V9: 0 | W9: programme_entier | X9: 62 | Y9: 100 | Z9: 90 | AA9: 1.35 | AB9: 0 | AC9: 16 | AD9: 18 | AE9: 55 | AF9: 5 | AG9: 3 | AH9: 27 | AI9: 61 | AJ9: 65 | AK9: 125 | AL9: oui | AM9: 3.2 | AN9: 5 | AO9: 98 | AP9: 2 | AQ9: 120 | AR9: 0 | AS9: 0 | AT9: no | AU9: clear | AV9: Non | AW9: Non | AX9: Non | AY9: Non | AZ9: Non | BA9: Non | BB9: Non | BC9: Non | BD9: Non | BE9: Non | BF9: 99.04 | BG9: NO_GO | BH9: Souffrance | BI9: 0 | BJ9: Non | BK9: 99.04 | BL9: 100 | BM9: 100 | BN9: 100 | BO9: 96 | BP9: 100
A10: T06 | B10: Cash coverage 0,99 : alerte -25 | E10: SAIN | F10: 8 | G10: 85 | H10: claire | I10: 35 | J10: structure | K10: 100 | L10: definitives | M10: aligne | N10: standard | O10: 100 | P10: faible | Q10: faible | R10: 22 | S10: 100 | T10: porteur | U10: qualifiee_garantie | V10: 0 | W10: programme_entier | X10: 62 | Y10: 100 | Z10: 90 | AA10: 0.99 | AB10: 0 | AC10: 16 | AD10: 18 | AE10: 55 | AF10: 5 | AG10: 3 | AH10: 27 | AI10: 61 | AJ10: 65 | AK10: 125 | AL10: oui | AM10: 3.2 | AN10: 5 | AO10: 98 | AP10: 2 | AQ10: 0 | AR10: 0 | AS10: 0 | AT10: no | AU10: clear | AV10: Non | AW10: Non | AX10: Non | AY10: Non | AZ10: Non | BA10: Non | BB10: Non | BC10: Non | BD10: Non | BE10: Non | BF10: 68.46 | BG10: GO_WITH_CONDITIONS | BH10: Surveillance | BI10: 25 | BJ10: Non | BK10: 93.46 | BL10: 100 | BM10: 100 | BN10: 82 | BO10: 96 | BP10: 100
A11: T07 | B11: Cash coverage absent : dossier incomplet | E11: SAIN | F11: 8 | G11: 85 | H11: claire | I11: 35 | J11: structure | K11: 100 | L11: definitives | M11: aligne | N11: standard | O11: 100 | P11: faible | Q11: faible | R11: 22 | S11: 100 | T11: porteur | U11: qualifiee_garantie | V11: 0 | W11: programme_entier | X11: 62 | Y11: 100 | Z11: 90 | AB11: 0 | AC11: 16 | AD11: 18 | AE11: 55 | AF11: 5 | AG11: 3 | AH11: 27 | AI11: 61 | AJ11: 65 | AK11: 125 | AL11: oui | AM11: 3.2 | AN11: 5 | AO11: 98 | AP11: 2 | AQ11: 0 | AR11: 0 | AS11: 0 | AT11: no | AU11: clear | AV11: Non | AW11: Non | AX11: Non | AY11: Non | AZ11: Non | BA11: Non | BB11: Non | BC11: Non | BD11: Non | BE11: Non | BF11: 68.46 | BG11: DOSSIER_INCOMPLET | BH11: Dossier incomplet | BI11: 25 | BJ11: Oui | BK11: 93.46 | BL11: 100 | BM11: 100 | BN11: 82 | BO11: 96 | BP11: 100
A12: T08 | B12: Classe pré-douteuse : défaut avéré | E12: PRE_DOUTEUX | F12: 8 | G12: 85 | H12: claire | I12: 35 | J12: structure | K12: 100 | L12: definitives | M12: aligne | N12: standard | O12: 100 | P12: faible | Q12: faible | R12: 22 | S12: 100 | T12: porteur | U12: qualifiee_garantie | V12: 0 | W12: programme_entier | X12: 62 | Y12: 100 | Z12: 90 | AA12: 1.35 | AB12: 0 | AC12: 16 | AD12: 18 | AE12: 55 | AF12: 5 | AG12: 3 | AH12: 27 | AI12: 61 | AJ12: 65 | AK12: 125 | AL12: oui | AM12: 3.2 | AN12: 5 | AO12: 98 | AP12: 2 | AQ12: 0 | AR12: 0 | AS12: 0 | AT12: no | AU12: clear | AV12: Non | AW12: Non | AX12: Non | AY12: Non | AZ12: Non | BA12: Non | BB12: Non | BC12: Non | BD12: Non | BE12: Non | BF12: 69.33 | BG12: NO_GO | BH12: Défaut avéré | BI12: 0 | BJ12: Non | BK12: 99.04 | BL12: 100 | BM12: 100 | BN12: 100 | BO12: 96 | BP12: 100
A13: T09 | B13: Classe contentieux CTX : score 0 | E13: CTX | F13: 8 | G13: 85 | H13: claire | I13: 35 | J13: structure | K13: 100 | L13: definitives | M13: aligne | N13: standard | O13: 100 | P13: faible | Q13: faible | R13: 22 | S13: 100 | T13: porteur | U13: qualifiee_garantie | V13: 0 | W13: programme_entier | X13: 62 | Y13: 100 | Z13: 90 | AA13: 1.35 | AB13: 0 | AC13: 16 | AD13: 18 | AE13: 55 | AF13: 5 | AG13: 3 | AH13: 27 | AI13: 61 | AJ13: 65 | AK13: 125 | AL13: oui | AM13: 3.2 | AN13: 5 | AO13: 98 | AP13: 2 | AQ13: 0 | AR13: 0 | AS13: 0 | AT13: no | AU13: clear | AV13: Non | AW13: Non | AX13: Non | AY13: Non | AZ13: Non | BA13: Non | BB13: Non | BC13: Non | BD13: Non | BE13: Non | BF13: 0 | BG13: NO_GO | BH13: Souffrance | BI13: 0 | BJ13: Non | BK13: 99.04 | BL13: 100 | BM13: 100 | BN13: 100 | BO13: 96 | BP13: 100
A14: T10 | B14: Classe sensible : coefficient 0,9 | E14: SENSIBLE | F14: 8 | G14: 85 | H14: claire | I14: 35 | J14: structure | K14: 100 | L14: definitives | M14: aligne | N14: standard | O14: 100 | P14: faible | Q14: faible | R14: 22 | S14: 100 | T14: porteur | U14: qualifiee_garantie | V14: 0 | W14: programme_entier | X14: 62 | Y14: 100 | Z14: 90 | AA14: 1.35 | AB14: 0 | AC14: 16 | AD14: 18 | AE14: 55 | AF14: 5 | AG14: 3 | AH14: 27 | AI14: 61 | AJ14: 65 | AK14: 125 | AL14: oui | AM14: 3.2 | AN14: 5 | AO14: 98 | AP14: 2 | AQ14: 0 | AR14: 0 | AS14: 0 | AT14: no | AU14: clear | AV14: Non | AW14: Non | AX14: Non | AY14: Non | AZ14: Non | BA14: Non | BB14: Non | BC14: Non | BD14: Non | BE14: Non | BF14: 89.14 | BG14: GO | BH14: Sain | BI14: 0 | BJ14: Non | BK14: 99.04 | BL14: 100 | BM14: 100 | BN14: 100 | BO14: 96 | BP14: 100
A15: T11 | B15: Apport 50 % : gate franchi | E15: SAIN | F15: 8 | G15: 85 | H15: claire | I15: 35 | J15: structure | K15: 50 | L15: definitives | M15: aligne | N15: standard | O15: 100 | P15: faible | Q15: faible | R15: 22 | S15: 100 | T15: porteur | U15: qualifiee_garantie | V15: 0 | W15: programme_entier | X15: 62 | Y15: 100 | Z15: 90 | AA15: 1.35 | AB15: 0 | AC15: 16 | AD15: 18 | AE15: 55 | AF15: 5 | AG15: 3 | AH15: 27 | AI15: 61 | AJ15: 65 | AK15: 125 | AL15: oui | AM15: 3.2 | AN15: 5 | AO15: 98 | AP15: 2 | AQ15: 0 | AR15: 0 | AS15: 0 | AT15: no | AU15: clear | AV15: Non | AW15: Non | AX15: Non | AY15: Non | AZ15: Non | BA15: Non | BB15: Non | BC15: Non | BD15: Non | BE15: Non | BF15: 95.67 | BG15: NO_GO | BH15: Sain | BI15: 0 | BJ15: Non | BK15: 95.67 | BL15: 86.5 | BM15: 100 | BN15: 100 | BO15: 96 | BP15: 100
A16: T12 | B16: Non 1er rang + restructuration : malus cumulés | E16: SAIN | F16: 8 | G16: 85 | H16: claire | I16: 35 | J16: structure | K16: 100 | L16: definitives | M16: aligne | N16: standard | O16: 100 | P16: faible | Q16: faible | R16: 22 | S16: 100 | T16: porteur | U16: qualifiee_garantie | V16: 0 | W16: programme_entier | X16: 62 | Y16: 100 | Z16: 90 | AA16: 1.35 | AB16: 0 | AC16: 16 | AD16: 18 | AE16: 55 | AF16: 5 | AG16: 3 | AH16: 27 | AI16: 61 | AJ16: 65 | AK16: 125 | AL16: non | AM16: 3.2 | AN16: 5 | AO16: 98 | AP16: 2 | AQ16: 0 | AR16: 0 | AS16: 0 | AT16: yes | AU16: clear | AV16: Non | AW16: Non | AX16: Non | AY16: Non | AZ16: Non | BA16: Non | BB16: Non | BC16: Non | BD16: Non | BE16: Non | BF16: 46.88 | BG16: NO_GO | BH16: Sensible | BI16: 50 | BJ16: Non | BK16: 96.88 | BL16: 100 | BM16: 100 | BN16: 100 | BO16: 87 | BP16: 83.64
A17: T13 | B17: Segment et zone hors référentiel | C17: segment_inconnu | D17: zone_inconnue | E17: SAIN | F17: 8 | G17: 85 | H17: claire | I17: 35 | J17: structure | K17: 100 | L17: definitives | M17: aligne | N17: standard | O17: 100 | P17: faible | Q17: faible | R17: 22 | S17: 100 | T17: porteur | U17: qualifiee_garantie | V17: 0 | W17: programme_entier | X17: 62 | Y17: 100 | Z17: 90 | AA17: 1.35 | AB17: 0 | AC17: 16 | AD17: 18 | AE17: 55 | AF17: 5 | AG17: 3 | AH17: 27 | AI17: 61 | AJ17: 65 | AK17: 125 | AL17: oui | AM17: 3.2 | AN17: 5 | AO17: 98 | AP17: 2 | AQ17: 0 | AR17: 0 | AS17: 0 | AT17: no | AU17: clear | AV17: Non | AW17: Non | AX17: Non | AY17: Non | AZ17: Non | BA17: Non | BB17: Non | BC17: Non | BD17: Non | BE17: Non | BF17: 99.04 | BG17: GO | BH17: Sain | BI17: 0 | BJ17: Non | BK17: 99.04 | BL17: 100 | BM17: 100 | BN17: 100 | BO17: 96 | BP17: 100
A18: T14 | B18: Classe non renseignée : dossier incomplet | F18: 8 | G18: 85 | H18: claire | I18: 35 | J18: structure | K18: 100 | L18: definitives | M18: aligne | N18: standard | O18: 100 | P18: faible | Q18: faible | R18: 22 | S18: 100 | T18: porteur | U18: qualifiee_garantie | V18: 0 | W18: programme_entier | X18: 62 | Y18: 100 | Z18: 90 | AA18: 1.35 | AB18: 0 | AC18: 16 | AD18: 18 | AE18: 55 | AF18: 5 | AG18: 3 | AH18: 27 | AI18: 61 | AJ18: 65 | AK18: 125 | AL18: oui | AM18: 3.2 | AN18: 5 | AO18: 98 | AP18: 2 | AQ18: 0 | AR18: 0 | AS18: 0 | AT18: no | AU18: clear | AV18: Non | AW18: Non | AX18: Non | AY18: Non | AZ18: Non | BA18: Non | BB18: Non | BC18: Non | BD18: Non | BE18: Non | BF18: 99.04 | BG18: DOSSIER_INCOMPLET | BH18: Dossier incomplet | BI18: 0 | BJ18: Oui | BK18: 99.04 | BL18: 100 | BM18: 100 | BN18: 100 | BO18: 96 | BP18: 100
A19: T15 | B19: Autorisation indispensable manquante (verrou de tirage) | E19: SAIN | F19: 8 | G19: 85 | H19: claire | I19: 35 | J19: structure | K19: 100 | L19: definitives | M19: aligne | N19: standard | O19: 100 | P19: faible | Q19: faible | R19: 22 | S19: 40 | T19: porteur | U19: qualifiee_garantie | V19: 0 | W19: programme_entier | X19: 62 | Y19: 100 | Z19: 90 | AA19: 1.35 | AB19: 0 | AC19: 16 | AD19: 18 | AE19: 55 | AF19: 5 | AG19: 3 | AH19: 27 | AI19: 61 | AJ19: 65 | AK19: 125 | AL19: oui | AM19: 3.2 | AN19: 5 | AO19: 98 | AP19: 2 | AQ19: 0 | AR19: 0 | AS19: 0 | AT19: no | AU19: clear | AV19: Non | AW19: Non | AX19: Oui | AY19: Non | AZ19: Non | BA19: Non | BB19: Non | BC19: Non | BD19: Non | BE19: Non | BF19: 82.24 | BG19: GO | BH19: Sain | BI19: 15 | BJ19: Non | BK19: 97.24 | BL19: 100 | BM19: 91 | BN19: 100 | BO19: 96 | BP19: 100
A20: T16 | B20: Gouvernance non renseignée (qualitatif : note plancher) | E20: SAIN | F20: 8 | G20: 85 | I20: 35 | J20: structure | K20: 100 | L20: definitives | M20: aligne | N20: standard | O20: 100 | P20: faible | Q20: faible | R20: 22 | S20: 100 | T20: porteur | U20: qualifiee_garantie | V20: 0 | W20: programme_entier | X20: 62 | Y20: 100 | Z20: 90 | AA20: 1.35 | AB20: 0 | AC20: 16 | AD20: 18 | AE20: 55 | AF20: 5 | AG20: 3 | AH20: 27 | AI20: 61 | AJ20: 65 | AK20: 125 | AL20: oui | AM20: 3.2 | AN20: 5 | AO20: 98 | AP20: 2 | AQ20: 0 | AR20: 0 | AS20: 0 | AT20: no | AU20: clear | AV20: Non | AW20: Non | AX20: Non | AY20: Non | AZ20: Non | BA20: Non | BB20: Non | BC20: Non | BD20: Non | BE20: Non | BF20: 95.67 | BG20: GO | BH20: Sain | BI20: 0 | BJ20: Non | BK20: 95.67 | BL20: 86.5 | BM20: 100 | BN20: 100 | BO20: 96 | BP20: 100
A21: T17 | B21: Retard chantier 8 mois + prix de mainlevée sous-tarifé | E21: SAIN | F21: 8 | G21: 85 | H21: claire | I21: 35 | J21: structure | K21: 100 | L21: definitives | M21: aligne | N21: standard | O21: 100 | P21: faible | Q21: faible | R21: 22 | S21: 100 | T21: porteur | U21: qualifiee_garantie | V21: 0 | W21: programme_entier | X21: 62 | Y21: 100 | Z21: 90 | AA21: 1.35 | AB21: 0 | AC21: 16 | AD21: 18 | AE21: 55 | AF21: 5 | AG21: 3 | AH21: 27 | AI21: 61 | AJ21: 65 | AK21: 125 | AL21: oui | AM21: 3.2 | AN21: -15 | AO21: 98 | AP21: 2 | AQ21: 0 | AR21: 8 | AS21: 0 | AT21: no | AU21: clear | AV21: Non | AW21: Non | AX21: Non | AY21: Non | AZ21: Oui | BA21: Non | BB21: Non | BC21: Non | BD21: Non | BE21: Non | BF21: 67.96 | BG21: GO_WITH_CONDITIONS | BH21: Surveillance | BI21: 30 | BJ21: Non | BK21: 97.96 | BL21: 100 | BM21: 100 | BN21: 100 | BO21: 91.5 | BP21: 91.82
A22: T18 | B22: Retard de paiement (dpd_days) absent : dossier incomplet | E22: SAIN | F22: 8 | G22: 85 | H22: claire | I22: 35 | J22: structure | K22: 100 | L22: definitives | M22: aligne | N22: standard | O22: 100 | P22: faible | Q22: faible | R22: 22 | S22: 100 | T22: porteur | U22: qualifiee_garantie | V22: 0 | W22: programme_entier | X22: 62 | Y22: 100 | Z22: 90 | AA22: 1.35 | AB22: 0 | AC22: 16 | AD22: 18 | AE22: 55 | AF22: 5 | AG22: 3 | AH22: 27 | AI22: 61 | AJ22: 65 | AK22: 125 | AL22: oui | AM22: 3.2 | AN22: 5 | AO22: 98 | AP22: 2 | AR22: 0 | AS22: 0 | AT22: no | AU22: clear | AV22: Non | AW22: Non | AX22: Non | AY22: Non | AZ22: Non | BA22: Non | BB22: Non | BC22: Non | BD22: Non | BE22: Non | BF22: 99.04 | BG22: DOSSIER_INCOMPLET | BH22: Dossier incomplet | BI22: 0 | BJ22: Oui | BK22: 99.04 | BL22: 100 | BM22: 100 | BN22: 100 | BO22: 96 | BP22: 100
A23: T19 | B23: Litige : alerte bloquante CTX | E23: SAIN | F23: 8 | G23: 85 | H23: claire | I23: 35 | J23: structure | K23: 100 | L23: definitives | M23: aligne | N23: standard | O23: 100 | P23: faible | Q23: faible | R23: 22 | S23: 100 | T23: porteur | U23: qualifiee_garantie | V23: 0 | W23: programme_entier | X23: 62 | Y23: 100 | Z23: 90 | AA23: 1.35 | AB23: 0 | AC23: 16 | AD23: 18 | AE23: 55 | AF23: 5 | AG23: 3 | AH23: 27 | AI23: 61 | AJ23: 65 | AK23: 125 | AL23: oui | AM23: 3.2 | AN23: 5 | AO23: 98 | AP23: 2 | AQ23: 0 | AR23: 0 | AS23: 0 | AT23: no | AU23: litigation | AV23: Non | AW23: Non | AX23: Non | AY23: Non | AZ23: Non | BA23: Non | BB23: Non | BC23: Non | BD23: Non | BE23: Non | BF23: 99.04 | BG23: NO_GO | BH23: Souffrance | BI23: 0 | BJ23: Non | BK23: 99.04 | BL23: 100 | BM23: 100 | BN23: 100 | BO23: 96 | BP23: 100
A24: T20 | B24: Projet en difficulté (dégradé + non 1er rang) | C24: villas | D24: regions_interieures | E24: SENSIBLE | F24: 2 | G24: 120 | H24: partielle | I24: 50 | J24: regional | K24: 90 | L24: partielles | M24: moyen | N24: moyenne | O24: 90 | P24: moyen | Q24: moyenne | R24: 30 | S24: 70 | T24: equilibre | U24: qualifiee | V24: 1.5 | W24: dependante_financee | X24: 35 | Y24: 90 | Z24: 180 | AA24: 0.95 | AB24: 5 | AC24: 24 | AD24: 12 | AE24: 30 | AF24: 25 | AG24: 12 | AH24: 12 | AI24: 85 | AJ24: 78 | AK24: 100 | AL24: non | AM24: 2 | AN24: -5 | AO24: 108 | AP24: 7 | AQ24: 0 | AR24: 0 | AS24: 0 | AT24: no | AU24: clear | AV24: Non | AW24: Non | AX24: Non | AY24: Non | AZ24: Non | BA24: Non | BB24: Non | BC24: Non | BD24: Non | BE24: Non | BF24: 0 | BG24: NO_GO | BH24: Sensible | BI24: 50 | BJ24: Non | BK24: 52.7 | BL24: 60 | BM24: 60 | BN24: 50 | BO24: 42.5 | BP24: 50.91
A25: T21 | B25: Tranche financée dépendante d'ouvrages communs non financés | E25: SAIN | F25: 8 | G25: 85 | H25: claire | I25: 35 | J25: structure | K25: 100 | L25: definitives | M25: aligne | N25: standard | O25: 100 | P25: faible | Q25: faible | R25: 22 | S25: 100 | T25: porteur | U25: qualifiee_garantie | V25: 0 | W25: dependante_non_financee | X25: 62 | Y25: 100 | Z25: 90 | AA25: 1.35 | AB25: 0 | AC25: 16 | AD25: 18 | AE25: 55 | AF25: 5 | AG25: 3 | AH25: 27 | AI25: 61 | AJ25: 65 | AK25: 125 | AL25: oui | AM25: 3.2 | AN25: 5 | AO25: 98 | AP25: 2 | AQ25: 0 | AR25: 0 | AS25: 0 | AT25: no | AU25: clear | AV25: Non | AW25: Non | AX25: Non | AY25: Non | AZ25: Non | BA25: Non | BB25: Non | BC25: Non | BD25: Non | BE25: Non | BF25: 83.14 | BG25: GO | BH25: Sain | BI25: 15 | BJ25: Non | BK25: 98.14 | BL25: 100 | BM25: 95.5 | BN25: 100 | BO25: 96 | BP25: 100
A26: T22 | B26: Déblocages en avance sur l'avancement (150 %) | E26: SAIN | F26: 8 | G26: 85 | H26: claire | I26: 35 | J26: structure | K26: 100 | L26: definitives | M26: aligne | N26: standard | O26: 100 | P26: faible | Q26: faible | R26: 22 | S26: 100 | T26: porteur | U26: qualifiee_garantie | V26: 0 | W26: programme_entier | X26: 62 | Y26: 100 | Z26: 90 | AA26: 1.35 | AB26: 0 | AC26: 16 | AD26: 18 | AE26: 55 | AF26: 5 | AG26: 3 | AH26: 27 | AI26: 61 | AJ26: 65 | AK26: 125 | AL26: oui | AM26: 3.2 | AN26: 5 | AO26: 150 | AP26: 2 | AQ26: 0 | AR26: 0 | AS26: 0 | AT26: no | AU26: clear | AV26: Non | AW26: Non | AX26: Non | AY26: Non | AZ26: Non | BA26: Non | BB26: Oui | BC26: Non | BD26: Non | BE26: Non | BF26: 81.88 | BG26: GO | BH26: Sain | BI26: 15 | BJ26: Non | BK26: 96.88 | BL26: 100 | BM26: 100 | BN26: 100 | BO26: 87 | BP26: 83.64
A27: T23 | B27: Mosquée exigée non budgétée (4 % du coût) et en retard | E27: SAIN | F27: 8 | G27: 85 | H27: claire | I27: 35 | J27: structure | K27: 100 | L27: definitives | M27: aligne | N27: standard | O27: 100 | P27: faible | Q27: faible | R27: 22 | S27: 100 | T27: porteur | U27: qualifiee_garantie | V27: 4 | W27: programme_entier | X27: 62 | Y27: 100 | Z27: 90 | AA27: 1.35 | AB27: 0 | AC27: 16 | AD27: 18 | AE27: 55 | AF27: 5 | AG27: 3 | AH27: 27 | AI27: 61 | AJ27: 65 | AK27: 125 | AL27: oui | AM27: 3.2 | AN27: 5 | AO27: 98 | AP27: 2 | AQ27: 0 | AR27: 0 | AS27: 0 | AT27: no | AU27: clear | AV27: Non | AW27: Non | AX27: Non | AY27: Non | AZ27: Non | BA27: Non | BB27: Non | BC27: Non | BD27: Oui | BE27: Non | BF27: 83.14 | BG27: GO | BH27: Sain | BI27: 15 | BJ27: Non | BK27: 98.14 | BL27: 100 | BM27: 95.5 | BN27: 100 | BO27: 96 | BP27: 100
A28: T24 | B28: Programme mixte : 45 % commerces et hôtel, sans preneur engagé | E28: SAIN | F28: 8 | G28: 85 | H28: claire | I28: 35 | J28: structure | K28: 100 | L28: definitives | M28: aligne | N28: standard | O28: 100 | P28: faible | Q28: faible | R28: 22 | S28: 100 | T28: porteur | U28: qualifiee_garantie | V28: 0 | W28: programme_entier | X28: 62 | Y28: 100 | Z28: 90 | AA28: 1.35 | AB28: 0 | AC28: 16 | AD28: 18 | AE28: 55 | AF28: 45 | AG28: 3 | AH28: 27 | AI28: 61 | AJ28: 65 | AK28: 125 | AL28: oui | AM28: 3.2 | AN28: 5 | AO28: 98 | AP28: 2 | AQ28: 0 | AR28: 0 | AS28: 0 | AT28: no | AU28: clear | AV28: Non | AW28: Non | AX28: Non | AY28: Non | AZ28: Non | BA28: Non | BB28: Non | BC28: Non | BD28: Non | BE28: Oui | BF28: 87.64 | BG28: GO | BH28: Sain | BI28: 10 | BJ28: Non | BK28: 97.64 | BL28: 100 | BM28: 100 | BN28: 95.5 | BO28: 96 | BP28: 100
A29: T25 | B29: Région en surstock, désistements 25 %, plan de tirage en retard | E29: SAIN | F29: 8 | G29: 85 | H29: claire | I29: 35 | J29: structure | K29: 100 | L29: definitives | M29: aligne | N29: standard | O29: 100 | P29: faible | Q29: faible | R29: 22 | S29: 100 | T29: surstock | U29: qualifiee_garantie | V29: 0 | W29: programme_entier | X29: 62 | Y29: 100 | Z29: 90 | AA29: 1.35 | AB29: 0 | AC29: 16 | AD29: 18 | AE29: 55 | AF29: 5 | AG29: 25 | AH29: 27 | AI29: 61 | AJ29: 65 | AK29: 125 | AL29: oui | AM29: 3.2 | AN29: 5 | AO29: 98 | AP29: 2 | AQ29: 0 | AR29: 0 | AS29: 0 | AT29: no | AU29: clear | AV29: Non | AW29: Non | AX29: Non | AY29: Non | AZ29: Non | BA29: Non | BB29: Non | BC29: Oui | BD29: Non | BE29: Non | BF29: 89.65 | BG29: GO | BH29: Sain | BI29: 5 | BJ29: Non | BK29: 94.65 | BL29: 100 | BM29: 92 | BN29: 91 | BO29: 96 | BP29: 100
A30: T26 | B30: Données v5 non renseignées (notes plancher) | E30: SAIN | F30: 8 | G30: 85 | H30: claire | I30: 35 | J30: structure | K30: 100 | L30: definitives | M30: aligne | N30: standard | O30: 100 | P30: faible | Q30: faible | R30: 22 | S30: 100 | X30: 62 | Y30: 100 | Z30: 90 | AA30: 1.35 | AB30: 0 | AC30: 16 | AD30: 18 | AE30: 55 | AH30: 27 | AI30: 61 | AJ30: 65 | AK30: 125 | AL30: oui | AM30: 3.2 | AN30: 5 | AQ30: 0 | AR30: 0 | AS30: 0 | AT30: no | AU30: clear | AV30: Non | AW30: Non | AX30: Non | AY30: Non | AZ30: Non | BA30: Non | BB30: Non | BC30: Non | BD30: Non | BE30: Non | BF30: 85.53 | BG30: GO | BH30: Sain | BI30: 0 | BJ30: Non | BK30: 85.53 | BL30: 100 | BM30: 75 | BN30: 86.5 | BO30: 78 | BP30: 83.64

Sheet Validation
A1: Validation du modèle : ruban « Scoring PI » › Valider le modèle (le rapport s'affiche ici).

Sheet P_General
A1: Paramètres généraux du modèle
A2: Cellules bleues = paramétrables. Toute modification doit être validée (macro ValiderModele) et versionnée.
A3: Paramètre | B3: Valeur
A4: Version du modèle | B4: v5.0.0 | D4: Calculateurs actifs | E4: TRUE
A5: Publié le | B5: 2026-10-01
A6: Échelle de notation des critères | B6: 10
A7: Seuil GO (score final ≥) | B7: 75
A8: Seuil GO sous conditions (≥) | B8: 65
A9: Seuil Watch list (≥) | B9: 50
A10: PD proxy — constante a | B10: 2.223
A11: PD proxy — coefficient b | B11: 0.0802
A12: Clé critique additionnelle | B12: dpd_days
A14: Domaines de notation
A15: Code | B15: Nom | C15: Poids
A16: D1 | B16: Sponsor & Gouvernance | C16: 0.25
A17: D2 | B17: Qualité intrinsèque du projet | C17: 0.2
A18: D3 | B18: Commercial & Cash-flow | C18: 0.31
A19: D4 | B19: Structuration financière & LGD | C19: 0.24
A25: Classes réglementaires (ordre de sévérité croissante)
A26: Code | B26: Libellé | C26: Défaut avéré | D26: Bloque GO | E26: Coefficient BAM
A27: SAIN | B27: Créance saine | C27: Non | D27: Non | E27: 1
A28: SENSIBLE | B28: Créance sensible (surveillance) | C28: Non | D28: Non | E28: 0.9
A29: PRE_DOUTEUX | B29: Pré-douteuse | C29: Oui | D29: Non | E29: 0.7
A30: DOUTEUX | B30: Douteuse | C30: Oui | D30: Non | E30: 0.4
A31: COMPROMIS | B31: Compromise | C31: Oui | D31: Non | E31: 0.2
A32: CTX | B32: Contentieux | C32: Oui | D32: Oui | E32: 0
A38: Grilles de pondération par phase (challenger — non adoptées)
A39: Phase | B39: D1 | C39: D2 | D39: D3 | E39: D4
A40: PRE_DEVELOPMENT | B40: 0.25 | C40: 0.3 | D40: 0.2 | E40: 0.25
A41: CONSTRUCTION | B41: 0.2 | C41: 0.25 | D41: 0.25 | E41: 0.3
A42: ECOULEMENT | B42: 0.15 | C42: 0.1 | D42: 0.35 | E42: 0.4
A44: Repères de retard de paiement (jours)
A45: Seuil pré-douteux | B45: 90
A46: Seuil douteux | B46: 180
A47: Seuil compromis | B47: 360
A50: Libellés des décisions (affichage)
A51: Code | B51: Libellé
A52: GO | B52: Favorable
A53: GO_WITH_CONDITIONS | B53: Favorable sous conditions
A54: WATCH_LIST | B54: Surveillance (watch list)
A55: NO_GO | B55: Défavorable
A56: DOSSIER_INCOMPLET | B56: Dossier incomplet

Sheet P_Criteres
A1: Critères de notation (37 dans la v5.0.0 — jusqu'à 60 lignes)
A2: Ajouter un critère = compléter une ligne + ses barèmes (P_Baremes) + sa clé dans Saisie. Poids du domaine : somme = 100 %.
A4: Code | B4: Domaine | C4: Libellé | D4: Type | E4: Poids | F4: Clé d'entrée | G4: Gate | H4: Seuil gate | I4: Jalon gate | J4: Famille | K4: Critique | L4: Unité
A5: D1C1 | B5: D1 | C5: Projets similaires livrés (5 ans) | D5: NUM | E5: 0.2 | F5: promoter_completed_projects | G5: Non | J5: ECONOMIC | K5: Non | L5: ratio/%
A6: D1C2 | B6: D1 | C6: Gearing promoteur (dettes nettes / FP) | D6: NUM | E6: 0.25 | F6: promoter_gearing | G6: Non | J6: ECONOMIC | K6: Non | L6: ratio/%
A7: D1C3 | B7: D1 | C7: Gouvernance & structure juridique | D7: QUAL | E7: 0.15 | F7: governance_quality | G7: Non | J7: ECONOMIC | K7: Non | L7: modalité
A8: D1C4 | B8: D1 | C8: Concentration mono-projet (CA projet / CA total) | D8: NUM | E8: 0.15 | F8: mono_project_concentration | G8: Non | J8: ECONOMIC | K8: Non | L8: ratio/%
A9: D1C5 | B9: D1 | C9: Typologie promoteur | D9: QUAL | E9: 0.1 | F9: promoter_type | G9: Non | J9: ECONOMIC | K9: Non | L9: modalité
A10: D1C6 | B10: D1 | C10: Apport effectif (injecté / prévu) | D10: NUM | E10: 0.15 | F10: equity_injected_ratio | G10: Oui | H10: 1 | I10: SIGNATURE | J10: ECONOMIC | K10: Non | L10: ratio/%
A11: D2C1 | B11: D2 | C11: Foncier & autorisations | D11: QUAL | E11: 0.1 | F11: land_permits_status | G11: Oui | H11: 1 | I11: TIRAGE | J11: ECONOMIC | K11: Non | L11: modalité
A12: D2C2 | B12: D2 | C12: Marché & positionnement | D12: QUAL | E12: 0.15 | F12: market_positioning | G12: Non | J12: ECONOMIC | K12: Non | L12: modalité
A13: D2C3 | B13: D2 | C13: Complexité technique | D13: QUAL | E13: 0.1 | F13: technical_complexity | G13: Non | J13: ECONOMIC | K13: Non | L13: modalité
A14: D2C4 | B14: D2 | C14: Avancement vs planning | D14: NUM | E14: 0.1 | F14: progress_vs_plan | G14: Non | J14: ECONOMIC | K14: Non | L14: ratio/%
A15: D2C5 | B15: D2 | C15: Litiges clients / SAV | D15: QUAL | E15: 0.05 | F15: sav_litigation | G15: Non | J15: ECONOMIC | K15: Non | L15: modalité
A16: D2C6 | B16: D2 | C16: Sensibilité macro / subvention | D16: QUAL | E16: 0.05 | F16: macro_sensitivity | G16: Non | J16: ECONOMIC | K16: Non | L16: modalité
A17: D2C7 | B17: D2 | C17: Coût foncier / CA | D17: NUM | E17: 0.05 | F17: land_cost_ratio | G17: Non | J17: ECONOMIC | K17: Non | L17: ratio/%
A18: D2C8 | B18: D2 | C18: Chaîne d'autorisations (complétude) | D18: NUM | E18: 0.1 | F18: authorization_completeness_pct | G18: Non | I18: TIRAGE | J18: ECONOMIC | K18: Non | L18: %
A19: D2C9 | B19: D2 | C19: Tension du marché régional | D19: QUAL | E19: 0.1 | F19: regional_market_tension | G19: Non | J19: ECONOMIC | K19: Non | L19: modalité
A20: D2C10 | B20: D2 | C20: Entreprise de travaux et garanties de marché | D20: QUAL | E20: 0.1 | F20: contractor_quality | G20: Non | J20: ECONOMIC | K20: Non | L20: modalité
A21: D2C11 | B21: D2 | C21: Équipements exigés non budgétés (% du coût) | D21: NUM | E21: 0.05 | F21: equipment_unbudgeted_pct | G21: Non | J21: ECONOMIC | K21: Non | L21: %
A22: D2C12 | B22: D2 | C22: Autonomie du périmètre financé (tranche) | D22: QUAL | E22: 0.05 | F22: tranche_dependency | G22: Non | J22: ECONOMIC | K22: Non | L22: modalité
A23: D3C1 | B23: D3 | C23: Préventes sécurisées (encaissées / CA) | D23: NUM | E23: 0.15 | F23: pre_sale_rate | G23: Non | J23: ECONOMIC | K23: Oui | L23: ratio/%
A24: D3C2 | B24: D3 | C24: Ventes vs planning | D24: NUM | E24: 0.1 | F24: sales_vs_plan | G24: Non | J24: ECONOMIC | K24: Non | L24: ratio/%
A25: D3C3 | B25: D3 | C25: DSO (jours) | D25: NUM | E25: 0.05 | F25: dso_days | G25: Non | J25: ECONOMIC | K25: Non | L25: ratio/%
A26: D3C4 | B26: D3 | C26: Cash coverage (cash / échéances) | D26: NUM | E26: 0.2 | F26: cash_coverage | G26: Non | J26: ECONOMIC | K26: Oui | L26: ratio/%
A27: D3C5 | B27: D3 | C27: Impasse brute | D27: NUM | E27: 0.15 | F27: funding_gap_pct | G27: Non | J27: ECONOMIC | K27: Oui | L27: ratio/%
A28: D3C6 | B28: D3 | C28: Rotation stock (mois) | D28: NUM | E28: 0.05 | F28: stock_rotation_months | G28: Non | J28: ECONOMIC | K28: Non | L28: ratio/%
A29: D3C7 | B29: D3 | C29: Marge brute stressée (prix -10%) | D29: NUM | E29: 0.1 | F29: stressed_margin_pct | G29: Non | J29: ECONOMIC | K29: Non | L29: ratio/%
A30: D3C8 | B30: D3 | C30: Ventes sécurisées (financement acquéreur) | D30: NUM | E30: 0.05 | F30: secured_sales_rate | G30: Non | J30: ECONOMIC | K30: Non | L30: %
... A41: D4C9 | B41: D4 | C41: Dépassement du coût à terminaison | D41: NUM | E41: 0.1 | F41: cost_overrun_pct | G41: Non | J41: ECONOMIC | K41: Non | L41: %

Sheet P_Baremes
A1: Barèmes de notation
A2: PLAGE : borne basse incluse (≥ Min), borne haute exclue (< Max) ; cellule vide = illimité. MODALITE : valeur exacte saisie. Note de 1 à 10.
A4: Critère | B4: Type | C4: Valeur (modalité) | D4: Min (≥) | E4: Max (<) | F4: Libellé | G4: Ordre | H4: Note
A5: D1C1 | B5: PLAGE | E5: 1 | F5: < 1 (critique) | G5: 0 | H5: 1
A6: D1C1 | B6: PLAGE | D6: 1 | E6: 3 | F6: 1 à < 3 (vigilance) | G6: 1 | H6: 6
A7: D1C1 | B7: PLAGE | D7: 3 | F7: ≥ 3 (favorable) | G7: 2 | H7: 10
A8: D1C2 | B8: PLAGE | E8: 100 | F8: < 100 (favorable) | G8: 0 | H8: 10
A9: D1C2 | B9: PLAGE | D9: 100 | E9: 150 | F9: 100 à < 150 (vigilance) | G9: 1 | H9: 6
A10: D1C2 | B10: PLAGE | D10: 150 | F10: ≥ 150 (critique) | G10: 2 | H10: 1
A11: D1C3 | B11: MODALITE | C11: opaque | F11: Opaque | G11: 0 | H11: 1
A12: D1C3 | B12: MODALITE | C12: partielle | F12: Partielle | G12: 1 | H12: 6
A13: D1C3 | B13: MODALITE | C13: claire | F13: Claire / structurée | G13: 2 | H13: 10
A14: D1C4 | B14: PLAGE | E14: 40 | F14: < 40 (favorable) | G14: 0 | H14: 10
A15: D1C4 | B15: PLAGE | D15: 40 | E15: 60 | F15: 40 à < 60 (vigilance) | G15: 1 | H15: 6
A16: D1C4 | B16: PLAGE | D16: 60 | F16: ≥ 60 (critique) | G16: 2 | H16: 1
A17: D1C5 | B17: MODALITE | C17: opportuniste | F17: Opportuniste | G17: 0 | H17: 2
A18: D1C5 | B18: MODALITE | C18: regional | F18: Régional | G18: 1 | H18: 6
A19: D1C5 | B19: MODALITE | C19: structure | F19: Structuré | G19: 2 | H19: 10
A20: D1C6 | B20: PLAGE | E20: 80 | F20: < 80 (critique) | G20: 0 | H20: 1
A21: D1C6 | B21: PLAGE | D21: 80 | E21: 100 | F21: 80 à < 100 (vigilance) | G21: 1 | H21: 6
A22: D1C6 | B22: PLAGE | D22: 100 | F22: ≥ 100 (favorable) | G22: 2 | H22: 10
A23: D2C1 | B23: MODALITE | C23: absentes | F23: Titre non purgé / autorisations absentes | G23: 0 | H23: 1
A24: D2C1 | B24: MODALITE | C24: partielles | F24: Partielles | G24: 1 | H24: 6
A25: D2C1 | B25: MODALITE | C25: definitives | F25: Titre purgé + autorisations définitives | G25: 2 | H25: 10
A26: D2C2 | B26: MODALITE | C26: sur_positionne | F26: Sur-positionné / sur-offre | G26: 0 | H26: 2
A27: D2C2 | B27: MODALITE | C27: moyen | F27: Correct | G27: 1 | H27: 6
A28: D2C2 | B28: MODALITE | C28: aligne | F28: Aligné / forte demande | G28: 2 | H28: 10
A29: D2C3 | B29: MODALITE | C29: elevee | F29: Élevée | G29: 0 | H29: 2
A30: D2C3 | B30: MODALITE | C30: moyenne | F30: Moyenne | G30: 1 | H30: 6
A31: D2C3 | B31: MODALITE | C31: standard | F31: Standard | G31: 2 | H31: 10
A32: D2C4 | B32: PLAGE | E32: 80 | F32: < 80 (critique) | G32: 0 | H32: 1
A33: D2C4 | B33: PLAGE | D33: 80 | E33: 100 | F33: 80 à < 100 (vigilance) | G33: 1 | H33: 6
A34: D2C4 | B34: PLAGE | D34: 100 | F34: ≥ 100 (favorable) | G34: 2 | H34: 10
A35: D2C5 | B35: MODALITE | C35: eleve | F35: Élevé | G35: 0 | H35: 2
A36: D2C5 | B36: MODALITE | C36: moyen | F36: Moyen | G36: 1 | H36: 6
A37: D2C5 | B37: MODALITE | C37: faible | F37: Faible | G37: 2 | H37: 10
A38: D2C6 | B38: MODALITE | C38: elevee | F38: Élevée | G38: 0 | H38: 2
A39: D2C6 | B39: MODALITE | C39: moyenne | F39: Moyenne | G39: 1 | H39: 6
A40: D2C6 | B40: MODALITE | C40: faible | F40: Faible | G40: 2 | H40: 10
A41: D2C7 | B41: PLAGE | E41: 25 | F41: < 25 (favorable) | G41: 0 | H41: 10
A42: D2C7 | B42: PLAGE | D42: 25 | E42: 35 | F42: 25 à < 35 (vigilance) | G42: 1 | H42: 6
A43: D2C7 | B43: PLAGE | D43: 35 | F43: ≥ 35 (critique) | G43: 2 | H43: 1
A44: D2C8 | B44: PLAGE | E44: 50 | F44: < 50 % (critique) | G44: 0 | H44: 1
A45: D2C8 | B45: PLAGE | D45: 50 | E45: 100 | F45: 50 à < 100 % (vigilance) | G45: 1 | H45: 6
A46: D2C8 | B46: PLAGE | D46: 100 | F46: ≥ 100 % (favorable) | G46: 2 | H46: 10
A47: D2C9 | B47: MODALITE | C47: surstock | F47: Marché en surstock (écoulement lent, prix sous pression) | G47: 0 | H47: 2
A48: D2C9 | B48: MODALITE | C48: equilibre | F48: Marché équilibré | G48: 1 | H48: 6
A49: D2C9 | B49: MODALITE | C49: porteur | F49: Marché porteur (demande soutenue) | G49: 2 | H49: 10
A50: D2C10 | B50: MODALITE | C50: non_qualifiee | F50: Entreprise non qualifiée, travaux en régie ou promoteur-constructeur sans structure | G50: 0 | H50: 2
A51: D2C10 | B51: MODALITE | C51: qualifiee | F51: Entreprise qualifiée, garanties de marché partielles | G51: 1 | H51: 6
A52: D2C10 | B52: MODALITE | C52: qualifiee_garantie | F52: Entreprise qualifiée et classée, marché forfaitaire avec caution de bonne exécution et retenue de garantie | G52: 2 | H52: 10
A53: D2C11 | B53: PLAGE | E53: 0.0001 | F53: 0 % — tout est budgété (favorable) | G53: 0 | H53: 10
A54: D2C11 | B54: PLAGE | D54: 0.0001 | E54: 3 | F54: > 0 à < 3 % (vigilance) | G54: 1 | H54: 6
A55: D2C11 | B55: PLAGE | D55: 3 | F55: ≥ 3 % (critique) | G55: 2 | H55: 1
A56: D2C12 | B56: MODALITE | C56: dependante_non_financee | F56: Tranche dépendante d'ouvrages communs non financés | G56: 0 | H56: 1
A57: D2C12 | B57: MODALITE | C57: dependante_financee | F57: Tranche dépendante d'ouvrages communs financés ou réalisés | G57: 1 | H57: 6
A58: D2C12 | B58: MODALITE | C58: autonome | F58: Tranche autonome (accès, VRD et raccordements propres) | G58: 2 | H58: 10
A59: D2C12 | B59: MODALITE | C59: programme_entier | F59: Financement du programme entier | G59: 3 | H59: 10
A60: D3C1 | B60: PLAGE | E60: 25 | F60: < 25 (critique) | G60: 0 | H60: 1
A61: D3C1 | B61: PLAGE | D61: 25 | E61: 40 | F61: 25 à < 40 (vigilance) | G61: 1 | H61: 6
A62: D3C1 | B62: PLAGE | D62: 40 | F62: ≥ 40 (favorable) | G62: 2 | H62: 10
A63: D3C2 | B63: PLAGE | E63: 80 | F63: < 80 (critique) | G63: 0 | H63: 1
A64: D3C2 | B64: PLAGE | D64: 80 | E64: 100 | F64: 80 à < 100 (vigilance) | G64: 1 | H64: 6
A65: D3C2 | B65: PLAGE | D65: 100 | F65: ≥ 100 (favorable) | G65: 2 | H65: 10
A66: D3C3 | B66: PLAGE | E66: 120 | F66: < 120 (favorable) | G66: 0 | H66: 10
A67: D3C3 | B67: PLAGE | D67: 120 | E67: 240 | F67: 120 à < 240 (vigilance) | G67: 1 | H67: 6
A68: D3C3 | B68: PLAGE | D68: 240 | F68: ≥ 240 (critique) | G68: 2 | H68: 1
A69: D3C4 | B69: PLAGE | E69: 1 | F69: < 1 (critique) | G69: 0 | H69: 1
A70: D3C4 | B70: PLAGE | D70: 1 | E70: 1.2 | F70: 1 à < 1,2 (vigilance) | G70: 1 | H70: 6
A71: D3C4 | B71: PLAGE | D71: 1.2 | F71: ≥ 1,2 (favorable) | G71: 2 | H71: 10
A72: D3C5 | B72: PLAGE | E72: 0.0001 | F72: ≤ 0 — aucune impasse (favorable) | G72: 0 | H72: 10
A73: D3C5 | B73: PLAGE | D73: 0.0001 | E73: 10 | F73: > 0 à < 10 (vigilance) | G73: 1 | H73: 6
A74: D3C5 | B74: PLAGE | D74: 10 | F74: ≥ 10 (critique) | G74: 2 | H74: 1
A75: D3C6 | B75: PLAGE | E75: 18 | F75: < 18 (favorable) | G75: 0 | H75: 10
A76: D3C6 | B76: PLAGE | D76: 18 | E76: 30 | F76: 18 à < 30 (vigilance) | G76: 1 | H76: 6
A77: D3C6 | B77: PLAGE | D77: 30 | F77: ≥ 30 (critique) | G77: 2 | H77: 1
A78: D3C7 | B78: PLAGE | E78: 10 | F78: < 10 (critique) | G78: 0 | H78: 1
A79: D3C7 | B79: PLAGE | D79: 10 | E79: 15 | F79: 10 à < 15 (vigilance) | G79: 1 | H79: 6
A80: D3C7 | B80: PLAGE | D80: 15 | F80: ≥ 15 (favorable) | G80: 2 | H80: 10
A81: D3C8 | B81: PLAGE | E81: 25 | F81: < 25 % (critique) | G81: 0 | H81: 1
A82: D3C8 | B82: PLAGE | D82: 25 | E82: 40 | F82: 25 à < 40 % (vigilance) | G82: 1 | H82: 6
A83: D3C8 | B83: PLAGE | D83: 40 | F83: ≥ 40 % (favorable) | G83: 2 | H83: 10
A84: D3C9 | B84: PLAGE | E84: 20 | F84: < 20 % (favorable) | G84: 0 | H84: 10
A85: D3C9 | B85: PLAGE | D85: 20 | E85: 40 | F85: 20 à < 40 % (vigilance) | G85: 1 | H85: 6
A86: D3C9 | B86: PLAGE | D86: 40 | F86: ≥ 40 % (critique) | G86: 2 | H86: 1
A87: D3C10 | B87: PLAGE | E87: 10 | F87: < 10 % (favorable) | G87: 0 | H87: 10
A88: D3C10 | B88: PLAGE | D88: 10 | E88: 20 | F88: 10 à < 20 % (vigilance) | G88: 1 | H88: 6
A89: D3C10 | B89: PLAGE | D89: 20 | F89: ≥ 20 % (critique) | G89: 2 | H89: 1
A90: D4C1 | B90: PLAGE | E90: 15 | F90: < 15 (critique) | G90: 0 | H90: 1
A91: D4C1 | B91: PLAGE | D91: 15 | E91: 25 | F91: 15 à < 25 (vigilance) | G91: 1 | H91: 6
A92: D4C1 | B92: PLAGE | D92: 25 | F92: ≥ 25 (favorable) | G92: 2 | H92: 10
A93: D4C2 | B93: PLAGE | E93: 60 | F93: < 60 (favorable) | G93: 0 | H93: 10
A94: D4C2 | B94: PLAGE | D94: 60 | E94: 80 | F94: 60 à < 80 (vigilance) | G94: 1 | H94: 6
A95: D4C2 | B95: PLAGE | D95: 80 | F95: ≥ 80 (critique) | G95: 2 | H95: 1
A96: D4C3 | B96: PLAGE | E96: 70 | F96: < 70 (favorable) | G96: 0 | H96: 10
A97: D4C3 | B97: PLAGE | D97: 70 | E97: 85 | F97: 70 à < 85 (vigilance) | G97: 1 | H97: 6
A98: D4C3 | B98: PLAGE | D98: 85 | F98: ≥ 85 (critique) | G98: 2 | H98: 1
A99: D4C4 | B99: PLAGE | E99: 90 | F99: < 90 (critique) | G99: 0 | H99: 1
A100: D4C4 | B100: PLAGE | D100: 90 | E100: 120 | F100: 90 à < 120 (vigilance) | G100: 1 | H100: 6
A101: D4C4 | B101: PLAGE | D101: 120 | F101: ≥ 120 (favorable) | G101: 2 | H101: 10
...

Sheet P_Alertes
A1: Couche D5 — alertes (red flags)
A2: Règle simple : Clé / Opérateur / Valeur. Opérateurs : isTrue, isFalse, eq, neq, gt, gte, lt, lte. BLOCKING = souffrance automatique (malus 0).
A4: Code | B4: Libellé | C4: Sévérité | D4: Malus | E4: Domaines | F4: Clé d'entrée | G4: Opérateur | H4: Valeur réf. | I4: Comité | J4: Effet | K4: Référence réglementaire / interne
A5: RF_ACQUEREURS_NON_FINANCES | B5: Financement acquéreur majoritairement non sécurisé | C5: MEDIUM | D5: 10 | E5: D3,D5 | F5: buyers_financing_at_risk | G5: isTrue | I5: Non | J5: HYPOTHESIS | K5: Liquidité des ventes — solvabilité acquéreur
A6: RF_AUTORISATION_TIRAGE | B6: Autorisation indispensable aux travaux non levée | C6: HIGH | D6: 15 | E6: D2,D5 | F6: works_authorization_blocked | G6: isTrue | I6: Non | J6: SURVEILLANCE | K6: Loi 25-90 (lotissements) ; loi 12-90 (urbanisme) ; ANCFCC
A7: RF_CASH_LT_ECH | B7: Cash coverage < 1,0x | C7: HIGH | D7: 25 | E7: D3,D5 | F7: cash_coverage | G7: lt | H7: 1 | I7: Non | J7: HYPOTHESIS
A8: RF_COMPOSANTE_SANS_PRENEUR | B8: Composante commerciale ou hôtelière sans preneur engagé | C8: MEDIUM | D8: 10 | E8: D3,D5 | F8: component_exit_unsecured | G8: isTrue | I8: Non | J8: HYPOTHESIS | K8: Programme mixte — liquidité des composantes non résidentielles
A9: RF_DIVISION_RISQUES | B9: Limite de division des risques dépassée | C9: MEDIUM | D9: 0 | E9: D5 | F9: division_limit_breach | G9: isTrue | I9: Oui | J9: REGULATORY | K9: Division des risques — limite par contrepartie / groupe d'intérêt
A10: RF_EQUIPEMENT_RECEPTION | B10: Équipement exigé en retard (conditionne la réception) | C10: HIGH | D10: 15 | E10: D2,D5 | F10: equipment_delivery_at_risk | G10: isTrue | I10: Oui | J10: SURVEILLANCE | K10: Cahier des charges / convention avec la commune ; réception et permis d'habiter
A11: RF_FP_NEG | B11: Fonds propres négatifs | C11: HIGH | D11: 25 | E11: D4,D5 | F11: equity_negative | G11: isTrue | I11: Non | J11: HYPOTHESIS
A12: RF_IMPASSE_PERSIST | B12: Impasse de trésorerie persistante | C12: HIGH | D12: 20 | E12: D3,D5 | F12: funding_gap_persistent | G12: isTrue | I12: Non | J12: HYPOTHESIS
A13: RF_IMPAYE_90J | B13: Impayé ≥ 90 jours (souffrance automatique) | C13: BLOCKING | D13: 0 | E13: D5 | F13: dpd_days | G13: gte | H13: 90 | I13: Non | J13: REGULATORY | K13: 1/W art.5 ; art.34
A14: RF_LITIGE | B14: Action en justice / contentieux (CTX) | C14: BLOCKING | D14: 0 | E14: D5 | F14: legal_exposure | G14: eq | H14: litigation | I14: Non | J14: REGULATORY | K14: 1/W art.12.8
A15: RF_MAINLEVEE_SOUS_TARIFEE | B15: Prix de mainlevée sous-tarifé | C15: HIGH | D15: 15 | E15: D4,D5 | F15: release_underpriced | G15: isTrue | I15: Oui | J15: SURVEILLANCE | K15: Politique interne — mainlevées partielles
A16: RF_NON_1ER_RANG | B16: Garantie non 1er rang | C16: MEDIUM | D16: 25 | E16: D4,D5 | F16: first_rank | G16: eq | H16: non | I16: Non | J16: SURVEILLANCE
A17: RF_PLAN_TIRAGE_RETARD | B17: Plan de tirage en retard sur le calendrier | C17: MEDIUM | D17: 5 | E17: D2,D5 | F17: drawdown_schedule_late | G17: isTrue | I17: Non | J17: SURVEILLANCE | K17: Planning des déblocages du business plan
A18: RF_PROJET_ARRET_12M | B18: Projet à l'arrêt ≥ 12 mois (souffrance automatique) | C18: BLOCKING | D18: 0 | E18: D5 | F18: project_stopped_months | G18: gte | H18: 12 | I18: Non | J18: REGULATORY | K18: 1/W art.12.7
A19: RF_RESTRUCT | B19: Première restructuration | C19: MEDIUM | D19: 25 | E19: D5 | F19: restructured | G19: eq | H19: yes | I19: Oui | J19: REGULATORY | K19: 1/W art.17-31
A20: RF_RETARD_6M | B20: Retard chantier ≥ 6 mois | C20: HIGH | D20: 15 | E20: D2,D5 | F20: construction_delay_months | G20: gte | H20: 6 | I20: Oui | J20: SURVEILLANCE | K20: 1/W art.12.7
A21: RF_TIRAGE_AVANCE | B21: Déblocages en avance sur l'avancement des travaux | C21: HIGH | D21: 15 | E21: D4,D5 | F21: drawdown_ahead_of_works | G21: isTrue | I21: Oui | J21: SURVEILLANCE | K21: Politique de crédit — déblocage sur situation de travaux visée
A22: RF_TRANCHE_DEPENDANTE | B22: Tranche financée dépendante d'ouvrages communs non financés | C22: HIGH | D22: 15 | E22: D2,D5 | F22: tranche_dependency | G22: eq | H22: dependante_non_financee | I22: Oui | J22: SURVEILLANCE | K22: Financement par tranche — ouvrages communs

Sheet P_Ajustements
A1: Ajustements segment (α) et zone (β)
A2: S_ajusté = S_éco × (1 + α + β). Un segment ou une zone hors de ces listes est signalé, jamais assimilé à un risque neutre.
A4: Segment | B4: Libellé | C4: α | E4: Zone | F4: Libellé | G4: β
A5: social | B5: Logement social | C5: 0 | E5: agadir | F5: Agadir | G5: 0
A6: villas | B6: Villas | C6: -0.04 | E6: tanger | F6: Tanger | G6: 0
A7: bureaux | B7: Bureaux | C7: -0.05 | E7: marrakech | F7: Marrakech | G7: -0.07
A8: commerces | B8: Commerces | C8: -0.03 | E8: casa_centre | F8: Casablanca — centre | G8: 0
A9: moyen_haut | B9: Moyen-haut standing | C9: 0 | E9: fes_oriental | F9: Fès / Oriental | G9: -0.03
A10: touristique | B10: Touristique / hôtelier | C10: -0.07 | E10: rabat_centre | F10: Rabat — centre | G10: 0.02
A11: intermediaire | B11: Logement intermédiaire | C11: -0.05 | E11: casa_peripherie | F11: Casablanca — périphérie | G11: -0.05
E12: rabat_peripherie | F12: Rabat — périphérie | G12: 0
E13: regions_interieures | F13: Régions intérieures | G13: -0.05

Sheet P_Referentiels
A1: Référentiels métier (pratique marocaine)
A2: Équivalents des référentiels administrables de l'application. Modifiables ici sans macro.
A4: Chaîne d'autorisations
A5: Code | B5: Pièce | C5: Jalon | D5: Lotissement | E5: Construction | F5: Mixte | G5: Bloque travaux | H5: Bloque livraison | I5: Référence
A6: note_renseignement | B6: Note de renseignements urbanistiques | C6: ETUDE | D6: Oui | E6: Oui | F6: Oui | G6: Non | H6: Non | I6: Urbanisme — agence urbaine
A7: titre_foncier_purge | B7: Titre foncier purgé (sans inscription contraignante) | C7: OCTROI | D7: Oui | E7: Oui | F7: Oui | G7: Oui | H7: Non | I7: ANCFCC — conservation foncière
A8: autorisation_lotir | B8: Autorisation de lotir | C8: TIRAGE | D8: Oui | E8: Non | F8: Oui | G8: Oui | H8: Non | I8: Loi 25-90 relative aux lotissements
A9: permis_construire | B9: Permis de construire | C9: TIRAGE | D9: Non | E9: Oui | F9: Oui | G9: Oui | H9: Non | I9: Loi 12-90 relative à l'urbanisme
A10: autorisation_morcellement | B10: Autorisation de morcellement / éclatement du titre | C10: TIRAGE | D10: Oui | E10: Non | F10: Oui | G10: Non | H10: Non | I10: ANCFCC — morcellement du titre mère
A11: reception_provisoire | B11: Réception provisoire des travaux | C11: TIRAGE | D11: Oui | E11: Oui | F11: Oui | G11: Non | H11: Oui
A12: permis_habiter | B12: Permis d'habiter | C12: TIRAGE | D12: Non | E12: Oui | F12: Oui | G12: Non | H12: Oui | I12: Loi 12-90
A13: certificat_conformite | B13: Certificat de conformité | C13: TIRAGE | D13: Oui | E13: Oui | F13: Oui | G13: Non | H13: Oui
A14: reception_definitive | B14: Réception définitive | C14: TIRAGE | D14: Oui | E14: Oui | F14: Oui | G14: Non | H14: Non
A32: Financement de l'acquéreur
A33: Code | B33: Libellé | C33: Facteur de sécurisation
A34: fonds_propres | B34: Autofinancement (fonds propres acquéreur) | C34: 1
A35: credit_debloque | B35: Crédit acquéreur débloqué | C35: 1
A36: credit_accorde | B36: Crédit accordé (accord de principe / offre) | C36: 0.8
A37: credit_en_cours | B37: Demande de crédit en cours d'instruction | C37: 0.4
A38: credit_refuse | B38: Crédit refusé | C38: 0
A39: non_instruit | B39: Financement non instruit | C39: 0.2
A48: Natures de concours (information — contrôle de tirage)
A49: Code | B49: Libellé | C49: Situation de travaux visée requise
A50: avance_foncier | B50: Avance sur acquisition du foncier | C50: Non
A51: credit_accompagnement | B51: Crédit d'accompagnement / de construction | C51: Oui
A52: credit_amenagement | B52: Crédit d'aménagement (lotissement / VRD) | C52: Oui
A53: credit_in_fine | B53: Crédit in fine (remboursement du principal au terme) | C53: Non
A54: caution_marche | B54: Caution / engagement par signature | C54: Non
A56: Dispositifs d'aide à l'acquéreur (information)
A57: aide_directe_logement | B57: Aide directe au logement
A58: fogarim | B58: FOGARIM (garantie revenus irréguliers)
A59: damane_assakane | B59: Damane Assakane
A60: aucun | B60: Aucun dispositif
A64: Modalités des données d'alerte (libellé affiché → code)
A65: Clé | B65: Code | C65: Libellé
A66: restructured | B66: no | C66: Non
A67: restructured | B67: yes | C67: Oui — créance restructurée
A68: legal_exposure | B68: clear | C68: Aucun litige
A69: legal_exposure | B69: watch | C69: Sous surveillance
A70: legal_exposure | B70: litigation | C70: Litige en cours
